Workbook
Name Juros_SAC: 'SAC @amigodopairico'!$E$6:$E$426

Sheet RAIO X DO SEU FINANCIAMENTO
C2: DIAGNÓSTICO DO FINANCIAMENTO - RAIO X - @amigodopairico
C5: NOS PRÓXIMOS 12 MESES | D5: SAC | E5: NOS PRÓXIMOS 3 ANOS | G5: NO TOTAL | M5: =IF(C17<1,"",IF(C14/C17>90%,"🛩",IF(C14/C17>70%,"🏎",IF(C14/C17>50%,"🚙",IF(C14/C17>30%,"🛵",IF(C14/C17>15%,"🐢","⚓️")))))) -> 🛵 | N5: PRICE | O5: SAC
C6: VOCÊ PAGA | D6: =IF(D5="PRICE",N18,O18) -> 0.10772141 | E6: VOCÊ PAGA | G6: VOCÊ PAGA | M6: NOS PRÓXIMOS 3 ANOS VOCÊ PAGA: | N6: =SUM('PRICE @amigodopairico'!G7:G42) -> 39890.345 | O6: =SUM('SAC @amigodopairico'!G7:G42) -> 49249.896
C7: =IF(D5="PRICE",N8,O8) -> 16486.772 | D7: CET REAL | E7: =IF(D5="PRICE",N6,O6) -> 49249.896 | G7: =IF(D5="PRICE",N10,O10) -> 400751.9 | M7: SUA DÍVIDA CAI EM 3 ANOS: | N7: ='PRICE @amigodopairico'!F3-'PRICE @amigodopairico'!I42 -> -3947.5023 | O7: ='SAC @amigodopairico'!F3-'SAC @amigodopairico'!I42 -> 6948.3685
M8: NOS PRÓXIMOS 12 MESES VOCÊ PAGA: | N8: =SUM('PRICE @amigodopairico'!G7:G18) -> 13039.868 | O8: =SUM('SAC @amigodopairico'!G7:G18) -> 16486.772
C9: ="SUA DÍVIDA "& IF(IF(D5="PRICE",N9,O9)<0,"AUMENTA","CAI") -> SUA DÍVIDA CAI | E9: ="SUA DÍVIDA "& IF(IF(D5="PRICE",N7,O7)<0,"AUMENTA","CAI") -> SUA DÍVIDA CAI | G9: A DÍVIDA ALÉM DA DÍVIDA | M9: SUA DÍVIDA CAI EM 12 MESES: | N9: ='PRICE @amigodopairico'!F3-'PRICE @amigodopairico'!I18 -> -1442.227 | O9: ='SAC @amigodopairico'!F3-'SAC @amigodopairico'!I18 -> 2164.7571
C10: =TEXT(IF(D5="PRICE",N9,O9),"#.##0"&" "&M5) -> 2.165 🛵 | E10: =TEXT(IF(D5="PRICE",N7,O7),"#.##0"&" "&M5) -> 6.948 🛵 | G10: =G7-C20 -> 258925.9 | M10: NO TOTAL VOCÊ PAGA: | N10: ='PRICE @amigodopairico'!F4 -> 491017.84 | O10: ='SAC @amigodopairico'!F4 -> 400751.9
C11: =IF(D5="PRICE",N9,O9)/C7 -> 0.13130267 | E11: =IF(D5="PRICE",N7,O7)/E7 -> 0.14108392 | G11: ="Paga "&TEXT((G10/C20),"0,0")&" mais" -> Paga 1,8 mais | M11: A DÍVIDA ALÉM DA DÍVIDA: | N11: =N10-C20 -> 349191.84 | O11: =O10-C20 -> 258925.9
C12: PARCELA PAGA DA DÍVIDA: | M12: PARCELA PAGA DA DÍVIDA EM %: | N12: ='PRICE @amigodopairico'!A7 -> 0.00082224734 | O12: ='SAC @amigodopairico'!A7 -> 0.0029361703
C13: =IF(D5="PRICE",N12,O12) -> 0.0029361703 | G13: @amigodopairico | M13: PARCELA DO ANO 5 PAGA DA DÍVIDA EM %: | N13: ='PRICE @amigodopairico'!A66 -> 0.0012721235 | O13: ='SAC @amigodopairico'!A66 -> 0.0035526578
C14: =IF(D5="PRICE",N14,O14) -> 415.91202 | M14: PARCELA PAGA DA DÍVIDA EM REAIS: | N14: ='PRICE @amigodopairico'!F7 -> 116.71833 | O14: ='SAC @amigodopairico'!F7 -> 415.91202
C15: =C14/C17 -> 0.30221096 | M15: VALOR DA PRÓXIMA PARCELA: | N15: ='PRICE @amigodopairico'!G7 -> 1077.0371 | O15: ='SAC @amigodopairico'!G7 -> 1376.2308
C16: VALOR DA PRÓXIMA PARCELA: | E16: PARCELAS RESTANTES: | G16: TR CONSIDERADA: | M16: VALOR DA PARCELA NO ANO 5: | N16: ='PRICE @amigodopairico'!G66 -> 1184.8845 | O16: ='SAC @amigodopairico'!G66 -> 1342.7656
C17: =IF(D5="PRICE",N15,O15) -> 1376.2308 | E17: 341 | G17: 0.0017 | M17: VALOR DA PARCELA NO ANO 10: | N17: ='PRICE @amigodopairico'!G126 -> 1306.3138 | O17: ='SAC @amigodopairico'!G126 -> 1286.3885
N18: ='PRICE @amigodopairico'!W3 -> 0.10663482 | O18: ='SAC @amigodopairico'!X3 -> 0.10772141
C19: SALDO DEVEDOR ATUAL: | E19: TAXA DE JUROS EFETIVA: | G19: SEGURO + TAXA | M19: =IF(C13<G17,"🚨CUIDADO: ESTE É UM FINANCIAMENTO EM QUE SALDO DEVEDOR AUMENTA. FAÇA SUA PARCELA PAGAR PELO MENOS 0,20% DA DÍVIDA","")
C20: 141826 | D20: =(1+2%)^12-1 -> 0.26824179 | E20: 0.079347 | G20: =25+30 -> 55
E21: =(1+E20)^(1/12)-1 -> 0.0063833061 | G21: v. 30/01/2026

Sheet PRICE @amigodopairico
A1: Conheça o PAQ, Programa de Aceleração de Quitação | G1: v. 24/01/2026 | I1: Clique e saiba mais | L1: @amigodopairico
E2: =SUM(E7:E426) -> 260945.12 | F2: =SUM(F7:F426) -> 211317.72 | G2: =SUM(G7:G426) -> 491017.84 | H2: =SUM(H7:H426) -> 69494.82 | N2: =SUM(N7:N426) -> 367269.65
A3: PRICE | E3: Valor financiado: | F3: ='RAIO X DO SEU FINANCIAMENTO'!C20 -> 141826 | G3: Meses: | H3: ='RAIO X DO SEU FINANCIAMENTO'!E17 -> 341 | I3: Juros a.a.: | J3: ='RAIO X DO SEU FINANCIAMENTO'!E20 -> 0.079347 | K3: Taxa Adm.: | L3: =IF('RAIO X DO SEU FINANCIAMENTO'!G20>25,25,0) -> 25 | N3: instagram.com/amigodopairico/ | V3: CÁLCULO DO | W3: =(1+W4)^12-1 -> 0.10663482
E4: Total pago: | F4: =G2 -> 491017.84 | I4: Juros a.m: | J4: =(1+J3)^(1/12)-1 -> 0.0063833061 | K4: Seguro: | L4: ='RAIO X DO SEU FINANCIAMENTO'!G20-L3 -> 30 | N4: youtube.com/amigodopairico | V4: CET REAL ➡️ | W4: =IRR(W6:W426) -> 0.0084793909
A6: Amort/SD | C6: Parcelas | D6: A | E6: Juros | F6: Amortização | G6: Parcela | H6: At. Monetária | I6: Saldo Devedor | K6: $ aproveitado | L6: TR | N6: Parcela Original | W6: =F3 -> 141826 | X6: LIBEROU
A7: =F7/I7 -> 0.00082224734 | B7: 1 | C7: =H3 -> 341 | D7: =C7/12 -> 28.416667 | E7: =F3*$J$4 -> 905.31877 | F7: =G7-E7-$L$3-$L$4 -> 116.71833 | G7: =-PMT($J$4,C7,F3)+$L$3+$L$4 -> 1077.0371 | H7: =F3*$L$7 -> 241.1042 | I7: =F3-F7+H7 -> 141950.39 | K7: =IF(C7<1,0,(F7-H7)/G7) -> -0.11548894 | L7: ='RAIO X DO SEU FINANCIAMENTO'!G17 -> 0.0017 | N7: =-PMT($J$4,C7,F3)+$L$3+$L$4 -> 1077.0371 | W7: =-G7 -> -1077.0371 | X7: Sai da conta
A8: =F8/I8 -> 0.00082818247 | B8: =B7+1 -> 2 | C8: =IF(C7-1<1,0,C7-1) -> 340 | D8: =C8/12 -> 28.333333 | E8: =IF(C8<1,0,I7*$J$4) -> 906.11276 | F8: =IF(C8<1,0,G8-E8-$L$3-$L$4) -> 117.66323 | G8: =IF(C8<1,0,-PMT($J$4,C8,I7)+$L$3+$L$4) -> 1078.776 | H8: =IF(C8<1,0,I7*L8) -> 241.31566 | I8: =IF(C8<1,0,I7-F8+H8) -> 142074.04 | K8: =IF(C8<1,0,(F8-H8)/G8) -> -0.1146229 | L8: =L7 -> 0.0017 | N8: =IF(C8<1,0,N7) -> 1077.0371 | W8: =-G8 -> -1078.776
A9: =F9/I9 -> 0.00083416543 | B9: =B8+1 -> 3 | C9: =IF(C8-1<1,0,C8-1) -> 339 | D9: =C9/12 -> 28.25 | E9: =IF(C9<1,0,I8*$J$4) -> 906.90207 | F9: =IF(C9<1,0,G9-E9-$L$3-$L$4) -> 118.61578 | G9: =IF(C9<1,0,-PMT($J$4,C9,I8)+$L$3+$L$4) -> 1080.5178 | H9: =IF(C9<1,0,I8*L9) -> 241.52587 | I9: =IF(C9<1,0,I8-F9+H9) -> 142196.95 | K9: =IF(C9<1,0,(F9-H9)/G9) -> -0.11375109 | L9: =L8 -> 0.0017 | N9: =IF(C9<1,0,N8) -> 1077.0371 | W9: =-G9 -> -1080.5178
A10: =F10/I10 -> 0.0008401967 | B10: =B9+1 -> 4 | C10: =IF(C9-1<1,0,C9-1) -> 338 | D10: =C10/12 -> 28.166667 | E10: =IF(C10<1,0,I9*$J$4) -> 907.68664 | F10: =IF(C10<1,0,G10-E10-$L$3-$L$4) -> 119.57604 | G10: =IF(C10<1,0,-PMT($J$4,C10,I9)+$L$3+$L$4) -> 1082.2627 | H10: =IF(C10<1,0,I9*L10) -> 241.73481 | I10: =IF(C10<1,0,I9-F10+H10) -> 142319.11 | K10: =IF(C10<1,0,(F10-H10)/G10) -> -0.11287349 | L10: =L9 -> 0.0017 | N10: =IF(C10<1,0,N9) -> 1077.0371 | W10: =-G10 -> -1082.2627
A11: =F11/I11 -> 0.00084627672 | B11: =B10+1 -> 5 | C11: =IF(C10-1<1,0,C10-1) -> 337 | D11: =C11/12 -> 28.083333 | E11: =IF(C11<1,0,I10*$J$4) -> 908.46642 | F11: =IF(C11<1,0,G11-E11-$L$3-$L$4) -> 120.54408 | G11: =IF(C11<1,0,-PMT($J$4,C11,I10)+$L$3+$L$4) -> 1084.0105 | H11: =IF(C11<1,0,I10*L11) -> 241.94248 | I11: =IF(C11<1,0,I10-F11+H11) -> 142440.51 | K11: =IF(C11<1,0,(F11-H11)/G11) -> -0.11199006 | L11: =L10 -> 0.0017 | N11: =IF(C11<1,0,N10) -> 1077.0371 | W11: =-G11 -> -1084.0105
A12: =F12/I12 -> 0.00085240596 | B12: =B11+1 -> 6 | C12: =IF(C11-1<1,0,C11-1) -> 336 | D12: =C12/12 -> 28 | E12: =IF(C12<1,0,I11*$J$4) -> 909.24134 | F12: =IF(C12<1,0,G12-E12-$L$3-$L$4) -> 121.51996 | G12: =IF(C12<1,0,-PMT($J$4,C12,I11)+$L$3+$L$4) -> 1085.7613 | H12: =IF(C12<1,0,I11*L12) -> 242.14886 | I12: =IF(C12<1,0,I11-F12+H12) -> 142561.13 | K12: =IF(C12<1,0,(F12-H12)/G12) -> -0.11110075 | L12: =L11 -> 0.0017 | N12: =IF(C12<1,0,N11) -> 1077.0371 | W12: =-G12 -> -1085.7613
A13: =F13/I13 -> 0.00085858491 | B13: =B12+1 -> 7 | C13: =IF(C12-1<1,0,C12-1) -> 335 | D13: =C13/12 -> 27.916667 | E13: =IF(C13<1,0,I12*$J$4) -> 910.01135 | F13: =IF(C13<1,0,G13-E13-$L$3-$L$4) -> 122.50374 | G13: =IF(C13<1,0,-PMT($J$4,C13,I12)+$L$3+$L$4) -> 1087.5151 | H13: =IF(C13<1,0,I12*L13) -> 242.35393 | I13: =IF(C13<1,0,I12-F13+H13) -> 142680.98 | K13: =IF(C13<1,0,(F13-H13)/G13) -> -0.11020554 | L13: =L12 -> 0.0017 | N13: =IF(C13<1,0,N12) -> 1077.0371 | W13: =-G13 -> -1087.5151
A14: =F14/I14 -> 0.00086481404 | B14: =B13+1 -> 8 | C14: =IF(C13-1<1,0,C13-1) -> 334 | D14: =C14/12 -> 27.833333 | E14: =IF(C14<1,0,I13*$J$4) -> 910.77639 | F14: =IF(C14<1,0,G14-E14-$L$3-$L$4) -> 123.49548 | G14: =IF(C14<1,0,-PMT($J$4,C14,I13)+$L$3+$L$4) -> 1089.2719 | H14: =IF(C14<1,0,I13*L14) -> 242.55767 | I14: =IF(C14<1,0,I13-F14+H14) -> 142800.05 | K14: =IF(C14<1,0,(F14-H14)/G14) -> -0.10930438 | L14: =L13 -> 0.0017 | N14: =IF(C14<1,0,N13) -> 1077.0371 | W14: =-G14 -> -1089.2719
A15: =F15/I15 -> 0.00087109383 | B15: =B14+1 -> 9 | C15: =IF(C14-1<1,0,C14-1) -> 333 | D15: =C15/12 -> 27.75 | E15: =IF(C15<1,0,I14*$J$4) -> 911.53641 | F15: =IF(C15<1,0,G15-E15-$L$3-$L$4) -> 124.49526 | G15: =IF(C15<1,0,-PMT($J$4,C15,I14)+$L$3+$L$4) -> 1091.0317 | H15: =IF(C15<1,0,I14*L15) -> 242.76008 | I15: =IF(C15<1,0,I14-F15+H15) -> 142918.31 | K15: =IF(C15<1,0,(F15-H15)/G15) -> -0.10839724 | L15: =L14 -> 0.0017 | N15: =IF(C15<1,0,N14) -> 1077.0371 | W15: =-G15 -> -1091.0317
A16: =F16/I16 -> 0.00087742479 | B16: =B15+1 -> 10 | C16: =IF(C15-1<1,0,C15-1) -> 332 | D16: =C16/12 -> 27.666667 | E16: =IF(C16<1,0,I15*$J$4) -> 912.29133 | F16: =IF(C16<1,0,G16-E16-$L$3-$L$4) -> 125.50313 | G16: =IF(C16<1,0,-PMT($J$4,C16,I15)+$L$3+$L$4) -> 1092.7945 | H16: =IF(C16<1,0,I15*L16) -> 242.96113 | I16: =IF(C16<1,0,I15-F16+H16) -> 143035.77 | K16: =IF(C16<1,0,(F16-H16)/G16) -> -0.10748407 | L16: =L15 -> 0.0017 | N16: =IF(C16<1,0,N15) -> 1077.0371 | W16: =-G16 -> -1092.7945
A17: =F17/I17 -> 0.0008838074 | B17: =B16+1 -> 11 | C17: =IF(C16-1<1,0,C16-1) -> 331 | D17: =C17/12 -> 27.583333 | E17: =IF(C17<1,0,I16*$J$4) -> 913.0411 | F17: =IF(C17<1,0,G17-E17-$L$3-$L$4) -> 126.51916 | G17: =IF(C17<1,0,-PMT($J$4,C17,I16)+$L$3+$L$4) -> 1094.5603 | H17: =IF(C17<1,0,I16*L17) -> 243.16081 | I17: =IF(C17<1,0,I16-F17+H17) -> 143152.41 | K17: =IF(C17<1,0,(F17-H17)/G17) -> -0.10656485 | L17: =L16 -> 0.0017 | N17: =IF(C17<1,0,N16) -> 1077.0371 | W17: =-G17 -> -1094.5603
A18: =F18/I18 -> 0.00089024218 | B18: =B17+1 -> 12 | C18: =IF(C17-1<1,0,C17-1) -> 330 | D18: =C18/12 -> 27.5 | E18: =IF(C18<1,0,I17*$J$4) -> 913.78566 | F18: =IF(C18<1,0,G18-E18-$L$3-$L$4) -> 127.54342 | G18: =IF(C18<1,0,-PMT($J$4,C18,I17)+$L$3+$L$4) -> 1096.3291 | H18: =IF(C18<1,0,I17*L18) -> 243.3591 | I18: =IF(C18<1,0,I17-F18+H18) -> 143268.23 | K18: =IF(C18<1,0,(F18-H18)/G18) -> -0.10563952 | L18: =L17 -> 0.0017 | N18: =IF(C18<1,0,N17) -> 1077.0371 | W18: =-G18 -> -1096.3291
A19: =F19/I19 -> 0.00089672963 | B19: =B18+1 -> 13 | C19: =IF(C18-1<1,0,C18-1) -> 329 | D19: =C19/12 -> 27.416667 | E19: =IF(C19<1,0,I18*$J$4) -> 914.52494 | F19: =IF(C19<1,0,G19-E19-$L$3-$L$4) -> 128.57597 | G19: =IF(C19<1,0,-PMT($J$4,C19,I18)+$L$3+$L$4) -> 1098.1009 | H19: =IF(C19<1,0,I18*L19) -> 243.55599 | I19: =IF(C19<1,0,I18-F19+H19) -> 143383.21 | K19: =IF(C19<1,0,(F19-H19)/G19) -> -0.10470806 | L19: =L18 -> 0.0017 | N19: =IF(C19<1,0,N18) -> 1077.0371 | W19: =-G19 -> -1098.1009
... A426: =F426/I426 -> #DIV/0! | B426: =B425+1 -> 420 | C426: =IF(C425-1<1,0,C425-1) -> 0 | D426: =C426/12 -> 0 | E426: =IF(C426<1,0,I425*$J$4) -> 0 | F426: =IF(C426<1,0,G426-E426-$L$3-$L$4) -> 0 | G426: =IF(C426<1,0,-PMT($J$4,C426,I425)+$L$3+$L$4) -> 0 | H426: =IF(C426<1,0,I425*L426) -> 0 | I426: =IF(C426<1,0,I425-F426+H426) -> 0 | K426: =IF(C426<1,0,(F426-H426)/G426) -> 0 | L426: =L425 -> 0.0017 | N426: =IF(C426<1,0,N425) -> 0 | W426: =-G426 -> 0

Sheet SAC @amigodopairico
A1: Conheça o PAQ, Programa de Aceleração de Quitação | I1: Clique e saiba mais | L1: @amigodopairico
E2: =SUM(Juros_SAC) -> 189661.57 | F2: =SUM(F7:F426) -> 192335.33 | G2: =SUM(G7:G426) -> 400751.9 | H2: =SUM(H7:H426) -> 50510.609 | O2: =SUM(O7:O426) -> 315390.51
A3: SAC | E3: Valor financiado: | F3: ='RAIO X DO SEU FINANCIAMENTO'!C20 -> 141826 | G3: Meses: | H3: ='RAIO X DO SEU FINANCIAMENTO'!E17 -> 341 | I3: Juros a.a.: | J3: ='RAIO X DO SEU FINANCIAMENTO'!E20 -> 0.079347 | K3: Taxa Adm.: | L3: =IF('RAIO X DO SEU FINANCIAMENTO'!G20>25,25,0) -> 25 | P3: instagram.com/amigodopairico/ | W3: CÁLCULO DO | X3: =(1+X4)^12-1 -> 0.10772141
E4: Total pago: | F4: =G2 -> 400751.9 | I4: Juros a.m: | J4: =(1+J3)^(1/12)-1 -> 0.0063833061 | K4: Seguro: | L4: ='RAIO X DO SEU FINANCIAMENTO'!G20-L3 -> 30 | P4: youtube.com/amigodopairico | W4: CET REAL ➡️ | X4: =IRR(X6:X430) -> 0.0085618719 | Y4: AO MÊS
A6: Amort/SD | C6: Parcelas | D6: A | E6: Juros | F6: Amortização | G6: Parcela | H6: At. Monetária | I6: Saldo Devedor | K6: $ aproveitado | L6: TR | N6: SD Original | O6: Parcela Original | X6: =F3 -> 141826 | Y6: VALOR LIBERADO
A7: =F7/I7 -> 0.0029361703 | B7: 1 | C7: =H3 -> 341 | D7: =C7/12 -> 28.416667 | E7: =F3*$J$4 -> 905.31877 | F7: =F3/C7 -> 415.91202 | G7: =E7+F7+L3+L4 -> 1376.2308 | H7: =F3*L7 -> 241.1042 | I7: =F3-F7+H7 -> 141651.19 | K7: =IF(C7<1,0,(F7-H7)/G7) -> 0.12701927 | L7: ='RAIO X DO SEU FINANCIAMENTO'!G17 -> 0.0017 | N7: =F3-(F3/C7) -> 141410.09 | O7: =F3/H3+F3*J4+L3+L4 -> 1376.2308 | X7: =-G7 -> -1376.2308
A8: =F8/I8 -> 0.0029448315 | B8: =B7+1 -> 2 | C8: =IF(C7-1<1,0,C7-1) -> 340 | D8: =C8/12 -> 28.333333 | E8: =I7*$J$4 -> 904.20291 | F8: =IF(C8<1,0,I7/C8) -> 416.62115 | G8: =IF(C8<1,0,F8+E8+$L$3+$L$4) -> 1375.8241 | H8: =I7*L8 -> 240.80703 | I8: =IF(C8<1,0,I7-F8+H8) -> 141475.38 | K8: =IF(C8<1,0,(F8-H8)/G8) -> 0.12778823 | L8: =L7 -> 0.0017 | N8: =IF(C8<1,0,N7-(N7/C8)) -> 140994.18 | O8: =IF(C8<1,0,N7/C8+N7*$J$4+$L$3+$L$4) -> 1373.5759 | X8: =-G8 -> -1375.8241
A9: =F9/I9 -> 0.002953544 | B9: =B8+1 -> 3 | C9: =IF(C8-1<1,0,C8-1) -> 339 | D9: =C9/12 -> 28.25 | E9: =I8*$J$4 -> 903.08064 | F9: =IF(C9<1,0,I8/C9) -> 417.3315 | G9: =IF(C9<1,0,F9+E9+$L$3+$L$4) -> 1375.4121 | H9: =I8*L9 -> 240.50814 | I9: =IF(C9<1,0,I8-F9+H9) -> 141298.55 | K9: =IF(C9<1,0,(F9-H9)/G9) -> 0.12856027 | L9: =L8 -> 0.0017 | N9: =IF(C9<1,0,N8-(N8/C9)) -> 140578.26 | O9: =IF(C9<1,0,N8/C9+N8*$J$4+$L$3+$L$4) -> 1370.921 | X9: =-G9 -> -1375.4121
A10: =F10/I10 -> 0.0029623082 | B10: =B9+1 -> 4 | C10: =IF(C9-1<1,0,C9-1) -> 338 | D10: =C10/12 -> 28.166667 | E10: =I9*$J$4 -> 901.95192 | F10: =IF(C10<1,0,I9/C10) -> 418.04306 | G10: =IF(C10<1,0,F10+E10+$L$3+$L$4) -> 1374.995 | H10: =I9*L10 -> 240.20754 | I10: =IF(C10<1,0,I9-F10+H10) -> 141120.72 | K10: =IF(C10<1,0,(F10-H10)/G10) -> 0.12933539 | L10: =L9 -> 0.0017 | N10: =IF(C10<1,0,N9-(N9/C10)) -> 140162.35 | O10: =IF(C10<1,0,N9/C10+N9*$J$4+$L$3+$L$4) -> 1368.2661 | X10: =-G10 -> -1374.995
A11: =F11/I11 -> 0.0029711245 | B11: =B10+1 -> 5 | C11: =IF(C10-1<1,0,C10-1) -> 337 | D11: =C11/12 -> 28.083333 | E11: =I10*$J$4 -> 900.81674 | F11: =IF(C11<1,0,I10/C11) -> 418.75584 | G11: =IF(C11<1,0,F11+E11+$L$3+$L$4) -> 1374.5726 | H11: =I10*L11 -> 239.90522 | I11: =IF(C11<1,0,I10-F11+H11) -> 140941.87 | K11: =IF(C11<1,0,(F11-H11)/G11) -> 0.13011362 | L11: =L10 -> 0.0017 | N11: =IF(C11<1,0,N10-(N10/C11)) -> 139746.44 | O11: =IF(C11<1,0,N10/C11+N10*$J$4+$L$3+$L$4) -> 1365.6112 | X11: =-G11 -> -1374.5726
A12: =F12/I12 -> 0.0029799935 | B12: =B11+1 -> 6 | C12: =IF(C11-1<1,0,C11-1) -> 336 | D12: =C12/12 -> 28 | E12: =I11*$J$4 -> 899.67508 | F12: =IF(C12<1,0,I11/C12) -> 419.46985 | G12: =IF(C12<1,0,F12+E12+$L$3+$L$4) -> 1374.1449 | H12: =I11*L12 -> 239.60118 | I12: =IF(C12<1,0,I11-F12+H12) -> 140762 | K12: =IF(C12<1,0,(F12-H12)/G12) -> 0.13089498 | L12: =L11 -> 0.0017 | N12: =IF(C12<1,0,N11-(N11/C12)) -> 139330.53 | O12: =IF(C12<1,0,N11/C12+N11*$J$4+$L$3+$L$4) -> 1362.9563 | X12: =-G12 -> -1374.1449
A13: =F13/I13 -> 0.0029889156 | B13: =B12+1 -> 7 | C13: =IF(C12-1<1,0,C12-1) -> 335 | D13: =C13/12 -> 27.916667 | E13: =I12*$J$4 -> 898.52693 | F13: =IF(C13<1,0,I12/C13) -> 420.18507 | G13: =IF(C13<1,0,F13+E13+$L$3+$L$4) -> 1373.712 | H13: =I12*L13 -> 239.2954 | I13: =IF(C13<1,0,I12-F13+H13) -> 140581.11 | K13: =IF(C13<1,0,(F13-H13)/G13) -> 0.13167947 | L13: =L12 -> 0.0017 | N13: =IF(C13<1,0,N12-(N12/C13)) -> 138914.62 | O13: =IF(C13<1,0,N12/C13+N12*$J$4+$L$3+$L$4) -> 1360.3014 | X13: =-G13 -> -1373.712
A14: =F14/I14 -> 0.0029978913 | B14: =B13+1 -> 8 | C14: =IF(C13-1<1,0,C13-1) -> 334 | D14: =C14/12 -> 27.833333 | E14: =I13*$J$4 -> 897.37225 | F14: =IF(C14<1,0,I13/C14) -> 420.90153 | G14: =IF(C14<1,0,F14+E14+$L$3+$L$4) -> 1373.2738 | H14: =I13*L14 -> 238.98789 | I14: =IF(C14<1,0,I13-F14+H14) -> 140399.2 | K14: =IF(C14<1,0,(F14-H14)/G14) -> 0.13246713 | L14: =L13 -> 0.0017 | N14: =IF(C14<1,0,N13-(N13/C14)) -> 138498.7 | O14: =IF(C14<1,0,N13/C14+N13*$J$4+$L$3+$L$4) -> 1357.6465 | X14: =-G14 -> -1373.2738
A15: =F15/I15 -> 0.003006921 | B15: =B14+1 -> 9 | C15: =IF(C14-1<1,0,C14-1) -> 333 | D15: =C15/12 -> 27.75 | E15: =I14*$J$4 -> 896.21104 | F15: =IF(C15<1,0,I14/C15) -> 421.61921 | G15: =IF(C15<1,0,F15+E15+$L$3+$L$4) -> 1372.8303 | H15: =I14*L15 -> 238.67863 | I15: =IF(C15<1,0,I14-F15+H15) -> 140216.26 | K15: =IF(C15<1,0,(F15-H15)/G15) -> 0.13325797 | L15: =L14 -> 0.0017 | N15: =IF(C15<1,0,N14-(N14/C15)) -> 138082.79 | O15: =IF(C15<1,0,N14/C15+N14*$J$4+$L$3+$L$4) -> 1354.9916 | X15: =-G15 -> -1372.8303
A16: =F16/I16 -> 0.0030160053 | B16: =B15+1 -> 10 | C16: =IF(C15-1<1,0,C15-1) -> 332 | D16: =C16/12 -> 27.666667 | E16: =I15*$J$4 -> 895.04328 | F16: =IF(C16<1,0,I15/C16) -> 422.33812 | G16: =IF(C16<1,0,F16+E16+$L$3+$L$4) -> 1372.3814 | H16: =I15*L16 -> 238.36764 | I16: =IF(C16<1,0,I15-F16+H16) -> 140032.29 | K16: =IF(C16<1,0,(F16-H16)/G16) -> 0.13405201 | L16: =L15 -> 0.0017 | N16: =IF(C16<1,0,N15-(N15/C16)) -> 137666.88 | O16: =IF(C16<1,0,N15/C16+N15*$J$4+$L$3+$L$4) -> 1352.3367 | X16: =-G16 -> -1372.3814
A17: =F17/I17 -> 0.0030251447 | B17: =B16+1 -> 11 | C17: =IF(C16-1<1,0,C16-1) -> 331 | D17: =C17/12 -> 27.583333 | E17: =I16*$J$4 -> 893.86894 | F17: =IF(C17<1,0,I16/C17) -> 423.05826 | G17: =IF(C17<1,0,F17+E17+$L$3+$L$4) -> 1371.9272 | H17: =I16*L17 -> 238.05489 | I17: =IF(C17<1,0,I16-F17+H17) -> 139847.28 | K17: =IF(C17<1,0,(F17-H17)/G17) -> 0.13484927 | L17: =L16 -> 0.0017 | N17: =IF(C17<1,0,N16-(N16/C17)) -> 137250.97 | O17: =IF(C17<1,0,N16/C17+N16*$J$4+$L$3+$L$4) -> 1349.6819 | X17: =-G17 -> -1371.9272
A18: =F18/I18 -> 0.0030343396 | B18: =B17+1 -> 12 | C18: =IF(C17-1<1,0,C17-1) -> 330 | D18: =C18/12 -> 27.5 | E18: =I17*$J$4 -> 892.688 | F18: =IF(C18<1,0,I17/C18) -> 423.77964 | G18: =IF(C18<1,0,F18+E18+$L$3+$L$4) -> 1371.4676 | H18: =I17*L18 -> 237.74038 | I18: =IF(C18<1,0,I17-F18+H18) -> 139661.24 | K18: =IF(C18<1,0,(F18-H18)/G18) -> 0.13564976 | L18: =L17 -> 0.0017 | N18: =IF(C18<1,0,N17-(N17/C18)) -> 136835.06 | O18: =IF(C18<1,0,N17/C18+N17*$J$4+$L$3+$L$4) -> 1347.027 | X18: =-G18 -> -1371.4676
A19: =F19/I19 -> 0.0030435906 | B19: =B18+1 -> 13 | C19: =IF(C18-1<1,0,C18-1) -> 329 | D19: =C19/12 -> 27.416667 | E19: =I18*$J$4 -> 891.50046 | F19: =IF(C19<1,0,I18/C19) -> 424.50226 | G19: =IF(C19<1,0,F19+E19+$L$3+$L$4) -> 1371.0027 | H19: =I18*L19 -> 237.42411 | I19: =IF(C19<1,0,I18-F19+H19) -> 139474.16 | K19: =IF(C19<1,0,(F19-H19)/G19) -> 0.13645352 | L19: =L18 -> 0.0017 | N19: =IF(C19<1,0,N18-(N18/C19)) -> 136419.14 | O19: =IF(C19<1,0,N18/C19+N18*$J$4+$L$3+$L$4) -> 1344.3721 | X19: =-G19 -> -1371.0027
... A426: =F426/I426 -> #DIV/0! | B426: =B425+1 -> 420 | C426: =IF(C425-1<1,0,C425-1) -> 0 | D426: =C426/12 -> 0 | E426: =I425*$J$4 -> 0 | F426: =IF(C426<1,0,I425/C426) -> 0 | G426: =IF(C426<1,0,F426+E426+$L$3+$L$4) -> 0 | H426: =I425*L426 -> 0 | I426: =IF(C426<1,0,I425-F426+H426) -> 0 | K426: =IF(C426<1,0,(F426-H426)/G426) -> 0 | L426: =L425 -> 0.0017 | N426: =IF(C426<1,0,N425-(N425/C426)) -> 0 | O426: =IF(C426<1,0,N425/C426+N425*$J$4+$L$3+$L$4) -> 0 | X426: =-G426 -> 0
X427: =-G427 -> 0
X428: =-G428 -> 0
X429: =-G429 -> 0
X430: =-G430 -> 0

Sheet Dados FGTS
A2: FGTS | C2: Atualização | D2: 0.04
C4: Saldo devedor
A5: Ano | C5: Price
A6: 1 | C6: ='PRICE @amigodopairico'!I18 -> 143268.23
A7: =A6+1 -> 2
A8: =A7+1 -> 3
A9: =A8+1 -> 4
A10: =A9+1 -> 5
A11: =A10+1 -> 6
A12: =A11+1 -> 7
A13: =A12+1 -> 8
A14: =A13+1 -> 9
A15: =A14+1 -> 10
A16: =A15+1 -> 11
A17: =A16+1 -> 12
A18: =A17+1 -> 13
... A25: =A24+1 -> 20

Sheet Data Tipo Finan
A1: SAC
A2: PRICE

Sheet Data Bancos
A1: Caixa
A2: Itaú
A3: Santander
A4: Bradesco
A5: BB
A6: Outros
