Workbook
Name JUROS: 'BASE PRICE @amigodopairico'!#REF!
Name Price: 'BASE PRICE @amigodopairico'!#REF!
Name Price_Adiantamento: 'BASE PRICE @amigodopairico'!$O$15:$O$434
Name Price_Amortizacao: 'BASE PRICE @amigodopairico'!$G$15:$G$434
Name Price_AtualizacaoMonetaria: 'BASE PRICE @amigodopairico'!$R$15:$R$434
Name Price_Invest: 'BASE PRICE @amigodopairico'!#REF!
Name Price_Juros: 'BASE PRICE @amigodopairico'!$F$15:$F$434
Name Price_Parcela: 'BASE PRICE @amigodopairico'!$L$15:$L$434
Name Price_PrevisaoAtualizacaoMonetaria: 'BASE PRICE @amigodopairico'!$R$15:$R$434
Name Price_QuedaSaldoDevedor: 'BASE PRICE @amigodopairico'!$J$15:$J$434
Name Price_Trienio: 'BASE PRICE @amigodopairico'!$A$15:$R$434
Name Price_Trienio2: 'BASE PRICE @amigodopairico'!$A$13:$R$434
Name Price_ValeCada100: 'BASE PRICE @amigodopairico'!#REF!
Name SAC: 'BASE PRICE @amigodopairico'!#REF!
Name SAC_Adiantamento: 'BASE PRICE @amigodopairico'!#REF!
Name SAC_Amortizacao: 'BASE PRICE @amigodopairico'!#REF!
Name SAC_AtualizacaoMonetaria: 'BASE PRICE @amigodopairico'!#REF!
Name SAC_Investimento: 'BASE PRICE @amigodopairico'!#REF!
Name SAC_Juros: 'BASE PRICE @amigodopairico'!#REF!
Name SAC_Parcela: 'BASE PRICE @amigodopairico'!#REF!
Name SAC_PrevisaoAtualizacaoMonetaria: 'BASE PRICE @amigodopairico'!#REF!
Name SAC_QuedaSaldoDevedor: 'BASE PRICE @amigodopairico'!#REF!
Name SAC_SaidobolsocomPPP: 'BASE PRICE @amigodopairico'!#REF!
Name SAC_Trienio: 'BASE PRICE @amigodopairico'!#REF!
Name SALDO_DEVEDOR: 'BASE PRICE @amigodopairico'!#REF!

Sheet BASE PRICE @amigodopairico
F4: ONDE TE AJUDO MAIS ➡️ amigodopairico.com.br/paq | X4: ONDE TE AJUDO MAIS ➡️ amigodopairico.com.br/paq
A5: =SUM(A15:A434) -> 2525 | B5: =SUM(B15:B434) -> 7575 | D5: PRICE | F5: =SUM(F15:F434) -> 48371.802 | G5: =SUM(G15:G434) -> 110312.28 | L5: =SUM(L15:L434) -> 168784.09 | O5: =SUM(O15:O434) -> 0 | R5: =SUM(R15:R434) -> 10312.342 | AJ5: =SUM(AJ15:AJ434) -> 2525 | AK5: =SUM(AK15:AK434) -> 7575 | AO5: =SUM(AO15:AO434) -> 48371.802 | AP5: =SUM(AP15:AP434) -> 110312.28 | AQ5: PRICE | AS5: =SUM(AS15:AS434) -> 168784.09 | AU5: =SUM(AU15:AU434) -> 0 | AX5: =SUM(AX15:AX434) -> 10312.342
B6: DADOS | F6: SE NÃO FIZER NADA | N6: COM ESTRATÉGIA | Y6: Em quantos anos quer quitar? | Z6: 5 | AK6: DADOS | AP6: SE NÃO FIZER NADA
C7: Taxa de juros | D7: 0.1 | E7: =((1+D7)^(1/12))-1 -> 0.0079741404 | G7: Meses | H7: 100 | N7: Passa a quitar em | O7: =COUNTIF(N15:N434,">10")+IF(COUNTIF(N15:N434,">10")+1>H7,0,1) -> 100 | P7: =" "&TEXT(O7/12,"0,0") & " anos" -> 8,3 anos | Y7: Amortize por mês pelo menos: | Z7: =-PMT(E7,Z6*12,D8)-L15+A15+B15 -> 648.63711 | AL7: Taxa de juros | AM7: =D7 -> 0.1 | AN7: =E7 -> 0.0079741404 | AR7: Meses | AS7: =H7 -> 100
C8: Valor financiado | D8: 100000 | G8: Correção monetária | H8: =R5 -> 10312.342 | J8: QUANTO É APROVEITADO | N8: Parcelas a menos | O8: =H7-O7 -> 0 | P8: =" "&TEXT(O8/12,"0,0") & " anos a menos" -> 0,0 anos a menos | S8: =IF(O8>0,O5/O8,0) -> 0 | T8: cada parcela | V8: VPL | AL8: Valor financiado | AM8: =D8 -> 100000 | AR8: Correção monetária | AS8: =H8 -> 10312.342
C9: Correção Monetária | D9: 0.0017 | G9: Total inicial | H9: =AS10 -> 168784.09 | J9: DO VALOR QUE VOCÊ PAGA | N9: Total pago | O9: =SUM(L15:L434)+SUM(O15:O434) -> 168784.09 | V9: =NPV(V10,V15:V434) -> -100000 | AL9: Correção Monetária | AM9: =D9 -> 0.0017 | AR9: Juros previstos | AS9: =AO5+AJ5+AK5 -> 58471.802
C10: CET REAL | D10: =V13 -> 0.14199141 | E10: =(1+D10)^(1/12)-1 -> 0.011125903 | G10: Juros totais pagos | H10: =AS9 -> 58471.802 | J10: ⬇️ | N10: Juros pagos | O10: =SUM(F15:F434)+A5+B5 -> 58471.802 | V10: =IRR(V14:V434) -> 0.011125903 | AL10: CET REAL | AM10: =D10 -> 0.14199141 | AN10: =(1+AM10)^(1/12)-1 -> 0.011125903 | AR10: Total previsto | AS10: =AS5 -> 168784.09
N11: ECONOMIA TOTAL | O11: =H9-O9 -> 0
A13: Taxa | B13: Seguro | C13: Momento | D13: % Amort Parcela | F13: Juros | G13: Amortização | J13: VALOR ÚTIL | K13: % VU | L13: Parcela do banco | M13: Parcela na SAC | N13: Saldo Devedor | O13: Amortização | P13: Faltam | Q13: T/V | R13: At. Monetária | V13: =(1+V10)^12-1 -> 0.14199141 | AA13: Década | AB13: Triênio | AC13: Ano | AJ13: Taxa | AK13: Seguro | AL13: Momento | AM13: =AV7/12 -> 0 | AO13: Juros | AP13: Amortização | AS13: Parcela do banco | AT13: Saldo Devedor | AU13: Amortização | AV13: Faltam | AW13: T/V | AX13: At. Monetária
V14: =D8 -> 100000 | AM14: Só parcela
A15: 25 | B15: 75 | C15: 46054 | D15: =IF(D8>0,G15/D8,"") -> 0.00657507 | E15: 1 | F15: =IF(D8>0,D8*$E$7,0) -> 797.41404 | G15: =IF(D8>G14,L15-F15-A15-B15,D8) -> 657.507 | H15: =IF(L15<1,"",IF(G15/L15>90%,"🛩",IF(G15/L15>70%,"🏎",IF(G15/L15>50%,"🚙",IF(G15/L15>30%,"🛵",IF(G15/L15>15%,"🐢","⚓️")))))) -> 🛵 | I15: =IFERROR(IF((G15+O15-R15)/L15<0,"🗑️",IF((G15+O15-R15)/L15<10%,"🥾",IF((G15+O15-R15)/L15<20%,"🛴",IF((G15+O15-R15)/L15<50%,"🚴‍♂️",IF((G15+O15-R15)/L15<75%,"🚖","🚁"))))),"") -> 🚴‍♂️ | J15: =G15+O15-R15 -> 487.507 | K15: =IFERROR(J15/(L15+O15),0) -> 0.31352525 | L15: =-PMT(E$7,$H$7,D8)+A15+B15 -> 1554.921 | M15: =IFERROR(D8/P15-G15+L15,0) -> 1907.5151 | N15: =IF(D8-O15-G15<0,0,IF(D8-G15>0,D8-G15,0)-IF(D8-G15>0,O15-R15,0)) -> 99512.493 | P15: =NPER($E$7,-L15+A15+B15,D8)-1 -> 99 | R15: =D8*$D$9 -> 170 | V15: =-L15-O15 -> -1554.921 | X15: ATENÇÃO: Esta planilha deve ser usada apenas para simulações. | AA15: =ROUNDUP(E15/120,0) -> 1 | AB15: =ROUNDUP(E15/36,0) -> 1 | AC15: =ROUNDUP(E15/12,0) -> 1 | AJ15: 25 | AK15: =B15 -> 75 | AL15: 46054 | AM15: =IF(AM8>0,AP15/AM8,"") -> 0.00657507 | AN15: 1 | AO15: =IF(AM8>0,AM8*$E$7,0) -> 797.41404 | AP15: =IF(AM8>AP14,AS15-AO15-AJ15-AK15,AM8) -> 657.507 | AQ15: =IF(AS15<1,"",IF(AP15/AS15>90%,"🛩",IF(AP15/AS15>70%,"🏎",IF(AP15/AS15>50%,"🚙",IF(AP15/AS15>30%,"🛵",IF(AP15/AS15>15%,"🐢","⚓️")))))) -> 🛵 | AR15: =IFERROR(IF((AP15+AU15-AX15)/AS15<0,"🗑️",IF((AP15+AU15-AX15)/AS15<10%,"🥾",IF((AP15+AU15-AX15)/AS15<20%,"🛴",IF((AP15+AU15-AX15)/AS15<50%,"🚴‍♂️",IF((AP15+AU15-AX15)/AS15<75%,"🚖","🚁"))))),"") -> 🚴‍♂️ | AS15: =-PMT(AN$7,$H$7,AM8)+AJ15+AK15 -> 1554.921 | AT15: =IF(AM8-AU15-AP15<0,0,IF(AM8-AP15>0,AM8-AP15,0)-IF(AM8-AP15>0,AU15-AX15,0)) -> 99512.493 | AU15: 0 | AV15: =NPER($E$7,-AS15+AJ15+AK15,AM8)-1 -> 99 | AX15: =AM8*$D$9 -> 170
A16: =IF(INT(N15)=0,0,A15) -> 25 | B16: =IF(N15<1,0,B15) -> 75 | C16: =DATE(YEAR(C15),MONTH(C15)+1,1) -> 46082 | D16: =IF(N15>0,G16/N15,"") -> 0.0066713225 | E16: =E15+1 -> 2 | F16: =IF(N15>0,N15*$E$7,0) -> 793.52659 | G16: =IF(N15>G15,L16-F16-A16-B16,N15) -> 663.87994 | H16: =IF(L16<1,"",IF(G16/L16>90%,"🛩",IF(G16/L16>70%,"🏎",IF(G16/L16>50%,"🚙",IF(G16/L16>30%,"🛵",IF(G16/L16>15%,"🐢","⚓️")))))) -> 🛵 | I16: =IFERROR(IF((G16+O16-R16)/L16<0,"🗑️",IF((G16+O16-R16)/L16<10%,"🥾",IF((G16+O16-R16)/L16<20%,"🛴",IF((G16+O16-R16)/L16<50%,"🚴‍♂️",IF((G16+O16-R16)/L16<75%,"🚖","🚁"))))),"") -> 🚴‍♂️ | J16: =G16+O16-R16 -> 494.7087 | K16: =IFERROR(J16/(L16+O16),0) -> 0.31764905 | L16: =IF(INT(N15)=0,0,IF(N15<G15,N15+F16+A16+B16,-PMT($E$7,IF(Q15="V",P15,NPER($E$7,-L15+A16+B16,N15)),N15+R15)+A16+B16))+IF(INT(P15)=1,R16,0) -> 1557.4065 | M16: =IFERROR(N15/P16-G16+L16,0) -> 1906.2961 | N16: =IF(N15-O16-G16<0,0,IF(N15-G16>0,N15-G16,0)-IF(N15-G16>0,O16-R16,0)) -> 99017.784 | P16: =IFERROR(NPER($E$7,-L16+A15+B15,N15+R15)-1,0) -> 98.257792 | R16: =N15*$D$9 -> 169.17124 | V16: =-L16-O16 -> -1557.4065 | X16: Confira sempre os valores no seu Documento Descritivo de Crédito. | AA16: =ROUNDUP(E16/120,0) -> 1 | AB16: =ROUNDUP(E16/36,0) -> 1 | AC16: =ROUNDUP(E16/12,0) -> 1 | AJ16: =IF(INT(AT15)=0,0,AJ15) -> 25 | AK16: =IF(AT15<1,0,AK15) -> 75 | AL16: =DATE(YEAR(AL15),MONTH(AL15)+1,1) -> 46082 | AM16: =IF(AT15>0,AP16/AT15,"") -> 0.0066713225 | AN16: =AN15+1 -> 2 | AO16: =IF(AT15>0,AT15*$E$7,0) -> 793.52659 | AP16: =IF(AT15>AP15,AS16-AO16-AJ16-AK16,AT15) -> 663.87994 | AQ16: =IF(AS16<1,"",IF(AP16/AS16>90%,"🛩",IF(AP16/AS16>70%,"🏎",IF(AP16/AS16>50%,"🚙",IF(AP16/AS16>30%,"🛵",IF(AP16/AS16>15%,"🐢","⚓️")))))) -> 🛵 | AR16: =IFERROR(IF((AP16+AU16-AX16)/AS16<0,"🗑️",IF((AP16+AU16-AX16)/AS16<10%,"🥾",IF((AP16+AU16-AX16)/AS16<20%,"🛴",IF((AP16+AU16-AX16)/AS16<50%,"🚴‍♂️",IF((AP16+AU16-AX16)/AS16<75%,"🚖","🚁"))))),"") -> 🚴‍♂️ | AS16: =IF(INT(AT15)=0,0,IF(AT15<AP15,AT15+AO16+AJ16+AK16,-PMT($E$7,IF(AW15="V",AV15,NPER($E$7,-AS15+AJ16+AK16,AT15)),AT15+AX15)+AJ16+AK16))+IF(INT(AV15)=1,AX16,0) -> 1557.4065 | AT16: =IF(AT15-AU16-AP16<0,0,IF(AT15-AP16>0,AT15-AP16,0)-IF(AT15-AP16>0,AU16-AX16,0)) -> 99017.784 | AU16: 0 | AV16: =IFERROR(NPER($E$7,-AS16+AJ15+AK15,AT15+AX15)-1,0) -> 98.257792 | AX16: =AT15*$D$9 -> 169.17124
A17: =IF(N16<1,0,A16) -> 25 | B17: =IF(N16<1,0,B16) -> 75 | C17: =DATE(YEAR(C16),MONTH(C16)+1,1) -> 46113 | D17: =IF(N16>0,G17/N16,"") -> 0.0067696403 | E17: =E16+1 -> 3 | F17: =IF(N16>0,N16*$E$7,0) -> 789.58172 | G17: =IF(N16>G16,L17-F17-A17-B17,N16) -> 670.31478 | H17: =IF(L17<1,"",IF(G17/L17>90%,"🛩",IF(G17/L17>70%,"🏎",IF(G17/L17>50%,"🚙",IF(G17/L17>30%,"🛵",IF(G17/L17>15%,"🐢","⚓️")))))) -> 🛵 | I17: =IFERROR(IF((G17+O17-R17)/L17<0,"🗑️",IF((G17+O17-R17)/L17<10%,"🥾",IF((G17+O17-R17)/L17<20%,"🛴",IF((G17+O17-R17)/L17<50%,"🚴‍♂️",IF((G17+O17-R17)/L17<75%,"🚖","🚁"))))),"") -> 🚴‍♂️ | J17: =G17+O17-R17 -> 501.98455 | K17: =IFERROR(J17/(L17+O17),0) -> 0.32180632 | L17: =IF(INT(N16)=0,0,IF(N16<G16,N16+F17+A17+B17,-PMT($E$7,IF(Q16="V",P16,NPER($E$7,-L16+A17+B17,N16)),N16+R16)+A17+B17))+IF(INT(P16)=1,R17,0) -> 1559.8965 | M17: =IFERROR(N16/P17-G17+L17,0) -> 1907.7123 | N17: =IF(N16-O17-G17<0,0,IF(N16-G17>0,N16-G17,0)-IF(N16-G17>0,O17-R17,0)) -> 98515.8 | P17: =IFERROR(NPER($E$7,-L17+A16+B16,N16+R16)-1,0) -> 97.254508 | R17: =N16*$D$9 -> 168.33023 | V17: =-L17-O17 -> -1559.8965 | X17: Para chegar nos valores mais próximos, adicione as | AA17: =ROUNDUP(E17/120,0) -> 1 | AB17: =ROUNDUP(E17/36,0) -> 1 | AC17: =ROUNDUP(E17/12,0) -> 1 | AJ17: =IF(AT16<1,0,AJ16) -> 25 | AK17: =IF(AT16<1,0,AK16) -> 75 | AL17: =DATE(YEAR(AL16),MONTH(AL16)+1,1) -> 46113 | AM17: =IF(AT16>0,AP17/AT16,"") -> 0.0067696403 | AN17: =AN16+1 -> 3 | AO17: =IF(AT16>0,AT16*$E$7,0) -> 789.58172 | AP17: =IF(AT16>AP16,AS17-AO17-AJ17-AK17,AT16) -> 670.31478 | AQ17: =IF(AS17<1,"",IF(AP17/AS17>90%,"🛩",IF(AP17/AS17>70%,"🏎",IF(AP17/AS17>50%,"🚙",IF(AP17/AS17>30%,"🛵",IF(AP17/AS17>15%,"🐢","⚓️")))))) -> 🛵 | AR17: =IFERROR(IF((AP17+AU17-AX17)/AS17<0,"🗑️",IF((AP17+AU17-AX17)/AS17<10%,"🥾",IF((AP17+AU17-AX17)/AS17<20%,"🛴",IF((AP17+AU17-AX17)/AS17<50%,"🚴‍♂️",IF((AP17+AU17-AX17)/AS17<75%,"🚖","🚁"))))),"") -> 🚴‍♂️ | AS17: =IF(INT(AT16)=0,0,IF(AT16<AP16,AT16+AO17+AJ17+AK17,-PMT($E$7,IF(AW16="V",AV16,NPER($E$7,-AS16+AJ17+AK17,AT16)),AT16+AX16)+AJ17+AK17))+IF(INT(AV16)=1,AX17,0) -> 1559.8965 | AT17: =IF(AT16-AU17-AP17<0,0,IF(AT16-AP17>0,AT16-AP17,0)-IF(AT16-AP17>0,AU17-AX17,0)) -> 98515.8 | AU17: 0 | AV17: =IFERROR(NPER($E$7,-AS17+AJ16+AK16,AT16+AX16)-1,0) -> 97.254508 | AX17: =AT16*$D$9 -> 168.33023
A18: =IF(N17<1,0,A17) -> 25 | B18: =IF(N17<1,0,B17) -> 75 | C18: =DATE(YEAR(C17),MONTH(C17)+1,1) -> 46143 | D18: =IF(N17>0,G18/N17,"") -> 0.0068700873 | E18: =E17+1 -> 4 | F18: =IF(N17>0,N17*$E$7,0) -> 785.57882 | G18: =IF(N17>G17,L18-F18-A18-B18,N17) -> 676.81215 | H18: =IF(L18<1,"",IF(G18/L18>90%,"🛩",IF(G18/L18>70%,"🏎",IF(G18/L18>50%,"🚙",IF(G18/L18>30%,"🛵",IF(G18/L18>15%,"🐢","⚓️")))))) -> 🛵 | I18: =IFERROR(IF((G18+O18-R18)/L18<0,"🗑️",IF((G18+O18-R18)/L18<10%,"🥾",IF((G18+O18-R18)/L18<20%,"🛴",IF((G18+O18-R18)/L18<50%,"🚴‍♂️",IF((G18+O18-R18)/L18<75%,"🚖","🚁"))))),"") -> 🚴‍♂️ | J18: =G18+O18-R18 -> 509.33529 | K18: =IFERROR(J18/(L18+O18),0) -> 0.32599733 | L18: =IF(INT(N17)=0,0,IF(N17<G17,N17+F18+A18+B18,-PMT($E$7,IF(Q17="V",P17,NPER($E$7,-L17+A18+B18,N17)),N17+R17)+A18+B18))+IF(INT(P17)=1,R18,0) -> 1562.391 | M18: =IFERROR(N17/P18-G18+L18,0) -> 1909.1063 | N18: =IF(N17-O18-G18<0,0,IF(N17-G18>0,N17-G18,0)-IF(N17-G18>0,O18-R18,0)) -> 98006.464 | P18: =IFERROR(NPER($E$7,-L18+A17+B17,N17+R17)-1,0) -> 96.251247 | R18: =N17*$D$9 -> 167.47686 | V18: =-L18-O18 -> -1562.391 | X18: correções monetárias e o seguro a cada mês. | AA18: =ROUNDUP(E18/120,0) -> 1 | AB18: =ROUNDUP(E18/36,0) -> 1 | AC18: =ROUNDUP(E18/12,0) -> 1 | AJ18: =IF(AT17<1,0,AJ17) -> 25 | AK18: =IF(AT17<1,0,AK17) -> 75 | AL18: =DATE(YEAR(AL17),MONTH(AL17)+1,1) -> 46143 | AM18: =IF(AT17>0,AP18/AT17,"") -> 0.0068700873 | AN18: =AN17+1 -> 4 | AO18: =IF(AT17>0,AT17*$E$7,0) -> 785.57882 | AP18: =IF(AT17>AP17,AS18-AO18-AJ18-AK18,AT17) -> 676.81215 | AQ18: =IF(AS18<1,"",IF(AP18/AS18>90%,"🛩",IF(AP18/AS18>70%,"🏎",IF(AP18/AS18>50%,"🚙",IF(AP18/AS18>30%,"🛵",IF(AP18/AS18>15%,"🐢","⚓️")))))) -> 🛵 | AR18: =IFERROR(IF((AP18+AU18-AX18)/AS18<0,"🗑️",IF((AP18+AU18-AX18)/AS18<10%,"🥾",IF((AP18+AU18-AX18)/AS18<20%,"🛴",IF((AP18+AU18-AX18)/AS18<50%,"🚴‍♂️",IF((AP18+AU18-AX18)/AS18<75%,"🚖","🚁"))))),"") -> 🚴‍♂️ | AS18: =IF(INT(AT17)=0,0,IF(AT17<AP17,AT17+AO18+AJ18+AK18,-PMT($E$7,IF(AW17="V",AV17,NPER($E$7,-AS17+AJ18+AK18,AT17)),AT17+AX17)+AJ18+AK18))+IF(INT(AV17)=1,AX18,0) -> 1562.391 | AT18: =IF(AT17-AU18-AP18<0,0,IF(AT17-AP18>0,AT17-AP18,0)-IF(AT17-AP18>0,AU18-AX18,0)) -> 98006.464 | AU18: 0 | AV18: =IFERROR(NPER($E$7,-AS18+AJ17+AK17,AT17+AX17)-1,0) -> 96.251247 | AX18: =AT17*$D$9 -> 167.47686
A19: =IF(N18<1,0,A18) -> 25 | B19: =IF(N18<1,0,B18) -> 75 | C19: =DATE(YEAR(C18),MONTH(C18)+1,1) -> 46174 | D19: =IF(N18>0,G19/N18,"") -> 0.0069727303 | E19: =E18+1 -> 5 | F19: =IF(N18>0,N18*$E$7,0) -> 781.51731 | G19: =IF(N18>G18,L19-F19-A19-B19,N18) -> 683.37264 | H19: =IF(L19<1,"",IF(G19/L19>90%,"🛩",IF(G19/L19>70%,"🏎",IF(G19/L19>50%,"🚙",IF(G19/L19>30%,"🛵",IF(G19/L19>15%,"🐢","⚓️")))))) -> 🛵 | I19: =IFERROR(IF((G19+O19-R19)/L19<0,"🗑️",IF((G19+O19-R19)/L19<10%,"🥾",IF((G19+O19-R19)/L19<20%,"🛴",IF((G19+O19-R19)/L19<50%,"🚴‍♂️",IF((G19+O19-R19)/L19<75%,"🚖","🚁"))))),"") -> 🚴‍♂️ | J19: =G19+O19-R19 -> 516.76165 | K19: =IFERROR(J19/(L19+O19),0) -> 0.33022236 | L19: =IF(INT(N18)=0,0,IF(N18<G18,N18+F19+A19+B19,-PMT($E$7,IF(Q18="V",P18,NPER($E$7,-L18+A19+B19,N18)),N18+R18)+A19+B19))+IF(INT(P18)=1,R19,0) -> 1564.89 | M19: =IFERROR(N18/P19-G19+L19,0) -> 1910.4781 | N19: =IF(N18-O19-G19<0,0,IF(N18-G19>0,N18-G19,0)-IF(N18-G19>0,O19-R19,0)) -> 97489.703 | P19: =IFERROR(NPER($E$7,-L19+A18+B18,N18+R18)-1,0) -> 95.24801 | R19: =N18*$D$9 -> 166.61099 | V19: =-L19-O19 -> -1564.89 | X19: https://www.habitacaodigital.caixa.gov.br/ | AA19: =ROUNDUP(E19/120,0) -> 1 | AB19: =ROUNDUP(E19/36,0) -> 1 | AC19: =ROUNDUP(E19/12,0) -> 1 | AJ19: =IF(AT18<1,0,AJ18) -> 25 | AK19: =IF(AT18<1,0,AK18) -> 75 | AL19: =DATE(YEAR(AL18),MONTH(AL18)+1,1) -> 46174 | AM19: =IF(AT18>0,AP19/AT18,"") -> 0.0069727303 | AN19: =AN18+1 -> 5 | AO19: =IF(AT18>0,AT18*$E$7,0) -> 781.51731 | AP19: =IF(AT18>AP18,AS19-AO19-AJ19-AK19,AT18) -> 683.37264 | AQ19: =IF(AS19<1,"",IF(AP19/AS19>90%,"🛩",IF(AP19/AS19>70%,"🏎",IF(AP19/AS19>50%,"🚙",IF(AP19/AS19>30%,"🛵",IF(AP19/AS19>15%,"🐢","⚓️")))))) -> 🛵 | AR19: =IFERROR(IF((AP19+AU19-AX19)/AS19<0,"🗑️",IF((AP19+AU19-AX19)/AS19<10%,"🥾",IF((AP19+AU19-AX19)/AS19<20%,"🛴",IF((AP19+AU19-AX19)/AS19<50%,"🚴‍♂️",IF((AP19+AU19-AX19)/AS19<75%,"🚖","🚁"))))),"") -> 🚴‍♂️ | AS19: =IF(INT(AT18)=0,0,IF(AT18<AP18,AT18+AO19+AJ19+AK19,-PMT($E$7,IF(AW18="V",AV18,NPER($E$7,-AS18+AJ19+AK19,AT18)),AT18+AX18)+AJ19+AK19))+IF(INT(AV18)=1,AX19,0) -> 1564.89 | AT19: =IF(AT18-AU19-AP19<0,0,IF(AT18-AP19>0,AT18-AP19,0)-IF(AT18-AP19>0,AU19-AX19,0)) -> 97489.703 | AU19: 0 | AV19: =IFERROR(NPER($E$7,-AS19+AJ18+AK18,AT18+AX18)-1,0) -> 95.24801 | AX19: =AT18*$D$9 -> 166.61099
A20: =IF(N19<1,0,A19) -> 25 | B20: =IF(N19<1,0,B19) -> 75 | C20: =DATE(YEAR(C19),MONTH(C19)+1,1) -> 46204 | D20: =IF(N19>0,G20/N19,"") -> 0.0070776386 | E20: =E19+1 -> 6 | F20: =IF(N19>0,N19*$E$7,0) -> 777.39658 | G20: =IF(N19>G19,L20-F20-A20-B20,N19) -> 689.99689 | H20: =IF(L20<1,"",IF(G20/L20>90%,"🛩",IF(G20/L20>70%,"🏎",IF(G20/L20>50%,"🚙",IF(G20/L20>30%,"🛵",IF(G20/L20>15%,"🐢","⚓️")))))) -> 🛵 | I20: =IFERROR(IF((G20+O20-R20)/L20<0,"🗑️",IF((G20+O20-R20)/L20<10%,"🥾",IF((G20+O20-R20)/L20<20%,"🛴",IF((G20+O20-R20)/L20<50%,"🚴‍♂️",IF((G20+O20-R20)/L20<75%,"🚖","🚁"))))),"") -> 🚴‍♂️ | J20: =G20+O20-R20 -> 524.26439 | K20: =IFERROR(J20/(L20+O20),0) -> 0.33448167 | L20: =IF(INT(N19)=0,0,IF(N19<G19,N19+F20+A20+B20,-PMT($E$7,IF(Q19="V",P19,NPER($E$7,-L19+A20+B20,N19)),N19+R19)+A20+B20))+IF(INT(P19)=1,R20,0) -> 1567.3935 | M20: =IFERROR(N19/P20-G20+L20,0) -> 1911.8272 | N20: =IF(N19-O20-G20<0,0,IF(N19-G20>0,N19-G20,0)-IF(N19-G20>0,O20-R20,0)) -> 96965.438 | P20: =IFERROR(NPER($E$7,-L20+A19+B19,N19+R19)-1,0) -> 94.244795 | R20: =N19*$D$9 -> 165.73249 | V20: =-L20-O20 -> -1567.3935 | X20: Documento Descritivo de Crédito | AA20: =ROUNDUP(E20/120,0) -> 1 | AB20: =ROUNDUP(E20/36,0) -> 1 | AC20: =ROUNDUP(E20/12,0) -> 1 | AJ20: =IF(AT19<1,0,AJ19) -> 25 | AK20: =IF(AT19<1,0,AK19) -> 75 | AL20: =DATE(YEAR(AL19),MONTH(AL19)+1,1) -> 46204 | AM20: =IF(AT19>0,AP20/AT19,"") -> 0.0070776386 | AN20: =AN19+1 -> 6 | AO20: =IF(AT19>0,AT19*$E$7,0) -> 777.39658 | AP20: =IF(AT19>AP19,AS20-AO20-AJ20-AK20,AT19) -> 689.99689 | AQ20: =IF(AS20<1,"",IF(AP20/AS20>90%,"🛩",IF(AP20/AS20>70%,"🏎",IF(AP20/AS20>50%,"🚙",IF(AP20/AS20>30%,"🛵",IF(AP20/AS20>15%,"🐢","⚓️")))))) -> 🛵 | AR20: =IFERROR(IF((AP20+AU20-AX20)/AS20<0,"🗑️",IF((AP20+AU20-AX20)/AS20<10%,"🥾",IF((AP20+AU20-AX20)/AS20<20%,"🛴",IF((AP20+AU20-AX20)/AS20<50%,"🚴‍♂️",IF((AP20+AU20-AX20)/AS20<75%,"🚖","🚁"))))),"") -> 🚴‍♂️ | AS20: =IF(INT(AT19)=0,0,IF(AT19<AP19,AT19+AO20+AJ20+AK20,-PMT($E$7,IF(AW19="V",AV19,NPER($E$7,-AS19+AJ20+AK20,AT19)),AT19+AX19)+AJ20+AK20))+IF(INT(AV19)=1,AX20,0) -> 1567.3935 | AT20: =IF(AT19-AU20-AP20<0,0,IF(AT19-AP20>0,AT19-AP20,0)-IF(AT19-AP20>0,AU20-AX20,0)) -> 96965.438 | AU20: 0 | AV20: =IFERROR(NPER($E$7,-AS20+AJ19+AK19,AT19+AX19)-1,0) -> 94.244795 | AX20: =AT19*$D$9 -> 165.73249
A21: =IF(N20<1,0,A20) -> 25 | B21: =IF(N20<1,0,B20) -> 75 | C21: =DATE(YEAR(C20),MONTH(C20)+1,1) -> 46235 | D21: =IF(N20>0,G21/N20,"") -> 0.0071848848 | E21: =E20+1 -> 7 | F21: =IF(N20>0,N20*$E$7,0) -> 773.21602 | G21: =IF(N20>G20,L21-F21-A21-B21,N20) -> 696.6855 | H21: =IF(L21<1,"",IF(G21/L21>90%,"🛩",IF(G21/L21>70%,"🏎",IF(G21/L21>50%,"🚙",IF(G21/L21>30%,"🛵",IF(G21/L21>15%,"🐢","⚓️")))))) -> 🛵 | I21: =IFERROR(IF((G21+O21-R21)/L21<0,"🗑️",IF((G21+O21-R21)/L21<10%,"🥾",IF((G21+O21-R21)/L21<20%,"🛴",IF((G21+O21-R21)/L21<50%,"🚴‍♂️",IF((G21+O21-R21)/L21<75%,"🚖","🚁"))))),"") -> 🚴‍♂️ | J21: =G21+O21-R21 -> 531.84426 | K21: =IFERROR(J21/(L21+O21),0) -> 0.33877555 | L21: =IF(INT(N20)=0,0,IF(N20<G20,N20+F21+A21+B21,-PMT($E$7,IF(Q20="V",P20,NPER($E$7,-L20+A21+B21,N20)),N20+R20)+A21+B21))+IF(INT(P20)=1,R21,0) -> 1569.9015 | M21: =IFERROR(N20/P21-G21+L21,0) -> 1913.1535 | N21: =IF(N20-O21-G21<0,0,IF(N20-G21>0,N20-G21,0)-IF(N20-G21>0,O21-R21,0)) -> 96433.594 | P21: =IFERROR(NPER($E$7,-L21+A20+B20,N20+R20)-1,0) -> 93.241603 | R21: =N20*$D$9 -> 164.84125 | V21: =-L21-O21 -> -1569.9015 | AA21: =ROUNDUP(E21/120,0) -> 1 | AB21: =ROUNDUP(E21/36,0) -> 1 | AC21: =ROUNDUP(E21/12,0) -> 1 | AJ21: =IF(AT20<1,0,AJ20) -> 25 | AK21: =IF(AT20<1,0,AK20) -> 75 | AL21: =DATE(YEAR(AL20),MONTH(AL20)+1,1) -> 46235 | AM21: =IF(AT20>0,AP21/AT20,"") -> 0.0071848848 | AN21: =AN20+1 -> 7 | AO21: =IF(AT20>0,AT20*$E$7,0) -> 773.21602 | AP21: =IF(AT20>AP20,AS21-AO21-AJ21-AK21,AT20) -> 696.6855 | AQ21: =IF(AS21<1,"",IF(AP21/AS21>90%,"🛩",IF(AP21/AS21>70%,"🏎",IF(AP21/AS21>50%,"🚙",IF(AP21/AS21>30%,"🛵",IF(AP21/AS21>15%,"🐢","⚓️")))))) -> 🛵 | AR21: =IFERROR(IF((AP21+AU21-AX21)/AS21<0,"🗑️",IF((AP21+AU21-AX21)/AS21<10%,"🥾",IF((AP21+AU21-AX21)/AS21<20%,"🛴",IF((AP21+AU21-AX21)/AS21<50%,"🚴‍♂️",IF((AP21+AU21-AX21)/AS21<75%,"🚖","🚁"))))),"") -> 🚴‍♂️ | AS21: =IF(INT(AT20)=0,0,IF(AT20<AP20,AT20+AO21+AJ21+AK21,-PMT($E$7,IF(AW20="V",AV20,NPER($E$7,-AS20+AJ21+AK21,AT20)),AT20+AX20)+AJ21+AK21))+IF(INT(AV20)=1,AX21,0) -> 1569.9015 | AT21: =IF(AT20-AU21-AP21<0,0,IF(AT20-AP21>0,AT20-AP21,0)-IF(AT20-AP21>0,AU21-AX21,0)) -> 96433.594 | AU21: 0 | AV21: =IFERROR(NPER($E$7,-AS21+AJ20+AK20,AT20+AX20)-1,0) -> 93.241603 | AX21: =AT20*$D$9 -> 164.84125
A22: =IF(N21<1,0,A21) -> 25 | B22: =IF(N21<1,0,B21) -> 75 | C22: =DATE(YEAR(C21),MONTH(C21)+1,1) -> 46266 | D22: =IF(N21>0,G22/N21,"") -> 0.0072945442 | E22: =E21+1 -> 8 | F22: =IF(N21>0,N21*$E$7,0) -> 768.97502 | G22: =IF(N21>G21,L22-F22-A22-B22,N21) -> 703.43912 | H22: =IF(L22<1,"",IF(G22/L22>90%,"🛩",IF(G22/L22>70%,"🏎",IF(G22/L22>50%,"🚙",IF(G22/L22>30%,"🛵",IF(G22/L22>15%,"🐢","⚓️")))))) -> 🛵 | I22: =IFERROR(IF((G22+O22-R22)/L22<0,"🗑️",IF((G22+O22-R22)/L22<10%,"🥾",IF((G22+O22-R22)/L22<20%,"🛴",IF((G22+O22-R22)/L22<50%,"🚴‍♂️",IF((G22+O22-R22)/L22<75%,"🚖","🚁"))))),"") -> 🚴‍♂️ | J22: =G22+O22-R22 -> 539.50201 | K22: =IFERROR(J22/(L22+O22),0) -> 0.34310427 | L22: =IF(INT(N21)=0,0,IF(N21<G21,N21+F22+A22+B22,-PMT($E$7,IF(Q21="V",P21,NPER($E$7,-L21+A22+B22,N21)),N21+R21)+A22+B22))+IF(INT(P21)=1,R22,0) -> 1572.4141 | M22: =IFERROR(N21/P22-G22+L22,0) -> 1914.4567 | N22: =IF(N21-O22-G22<0,0,IF(N21-G22>0,N21-G22,0)-IF(N21-G22>0,O22-R22,0)) -> 95894.092 | P22: =IFERROR(NPER($E$7,-L22+A21+B21,N21+R21)-1,0) -> 92.238433 | R22: =N21*$D$9 -> 163.93711 | V22: =-L22-O22 -> -1572.4141 | X22: Autor: Alessandro Rodolpho Gonçalves da Silva | AA22: =ROUNDUP(E22/120,0) -> 1 | AB22: =ROUNDUP(E22/36,0) -> 1 | AC22: =ROUNDUP(E22/12,0) -> 1 | AJ22: =IF(AT21<1,0,AJ21) -> 25 | AK22: =IF(AT21<1,0,AK21) -> 75 | AL22: =DATE(YEAR(AL21),MONTH(AL21)+1,1) -> 46266 | AM22: =IF(AT21>0,AP22/AT21,"") -> 0.0072945442 | AN22: =AN21+1 -> 8 | AO22: =IF(AT21>0,AT21*$E$7,0) -> 768.97502 | AP22: =IF(AT21>AP21,AS22-AO22-AJ22-AK22,AT21) -> 703.43912 | AQ22: =IF(AS22<1,"",IF(AP22/AS22>90%,"🛩",IF(AP22/AS22>70%,"🏎",IF(AP22/AS22>50%,"🚙",IF(AP22/AS22>30%,"🛵",IF(AP22/AS22>15%,"🐢","⚓️")))))) -> 🛵 | AR22: =IFERROR(IF((AP22+AU22-AX22)/AS22<0,"🗑️",IF((AP22+AU22-AX22)/AS22<10%,"🥾",IF((AP22+AU22-AX22)/AS22<20%,"🛴",IF((AP22+AU22-AX22)/AS22<50%,"🚴‍♂️",IF((AP22+AU22-AX22)/AS22<75%,"🚖","🚁"))))),"") -> 🚴‍♂️ | AS22: =IF(INT(AT21)=0,0,IF(AT21<AP21,AT21+AO22+AJ22+AK22,-PMT($E$7,IF(AW21="V",AV21,NPER($E$7,-AS21+AJ22+AK22,AT21)),AT21+AX21)+AJ22+AK22))+IF(INT(AV21)=1,AX22,0) -> 1572.4141 | AT22: =IF(AT21-AU22-AP22<0,0,IF(AT21-AP22>0,AT21-AP22,0)-IF(AT21-AP22>0,AU22-AX22,0)) -> 95894.092 | AU22: 0 | AV22: =IFERROR(NPER($E$7,-AS22+AJ21+AK21,AT21+AX21)-1,0) -> 92.238433 | AX22: =AT21*$D$9 -> 163.93711
A23: =IF(N22<1,0,A22) -> 25 | B23: =IF(N22<1,0,B22) -> 75 | C23: =DATE(YEAR(C22),MONTH(C22)+1,1) -> 46296 | D23: =IF(N22>0,G23/N22,"") -> 0.0074066958 | E23: =E22+1 -> 9 | F23: =IF(N22>0,N22*$E$7,0) -> 764.67296 | G23: =IF(N22>G22,L23-F23-A23-B23,N22) -> 710.25837 | H23: =IF(L23<1,"",IF(G23/L23>90%,"🛩",IF(G23/L23>70%,"🏎",IF(G23/L23>50%,"🚙",IF(G23/L23>30%,"🛵",IF(G23/L23>15%,"🐢","⚓️")))))) -> 🛵 | I23: =IFERROR(IF((G23+O23-R23)/L23<0,"🗑️",IF((G23+O23-R23)/L23<10%,"🥾",IF((G23+O23-R23)/L23<20%,"🛴",IF((G23+O23-R23)/L23<50%,"🚴‍♂️",IF((G23+O23-R23)/L23<75%,"🚖","🚁"))))),"") -> 🚴‍♂️ | J23: =G23+O23-R23 -> 547.23841 | K23: =IFERROR(J23/(L23+O23),0) -> 0.34746811 | L23: =IF(INT(N22)=0,0,IF(N22<G22,N22+F23+A23+B23,-PMT($E$7,IF(Q22="V",P22,NPER($E$7,-L22+A23+B23,N22)),N22+R22)+A23+B23))+IF(INT(P22)=1,R23,0) -> 1574.9313 | M23: =IFERROR(N22/P23-G23+L23,0) -> 1915.7366 | N23: =IF(N22-O23-G23<0,0,IF(N22-G23>0,N22-G23,0)-IF(N22-G23>0,O23-R23,0)) -> 95346.854 | P23: =IFERROR(NPER($E$7,-L23+A22+B22,N22+R22)-1,0) -> 91.235286 | R23: =N22*$D$9 -> 163.01996 | V23: =-L23-O23 -> -1574.9313 | X23: instagram.com/amigodopairico | AA23: =ROUNDUP(E23/120,0) -> 1 | AB23: =ROUNDUP(E23/36,0) -> 1 | AC23: =ROUNDUP(E23/12,0) -> 1 | AJ23: =IF(AT22<1,0,AJ22) -> 25 | AK23: =IF(AT22<1,0,AK22) -> 75 | AL23: =DATE(YEAR(AL22),MONTH(AL22)+1,1) -> 46296 | AM23: =IF(AT22>0,AP23/AT22,"") -> 0.0074066958 | AN23: =AN22+1 -> 9 | AO23: =IF(AT22>0,AT22*$E$7,0) -> 764.67296 | AP23: =IF(AT22>AP22,AS23-AO23-AJ23-AK23,AT22) -> 710.25837 | AQ23: =IF(AS23<1,"",IF(AP23/AS23>90%,"🛩",IF(AP23/AS23>70%,"🏎",IF(AP23/AS23>50%,"🚙",IF(AP23/AS23>30%,"🛵",IF(AP23/AS23>15%,"🐢","⚓️")))))) -> 🛵 | AR23: =IFERROR(IF((AP23+AU23-AX23)/AS23<0,"🗑️",IF((AP23+AU23-AX23)/AS23<10%,"🥾",IF((AP23+AU23-AX23)/AS23<20%,"🛴",IF((AP23+AU23-AX23)/AS23<50%,"🚴‍♂️",IF((AP23+AU23-AX23)/AS23<75%,"🚖","🚁"))))),"") -> 🚴‍♂️ | AS23: =IF(INT(AT22)=0,0,IF(AT22<AP22,AT22+AO23+AJ23+AK23,-PMT($E$7,IF(AW22="V",AV22,NPER($E$7,-AS22+AJ23+AK23,AT22)),AT22+AX22)+AJ23+AK23))+IF(INT(AV22)=1,AX23,0) -> 1574.9313 | AT23: =IF(AT22-AU23-AP23<0,0,IF(AT22-AP23>0,AT22-AP23,0)-IF(AT22-AP23>0,AU23-AX23,0)) -> 95346.854 | AU23: 0 | AV23: =IFERROR(NPER($E$7,-AS23+AJ22+AK22,AT22+AX22)-1,0) -> 91.235286 | AX23: =AT22*$D$9 -> 163.01996
A24: =IF(N23<1,0,A23) -> 25 | B24: =IF(N23<1,0,B23) -> 75 | C24: =DATE(YEAR(C23),MONTH(C23)+1,1) -> 46327 | D24: =IF(N23>0,G24/N23,"") -> 0.0075214217 | E24: =E23+1 -> 10 | F24: =IF(N23>0,N23*$E$7,0) -> 760.3092 | G24: =IF(N23>G23,L24-F24-A24-B24,N23) -> 717.1439 | H24: =IF(L24<1,"",IF(G24/L24>90%,"🛩",IF(G24/L24>70%,"🏎",IF(G24/L24>50%,"🚙",IF(G24/L24>30%,"🛵",IF(G24/L24>15%,"🐢","⚓️")))))) -> 🛵 | I24: =IFERROR(IF((G24+O24-R24)/L24<0,"🗑️",IF((G24+O24-R24)/L24<10%,"🥾",IF((G24+O24-R24)/L24<20%,"🛴",IF((G24+O24-R24)/L24<50%,"🚴‍♂️",IF((G24+O24-R24)/L24<75%,"🚖","🚁"))))),"") -> 🚴‍♂️ | J24: =G24+O24-R24 -> 555.05425 | K24: =IFERROR(J24/(L24+O24),0) -> 0.35186735 | L24: =IF(INT(N23)=0,0,IF(N23<G23,N23+F24+A24+B24,-PMT($E$7,IF(Q23="V",P23,NPER($E$7,-L23+A24+B24,N23)),N23+R23)+A24+B24))+IF(INT(P23)=1,R24,0) -> 1577.4531 | M24: =IFERROR(N23/P24-G24+L24,0) -> 1916.9929 | N24: =IF(N23-O24-G24<0,0,IF(N23-G24>0,N23-G24,0)-IF(N23-G24>0,O24-R24,0)) -> 94791.799 | P24: =IFERROR(NPER($E$7,-L24+A23+B23,N23+R23)-1,0) -> 90.232161 | R24: =N23*$D$9 -> 162.08965 | V24: =-L24-O24 -> -1577.4531 | X24: alessandrogon.com.br / amigodopairico.com.br | AA24: =ROUNDUP(E24/120,0) -> 1 | AB24: =ROUNDUP(E24/36,0) -> 1 | AC24: =ROUNDUP(E24/12,0) -> 1 | AJ24: =IF(AT23<1,0,AJ23) -> 25 | AK24: =IF(AT23<1,0,AK23) -> 75 | AL24: =DATE(YEAR(AL23),MONTH(AL23)+1,1) -> 46327 | AM24: =IF(AT23>0,AP24/AT23,"") -> 0.0075214217 | AN24: =AN23+1 -> 10 | AO24: =IF(AT23>0,AT23*$E$7,0) -> 760.3092 | AP24: =IF(AT23>AP23,AS24-AO24-AJ24-AK24,AT23) -> 717.1439 | AQ24: =IF(AS24<1,"",IF(AP24/AS24>90%,"🛩",IF(AP24/AS24>70%,"🏎",IF(AP24/AS24>50%,"🚙",IF(AP24/AS24>30%,"🛵",IF(AP24/AS24>15%,"🐢","⚓️")))))) -> 🛵 | AR24: =IFERROR(IF((AP24+AU24-AX24)/AS24<0,"🗑️",IF((AP24+AU24-AX24)/AS24<10%,"🥾",IF((AP24+AU24-AX24)/AS24<20%,"🛴",IF((AP24+AU24-AX24)/AS24<50%,"🚴‍♂️",IF((AP24+AU24-AX24)/AS24<75%,"🚖","🚁"))))),"") -> 🚴‍♂️ | AS24: =IF(INT(AT23)=0,0,IF(AT23<AP23,AT23+AO24+AJ24+AK24,-PMT($E$7,IF(AW23="V",AV23,NPER($E$7,-AS23+AJ24+AK24,AT23)),AT23+AX23)+AJ24+AK24))+IF(INT(AV23)=1,AX24,0) -> 1577.4531 | AT24: =IF(AT23-AU24-AP24<0,0,IF(AT23-AP24>0,AT23-AP24,0)-IF(AT23-AP24>0,AU24-AX24,0)) -> 94791.799 | AU24: 0 | AV24: =IFERROR(NPER($E$7,-AS24+AJ23+AK23,AT23+AX23)-1,0) -> 90.232161 | AX24: =AT23*$D$9 -> 162.08965
A25: =IF(N24<1,0,A24) -> 25 | B25: =IF(N24<1,0,B24) -> 75 | C25: =DATE(YEAR(C24),MONTH(C24)+1,1) -> 46357 | D25: =IF(N24>0,G25/N24,"") -> 0.007638808 | E25: =E24+1 -> 11 | F25: =IF(N24>0,N24*$E$7,0) -> 755.88312 | G25: =IF(N24>G24,L25-F25-A25-B25,N24) -> 724.09635 | H25: =IF(L25<1,"",IF(G25/L25>90%,"🛩",IF(G25/L25>70%,"🏎",IF(G25/L25>50%,"🚙",IF(G25/L25>30%,"🛵",IF(G25/L25>15%,"🐢","⚓️")))))) -> 🛵 | I25: =IFERROR(IF((G25+O25-R25)/L25<0,"🗑️",IF((G25+O25-R25)/L25<10%,"🥾",IF((G25+O25-R25)/L25<20%,"🛴",IF((G25+O25-R25)/L25<50%,"🚴‍♂️",IF((G25+O25-R25)/L25<75%,"🚖","🚁"))))),"") -> 🚴‍♂️ | J25: =G25+O25-R25 -> 562.9503 | K25: =IFERROR(J25/(L25+O25),0) -> 0.35630228 | L25: =IF(INT(N24)=0,0,IF(N24<G24,N24+F25+A25+B25,-PMT($E$7,IF(Q24="V",P24,NPER($E$7,-L24+A25+B25,N24)),N24+R24)+A25+B25))+IF(INT(P24)=1,R25,0) -> 1579.9795 | M25: =IFERROR(N24/P25-G25+L25,0) -> 1918.2254 | N25: =IF(N24-O25-G25<0,0,IF(N24-G25>0,N24-G25,0)-IF(N24-G25>0,O25-R25,0)) -> 94228.849 | P25: =IFERROR(NPER($E$7,-L25+A24+B24,N24+R24)-1,0) -> 89.229058 | R25: =N24*$D$9 -> 161.14606 | V25: =-L25-O25 -> -1579.9795 | AA25: =ROUNDUP(E25/120,0) -> 1 | AB25: =ROUNDUP(E25/36,0) -> 1 | AC25: =ROUNDUP(E25/12,0) -> 1 | AJ25: =IF(AT24<1,0,AJ24) -> 25 | AK25: =IF(AT24<1,0,AK24) -> 75 | AL25: =DATE(YEAR(AL24),MONTH(AL24)+1,1) -> 46357 | AM25: =IF(AT24>0,AP25/AT24,"") -> 0.007638808 | AN25: =AN24+1 -> 11 | AO25: =IF(AT24>0,AT24*$E$7,0) -> 755.88312 | AP25: =IF(AT24>AP24,AS25-AO25-AJ25-AK25,AT24) -> 724.09635 | AQ25: =IF(AS25<1,"",IF(AP25/AS25>90%,"🛩",IF(AP25/AS25>70%,"🏎",IF(AP25/AS25>50%,"🚙",IF(AP25/AS25>30%,"🛵",IF(AP25/AS25>15%,"🐢","⚓️")))))) -> 🛵 | AR25: =IFERROR(IF((AP25+AU25-AX25)/AS25<0,"🗑️",IF((AP25+AU25-AX25)/AS25<10%,"🥾",IF((AP25+AU25-AX25)/AS25<20%,"🛴",IF((AP25+AU25-AX25)/AS25<50%,"🚴‍♂️",IF((AP25+AU25-AX25)/AS25<75%,"🚖","🚁"))))),"") -> 🚴‍♂️ | AS25: =IF(INT(AT24)=0,0,IF(AT24<AP24,AT24+AO25+AJ25+AK25,-PMT($E$7,IF(AW24="V",AV24,NPER($E$7,-AS24+AJ25+AK25,AT24)),AT24+AX24)+AJ25+AK25))+IF(INT(AV24)=1,AX25,0) -> 1579.9795 | AT25: =IF(AT24-AU25-AP25<0,0,IF(AT24-AP25>0,AT24-AP25,0)-IF(AT24-AP25>0,AU25-AX25,0)) -> 94228.849 | AU25: 0 | AV25: =IFERROR(NPER($E$7,-AS25+AJ24+AK24,AT24+AX24)-1,0) -> 89.229058 | AX25: =AT24*$D$9 -> 161.14606
A26: =IF(N25<1,0,A25) -> 25 | B26: =IF(N25<1,0,B25) -> 75 | C26: =DATE(YEAR(C25),MONTH(C25)+1,1) -> 46388 | D26: =IF(N25>0,G26/N25,"") -> 0.0077589443 | E26: =E25+1 -> 12 | F26: =IF(N25>0,N25*$E$7,0) -> 751.39408 | G26: =IF(N25>G25,L26-F26-A26-B26,N25) -> 731.1164 | H26: =IF(L26<1,"",IF(G26/L26>90%,"🛩",IF(G26/L26>70%,"🏎",IF(G26/L26>50%,"🚙",IF(G26/L26>30%,"🛵",IF(G26/L26>15%,"🐢","⚓️")))))) -> 🛵 | I26: =IFERROR(IF((G26+O26-R26)/L26<0,"🗑️",IF((G26+O26-R26)/L26<10%,"🥾",IF((G26+O26-R26)/L26<20%,"🛴",IF((G26+O26-R26)/L26<50%,"🚴‍♂️",IF((G26+O26-R26)/L26<75%,"🚖","🚁"))))),"") -> 🚴‍♂️ | J26: =G26+O26-R26 -> 570.92735 | K26: =IFERROR(J26/(L26+O26),0) -> 0.36077319 | L26: =IF(INT(N25)=0,0,IF(N25<G25,N25+F26+A26+B26,-PMT($E$7,IF(Q25="V",P25,NPER($E$7,-L25+A26+B26,N25)),N25+R25)+A26+B26))+IF(INT(P25)=1,R26,0) -> 1582.5105 | M26: =IFERROR(N25/P26-G26+L26,0) -> 1919.4338 | N26: =IF(N25-O26-G26<0,0,IF(N25-G26>0,N25-G26,0)-IF(N25-G26>0,O26-R26,0)) -> 93657.922 | P26: =IFERROR(NPER($E$7,-L26+A25+B25,N25+R25)-1,0) -> 88.225976 | R26: =N25*$D$9 -> 160.18904 | V26: =-L26-O26 -> -1582.5105 | X26: O conteúdo e formato desta planilha encontram-se protegidos pelas | AA26: =ROUNDUP(E26/120,0) -> 1 | AB26: =ROUNDUP(E26/36,0) -> 1 | AC26: =ROUNDUP(E26/12,0) -> 1 | AJ26: =IF(AT25<1,0,AJ25) -> 25 | AK26: =IF(AT25<1,0,AK25) -> 75 | AL26: =DATE(YEAR(AL25),MONTH(AL25)+1,1) -> 46388 | AM26: =IF(AT25>0,AP26/AT25,"") -> 0.0077589443 | AN26: =AN25+1 -> 12 | AO26: =IF(AT25>0,AT25*$E$7,0) -> 751.39408 | AP26: =IF(AT25>AP25,AS26-AO26-AJ26-AK26,AT25) -> 731.1164 | AQ26: =IF(AS26<1,"",IF(AP26/AS26>90%,"🛩",IF(AP26/AS26>70%,"🏎",IF(AP26/AS26>50%,"🚙",IF(AP26/AS26>30%,"🛵",IF(AP26/AS26>15%,"🐢","⚓️")))))) -> 🛵 | AR26: =IFERROR(IF((AP26+AU26-AX26)/AS26<0,"🗑️",IF((AP26+AU26-AX26)/AS26<10%,"🥾",IF((AP26+AU26-AX26)/AS26<20%,"🛴",IF((AP26+AU26-AX26)/AS26<50%,"🚴‍♂️",IF((AP26+AU26-AX26)/AS26<75%,"🚖","🚁"))))),"") -> 🚴‍♂️ | AS26: =IF(INT(AT25)=0,0,IF(AT25<AP25,AT25+AO26+AJ26+AK26,-PMT($E$7,IF(AW25="V",AV25,NPER($E$7,-AS25+AJ26+AK26,AT25)),AT25+AX25)+AJ26+AK26))+IF(INT(AV25)=1,AX26,0) -> 1582.5105 | AT26: =IF(AT25-AU26-AP26<0,0,IF(AT25-AP26>0,AT25-AP26,0)-IF(AT25-AP26>0,AU26-AX26,0)) -> 93657.922 | AU26: 0 | AV26: =IFERROR(NPER($E$7,-AS26+AJ25+AK25,AT25+AX25)-1,0) -> 88.225976 | AX26: =AT25*$D$9 -> 160.18904
A27: =IF(N26<1,0,A26) -> 25 | B27: =IF(N26<1,0,B26) -> 75 | C27: =DATE(YEAR(C26),MONTH(C26)+1,1) -> 46419 | D27: =IF(N26>0,G27/N26,"") -> 0.0078819246 | E27: =E26+1 -> 13 | F27: =IF(N26>0,N26*$E$7,0) -> 746.84142 | G27: =IF(N26>G26,L27-F27-A27-B27,N26) -> 738.20468 | H27: =IF(L27<1,"",IF(G27/L27>90%,"🛩",IF(G27/L27>70%,"🏎",IF(G27/L27>50%,"🚙",IF(G27/L27>30%,"🛵",IF(G27/L27>15%,"🐢","⚓️")))))) -> 🛵 | I27: =IFERROR(IF((G27+O27-R27)/L27<0,"🗑️",IF((G27+O27-R27)/L27<10%,"🥾",IF((G27+O27-R27)/L27<20%,"🛴",IF((G27+O27-R27)/L27<50%,"🚴‍♂️",IF((G27+O27-R27)/L27<75%,"🚖","🚁"))))),"") -> 🚴‍♂️ | J27: =G27+O27-R27 -> 578.98621 | K27: =IFERROR(J27/(L27+O27),0) -> 0.36528036 | L27: =IF(INT(N26)=0,0,IF(N26<G26,N26+F27+A27+B27,-PMT($E$7,IF(Q26="V",P26,NPER($E$7,-L26+A27+B27,N26)),N26+R26)+A27+B27))+IF(INT(P26)=1,R27,0) -> 1585.0461 | M27: =IFERROR(N26/P27-G27+L27,0) -> 1920.618 | N27: =IF(N26-O27-G27<0,0,IF(N26-G27>0,N26-G27,0)-IF(N26-G27>0,O27-R27,0)) -> 93078.936 | P27: =IFERROR(NPER($E$7,-L27+A26+B26,N26+R26)-1,0) -> 87.222917 | R27: =N26*$D$9 -> 159.21847 | V27: =-L27-O27 -> -1585.0461 | X27: leis brasileiras e internacionais sobre propriedade intelectual | AA27: =ROUNDUP(E27/120,0) -> 1 | AB27: =ROUNDUP(E27/36,0) -> 1 | AC27: =ROUNDUP(E27/12,0) -> 2 | AJ27: =IF(AT26<1,0,AJ26) -> 25 | AK27: =IF(AT26<1,0,AK26) -> 75 | AL27: =DATE(YEAR(AL26),MONTH(AL26)+1,1) -> 46419 | AM27: =IF(AT26>0,AP27/AT26,"") -> 0.0078819246 | AN27: =AN26+1 -> 13 | AO27: =IF(AT26>0,AT26*$E$7,0) -> 746.84142 | AP27: =IF(AT26>AP26,AS27-AO27-AJ27-AK27,AT26) -> 738.20468 | AQ27: =IF(AS27<1,"",IF(AP27/AS27>90%,"🛩",IF(AP27/AS27>70%,"🏎",IF(AP27/AS27>50%,"🚙",IF(AP27/AS27>30%,"🛵",IF(AP27/AS27>15%,"🐢","⚓️")))))) -> 🛵 | AR27: =IFERROR(IF((AP27+AU27-AX27)/AS27<0,"🗑️",IF((AP27+AU27-AX27)/AS27<10%,"🥾",IF((AP27+AU27-AX27)/AS27<20%,"🛴",IF((AP27+AU27-AX27)/AS27<50%,"🚴‍♂️",IF((AP27+AU27-AX27)/AS27<75%,"🚖","🚁"))))),"") -> 🚴‍♂️ | AS27: =IF(INT(AT26)=0,0,IF(AT26<AP26,AT26+AO27+AJ27+AK27,-PMT($E$7,IF(AW26="V",AV26,NPER($E$7,-AS26+AJ27+AK27,AT26)),AT26+AX26)+AJ27+AK27))+IF(INT(AV26)=1,AX27,0) -> 1585.0461 | AT27: =IF(AT26-AU27-AP27<0,0,IF(AT26-AP27>0,AT26-AP27,0)-IF(AT26-AP27>0,AU27-AX27,0)) -> 93078.936 | AU27: 0 | AV27: =IFERROR(NPER($E$7,-AS27+AJ26+AK26,AT26+AX26)-1,0) -> 87.222917 | AX27: =AT26*$D$9 -> 159.21847
A28: =IF(N27<1,0,A27) -> 25 | B28: =IF(N27<1,0,B27) -> 75 | C28: =DATE(YEAR(C27),MONTH(C27)+1,1) -> 46447 | D28: =IF(N27>0,G28/N27,"") -> 0.0080078471 | E28: =E27+1 -> 14 | F28: =IF(N27>0,N27*$E$7,0) -> 742.2245 | G28: =IF(N27>G27,L28-F28-A28-B28,N27) -> 745.36188 | H28: =IF(L28<1,"",IF(G28/L28>90%,"🛩",IF(G28/L28>70%,"🏎",IF(G28/L28>50%,"🚙",IF(G28/L28>30%,"🛵",IF(G28/L28>15%,"🐢","⚓️")))))) -> 🛵 | I28: =IFERROR(IF((G28+O28-R28)/L28<0,"🗑️",IF((G28+O28-R28)/L28<10%,"🥾",IF((G28+O28-R28)/L28<20%,"🛴",IF((G28+O28-R28)/L28<50%,"🚴‍♂️",IF((G28+O28-R28)/L28<75%,"🚖","🚁"))))),"") -> 🚴‍♂️ | J28: =G28+O28-R28 -> 587.12769 | K28: =IFERROR(J28/(L28+O28),0) -> 0.36982409 | L28: =IF(INT(N27)=0,0,IF(N27<G27,N27+F28+A28+B28,-PMT($E$7,IF(Q27="V",P27,NPER($E$7,-L27+A28+B28,N27)),N27+R27)+A28+B28))+IF(INT(P27)=1,R28,0) -> 1587.5864 | M28: =IFERROR(N27/P28-G28+L28,0) -> 1921.7776 | N28: =IF(N27-O28-G28<0,0,IF(N27-G28>0,N27-G28,0)-IF(N27-G28>0,O28-R28,0)) -> 92491.808 | P28: =IFERROR(NPER($E$7,-L28+A27+B27,N27+R27)-1,0) -> 86.219878 | R28: =N27*$D$9 -> 158.23419 | V28: =-L28-O28 -> -1587.5864 | X28: e industrial. É expressamente proibida a reprodução, transferência, | AA28: =ROUNDUP(E28/120,0) -> 1 | AB28: =ROUNDUP(E28/36,0) -> 1 | AC28: =ROUNDUP(E28/12,0) -> 2 | AJ28: =IF(AT27<1,0,AJ27) -> 25 | AK28: =IF(AT27<1,0,AK27) -> 75 | AL28: =DATE(YEAR(AL27),MONTH(AL27)+1,1) -> 46447 | AM28: =IF(AT27>0,AP28/AT27,"") -> 0.0080078471 | AN28: =AN27+1 -> 14 | AO28: =IF(AT27>0,AT27*$E$7,0) -> 742.2245 | AP28: =IF(AT27>AP27,AS28-AO28-AJ28-AK28,AT27) -> 745.36188 | AQ28: =IF(AS28<1,"",IF(AP28/AS28>90%,"🛩",IF(AP28/AS28>70%,"🏎",IF(AP28/AS28>50%,"🚙",IF(AP28/AS28>30%,"🛵",IF(AP28/AS28>15%,"🐢","⚓️")))))) -> 🛵 | AR28: =IFERROR(IF((AP28+AU28-AX28)/AS28<0,"🗑️",IF((AP28+AU28-AX28)/AS28<10%,"🥾",IF((AP28+AU28-AX28)/AS28<20%,"🛴",IF((AP28+AU28-AX28)/AS28<50%,"🚴‍♂️",IF((AP28+AU28-AX28)/AS28<75%,"🚖","🚁"))))),"") -> 🚴‍♂️ | AS28: =IF(INT(AT27)=0,0,IF(AT27<AP27,AT27+AO28+AJ28+AK28,-PMT($E$7,IF(AW27="V",AV27,NPER($E$7,-AS27+AJ28+AK28,AT27)),AT27+AX27)+AJ28+AK28))+IF(INT(AV27)=1,AX28,0) -> 1587.5864 | AT28: =IF(AT27-AU28-AP28<0,0,IF(AT27-AP28>0,AT27-AP28,0)-IF(AT27-AP28>0,AU28-AX28,0)) -> 92491.808 | AU28: 0 | AV28: =IFERROR(NPER($E$7,-AS28+AJ27+AK27,AT27+AX27)-1,0) -> 86.219878 | AX28: =AT27*$D$9 -> 158.23419
A29: =IF(N28<1,0,A28) -> 25 | B29: =IF(N28<1,0,B28) -> 75 | C29: =DATE(YEAR(C28),MONTH(C28)+1,1) -> 46478 | D29: =IF(N28>0,G29/N28,"") -> 0.0081368143 | E29: =E28+1 -> 15 | F29: =IF(N28>0,N28*$E$7,0) -> 737.54267 | G29: =IF(N28>G28,L29-F29-A29-B29,N28) -> 752.58867 | H29: =IF(L29<1,"",IF(G29/L29>90%,"🛩",IF(G29/L29>70%,"🏎",IF(G29/L29>50%,"🚙",IF(G29/L29>30%,"🛵",IF(G29/L29>15%,"🐢","⚓️")))))) -> 🛵 | I29: =IFERROR(IF((G29+O29-R29)/L29<0,"🗑️",IF((G29+O29-R29)/L29<10%,"🥾",IF((G29+O29-R29)/L29<20%,"🛴",IF((G29+O29-R29)/L29<50%,"🚴‍♂️",IF((G29+O29-R29)/L29<75%,"🚖","🚁"))))),"") -> 🚴‍♂️ | J29: =G29+O29-R29 -> 595.3526 | K29: =IFERROR(J29/(L29+O29),0) -> 0.37440467 | L29: =IF(INT(N28)=0,0,IF(N28<G28,N28+F29+A29+B29,-PMT($E$7,IF(Q28="V",P28,NPER($E$7,-L28+A29+B29,N28)),N28+R28)+A29+B29))+IF(INT(P28)=1,R29,0) -> 1590.1313 | M29: =IFERROR(N28/P29-G29+L29,0) -> 1922.9125 | N29: =IF(N28-O29-G29<0,0,IF(N28-G29>0,N28-G29,0)-IF(N28-G29>0,O29-R29,0)) -> 91896.455 | P29: =IFERROR(NPER($E$7,-L29+A28+B28,N28+R28)-1,0) -> 85.216861 | R29: =N28*$D$9 -> 157.23607 | V29: =-L29-O29 -> -1590.1313 | X29: negociação ou distribuição do conteúdo, total ou parcial, desta | AA29: =ROUNDUP(E29/120,0) -> 1 | AB29: =ROUNDUP(E29/36,0) -> 1 | AC29: =ROUNDUP(E29/12,0) -> 2 | AJ29: =IF(AT28<1,0,AJ28) -> 25 | AK29: =IF(AT28<1,0,AK28) -> 75 | AL29: =DATE(YEAR(AL28),MONTH(AL28)+1,1) -> 46478 | AM29: =IF(AT28>0,AP29/AT28,"") -> 0.0081368143 | AN29: =AN28+1 -> 15 | AO29: =IF(AT28>0,AT28*$E$7,0) -> 737.54267 | AP29: =IF(AT28>AP28,AS29-AO29-AJ29-AK29,AT28) -> 752.58867 | AQ29: =IF(AS29<1,"",IF(AP29/AS29>90%,"🛩",IF(AP29/AS29>70%,"🏎",IF(AP29/AS29>50%,"🚙",IF(AP29/AS29>30%,"🛵",IF(AP29/AS29>15%,"🐢","⚓️")))))) -> 🛵 | AR29: =IFERROR(IF((AP29+AU29-AX29)/AS29<0,"🗑️",IF((AP29+AU29-AX29)/AS29<10%,"🥾",IF((AP29+AU29-AX29)/AS29<20%,"🛴",IF((AP29+AU29-AX29)/AS29<50%,"🚴‍♂️",IF((AP29+AU29-AX29)/AS29<75%,"🚖","🚁"))))),"") -> 🚴‍♂️ | AS29: =IF(INT(AT28)=0,0,IF(AT28<AP28,AT28+AO29+AJ29+AK29,-PMT($E$7,IF(AW28="V",AV28,NPER($E$7,-AS28+AJ29+AK29,AT28)),AT28+AX28)+AJ29+AK29))+IF(INT(AV28)=1,AX29,0) -> 1590.1313 | AT29: =IF(AT28-AU29-AP29<0,0,IF(AT28-AP29>0,AT28-AP29,0)-IF(AT28-AP29>0,AU29-AX29,0)) -> 91896.455 | AU29: 0 | AV29: =IFERROR(NPER($E$7,-AS29+AJ28+AK28,AT28+AX28)-1,0) -> 85.216861 | AX29: =AT28*$D$9 -> 157.23607
A30: =IF(N29<1,0,A29) -> 25 | B30: =IF(N29<1,0,B29) -> 75 | C30: =DATE(YEAR(C29),MONTH(C29)+1,1) -> 46508 | D30: =IF(N29>0,G30/N29,"") -> 0.0082689341 | E30: =E29+1 -> 16 | F30: =IF(N29>0,N29*$E$7,0) -> 732.79524 | G30: =IF(N29>G29,L30-F30-A30-B30,N29) -> 759.88573 | H30: =IF(L30<1,"",IF(G30/L30>90%,"🛩",IF(G30/L30>70%,"🏎",IF(G30/L30>50%,"🚙",IF(G30/L30>30%,"🛵",IF(G30/L30>15%,"🐢","⚓️")))))) -> 🛵 | I30: =IFERROR(IF((G30+O30-R30)/L30<0,"🗑️",IF((G30+O30-R30)/L30<10%,"🥾",IF((G30+O30-R30)/L30<20%,"🛴",IF((G30+O30-R30)/L30<50%,"🚴‍♂️",IF((G30+O30-R30)/L30<75%,"🚖","🚁"))))),"") -> 🚴‍♂️ | J30: =G30+O30-R30 -> 603.66176 | K30: =IFERROR(J30/(L30+O30),0) -> 0.3790224 | L30: =IF(INT(N29)=0,0,IF(N29<G29,N29+F30+A30+B30,-PMT($E$7,IF(Q29="V",P29,NPER($E$7,-L29+A30+B30,N29)),N29+R29)+A30+B30))+IF(INT(P29)=1,R30,0) -> 1592.681 | M30: =IFERROR(N29/P30-G30+L30,0) -> 1924.0224 | N30: =IF(N29-O30-G30<0,0,IF(N29-G30>0,N29-G30,0)-IF(N29-G30>0,O30-R30,0)) -> 91292.794 | P30: =IFERROR(NPER($E$7,-L30+A29+B29,N29+R29)-1,0) -> 84.213865 | R30: =N29*$D$9 -> 156.22397 | V30: =-L30-O30 -> -1592.681 | X30: planilha sem o consentimento expresso e por escrito do proprietário, | AA30: =ROUNDUP(E30/120,0) -> 1 | AB30: =ROUNDUP(E30/36,0) -> 1 | AC30: =ROUNDUP(E30/12,0) -> 2 | AJ30: =IF(AT29<1,0,AJ29) -> 25 | AK30: =IF(AT29<1,0,AK29) -> 75 | AL30: =DATE(YEAR(AL29),MONTH(AL29)+1,1) -> 46508 | AM30: =IF(AT29>0,AP30/AT29,"") -> 0.0082689341 | AN30: =AN29+1 -> 16 | AO30: =IF(AT29>0,AT29*$E$7,0) -> 732.79524 | AP30: =IF(AT29>AP29,AS30-AO30-AJ30-AK30,AT29) -> 759.88573 | AQ30: =IF(AS30<1,"",IF(AP30/AS30>90%,"🛩",IF(AP30/AS30>70%,"🏎",IF(AP30/AS30>50%,"🚙",IF(AP30/AS30>30%,"🛵",IF(AP30/AS30>15%,"🐢","⚓️")))))) -> 🛵 | AR30: =IFERROR(IF((AP30+AU30-AX30)/AS30<0,"🗑️",IF((AP30+AU30-AX30)/AS30<10%,"🥾",IF((AP30+AU30-AX30)/AS30<20%,"🛴",IF((AP30+AU30-AX30)/AS30<50%,"🚴‍♂️",IF((AP30+AU30-AX30)/AS30<75%,"🚖","🚁"))))),"") -> 🚴‍♂️ | AS30: =IF(INT(AT29)=0,0,IF(AT29<AP29,AT29+AO30+AJ30+AK30,-PMT($E$7,IF(AW29="V",AV29,NPER($E$7,-AS29+AJ30+AK30,AT29)),AT29+AX29)+AJ30+AK30))+IF(INT(AV29)=1,AX30,0) -> 1592.681 | AT30: =IF(AT29-AU30-AP30<0,0,IF(AT29-AP30>0,AT29-AP30,0)-IF(AT29-AP30>0,AU30-AX30,0)) -> 91292.794 | AU30: 0 | AV30: =IFERROR(NPER($E$7,-AS30+AJ29+AK29,AT29+AX29)-1,0) -> 84.213865 | AX30: =AT29*$D$9 -> 156.22397
A31: =IF(N30<1,0,A30) -> 25 | B31: =IF(N30<1,0,B30) -> 75 | C31: =DATE(YEAR(C30),MONTH(C30)+1,1) -> 46539 | D31: =IF(N30>0,G31/N30,"") -> 0.0084043189 | E31: =E30+1 -> 17 | F31: =IF(N30>0,N30*$E$7,0) -> 727.98156 | G31: =IF(N30>G30,L31-F31-A31-B31,N30) -> 767.25375 | H31: =IF(L31<1,"",IF(G31/L31>90%,"🛩",IF(G31/L31>70%,"🏎",IF(G31/L31>50%,"🚙",IF(G31/L31>30%,"🛵",IF(G31/L31>15%,"🐢","⚓️")))))) -> 🛵 | I31: =IFERROR(IF((G31+O31-R31)/L31<0,"🗑️",IF((G31+O31-R31)/L31<10%,"🥾",IF((G31+O31-R31)/L31<20%,"🛴",IF((G31+O31-R31)/L31<50%,"🚴‍♂️",IF((G31+O31-R31)/L31<75%,"🚖","🚁"))))),"") -> 🚴‍♂️ | J31: =G31+O31-R31 -> 612.056 | K31: =IFERROR(J31/(L31+O31),0) -> 0.38367757 | L31: =IF(INT(N30)=0,0,IF(N30<G30,N30+F31+A31+B31,-PMT($E$7,IF(Q30="V",P30,NPER($E$7,-L30+A31+B31,N30)),N30+R30)+A31+B31))+IF(INT(P30)=1,R31,0) -> 1595.2353 | M31: =IFERROR(N30/P31-G31+L31,0) -> 1925.1071 | N31: =IF(N30-O31-G31<0,0,IF(N30-G31>0,N30-G31,0)-IF(N30-G31>0,O31-R31,0)) -> 90680.738 | P31: =IFERROR(NPER($E$7,-L31+A30+B30,N30+R30)-1,0) -> 83.21089 | R31: =N30*$D$9 -> 155.19775 | V31: =-L31-O31 -> -1595.2353 | X31: sujeitando-se o infrator às penalidades cíveis e criminais cabíveis. | AA31: =ROUNDUP(E31/120,0) -> 1 | AB31: =ROUNDUP(E31/36,0) -> 1 | AC31: =ROUNDUP(E31/12,0) -> 2 | AJ31: =IF(AT30<1,0,AJ30) -> 25 | AK31: =IF(AT30<1,0,AK30) -> 75 | AL31: =DATE(YEAR(AL30),MONTH(AL30)+1,1) -> 46539 | AM31: =IF(AT30>0,AP31/AT30,"") -> 0.0084043189 | AN31: =AN30+1 -> 17 | AO31: =IF(AT30>0,AT30*$E$7,0) -> 727.98156 | AP31: =IF(AT30>AP30,AS31-AO31-AJ31-AK31,AT30) -> 767.25375 | AQ31: =IF(AS31<1,"",IF(AP31/AS31>90%,"🛩",IF(AP31/AS31>70%,"🏎",IF(AP31/AS31>50%,"🚙",IF(AP31/AS31>30%,"🛵",IF(AP31/AS31>15%,"🐢","⚓️")))))) -> 🛵 | AR31: =IFERROR(IF((AP31+AU31-AX31)/AS31<0,"🗑️",IF((AP31+AU31-AX31)/AS31<10%,"🥾",IF((AP31+AU31-AX31)/AS31<20%,"🛴",IF((AP31+AU31-AX31)/AS31<50%,"🚴‍♂️",IF((AP31+AU31-AX31)/AS31<75%,"🚖","🚁"))))),"") -> 🚴‍♂️ | AS31: =IF(INT(AT30)=0,0,IF(AT30<AP30,AT30+AO31+AJ31+AK31,-PMT($E$7,IF(AW30="V",AV30,NPER($E$7,-AS30+AJ31+AK31,AT30)),AT30+AX30)+AJ31+AK31))+IF(INT(AV30)=1,AX31,0) -> 1595.2353 | AT31: =IF(AT30-AU31-AP31<0,0,IF(AT30-AP31>0,AT30-AP31,0)-IF(AT30-AP31>0,AU31-AX31,0)) -> 90680.738 | AU31: 0 | AV31: =IFERROR(NPER($E$7,-AS31+AJ30+AK30,AT30+AX30)-1,0) -> 83.21089 | AX31: =AT30*$D$9 -> 155.19775
A32: =IF(N31<1,0,A31) -> 25 | B32: =IF(N31<1,0,B31) -> 75 | C32: =DATE(YEAR(C31),MONTH(C31)+1,1) -> 46569 | D32: =IF(N31>0,G32/N31,"") -> 0.008543087 | E32: =E31+1 -> 18 | F32: =IF(N31>0,N31*$E$7,0) -> 723.10094 | G32: =IF(N31>G31,L32-F32-A32-B32,N31) -> 774.69343 | H32: =IF(L32<1,"",IF(G32/L32>90%,"🛩",IF(G32/L32>70%,"🏎",IF(G32/L32>50%,"🚙",IF(G32/L32>30%,"🛵",IF(G32/L32>15%,"🐢","⚓️")))))) -> 🛵 | I32: =IFERROR(IF((G32+O32-R32)/L32<0,"🗑️",IF((G32+O32-R32)/L32<10%,"🥾",IF((G32+O32-R32)/L32<20%,"🛴",IF((G32+O32-R32)/L32<50%,"🚴‍♂️",IF((G32+O32-R32)/L32<75%,"🚖","🚁"))))),"") -> 🚴‍♂️ | J32: =G32+O32-R32 -> 620.53617 | K32: =IFERROR(J32/(L32+O32),0) -> 0.38837049 | L32: =IF(INT(N31)=0,0,IF(N31<G31,N31+F32+A32+B32,-PMT($E$7,IF(Q31="V",P31,NPER($E$7,-L31+A32+B32,N31)),N31+R31)+A32+B32))+IF(INT(P31)=1,R32,0) -> 1597.7944 | M32: =IFERROR(N31/P32-G32+L32,0) -> 1926.1664 | N32: =IF(N31-O32-G32<0,0,IF(N31-G32>0,N31-G32,0)-IF(N31-G32>0,O32-R32,0)) -> 90060.201 | P32: =IFERROR(NPER($E$7,-L32+A31+B31,N31+R31)-1,0) -> 82.207936 | R32: =N31*$D$9 -> 154.15725 | V32: =-L32-O32 -> -1597.7944 | AA32: =ROUNDUP(E32/120,0) -> 1 | AB32: =ROUNDUP(E32/36,0) -> 1 | AC32: =ROUNDUP(E32/12,0) -> 2 | AJ32: =IF(AT31<1,0,AJ31) -> 25 | AK32: =IF(AT31<1,0,AK31) -> 75 | AL32: =DATE(YEAR(AL31),MONTH(AL31)+1,1) -> 46569 | AM32: =IF(AT31>0,AP32/AT31,"") -> 0.008543087 | AN32: =AN31+1 -> 18 | AO32: =IF(AT31>0,AT31*$E$7,0) -> 723.10094 | AP32: =IF(AT31>AP31,AS32-AO32-AJ32-AK32,AT31) -> 774.69343 | AQ32: =IF(AS32<1,"",IF(AP32/AS32>90%,"🛩",IF(AP32/AS32>70%,"🏎",IF(AP32/AS32>50%,"🚙",IF(AP32/AS32>30%,"🛵",IF(AP32/AS32>15%,"🐢","⚓️")))))) -> 🛵 | AR32: =IFERROR(IF((AP32+AU32-AX32)/AS32<0,"🗑️",IF((AP32+AU32-AX32)/AS32<10%,"🥾",IF((AP32+AU32-AX32)/AS32<20%,"🛴",IF((AP32+AU32-AX32)/AS32<50%,"🚴‍♂️",IF((AP32+AU32-AX32)/AS32<75%,"🚖","🚁"))))),"") -> 🚴‍♂️ | AS32: =IF(INT(AT31)=0,0,IF(AT31<AP31,AT31+AO32+AJ32+AK32,-PMT($E$7,IF(AW31="V",AV31,NPER($E$7,-AS31+AJ32+AK32,AT31)),AT31+AX31)+AJ32+AK32))+IF(INT(AV31)=1,AX32,0) -> 1597.7944 | AT32: =IF(AT31-AU32-AP32<0,0,IF(AT31-AP32>0,AT31-AP32,0)-IF(AT31-AP32>0,AU32-AX32,0)) -> 90060.201 | AU32: 0 | AV32: =IFERROR(NPER($E$7,-AS32+AJ31+AK31,AT31+AX31)-1,0) -> 82.207936 | AX32: =AT31*$D$9 -> 154.15725
A33: =IF(N32<1,0,A32) -> 25 | B33: =IF(N32<1,0,B32) -> 75 | C33: =DATE(YEAR(C32),MONTH(C32)+1,1) -> 46600 | D33: =IF(N32>0,G33/N32,"") -> 0.0086853622 | E33: =E32+1 -> 19 | F33: =IF(N32>0,N32*$E$7,0) -> 718.15269 | G33: =IF(N32>G32,L33-F33-A33-B33,N32) -> 782.20547 | H33: =IF(L33<1,"",IF(G33/L33>90%,"🛩",IF(G33/L33>70%,"🏎",IF(G33/L33>50%,"🚙",IF(G33/L33>30%,"🛵",IF(G33/L33>15%,"🐢","⚓️")))))) -> 🛵 | I33: =IFERROR(IF((G33+O33-R33)/L33<0,"🗑️",IF((G33+O33-R33)/L33<10%,"🥾",IF((G33+O33-R33)/L33<20%,"🛴",IF((G33+O33-R33)/L33<50%,"🚴‍♂️",IF((G33+O33-R33)/L33<75%,"🚖","🚁"))))),"") -> 🚴‍♂️ | J33: =G33+O33-R33 -> 629.10312 | K33: =IFERROR(J33/(L33+O33),0) -> 0.39310146 | L33: =IF(INT(N32)=0,0,IF(N32<G32,N32+F33+A33+B33,-PMT($E$7,IF(Q32="V",P32,NPER($E$7,-L32+A33+B33,N32)),N32+R32)+A33+B33))+IF(INT(P32)=1,R33,0) -> 1600.3582 | M33: =IFERROR(N32/P33-G33+L33,0) -> 1927.2001 | N33: =IF(N32-O33-G33<0,0,IF(N32-G33>0,N32-G33,0)-IF(N32-G33>0,O33-R33,0)) -> 89431.098 | P33: =IFERROR(NPER($E$7,-L33+A32+B32,N32+R32)-1,0) -> 81.205002 | R33: =N32*$D$9 -> 153.10234 | V33: =-L33-O33 -> -1600.3582 | AA33: =ROUNDUP(E33/120,0) -> 1 | AB33: =ROUNDUP(E33/36,0) -> 1 | AC33: =ROUNDUP(E33/12,0) -> 2 | AJ33: =IF(AT32<1,0,AJ32) -> 25 | AK33: =IF(AT32<1,0,AK32) -> 75 | AL33: =DATE(YEAR(AL32),MONTH(AL32)+1,1) -> 46600 | AM33: =IF(AT32>0,AP33/AT32,"") -> 0.0086853622 | AN33: =AN32+1 -> 19 | AO33: =IF(AT32>0,AT32*$E$7,0) -> 718.15269 | AP33: =IF(AT32>AP32,AS33-AO33-AJ33-AK33,AT32) -> 782.20547 | AQ33: =IF(AS33<1,"",IF(AP33/AS33>90%,"🛩",IF(AP33/AS33>70%,"🏎",IF(AP33/AS33>50%,"🚙",IF(AP33/AS33>30%,"🛵",IF(AP33/AS33>15%,"🐢","⚓️")))))) -> 🛵 | AR33: =IFERROR(IF((AP33+AU33-AX33)/AS33<0,"🗑️",IF((AP33+AU33-AX33)/AS33<10%,"🥾",IF((AP33+AU33-AX33)/AS33<20%,"🛴",IF((AP33+AU33-AX33)/AS33<50%,"🚴‍♂️",IF((AP33+AU33-AX33)/AS33<75%,"🚖","🚁"))))),"") -> 🚴‍♂️ | AS33: =IF(INT(AT32)=0,0,IF(AT32<AP32,AT32+AO33+AJ33+AK33,-PMT($E$7,IF(AW32="V",AV32,NPER($E$7,-AS32+AJ33+AK33,AT32)),AT32+AX32)+AJ33+AK33))+IF(INT(AV32)=1,AX33,0) -> 1600.3582 | AT33: =IF(AT32-AU33-AP33<0,0,IF(AT32-AP33>0,AT32-AP33,0)-IF(AT32-AP33>0,AU33-AX33,0)) -> 89431.098 | AU33: 0 | AV33: =IFERROR(NPER($E$7,-AS33+AJ32+AK32,AT32+AX32)-1,0) -> 81.205002 | AX33: =AT32*$D$9 -> 153.10234
A34: =IF(N33<1,0,A33) -> 25 | B34: =IF(N33<1,0,B33) -> 75 | C34: =DATE(YEAR(C33),MONTH(C33)+1,1) -> 46631 | D34: =IF(N33>0,G34/N33,"") -> 0.0088312744 | E34: =E33+1 -> 20 | F34: =IF(N33>0,N33*$E$7,0) -> 713.13614 | G34: =IF(N33>G33,L34-F34-A34-B34,N33) -> 789.79057 | H34: =IF(L34<1,"",IF(G34/L34>90%,"🛩",IF(G34/L34>70%,"🏎",IF(G34/L34>50%,"🚙",IF(G34/L34>30%,"🛵",IF(G34/L34>15%,"🐢","⚓️")))))) -> 🛵 | I34: =IFERROR(IF((G34+O34-R34)/L34<0,"🗑️",IF((G34+O34-R34)/L34<10%,"🥾",IF((G34+O34-R34)/L34<20%,"🛴",IF((G34+O34-R34)/L34<50%,"🚴‍♂️",IF((G34+O34-R34)/L34<75%,"🚖","🚁"))))),"") -> 🚴‍♂️ | J34: =G34+O34-R34 -> 637.75771 | K34: =IFERROR(J34/(L34+O34),0) -> 0.39787078 | L34: =IF(INT(N33)=0,0,IF(N33<G33,N33+F34+A34+B34,-PMT($E$7,IF(Q33="V",P33,NPER($E$7,-L33+A34+B34,N33)),N33+R33)+A34+B34))+IF(INT(P33)=1,R34,0) -> 1602.9267 | M34: =IFERROR(N33/P34-G34+L34,0) -> 1928.2081 | N34: =IF(N33-O34-G34<0,0,IF(N33-G34>0,N33-G34,0)-IF(N33-G34>0,O34-R34,0)) -> 88793.341 | P34: =IFERROR(NPER($E$7,-L34+A33+B33,N33+R33)-1,0) -> 80.202089 | R34: =N33*$D$9 -> 152.03287 | V34: =-L34-O34 -> -1602.9267 | AA34: =ROUNDUP(E34/120,0) -> 1 | AB34: =ROUNDUP(E34/36,0) -> 1 | AC34: =ROUNDUP(E34/12,0) -> 2 | AJ34: =IF(AT33<1,0,AJ33) -> 25 | AK34: =IF(AT33<1,0,AK33) -> 75 | AL34: =DATE(YEAR(AL33),MONTH(AL33)+1,1) -> 46631 | AM34: =IF(AT33>0,AP34/AT33,"") -> 0.0088312744 | AN34: =AN33+1 -> 20 | AO34: =IF(AT33>0,AT33*$E$7,0) -> 713.13614 | AP34: =IF(AT33>AP33,AS34-AO34-AJ34-AK34,AT33) -> 789.79057 | AQ34: =IF(AS34<1,"",IF(AP34/AS34>90%,"🛩",IF(AP34/AS34>70%,"🏎",IF(AP34/AS34>50%,"🚙",IF(AP34/AS34>30%,"🛵",IF(AP34/AS34>15%,"🐢","⚓️")))))) -> 🛵 | AR34: =IFERROR(IF((AP34+AU34-AX34)/AS34<0,"🗑️",IF((AP34+AU34-AX34)/AS34<10%,"🥾",IF((AP34+AU34-AX34)/AS34<20%,"🛴",IF((AP34+AU34-AX34)/AS34<50%,"🚴‍♂️",IF((AP34+AU34-AX34)/AS34<75%,"🚖","🚁"))))),"") -> 🚴‍♂️ | AS34: =IF(INT(AT33)=0,0,IF(AT33<AP33,AT33+AO34+AJ34+AK34,-PMT($E$7,IF(AW33="V",AV33,NPER($E$7,-AS33+AJ34+AK34,AT33)),AT33+AX33)+AJ34+AK34))+IF(INT(AV33)=1,AX34,0) -> 1602.9267 | AT34: =IF(AT33-AU34-AP34<0,0,IF(AT33-AP34>0,AT33-AP34,0)-IF(AT33-AP34>0,AU34-AX34,0)) -> 88793.341 | AU34: 0 | AV34: =IFERROR(NPER($E$7,-AS34+AJ33+AK33,AT33+AX33)-1,0) -> 80.202089 | AX34: =AT33*$D$9 -> 152.03287
A35: =IF(N34<1,0,A34) -> 25 | B35: =IF(N34<1,0,B34) -> 75 | C35: =DATE(YEAR(C34),MONTH(C34)+1,1) -> 46661 | D35: =IF(N34>0,G35/N34,"") -> 0.0089809603 | E35: =E34+1 -> 21 | F35: =IF(N34>0,N34*$E$7,0) -> 708.05057 | G35: =IF(N34>G34,L35-F35-A35-B35,N34) -> 797.44947 | H35: =IF(L35<1,"",IF(G35/L35>90%,"🛩",IF(G35/L35>70%,"🏎",IF(G35/L35>50%,"🚙",IF(G35/L35>30%,"🛵",IF(G35/L35>15%,"🐢","⚓️")))))) -> 🛵 | I35: =IFERROR(IF((G35+O35-R35)/L35<0,"🗑️",IF((G35+O35-R35)/L35<10%,"🥾",IF((G35+O35-R35)/L35<20%,"🛴",IF((G35+O35-R35)/L35<50%,"🚴‍♂️",IF((G35+O35-R35)/L35<75%,"🚖","🚁"))))),"") -> 🚴‍♂️ | J35: =G35+O35-R35 -> 646.50079 | K35: =IFERROR(J35/(L35+O35),0) -> 0.40267878 | L35: =IF(INT(N34)=0,0,IF(N34<G34,N34+F35+A35+B35,-PMT($E$7,IF(Q34="V",P34,NPER($E$7,-L34+A35+B35,N34)),N34+R34)+A35+B35))+IF(INT(P34)=1,R35,0) -> 1605.5 | M35: =IFERROR(N34/P35-G35+L35,0) -> 1929.19 | N35: =IF(N34-O35-G35<0,0,IF(N34-G35>0,N34-G35,0)-IF(N34-G35>0,O35-R35,0)) -> 88146.84 | P35: =IFERROR(NPER($E$7,-L35+A34+B34,N34+R34)-1,0) -> 79.199196 | R35: =N34*$D$9 -> 150.94868 | V35: =-L35-O35 -> -1605.5 | AA35: =ROUNDUP(E35/120,0) -> 1 | AB35: =ROUNDUP(E35/36,0) -> 1 | AC35: =ROUNDUP(E35/12,0) -> 2 | AJ35: =IF(AT34<1,0,AJ34) -> 25 | AK35: =IF(AT34<1,0,AK34) -> 75 | AL35: =DATE(YEAR(AL34),MONTH(AL34)+1,1) -> 46661 | AM35: =IF(AT34>0,AP35/AT34,"") -> 0.0089809603 | AN35: =AN34+1 -> 21 | AO35: =IF(AT34>0,AT34*$E$7,0) -> 708.05057 | AP35: =IF(AT34>AP34,AS35-AO35-AJ35-AK35,AT34) -> 797.44947 | AQ35: =IF(AS35<1,"",IF(AP35/AS35>90%,"🛩",IF(AP35/AS35>70%,"🏎",IF(AP35/AS35>50%,"🚙",IF(AP35/AS35>30%,"🛵",IF(AP35/AS35>15%,"🐢","⚓️")))))) -> 🛵 | AR35: =IFERROR(IF((AP35+AU35-AX35)/AS35<0,"🗑️",IF((AP35+AU35-AX35)/AS35<10%,"🥾",IF((AP35+AU35-AX35)/AS35<20%,"🛴",IF((AP35+AU35-AX35)/AS35<50%,"🚴‍♂️",IF((AP35+AU35-AX35)/AS35<75%,"🚖","🚁"))))),"") -> 🚴‍♂️ | AS35: =IF(INT(AT34)=0,0,IF(AT34<AP34,AT34+AO35+AJ35+AK35,-PMT($E$7,IF(AW34="V",AV34,NPER($E$7,-AS34+AJ35+AK35,AT34)),AT34+AX34)+AJ35+AK35))+IF(INT(AV34)=1,AX35,0) -> 1605.5 | AT35: =IF(AT34-AU35-AP35<0,0,IF(AT34-AP35>0,AT34-AP35,0)-IF(AT34-AP35>0,AU35-AX35,0)) -> 88146.84 | AU35: 0 | AV35: =IFERROR(NPER($E$7,-AS35+AJ34+AK34,AT34+AX34)-1,0) -> 79.199196 | AX35: =AT34*$D$9 -> 150.94868
A36: =IF(N35<1,0,A35) -> 25 | B36: =IF(N35<1,0,B35) -> 75 | C36: =DATE(YEAR(C35),MONTH(C35)+1,1) -> 46692 | D36: =IF(N35>0,G36/N35,"") -> 0.0091345632 | E36: =E35+1 -> 22 | F36: =IF(N35>0,N35*$E$7,0) -> 702.89528 | G36: =IF(N35>G35,L36-F36-A36-B36,N35) -> 805.18288 | H36: =IF(L36<1,"",IF(G36/L36>90%,"🛩",IF(G36/L36>70%,"🏎",IF(G36/L36>50%,"🚙",IF(G36/L36>30%,"🛵",IF(G36/L36>15%,"🐢","⚓️")))))) -> 🚙 | I36: =IFERROR(IF((G36+O36-R36)/L36<0,"🗑️",IF((G36+O36-R36)/L36<10%,"🥾",IF((G36+O36-R36)/L36<20%,"🛴",IF((G36+O36-R36)/L36<50%,"🚴‍♂️",IF((G36+O36-R36)/L36<75%,"🚖","🚁"))))),"") -> 🚴‍♂️ | J36: =G36+O36-R36 -> 655.33325 | K36: =IFERROR(J36/(L36+O36),0) -> 0.40752575 | L36: =IF(INT(N35)=0,0,IF(N35<G35,N35+F36+A36+B36,-PMT($E$7,IF(Q35="V",P35,NPER($E$7,-L35+A36+B36,N35)),N35+R35)+A36+B36))+IF(INT(P35)=1,R36,0) -> 1608.0782 | M36: =IFERROR(N35/P36-G36+L36,0) -> 1930.1457 | N36: =IF(N35-O36-G36<0,0,IF(N35-G36>0,N35-G36,0)-IF(N35-G36>0,O36-R36,0)) -> 87491.507 | P36: =IFERROR(NPER($E$7,-L36+A35+B35,N35+R35)-1,0) -> 78.196324 | R36: =N35*$D$9 -> 149.84963 | V36: =-L36-O36 -> -1608.0782 | AA36: =ROUNDUP(E36/120,0) -> 1 | AB36: =ROUNDUP(E36/36,0) -> 1 | AC36: =ROUNDUP(E36/12,0) -> 2 | AJ36: =IF(AT35<1,0,AJ35) -> 25 | AK36: =IF(AT35<1,0,AK35) -> 75 | AL36: =DATE(YEAR(AL35),MONTH(AL35)+1,1) -> 46692 | AM36: =IF(AT35>0,AP36/AT35,"") -> 0.0091345632 | AN36: =AN35+1 -> 22 | AO36: =IF(AT35>0,AT35*$E$7,0) -> 702.89528 | AP36: =IF(AT35>AP35,AS36-AO36-AJ36-AK36,AT35) -> 805.18288 | AQ36: =IF(AS36<1,"",IF(AP36/AS36>90%,"🛩",IF(AP36/AS36>70%,"🏎",IF(AP36/AS36>50%,"🚙",IF(AP36/AS36>30%,"🛵",IF(AP36/AS36>15%,"🐢","⚓️")))))) -> 🚙 | AR36: =IFERROR(IF((AP36+AU36-AX36)/AS36<0,"🗑️",IF((AP36+AU36-AX36)/AS36<10%,"🥾",IF((AP36+AU36-AX36)/AS36<20%,"🛴",IF((AP36+AU36-AX36)/AS36<50%,"🚴‍♂️",IF((AP36+AU36-AX36)/AS36<75%,"🚖","🚁"))))),"") -> 🚴‍♂️ | AS36: =IF(INT(AT35)=0,0,IF(AT35<AP35,AT35+AO36+AJ36+AK36,-PMT($E$7,IF(AW35="V",AV35,NPER($E$7,-AS35+AJ36+AK36,AT35)),AT35+AX35)+AJ36+AK36))+IF(INT(AV35)=1,AX36,0) -> 1608.0782 | AT36: =IF(AT35-AU36-AP36<0,0,IF(AT35-AP36>0,AT35-AP36,0)-IF(AT35-AP36>0,AU36-AX36,0)) -> 87491.507 | AU36: 0 | AV36: =IFERROR(NPER($E$7,-AS36+AJ35+AK35,AT35+AX35)-1,0) -> 78.196324 | AX36: =AT35*$D$9 -> 149.84963
A37: =IF(N36<1,0,A36) -> 25 | B37: =IF(N36<1,0,B36) -> 75 | C37: =DATE(YEAR(C36),MONTH(C36)+1,1) -> 46722 | D37: =IF(N36>0,G37/N36,"") -> 0.0092922338 | E37: =E36+1 -> 23 | F37: =IF(N36>0,N36*$E$7,0) -> 697.66956 | G37: =IF(N36>G36,L37-F37-A37-B37,N36) -> 812.99153 | H37: =IF(L37<1,"",IF(G37/L37>90%,"🛩",IF(G37/L37>70%,"🏎",IF(G37/L37>50%,"🚙",IF(G37/L37>30%,"🛵",IF(G37/L37>15%,"🐢","⚓️")))))) -> 🚙 | I37: =IFERROR(IF((G37+O37-R37)/L37<0,"🗑️",IF((G37+O37-R37)/L37<10%,"🥾",IF((G37+O37-R37)/L37<20%,"🛴",IF((G37+O37-R37)/L37<50%,"🚴‍♂️",IF((G37+O37-R37)/L37<75%,"🚖","🚁"))))),"") -> 🚴‍♂️ | J37: =G37+O37-R37 -> 664.25597 | K37: =IFERROR(J37/(L37+O37),0) -> 0.41241201 | L37: =IF(INT(N36)=0,0,IF(N36<G36,N36+F37+A37+B37,-PMT($E$7,IF(Q36="V",P36,NPER($E$7,-L36+A37+B37,N36)),N36+R36)+A37+B37))+IF(INT(P36)=1,R37,0) -> 1610.6611 | M37: =IFERROR(N36/P37-G37+L37,0) -> 1931.0751 | N37: =IF(N36-O37-G37<0,0,IF(N36-G37>0,N36-G37,0)-IF(N36-G37>0,O37-R37,0)) -> 86827.251 | P37: =IFERROR(NPER($E$7,-L37+A36+B36,N36+R36)-1,0) -> 77.193471 | R37: =N36*$D$9 -> 148.73556 | V37: =-L37-O37 -> -1610.6611 | AA37: =ROUNDUP(E37/120,0) -> 1 | AB37: =ROUNDUP(E37/36,0) -> 1 | AC37: =ROUNDUP(E37/12,0) -> 2 | AJ37: =IF(AT36<1,0,AJ36) -> 25 | AK37: =IF(AT36<1,0,AK36) -> 75 | AL37: =DATE(YEAR(AL36),MONTH(AL36)+1,1) -> 46722 | AM37: =IF(AT36>0,AP37/AT36,"") -> 0.0092922338 | AN37: =AN36+1 -> 23 | AO37: =IF(AT36>0,AT36*$E$7,0) -> 697.66956 | AP37: =IF(AT36>AP36,AS37-AO37-AJ37-AK37,AT36) -> 812.99153 | AQ37: =IF(AS37<1,"",IF(AP37/AS37>90%,"🛩",IF(AP37/AS37>70%,"🏎",IF(AP37/AS37>50%,"🚙",IF(AP37/AS37>30%,"🛵",IF(AP37/AS37>15%,"🐢","⚓️")))))) -> 🚙 | AR37: =IFERROR(IF((AP37+AU37-AX37)/AS37<0,"🗑️",IF((AP37+AU37-AX37)/AS37<10%,"🥾",IF((AP37+AU37-AX37)/AS37<20%,"🛴",IF((AP37+AU37-AX37)/AS37<50%,"🚴‍♂️",IF((AP37+AU37-AX37)/AS37<75%,"🚖","🚁"))))),"") -> 🚴‍♂️ | AS37: =IF(INT(AT36)=0,0,IF(AT36<AP36,AT36+AO37+AJ37+AK37,-PMT($E$7,IF(AW36="V",AV36,NPER($E$7,-AS36+AJ37+AK37,AT36)),AT36+AX36)+AJ37+AK37))+IF(INT(AV36)=1,AX37,0) -> 1610.6611 | AT37: =IF(AT36-AU37-AP37<0,0,IF(AT36-AP37>0,AT36-AP37,0)-IF(AT36-AP37>0,AU37-AX37,0)) -> 86827.251 | AU37: 0 | AV37: =IFERROR(NPER($E$7,-AS37+AJ36+AK36,AT36+AX36)-1,0) -> 77.193471 | AX37: =AT36*$D$9 -> 148.73556
A38: =IF(N37<1,0,A37) -> 25 | B38: =IF(N37<1,0,B37) -> 75 | C38: =DATE(YEAR(C37),MONTH(C37)+1,1) -> 46753 | D38: =IF(N37>0,G38/N37,"") -> 0.0094541307 | E38: =E37+1 -> 24 | F38: =IF(N37>0,N37*$E$7,0) -> 692.37269 | G38: =IF(N37>G37,L38-F38-A38-B38,N37) -> 820.87617 | H38: =IF(L38<1,"",IF(G38/L38>90%,"🛩",IF(G38/L38>70%,"🏎",IF(G38/L38>50%,"🚙",IF(G38/L38>30%,"🛵",IF(G38/L38>15%,"🐢","⚓️")))))) -> 🚙 | I38: =IFERROR(IF((G38+O38-R38)/L38<0,"🗑️",IF((G38+O38-R38)/L38<10%,"🥾",IF((G38+O38-R38)/L38<20%,"🛴",IF((G38+O38-R38)/L38<50%,"🚴‍♂️",IF((G38+O38-R38)/L38<75%,"🚖","🚁"))))),"") -> 🚴‍♂️ | J38: =G38+O38-R38 -> 673.26985 | K38: =IFERROR(J38/(L38+O38),0) -> 0.41733787 | L38: =IF(INT(N37)=0,0,IF(N37<G37,N37+F38+A38+B38,-PMT($E$7,IF(Q37="V",P37,NPER($E$7,-L37+A38+B38,N37)),N37+R37)+A38+B38))+IF(INT(P37)=1,R38,0) -> 1613.2489 | M38: =IFERROR(N37/P38-G38+L38,0) -> 1931.9779 | N38: =IF(N37-O38-G38<0,0,IF(N37-G38>0,N37-G38,0)-IF(N37-G38>0,O38-R38,0)) -> 86153.981 | P38: =IFERROR(NPER($E$7,-L38+A37+B37,N37+R37)-1,0) -> 76.190638 | R38: =N37*$D$9 -> 147.60633 | V38: =-L38-O38 -> -1613.2489 | AA38: =ROUNDUP(E38/120,0) -> 1 | AB38: =ROUNDUP(E38/36,0) -> 1 | AC38: =ROUNDUP(E38/12,0) -> 2 | AJ38: =IF(AT37<1,0,AJ37) -> 25 | AK38: =IF(AT37<1,0,AK37) -> 75 | AL38: =DATE(YEAR(AL37),MONTH(AL37)+1,1) -> 46753 | AM38: =IF(AT37>0,AP38/AT37,"") -> 0.0094541307 | AN38: =AN37+1 -> 24 | AO38: =IF(AT37>0,AT37*$E$7,0) -> 692.37269 | AP38: =IF(AT37>AP37,AS38-AO38-AJ38-AK38,AT37) -> 820.87617 | AQ38: =IF(AS38<1,"",IF(AP38/AS38>90%,"🛩",IF(AP38/AS38>70%,"🏎",IF(AP38/AS38>50%,"🚙",IF(AP38/AS38>30%,"🛵",IF(AP38/AS38>15%,"🐢","⚓️")))))) -> 🚙 | AR38: =IFERROR(IF((AP38+AU38-AX38)/AS38<0,"🗑️",IF((AP38+AU38-AX38)/AS38<10%,"🥾",IF((AP38+AU38-AX38)/AS38<20%,"🛴",IF((AP38+AU38-AX38)/AS38<50%,"🚴‍♂️",IF((AP38+AU38-AX38)/AS38<75%,"🚖","🚁"))))),"") -> 🚴‍♂️ | AS38: =IF(INT(AT37)=0,0,IF(AT37<AP37,AT37+AO38+AJ38+AK38,-PMT($E$7,IF(AW37="V",AV37,NPER($E$7,-AS37+AJ38+AK38,AT37)),AT37+AX37)+AJ38+AK38))+IF(INT(AV37)=1,AX38,0) -> 1613.2489 | AT38: =IF(AT37-AU38-AP38<0,0,IF(AT37-AP38>0,AT37-AP38,0)-IF(AT37-AP38>0,AU38-AX38,0)) -> 86153.981 | AU38: 0 | AV38: =IFERROR(NPER($E$7,-AS38+AJ37+AK37,AT37+AX37)-1,0) -> 76.190638 | AX38: =AT37*$D$9 -> 147.60633
A39: =IF(N38<1,0,A38) -> 25 | B39: =IF(N38<1,0,B38) -> 75 | C39: =DATE(YEAR(C38),MONTH(C38)+1,1) -> 46784 | D39: =IF(N38>0,G39/N38,"") -> 0.0096204208 | E39: =E38+1 -> 25 | F39: =IF(N38>0,N38*$E$7,0) -> 687.00394 | G39: =IF(N38>G38,L39-F39-A39-B39,N38) -> 828.83755 | H39: =IF(L39<1,"",IF(G39/L39>90%,"🛩",IF(G39/L39>70%,"🏎",IF(G39/L39>50%,"🚙",IF(G39/L39>30%,"🛵",IF(G39/L39>15%,"🐢","⚓️")))))) -> 🚙 | I39: =IFERROR(IF((G39+O39-R39)/L39<0,"🗑️",IF((G39+O39-R39)/L39<10%,"🥾",IF((G39+O39-R39)/L39<20%,"🛴",IF((G39+O39-R39)/L39<50%,"🚴‍♂️",IF((G39+O39-R39)/L39<75%,"🚖","🚁"))))),"") -> 🚴‍♂️ | J39: =G39+O39-R39 -> 682.37578 | K39: =IFERROR(J39/(L39+O39),0) -> 0.42230366 | L39: =IF(INT(N38)=0,0,IF(N38<G38,N38+F39+A39+B39,-PMT($E$7,IF(Q38="V",P38,NPER($E$7,-L38+A39+B39,N38)),N38+R38)+A39+B39))+IF(INT(P38)=1,R39,0) -> 1615.8415 | M39: =IFERROR(N38/P39-G39+L39,0) -> 1932.8541 | N39: =IF(N38-O39-G39<0,0,IF(N38-G39>0,N38-G39,0)-IF(N38-G39>0,O39-R39,0)) -> 85471.605 | P39: =IFERROR(NPER($E$7,-L39+A38+B38,N38+R38)-1,0) -> 75.187824 | R39: =N38*$D$9 -> 146.46177 | V39: =-L39-O39 -> -1615.8415 | AA39: =ROUNDUP(E39/120,0) -> 1 | AB39: =ROUNDUP(E39/36,0) -> 1 | AC39: =ROUNDUP(E39/12,0) -> 3 | AJ39: =IF(AT38<1,0,AJ38) -> 25 | AK39: =IF(AT38<1,0,AK38) -> 75 | AL39: =DATE(YEAR(AL38),MONTH(AL38)+1,1) -> 46784 | AM39: =IF(AT38>0,AP39/AT38,"") -> 0.0096204208 | AN39: =AN38+1 -> 25 | AO39: =IF(AT38>0,AT38*$E$7,0) -> 687.00394 | AP39: =IF(AT38>AP38,AS39-AO39-AJ39-AK39,AT38) -> 828.83755 | AQ39: =IF(AS39<1,"",IF(AP39/AS39>90%,"🛩",IF(AP39/AS39>70%,"🏎",IF(AP39/AS39>50%,"🚙",IF(AP39/AS39>30%,"🛵",IF(AP39/AS39>15%,"🐢","⚓️")))))) -> 🚙 | AR39: =IFERROR(IF((AP39+AU39-AX39)/AS39<0,"🗑️",IF((AP39+AU39-AX39)/AS39<10%,"🥾",IF((AP39+AU39-AX39)/AS39<20%,"🛴",IF((AP39+AU39-AX39)/AS39<50%,"🚴‍♂️",IF((AP39+AU39-AX39)/AS39<75%,"🚖","🚁"))))),"") -> 🚴‍♂️ | AS39: =IF(INT(AT38)=0,0,IF(AT38<AP38,AT38+AO39+AJ39+AK39,-PMT($E$7,IF(AW38="V",AV38,NPER($E$7,-AS38+AJ39+AK39,AT38)),AT38+AX38)+AJ39+AK39))+IF(INT(AV38)=1,AX39,0) -> 1615.8415 | AT39: =IF(AT38-AU39-AP39<0,0,IF(AT38-AP39>0,AT38-AP39,0)-IF(AT38-AP39>0,AU39-AX39,0)) -> 85471.605 | AU39: 0 | AV39: =IFERROR(NPER($E$7,-AS39+AJ38+AK38,AT38+AX38)-1,0) -> 75.187824 | AX39: =AT38*$D$9 -> 146.46177
A40: =IF(N39<1,0,A39) -> 25 | B40: =IF(N39<1,0,B39) -> 75 | C40: =DATE(YEAR(C39),MONTH(C39)+1,1) -> 46813 | D40: =IF(N39>0,G40/N39,"") -> 0.00979128 | E40: =E39+1 -> 26 | F40: =IF(N39>0,N39*$E$7,0) -> 681.56258 | G40: =IF(N39>G39,L40-F40-A40-B40,N39) -> 836.87641 | H40: =IF(L40<1,"",IF(G40/L40>90%,"🛩",IF(G40/L40>70%,"🏎",IF(G40/L40>50%,"🚙",IF(G40/L40>30%,"🛵",IF(G40/L40>15%,"🐢","⚓️")))))) -> 🚙 | I40: =IFERROR(IF((G40+O40-R40)/L40<0,"🗑️",IF((G40+O40-R40)/L40<10%,"🥾",IF((G40+O40-R40)/L40<20%,"🛴",IF((G40+O40-R40)/L40<50%,"🚴‍♂️",IF((G40+O40-R40)/L40<75%,"🚖","🚁"))))),"") -> 🚴‍♂️ | J40: =G40+O40-R40 -> 691.57469 | K40: =IFERROR(J40/(L40+O40),0) -> 0.4273097 | L40: =IF(INT(N39)=0,0,IF(N39<G39,N39+F40+A40+B40,-PMT($E$7,IF(Q39="V",P39,NPER($E$7,-L39+A40+B40,N39)),N39+R39)+A40+B40))+IF(INT(P39)=1,R40,0) -> 1618.439 | M40: =IFERROR(N39/P40-G40+L40,0) -> 1933.7034 | N40: =IF(N39-O40-G40<0,0,IF(N39-G40>0,N39-G40,0)-IF(N39-G40>0,O40-R40,0)) -> 84780.03 | P40: =IFERROR(NPER($E$7,-L40+A39+B39,N39+R39)-1,0) -> 74.185031 | R40: =N39*$D$9 -> 145.30173 | V40: =-L40-O40 -> -1618.439 | AA40: =ROUNDUP(E40/120,0) -> 1 | AB40: =ROUNDUP(E40/36,0) -> 1 | AC40: =ROUNDUP(E40/12,0) -> 3 | AJ40: =IF(AT39<1,0,AJ39) -> 25 | AK40: =IF(AT39<1,0,AK39) -> 75 | AL40: =DATE(YEAR(AL39),MONTH(AL39)+1,1) -> 46813 | AM40: =IF(AT39>0,AP40/AT39,"") -> 0.00979128 | AN40: =AN39+1 -> 26 | AO40: =IF(AT39>0,AT39*$E$7,0) -> 681.56258 | AP40: =IF(AT39>AP39,AS40-AO40-AJ40-AK40,AT39) -> 836.87641 | AQ40: =IF(AS40<1,"",IF(AP40/AS40>90%,"🛩",IF(AP40/AS40>70%,"🏎",IF(AP40/AS40>50%,"🚙",IF(AP40/AS40>30%,"🛵",IF(AP40/AS40>15%,"🐢","⚓️")))))) -> 🚙 | AR40: =IFERROR(IF((AP40+AU40-AX40)/AS40<0,"🗑️",IF((AP40+AU40-AX40)/AS40<10%,"🥾",IF((AP40+AU40-AX40)/AS40<20%,"🛴",IF((AP40+AU40-AX40)/AS40<50%,"🚴‍♂️",IF((AP40+AU40-AX40)/AS40<75%,"🚖","🚁"))))),"") -> 🚴‍♂️ | AS40: =IF(INT(AT39)=0,0,IF(AT39<AP39,AT39+AO40+AJ40+AK40,-PMT($E$7,IF(AW39="V",AV39,NPER($E$7,-AS39+AJ40+AK40,AT39)),AT39+AX39)+AJ40+AK40))+IF(INT(AV39)=1,AX40,0) -> 1618.439 | AT40: =IF(AT39-AU40-AP40<0,0,IF(AT39-AP40>0,AT39-AP40,0)-IF(AT39-AP40>0,AU40-AX40,0)) -> 84780.03 | AU40: 0 | AV40: =IFERROR(NPER($E$7,-AS40+AJ39+AK39,AT39+AX39)-1,0) -> 74.185031 | AX40: =AT39*$D$9 -> 145.30173
A41: =IF(N40<1,0,A40) -> 25 | B41: =IF(N40<1,0,B40) -> 75 | C41: =DATE(YEAR(C40),MONTH(C40)+1,1) -> 46844 | D41: =IF(N40>0,G41/N40,"") -> 0.0099668935 | E41: =E40+1 -> 27 | F41: =IF(N40>0,N40*$E$7,0) -> 676.04787 | G41: =IF(N40>G40,L41-F41-A41-B41,N40) -> 844.99353 | H41: =IF(L41<1,"",IF(G41/L41>90%,"🛩",IF(G41/L41>70%,"🏎",IF(G41/L41>50%,"🚙",IF(G41/L41>30%,"🛵",IF(G41/L41>15%,"🐢","⚓️")))))) -> 🚙 | I41: =IFERROR(IF((G41+O41-R41)/L41<0,"🗑️",IF((G41+O41-R41)/L41<10%,"🥾",IF((G41+O41-R41)/L41<20%,"🛴",IF((G41+O41-R41)/L41<50%,"🚴‍♂️",IF((G41+O41-R41)/L41<75%,"🚖","🚁"))))),"") -> 🚴‍♂️ | J41: =G41+O41-R41 -> 700.86748 | K41: =IFERROR(J41/(L41+O41),0) -> 0.43235631 | L41: =IF(INT(N40)=0,0,IF(N40<G40,N40+F41+A41+B41,-PMT($E$7,IF(Q40="V",P40,NPER($E$7,-L40+A41+B41,N40)),N40+R40)+A41+B41))+IF(INT(P40)=1,R41,0) -> 1621.0414 | M41: =IFERROR(N40/P41-G41+L41,0) -> 1934.5258 | N41: =IF(N40-O41-G41<0,0,IF(N40-G41>0,N40-G41,0)-IF(N40-G41>0,O41-R41,0)) -> 84079.163 | P41: =IFERROR(NPER($E$7,-L41+A40+B40,N40+R40)-1,0) -> 73.182256 | R41: =N40*$D$9 -> 144.12605 | V41: =-L41-O41 -> -1621.0414 | AA41: =ROUNDUP(E41/120,0) -> 1 | AB41: =ROUNDUP(E41/36,0) -> 1 | AC41: =ROUNDUP(E41/12,0) -> 3 | AJ41: =IF(AT40<1,0,AJ40) -> 25 | AK41: =IF(AT40<1,0,AK40) -> 75 | AL41: =DATE(YEAR(AL40),MONTH(AL40)+1,1) -> 46844 | AM41: =IF(AT40>0,AP41/AT40,"") -> 0.0099668935 | AN41: =AN40+1 -> 27 | AO41: =IF(AT40>0,AT40*$E$7,0) -> 676.04787 | AP41: =IF(AT40>AP40,AS41-AO41-AJ41-AK41,AT40) -> 844.99353 | AQ41: =IF(AS41<1,"",IF(AP41/AS41>90%,"🛩",IF(AP41/AS41>70%,"🏎",IF(AP41/AS41>50%,"🚙",IF(AP41/AS41>30%,"🛵",IF(AP41/AS41>15%,"🐢","⚓️")))))) -> 🚙 | AR41: =IFERROR(IF((AP41+AU41-AX41)/AS41<0,"🗑️",IF((AP41+AU41-AX41)/AS41<10%,"🥾",IF((AP41+AU41-AX41)/AS41<20%,"🛴",IF((AP41+AU41-AX41)/AS41<50%,"🚴‍♂️",IF((AP41+AU41-AX41)/AS41<75%,"🚖","🚁"))))),"") -> 🚴‍♂️ | AS41: =IF(INT(AT40)=0,0,IF(AT40<AP40,AT40+AO41+AJ41+AK41,-PMT($E$7,IF(AW40="V",AV40,NPER($E$7,-AS40+AJ41+AK41,AT40)),AT40+AX40)+AJ41+AK41))+IF(INT(AV40)=1,AX41,0) -> 1621.0414 | AT41: =IF(AT40-AU41-AP41<0,0,IF(AT40-AP41>0,AT40-AP41,0)-IF(AT40-AP41>0,AU41-AX41,0)) -> 84079.163 | AU41: 0 | AV41: =IFERROR(NPER($E$7,-AS41+AJ40+AK40,AT40+AX40)-1,0) -> 73.182256 | AX41: =AT40*$D$9 -> 144.12605
A42: =IF(N41<1,0,A41) -> 25 | B42: =IF(N41<1,0,B41) -> 75 | C42: =DATE(YEAR(C41),MONTH(C41)+1,1) -> 46874 | D42: =IF(N41>0,G42/N41,"") -> 0.010147457 | E42: =E41+1 -> 28 | F42: =IF(N41>0,N41*$E$7,0) -> 670.45905 | G42: =IF(N41>G41,L42-F42-A42-B42,N41) -> 853.18967 | H42: =IF(L42<1,"",IF(G42/L42>90%,"🛩",IF(G42/L42>70%,"🏎",IF(G42/L42>50%,"🚙",IF(G42/L42>30%,"🛵",IF(G42/L42>15%,"🐢","⚓️")))))) -> 🚙 | I42: =IFERROR(IF((G42+O42-R42)/L42<0,"🗑️",IF((G42+O42-R42)/L42<10%,"🥾",IF((G42+O42-R42)/L42<20%,"🛴",IF((G42+O42-R42)/L42<50%,"🚴‍♂️",IF((G42+O42-R42)/L42<75%,"🚖","🚁"))))),"") -> 🚴‍♂️ | J42: =G42+O42-R42 -> 710.25509 | K42: =IFERROR(J42/(L42+O42),0) -> 0.43744382 | L42: =IF(INT(N41)=0,0,IF(N41<G41,N41+F42+A42+B42,-PMT($E$7,IF(Q41="V",P41,NPER($E$7,-L41+A42+B42,N41)),N41+R41)+A42+B42))+IF(INT(P41)=1,R42,0) -> 1623.6487 | M42: =IFERROR(N41/P42-G42+L42,0) -> 1935.3211 | N42: =IF(N41-O42-G42<0,0,IF(N41-G42>0,N41-G42,0)-IF(N41-G42>0,O42-R42,0)) -> 83368.908 | P42: =IFERROR(NPER($E$7,-L42+A41+B41,N41+R41)-1,0) -> 72.179501 | R42: =N41*$D$9 -> 142.93458 | V42: =-L42-O42 -> -1623.6487 | AA42: =ROUNDUP(E42/120,0) -> 1 | AB42: =ROUNDUP(E42/36,0) -> 1 | AC42: =ROUNDUP(E42/12,0) -> 3 | AJ42: =IF(AT41<1,0,AJ41) -> 25 | AK42: =IF(AT41<1,0,AK41) -> 75 | AL42: =DATE(YEAR(AL41),MONTH(AL41)+1,1) -> 46874 | AM42: =IF(AT41>0,AP42/AT41,"") -> 0.010147457 | AN42: =AN41+1 -> 28 | AO42: =IF(AT41>0,AT41*$E$7,0) -> 670.45905 | AP42: =IF(AT41>AP41,AS42-AO42-AJ42-AK42,AT41) -> 853.18967 | AQ42: =IF(AS42<1,"",IF(AP42/AS42>90%,"🛩",IF(AP42/AS42>70%,"🏎",IF(AP42/AS42>50%,"🚙",IF(AP42/AS42>30%,"🛵",IF(AP42/AS42>15%,"🐢","⚓️")))))) -> 🚙 | AR42: =IFERROR(IF((AP42+AU42-AX42)/AS42<0,"🗑️",IF((AP42+AU42-AX42)/AS42<10%,"🥾",IF((AP42+AU42-AX42)/AS42<20%,"🛴",IF((AP42+AU42-AX42)/AS42<50%,"🚴‍♂️",IF((AP42+AU42-AX42)/AS42<75%,"🚖","🚁"))))),"") -> 🚴‍♂️ | AS42: =IF(INT(AT41)=0,0,IF(AT41<AP41,AT41+AO42+AJ42+AK42,-PMT($E$7,IF(AW41="V",AV41,NPER($E$7,-AS41+AJ42+AK42,AT41)),AT41+AX41)+AJ42+AK42))+IF(INT(AV41)=1,AX42,0) -> 1623.6487 | AT42: =IF(AT41-AU42-AP42<0,0,IF(AT41-AP42>0,AT41-AP42,0)-IF(AT41-AP42>0,AU42-AX42,0)) -> 83368.908 | AU42: 0 | AV42: =IFERROR(NPER($E$7,-AS42+AJ41+AK41,AT41+AX41)-1,0) -> 72.179501 | AX42: =AT41*$D$9 -> 142.93458
A43: =IF(N42<1,0,A42) -> 25 | B43: =IF(N42<1,0,B42) -> 75 | C43: =DATE(YEAR(C42),MONTH(C42)+1,1) -> 46905 | D43: =IF(N42>0,G43/N42,"") -> 0.010333176 | E43: =E42+1 -> 29 | F43: =IF(N42>0,N42*$E$7,0) -> 664.79538 | G43: =IF(N42>G42,L43-F43-A43-B43,N42) -> 861.46561 | H43: =IF(L43<1,"",IF(G43/L43>90%,"🛩",IF(G43/L43>70%,"🏎",IF(G43/L43>50%,"🚙",IF(G43/L43>30%,"🛵",IF(G43/L43>15%,"🐢","⚓️")))))) -> 🚙 | I43: =IFERROR(IF((G43+O43-R43)/L43<0,"🗑️",IF((G43+O43-R43)/L43<10%,"🥾",IF((G43+O43-R43)/L43<20%,"🛴",IF((G43+O43-R43)/L43<50%,"🚴‍♂️",IF((G43+O43-R43)/L43<75%,"🚖","🚁"))))),"") -> 🚴‍♂️ | J43: =G43+O43-R43 -> 719.73847 | K43: =IFERROR(J43/(L43+O43),0) -> 0.44257255 | L43: =IF(INT(N42)=0,0,IF(N42<G42,N42+F43+A43+B43,-PMT($E$7,IF(Q42="V",P42,NPER($E$7,-L42+A43+B43,N42)),N42+R42)+A43+B43))+IF(INT(P42)=1,R43,0) -> 1626.261 | M43: =IFERROR(N42/P43-G43+L43,0) -> 1936.0892 | N43: =IF(N42-O43-G43<0,0,IF(N42-G43>0,N42-G43,0)-IF(N42-G43>0,O43-R43,0)) -> 82649.169 | P43: =IFERROR(NPER($E$7,-L43+A42+B42,N42+R42)-1,0) -> 71.176764 | R43: =N42*$D$9 -> 141.72714 | V43: =-L43-O43 -> -1626.261 | AA43: =ROUNDUP(E43/120,0) -> 1 | AB43: =ROUNDUP(E43/36,0) -> 1 | AC43: =ROUNDUP(E43/12,0) -> 3 | AJ43: =IF(AT42<1,0,AJ42) -> 25 | AK43: =IF(AT42<1,0,AK42) -> 75 | AL43: =DATE(YEAR(AL42),MONTH(AL42)+1,1) -> 46905 | AM43: =IF(AT42>0,AP43/AT42,"") -> 0.010333176 | AN43: =AN42+1 -> 29 | AO43: =IF(AT42>0,AT42*$E$7,0) -> 664.79538 | AP43: =IF(AT42>AP42,AS43-AO43-AJ43-AK43,AT42) -> 861.46561 | AQ43: =IF(AS43<1,"",IF(AP43/AS43>90%,"🛩",IF(AP43/AS43>70%,"🏎",IF(AP43/AS43>50%,"🚙",IF(AP43/AS43>30%,"🛵",IF(AP43/AS43>15%,"🐢","⚓️")))))) -> 🚙 | AR43: =IFERROR(IF((AP43+AU43-AX43)/AS43<0,"🗑️",IF((AP43+AU43-AX43)/AS43<10%,"🥾",IF((AP43+AU43-AX43)/AS43<20%,"🛴",IF((AP43+AU43-AX43)/AS43<50%,"🚴‍♂️",IF((AP43+AU43-AX43)/AS43<75%,"🚖","🚁"))))),"") -> 🚴‍♂️ | AS43: =IF(INT(AT42)=0,0,IF(AT42<AP42,AT42+AO43+AJ43+AK43,-PMT($E$7,IF(AW42="V",AV42,NPER($E$7,-AS42+AJ43+AK43,AT42)),AT42+AX42)+AJ43+AK43))+IF(INT(AV42)=1,AX43,0) -> 1626.261 | AT43: =IF(AT42-AU43-AP43<0,0,IF(AT42-AP43>0,AT42-AP43,0)-IF(AT42-AP43>0,AU43-AX43,0)) -> 82649.169 | AU43: 0 | AV43: =IFERROR(NPER($E$7,-AS43+AJ42+AK42,AT42+AX42)-1,0) -> 71.176764 | AX43: =AT42*$D$9 -> 141.72714
... A433: =IF(N432<1,0,A432) -> 0 | B433: =IF(N432<1,0,B432) -> 0 | C433: =DATE(YEAR(C432),MONTH(C432)+1,1) -> 58776 | D433: =IF(N432>0,G433/N432,"") | E433: =E432+1 -> 419 | F433: =IF(N432>0,N432*$E$7,0) -> 0 | G433: =IF(N432>G432,L433-F433-A433-B433,N432) -> 0 | H433: =IF(L433<1,"",IF(G433/L433>90%,"🛩",IF(G433/L433>70%,"🏎",IF(G433/L433>50%,"🚙",IF(G433/L433>30%,"🛵",IF(G433/L433>15%,"🐢","⚓️")))))) | I433: =IFERROR(IF((G433+O433-R433)/L433<0,"🗑️",IF((G433+O433-R433)/L433<10%,"🥾",IF((G433+O433-R433)/L433<20%,"🛴",IF((G433+O433-R433)/L433<50%,"🚴‍♂️",IF((G433+O433-R433)/L433<75%,"🚖","🚁"))))),"") | J433: =G433+O433-R433 -> 0 | K433: =IFERROR(J433/(L433+O433),0) -> 0 | L433: =IF(INT(N432)=0,0,IF(N432<G432,N432+F433+A433+B433,-PMT($E$7,IF(Q432="V",P432,NPER($E$7,-L432+A433+B433,N432)),N432+R432)+A433+B433))+IF(INT(P432)=1,R433,0) -> 0 | M433: =IFERROR(N432/P433-G433+L433,0) -> 0 | N433: =IF(N432-O433-G433<0,0,IF(N432-G433>0,N432-G433,0)-IF(N432-G433>0,O433-R433,0)) -> 0 | P433: =IFERROR(NPER($E$7,-L433+A432+B432,N432+R432)-1,0) -> 0 | R433: =N432*$D$9 -> 0 | V433: =-L433-O433 -> 0 | AA433: =ROUNDUP(E433/120,0) -> 4 | AB433: =ROUNDUP(E433/36,0) -> 12 | AC433: =ROUNDUP(E433/12,0) -> 35 | AJ433: =IF(AT432<1,0,AJ432) -> 0 | AK433: =IF(AT432<1,0,AK432) -> 0 | AL433: =DATE(YEAR(AL432),MONTH(AL432)+1,1) -> 58776 | AM433: =IF(AT432>0,AP433/AT432,"") | AN433: =AN432+1 -> 419 | AO433: =IF(AT432>0,AT432*$E$7,0) -> 0 | AP433: =IF(AT432>AP432,AS433-AO433-AJ433-AK433,AT432) -> 0 | AQ433: =IF(AS433<1,"",IF(AP433/AS433>90%,"🛩",IF(AP433/AS433>70%,"🏎",IF(AP433/AS433>50%,"🚙",IF(AP433/AS433>30%,"🛵",IF(AP433/AS433>15%,"🐢","⚓️")))))) | AR433: =IFERROR(IF((AP433+AU433-AX433)/AS433<0,"🗑️",IF((AP433+AU433-AX433)/AS433<10%,"🥾",IF((AP433+AU433-AX433)/AS433<20%,"🛴",IF((AP433+AU433-AX433)/AS433<50%,"🚴‍♂️",IF((AP433+AU433-AX433)/AS433<75%,"🚖","🚁"))))),"") | AS433: =IF(INT(AT432)=0,0,IF(AT432<AP432,AT432+AO433+AJ433+AK433,-PMT($E$7,IF(AW432="V",AV432,NPER($E$7,-AS432+AJ433+AK433,AT432)),AT432+AX432)+AJ433+AK433))+IF(INT(AV432)=1,AX433,0) -> 0 | AT433: =IF(AT432-AU433-AP433<0,0,IF(AT432-AP433>0,AT432-AP433,0)-IF(AT432-AP433>0,AU433-AX433,0)) -> 0 | AU433: 0 | AV433: =IFERROR(NPER($E$7,-AS433+AJ432+AK432,AT432+AX432)-1,0) -> 0 | AX433: =AT432*$D$9 -> 0
A434: =IF(N433<1,0,A433) -> 0 | B434: =IF(N433<1,0,B433) -> 0 | D434: =IF(N433>0,G434/N433,"") | E434: =E433+1 -> 420 | F434: =IF(N433>0,N433*$E$7,0) -> 0 | G434: =IF(N433>G433,L434-F434-A434-B434,N433) -> 0 | H434: =IF(L434<1,"",IF(G434/L434>90%,"🛩",IF(G434/L434>70%,"🏎",IF(G434/L434>50%,"🚙",IF(G434/L434>30%,"🛵",IF(G434/L434>15%,"🐢","⚓️")))))) | I434: =IFERROR(IF((G434+O434-R434)/L434<0,"🗑️",IF((G434+O434-R434)/L434<10%,"🥾",IF((G434+O434-R434)/L434<20%,"🛴",IF((G434+O434-R434)/L434<50%,"🚴‍♂️",IF((G434+O434-R434)/L434<75%,"🚖","🚁"))))),"") | J434: =G434+O434-R434 -> 0 | K434: =IFERROR(J434/(L434+O434),0) -> 0 | L434: =IF(INT(N433)=0,0,IF(N433<G433,N433+F434+A434+B434,-PMT($E$7,IF(Q433="V",P433,NPER($E$7,-L433+A434+B434,N433)),N433+R433)+A434+B434))+IF(INT(P433)=1,R434,0) -> 0 | M434: =IFERROR(N433/P434-G434+L434,0) -> 0 | N434: =IF(N433-O434-G434<0,0,IF(N433-G434>0,N433-G434,0)-IF(N433-G434>0,O434-R434,0)) -> 0 | P434: =IFERROR(NPER($E$7,-L434+A433+B433,N433+R433)-1,0) -> 0 | R434: =N433*$D$9 -> 0 | V434: =-L434-O434 -> 0 | AA434: =ROUNDUP(E434/120,0) -> 4 | AB434: =ROUNDUP(E434/36,0) -> 12 | AC434: =ROUNDUP(E434/12,0) -> 35 | AJ434: =IF(AT433<1,0,AJ433) -> 0 | AK434: =IF(AT433<1,0,AK433) -> 0 | AM434: =IF(AT433>0,AP434/AT433,"") | AN434: =AN433+1 -> 420 | AO434: =IF(AT433>0,AT433*$E$7,0) -> 0 | AP434: =IF(AT433>AP433,AS434-AO434-AJ434-AK434,AT433) -> 0 | AQ434: =IF(AS434<1,"",IF(AP434/AS434>90%,"🛩",IF(AP434/AS434>70%,"🏎",IF(AP434/AS434>50%,"🚙",IF(AP434/AS434>30%,"🛵",IF(AP434/AS434>15%,"🐢","⚓️")))))) | AR434: =IFERROR(IF((AP434+AU434-AX434)/AS434<0,"🗑️",IF((AP434+AU434-AX434)/AS434<10%,"🥾",IF((AP434+AU434-AX434)/AS434<20%,"🛴",IF((AP434+AU434-AX434)/AS434<50%,"🚴‍♂️",IF((AP434+AU434-AX434)/AS434<75%,"🚖","🚁"))))),"") | AS434: =IF(INT(AT433)=0,0,IF(AT433<AP433,AT433+AO434+AJ434+AK434,-PMT($E$7,IF(AW433="V",AV433,NPER($E$7,-AS433+AJ434+AK434,AT433)),AT433+AX433)+AJ434+AK434))+IF(INT(AV433)=1,AX434,0) -> 0 | AT434: =IF(AT433-AU434-AP434<0,0,IF(AT433-AP434>0,AT433-AP434,0)-IF(AT433-AP434>0,AU434-AX434,0)) -> 0 | AU434: 0 | AV434: =IFERROR(NPER($E$7,-AS434+AJ433+AK433,AT433+AX433)-1,0) -> 0 | AX434: =AT433*$D$9 -> 0

Sheet Painel de Acompanhamento PRICE
C2: ACOMPANHAMENTO A CADA 3 ANOS | G2: Financiado | H2: ='BASE PRICE @amigodopairico'!$D$8 -> 100000 | I2: Parcela | J2: ='BASE PRICE @amigodopairico'!$L$15 -> 1554.921
C3: PRICE | G3: Juros | H3: ='BASE PRICE @amigodopairico'!$D$7 -> 0.1
B5: TRIÊNIO | C5: ANOS | D5: PARCELAS | E5: JUROS | F5: AMORTIZAÇÃO | G5: DIF. DÍVIDA | H5: ADIANTAMENTO | I5: PREV. AT. MON.
B6: 1 | C6: ANO 1 AO 3 | D6: =SUMIF('BASE PRICE @amigodopairico'!$AB$15:$AB$434,"="&$B6,Price_Parcela) -> 57575.959 | E6: =SUMIF('BASE PRICE @amigodopairico'!$AB$15:$AB$434,"="&$B6,Price_Juros) -> 25810.632 | F6: =SUMIF('BASE PRICE @amigodopairico'!$AB$15:$AB$434,"="&$B6,Price_Amortizacao) -> 28165.327 | G6: =SUMIF('BASE PRICE @amigodopairico'!$AB$15:$AB$434,"="&$B6,Price_QuedaSaldoDevedor) -> 22662.781 | H6: =SUMIF('BASE PRICE @amigodopairico'!$AB$15:$AB$434,"="&$B6,Price_Adiantamento) -> 0 | I6: =SUMIF('BASE PRICE @amigodopairico'!$AB$15:$AB$434,"="&$B6,Price_PrevisaoAtualizacaoMonetaria) -> 5502.546 | K6: ='BASE PRICE @amigodopairico'!D50 -> 0.011797579
B7: =B6+1 -> 2 | C7: ANO 4 AO 6 | D7: =SUMIF('BASE PRICE @amigodopairico'!$AB$15:$AB$434,"="&$B7,Price_Parcela) -> 61018.733 | E7: =SUMIF('BASE PRICE @amigodopairico'!$AB$15:$AB$434,"="&$B7,Price_Juros) -> 17541.785 | F7: =SUMIF('BASE PRICE @amigodopairico'!$AB$15:$AB$434,"="&$B7,Price_Amortizacao) -> 39876.948 | G7: =SUMIF('BASE PRICE @amigodopairico'!$AB$15:$AB$434,"="&$B7,Price_QuedaSaldoDevedor) -> 36137.23 | H7: =SUMIF('BASE PRICE @amigodopairico'!$AB$15:$AB$434,"="&$B7,Price_Adiantamento) -> 0 | I7: =SUMIF('BASE PRICE @amigodopairico'!$AB$15:$AB$434,"="&$B7,Price_PrevisaoAtualizacaoMonetaria) -> 3739.7177 | K7: ='BASE PRICE @amigodopairico'!D86 -> 0.030764488
B8: =B7+1 -> 3 | C8: ANO 7 AO 9 | D8: =SUMIF('BASE PRICE @amigodopairico'!$AB$15:$AB$434,"="&$B8,Price_Parcela) -> 50189.396 | E8: =SUMIF('BASE PRICE @amigodopairico'!$AB$15:$AB$434,"="&$B8,Price_Juros) -> 5019.3858 | F8: =SUMIF('BASE PRICE @amigodopairico'!$AB$15:$AB$434,"="&$B8,Price_Amortizacao) -> 42270.01 | G8: =SUMIF('BASE PRICE @amigodopairico'!$AB$15:$AB$434,"="&$B8,Price_QuedaSaldoDevedor) -> 41199.932 | H8: =SUMIF('BASE PRICE @amigodopairico'!$AB$15:$AB$434,"="&$B8,Price_Adiantamento) -> 0 | I8: =SUMIF('BASE PRICE @amigodopairico'!$AB$15:$AB$434,"="&$B8,Price_PrevisaoAtualizacaoMonetaria) -> 1070.0785 | K8: ='BASE PRICE @amigodopairico'!D122
B9: =B8+1 -> 4 | C9: ANO 10 AO 12 | D9: =SUMIF('BASE PRICE @amigodopairico'!$AB$15:$AB$434,"="&$B9,Price_Parcela) -> 0 | E9: =SUMIF('BASE PRICE @amigodopairico'!$AB$15:$AB$434,"="&$B9,Price_Juros) -> 0 | F9: =SUMIF('BASE PRICE @amigodopairico'!$AB$15:$AB$434,"="&$B9,Price_Amortizacao) -> 0 | G9: =SUMIF('BASE PRICE @amigodopairico'!$AB$15:$AB$434,"="&$B9,Price_QuedaSaldoDevedor) -> 0 | H9: =SUMIF('BASE PRICE @amigodopairico'!$AB$15:$AB$434,"="&$B9,Price_Adiantamento) -> 0 | I9: =SUMIF('BASE PRICE @amigodopairico'!$AB$15:$AB$434,"="&$B9,Price_PrevisaoAtualizacaoMonetaria) -> 0 | K9: ='BASE PRICE @amigodopairico'!D158
B10: =B9+1 -> 5 | C10: ANO 13 AO 15 | D10: =SUMIF('BASE PRICE @amigodopairico'!$AB$15:$AB$434,"="&$B10,Price_Parcela) -> 0 | E10: =SUMIF('BASE PRICE @amigodopairico'!$AB$15:$AB$434,"="&$B10,Price_Juros) -> 0 | F10: =SUMIF('BASE PRICE @amigodopairico'!$AB$15:$AB$434,"="&$B10,Price_Amortizacao) -> 0 | G10: =SUMIF('BASE PRICE @amigodopairico'!$AB$15:$AB$434,"="&$B10,Price_QuedaSaldoDevedor) -> 0 | H10: =SUMIF('BASE PRICE @amigodopairico'!$AB$15:$AB$434,"="&$B10,Price_Adiantamento) -> 0 | I10: =SUMIF('BASE PRICE @amigodopairico'!$AB$15:$AB$434,"="&$B10,Price_PrevisaoAtualizacaoMonetaria) -> 0 | K10: ='BASE PRICE @amigodopairico'!D194
B11: =B10+1 -> 6 | C11: ANO 16 AO 18 | D11: =SUMIF('BASE PRICE @amigodopairico'!$AB$15:$AB$434,"="&$B11,Price_Parcela) -> 0 | E11: =SUMIF('BASE PRICE @amigodopairico'!$AB$15:$AB$434,"="&$B11,Price_Juros) -> 0 | F11: =SUMIF('BASE PRICE @amigodopairico'!$AB$15:$AB$434,"="&$B11,Price_Amortizacao) -> 0 | G11: =SUMIF('BASE PRICE @amigodopairico'!$AB$15:$AB$434,"="&$B11,Price_QuedaSaldoDevedor) -> 0 | H11: =SUMIF('BASE PRICE @amigodopairico'!$AB$15:$AB$434,"="&$B11,Price_Adiantamento) -> 0 | I11: =SUMIF('BASE PRICE @amigodopairico'!$AB$15:$AB$434,"="&$B11,Price_PrevisaoAtualizacaoMonetaria) -> 0 | K11: ='BASE PRICE @amigodopairico'!D230
B12: =B11+1 -> 7 | C12: ANO 19 AO 21 | D12: =SUMIF('BASE PRICE @amigodopairico'!$AB$15:$AB$434,"="&$B12,Price_Parcela) -> 0 | E12: =SUMIF('BASE PRICE @amigodopairico'!$AB$15:$AB$434,"="&$B12,Price_Juros) -> 0 | F12: =SUMIF('BASE PRICE @amigodopairico'!$AB$15:$AB$434,"="&$B12,Price_Amortizacao) -> 0 | G12: =SUMIF('BASE PRICE @amigodopairico'!$AB$15:$AB$434,"="&$B12,Price_QuedaSaldoDevedor) -> 0 | H12: =SUMIF('BASE PRICE @amigodopairico'!$AB$15:$AB$434,"="&$B12,Price_Adiantamento) -> 0 | I12: =SUMIF('BASE PRICE @amigodopairico'!$AB$15:$AB$434,"="&$B12,Price_PrevisaoAtualizacaoMonetaria) -> 0 | K12: ='BASE PRICE @amigodopairico'!D266
B13: =B12+1 -> 8 | C13: ANO 22 AO 24 | D13: =SUMIF('BASE PRICE @amigodopairico'!$AB$15:$AB$434,"="&$B13,Price_Parcela) -> 0 | E13: =SUMIF('BASE PRICE @amigodopairico'!$AB$15:$AB$434,"="&$B13,Price_Juros) -> 0 | F13: =SUMIF('BASE PRICE @amigodopairico'!$AB$15:$AB$434,"="&$B13,Price_Amortizacao) -> 0 | G13: =SUMIF('BASE PRICE @amigodopairico'!$AB$15:$AB$434,"="&$B13,Price_QuedaSaldoDevedor) -> 0 | H13: =SUMIF('BASE PRICE @amigodopairico'!$AB$15:$AB$434,"="&$B13,Price_Adiantamento) -> 0 | I13: =SUMIF('BASE PRICE @amigodopairico'!$AB$15:$AB$434,"="&$B13,Price_PrevisaoAtualizacaoMonetaria) -> 0 | K13: ='BASE PRICE @amigodopairico'!D302
B14: =B13+1 -> 9 | C14: ANO 25 AO 27 | D14: =SUMIF('BASE PRICE @amigodopairico'!$AB$15:$AB$434,"="&$B14,Price_Parcela) -> 0 | E14: =SUMIF('BASE PRICE @amigodopairico'!$AB$15:$AB$434,"="&$B14,Price_Juros) -> 0 | F14: =SUMIF('BASE PRICE @amigodopairico'!$AB$15:$AB$434,"="&$B14,Price_Amortizacao) -> 0 | G14: =SUMIF('BASE PRICE @amigodopairico'!$AB$15:$AB$434,"="&$B14,Price_QuedaSaldoDevedor) -> 0 | H14: =SUMIF('BASE PRICE @amigodopairico'!$AB$15:$AB$434,"="&$B14,Price_Adiantamento) -> 0 | I14: =SUMIF('BASE PRICE @amigodopairico'!$AB$15:$AB$434,"="&$B14,Price_PrevisaoAtualizacaoMonetaria) -> 0 | K14: ='BASE PRICE @amigodopairico'!D338
B15: =B14+1 -> 10 | C15: ANO 28 AO 30 | D15: =SUMIF('BASE PRICE @amigodopairico'!$AB$15:$AB$434,"="&$B15,Price_Parcela) -> 0 | E15: =SUMIF('BASE PRICE @amigodopairico'!$AB$15:$AB$434,"="&$B15,Price_Juros) -> 0 | F15: =SUMIF('BASE PRICE @amigodopairico'!$AB$15:$AB$434,"="&$B15,Price_Amortizacao) -> 0 | G15: =SUMIF('BASE PRICE @amigodopairico'!$AB$15:$AB$434,"="&$B15,Price_QuedaSaldoDevedor) -> 0 | I15: =SUMIF('BASE PRICE @amigodopairico'!$AB$15:$AB$434,"="&$B15,Price_PrevisaoAtualizacaoMonetaria) -> 0 | K15: ='BASE PRICE @amigodopairico'!D339
C17: TOTAIS | D17: =SUM(D6:D15) -> 168784.09 | E17: =SUM(E6:E15) -> 48371.802 | F17: =SUM(F6:F15) -> 110312.28 | G17: =SUM(G6:G15) -> 99999.943 | H17: =SUM(H6:H15) -> 0
C20: Pagaria em juros:
C21: ='BASE PRICE @amigodopairico'!H10 -> 58471.802
C23: Passa a pagar em juros:
C24: ='BASE PRICE @amigodopairico'!O10 -> 58471.802
C26: Quita em:
C27: ='BASE PRICE @amigodopairico'!O7 -> 100
C29: ='BASE PRICE @amigodopairico'!O8 -> 0
C30: meses a menos
C33: ECONOMIZA
C34: ='BASE PRICE @amigodopairico'!O11 -> 0

Sheet Configurações
A1: Caixa
A2: Itaú
A3: Santander
A4: Bradesco
A5: BB
A6: Outros
