Workbook
Name JUROS: 'BASE SAC @amigodopairico'!$F$13:$F$374
Name SAC: 'BASE SAC @amigodopairico'!#REF!
Name SAC_Adiantamento: 'BASE SAC @amigodopairico'!$N$15:$N$434
Name SAC_Amortizacao: 'BASE SAC @amigodopairico'!$G$15:$G$434
Name SAC_AtualizacaoMonetaria: 'BASE SAC @amigodopairico'!$S$15:$S$434
Name SAC_Juros: 'BASE SAC @amigodopairico'!$F$15:$F$434
Name SAC_Parcela: 'BASE SAC @amigodopairico'!$L$15:$L$434
Name SAC_PrevisaoAtualizacaoMonetaria: 'BASE SAC @amigodopairico'!$S$15:$S$434
Name SAC_QuedaSaldoDevedor: 'BASE SAC @amigodopairico'!$J$15:$J$434
Name SAC_Trienio: 'BASE SAC @amigodopairico'!$A$15:$T$434
Name SALDO_DEVEDOR: 'BASE SAC @amigodopairico'!$M$13:$M$374

Sheet BASE SAC @amigodopairico
AD4: ONDE TE AJUDO MAIS ➡️ amigodopairico.com.br/paq
A5: =SUM(A15:A1187) -> 9725 | B5: =SUM(B15:B1187) -> 29175 | D5: SAC | F5: =SUM(F15:F1187) -> 814601.51 | G5: =SUM(G15:G1187) -> 561741.29 | L5: =SUM(L15:L1187) -> 1415242.8 | N5: =SUM(N15:N1187) -> 0 | S5: =SUM(S15:S1187) -> 165744.68 | AA5: =SUM(AA15:AA1187) -> -1415242.8 | AR5: =SUM(AR15:AR1187) -> 9725 | AS5: =SUM(AS15:AS1187) -> 29175 | AW5: =SUM(AW15:AW1187) -> 814601.51 | AX5: =SUM(AX15:AX1187) -> 561741.29 | AY5: SAC | BC5: =SUM(BC15:BC1187) -> 1415242.8 | BE5: =SUM(BE15:BE1187) -> 0 | BJ5: =SUM(BJ15:BJ1187) -> 165744.68
B6: DADOS | F6: SE NÃO FIZER NADA | M6: COM ESTRATÉGIA | AS6: DADOS | AW6: SE NÃO FIZER NADA | BD6: COM ESTRATÉGIA
C7: Taxa de juros | D7: 0.105 | E7: =((1+D7)^(1/12))-1 -> 0.0083551557 | G7: Meses | H7: 389 | M7: Passa a quitar em | N7: =IF(M434<G15,COUNTIF(L15:L434,">1"),"⚠️ MAIS DE 420") -> 389 | O7: =" "&TEXT(N7/12,"0,0") & " anos" -> 32,4 anos | X7: Nominal | Y7: 0.0766 | AA7: TIR | AD7: VERSÃO SAC ESSENCIAL DO SIMULADOR DE AMORTIZAÇÕES | AT7: Taxa de juros | AU7: =D7 -> 0.105 | AV7: =((1+AU7)^(1/12))-1 -> 0.0083551557 | AX7: Meses | AY7: =H7 -> 389 | BA7: 360 | BD7: Passa a quitar em | BE7: =IF(BD434<AX15,COUNTIF(BC15:BC434,">1"),"⚠️ MAIS DE 420") -> 389 | BF7: =" "&TEXT(BE7/12,"0,0") & " anos" -> 32,4 anos
C8: Valor financiado | D8: 396000 | G8: Correção monetária | H8: =S5 -> 165744.68 | J8: QUANTO É APROVEITADO | M8: Parcelas a menos | N8: =H7-N7 -> 0 | O8: =" "&TEXT(N8/12,"0,0") & " anos a menos" -> 0,0 anos a menos | U8: =IF(N8>0,N5/N8,0) -> 0 | V8: cada parcela | Y8: =Y7/12 -> 0.0063833333 | AA8: =(1+AA9)^12-1 -> 0.13146251 | AD8: DO AMIGO DO PAI RICO | AT8: Valor financiado | AU8: =D8 -> 396000 | AX8: Correção monetária | AY8: =BJ5 -> 165744.68 | BA8: =BG5 -> 0 | BD8: Parcelas a menos | BE8: =AY7-BE7 -> 0 | BF8: =" "&TEXT(BE8/12,"0,0") & " anos a menos" -> 0,0 anos a menos
C9: Correção Monetária | D9: 0.0017 | G9: Total inicial | H9: =BE10 -> 1415242.8 | J9: DO VALOR QUE VOCÊ PAGA | M9: Total pago | N9: =SUM(L15:L434)+SUM(N15:N434) -> 1415242.8 | X9: Efetiva | Y9: =(1+Y8)^12-1 -> 0.079347351 | AA9: =IRR(AA14:AA434) -> 0.010345739 | AT9: Correção Monetária | AU9: =D9 -> 0.0017 | AX9: Juros totais pagos | AY9: =CF9 -> 0 | BA9: =CH9 -> 0 | BD9: Juros pagos | BE9: =SUM(AW15:AW434)+AR5+AS5 -> 853501.51
C10: CET REAL | D10: =AA8 -> 0.13146251 | E10: =(1+D10)^(1/12)-1 -> 0.010345739 | G10: Juros + Seguro total | H10: =BE9 -> 853501.51 | J10: ⬇️ | M10: Juros pagos | N10: =SUM(F15:F434)+A5+B5 -> 853501.51 | AT10: CET REAL | AU10: =D10 -> 0.13146251 | AV10: =(1+AU10)^(1/12)-1 -> 0.010345739 | AX10: Total inicial | AY10: =CF10 -> 0 | BA10: =CH10 -> 0 | BD10: Total pago | BE10: =SUM(BC15:BC434)+SUM(BE15:BE434) -> 1415242.8
C11: Banco | D11: Caixa | M11: ECONOMIA TOTAL | N11: =H9-N9 -> 0 | AT11: Banco | AU11: =D11 -> Caixa | BD11: ECONOMIA TOTAL | BE11: =AY10-BE10 -> -1415242.8
A13: Taxa | B13: Seguro | C13: Momento | D13: % Amort Parcela | F13: Juros | G13: Amortização | J13: VALOR ÚTIL | K13: % VU | L13: Parcela do banco | M13: Saldo Devedor | N13: Amortização Ad | O13: T/V | P13: % $ | R13: Faltam | S13: At. Monetária | T13: AT. MONET. | AA13: FLUXO DE $ | AH13: Década | AI13: Triênio | AJ13: Ano | AK13: Dias | AR13: Taxa | AS13: Seguro | AT13: Momento | AU13: % Amort Parcela | AW13: Juros | AX13: Amortização | BA13: VALOR ÚTIL | BB13: % VU | BC13: Parcela do banco | BD13: Saldo Devedor | BE13: Amortização Ad | BF13: T/V | BG13: % $ | BI13: Faltam | BJ13: At. Monetária | BK13: AT. MONET.
C14: =DATE(YEAR(C15),MONTH(C15)-1,1) -> 46023 | AA14: =D8 -> 396000 | AK14: =DAY(DATE(YEAR(C14),MONTH(C14)+1,1)-1) -> 31 | AT14: =DATE(YEAR(AT15),MONTH(AT15)-1,1) -> 46023
A15: 25 | B15: 75 | C15: 46054 | D15: =IFERROR(G15/D8,0) -> 0.0025706941 | E15: 1 | F15: =IF(OR(D8<1,N14>D8),0,(D8-N14)*IF(D$11<>"BB",$E$7,(1+$D$7)^(AK14/365)-1)) -> 3308.6417 | G15: =IF(R15=0,0,IF(D8<1,0,(D8-N14)/R15)) -> 1017.9949 | H15: =IF(OR(G15=0,L15<1),"",IF(G15/L15>90%,"🛩",IF(G15/L15>70%,"🏎",IF(G15/L15>50%,"🚙",IF(G15/L15>30%,"🛵",IF(G15/L15>15%,"🐢","⚓️")))))) -> 🐢 | I15: =IFERROR(IF((G15+N15-S15)/L15<0,"🔙",IF((G15+N15-S15)/L15<10%,"🥾",IF((G15+N15-S15)/L15<20%,"🛴",IF((G15+N15-S15)/L15<50%,"🚴‍♂️",IF((G15+N15-S15)/L15<75%,"🚖","🚁"))))),"") -> 🥾 | J15: =G15+N15-S15 -> 344.79486 | K15: =IFERROR(J15/(L15+N15),0) -> 0.077890935 | L15: =G15+F15+A15+B15 -> 4426.6365 | M15: =IF(R15=0,0,MAX(0,D8-G15+S15-N14)) -> 395655.21 | O15: =IF(AND(N15<>"",N15<R15),"V","") | Q15: =IF(N15=0,"",IF(N15>M15,"🚫",IF(INT(N15/G15<1),"👍",INT(N15/G15)&"x"))) | R15: =H7 -> 389 | S15: =D8*$T15 -> 673.2 | T15: =D9 -> 0.0017 | AA15: =-(L15+N15) -> -4426.6365 | AH15: =ROUNDUP(E15/120,0) -> 1 | AI15: =ROUNDUP(E15/36,0) -> 1 | AJ15: =ROUNDUP(E15/12,0) -> 1 | AK15: =DAY(DATE(YEAR(C15),MONTH(C15)+1,1)-1) -> 28 | AR15: =A15 -> 25 | AS15: =B15 -> 75 | AT15: =C15 -> 46054 | AU15: =IFERROR(AX15/AU8,0) -> 0.0025706941 | AV15: 1 | AW15: =IF(OR(AU8<1,BE14>AU8),0,(AU8-BE14)*IF(AU$11<>"BB",$E$7,(1+$D$7)^(BY14/365)-1)) -> 3308.6417 | AX15: =IF(BI15=0,0,IF(AU8<1,0,(AU8-BE14)/BI15)) -> 1017.9949 | AY15: =IF(OR(AX15=0,BC15<1),"",IF(AX15/BC15>90%,"🛩",IF(AX15/BC15>70%,"🏎",IF(AX15/BC15>50%,"🚙",IF(AX15/BC15>30%,"🛵",IF(AX15/BC15>15%,"🐢","⚓️")))))) -> 🐢 | AZ15: =IFERROR(IF((AX15+BE15-BJ15)/BC15<0,"🔙",IF((AX15+BE15-BJ15)/BC15<10%,"🥾",IF((AX15+BE15-BJ15)/BC15<20%,"🛴",IF((AX15+BE15-BJ15)/BC15<50%,"🚴‍♂️",IF((AX15+BE15-BJ15)/BC15<75%,"🚖","🚁"))))),"") -> 🥾 | BA15: =AX15+BE15-BJ15 -> 344.79486 | BB15: =IFERROR(BA15/(BC15+BE15),0) -> 0.077890935 | BC15: =AX15+AW15+AR15+AS15 -> 4426.6365 | BD15: =IF(BI15=0,0,MAX(0,AU8-AX15+BJ15-BE14)) -> 395655.21 | BF15: =IF(AND(BE15<>"",BE15<BI15),"V","") | BH15: =IF(BE15=0,"",IF(BE15>BD15,"🚫",IF(INT(BE15/AX15<1),"👍",INT(BE15/AX15)&"x"))) | BI15: =AY7 -> 389 | BJ15: =AU8*$BK15 -> 673.2 | BK15: =AU9 -> 0.0017
A16: =IF(INT(F16)>0,A15,0) -> 25 | B16: =IF(F16>0.1,B15,0) -> 75 | C16: =DATE(YEAR(C15),MONTH(C15)+1,1) -> 46082 | D16: =IFERROR(G16/M15,0) -> 0.0025773196 | E16: =E15+1 -> 2 | F16: =IF(OR(M15<1,N15>M15),0,(M15-N15)*IF(D$11<>"BB",$E$7,(1+$D$7)^(AK15/365)-1)) -> 3305.7608 | G16: =IF(R16=0,0,IF(M15<1,0,IF(AND(((M15-N15)/R16)<G15,O15<>"V"),G15, (M15-N15)/R16))) -> 1019.7299 | H16: =IF(OR(G16=0,L16<1),"",IF(G16/L16>90%,"🛩",IF(G16/L16>70%,"🏎",IF(G16/L16>50%,"🚙",IF(G16/L16>30%,"🛵",IF(G16/L16>15%,"🐢","⚓️")))))) -> 🐢 | I16: =IFERROR(IF((G16+N16-S16)/L16<0,"🔙",IF((G16+N16-S16)/L16<10%,"🥾",IF((G16+N16-S16)/L16<20%,"🛴",IF((G16+N16-S16)/L16<50%,"🚴‍♂️",IF((G16+N16-S16)/L16<75%,"🚖","🚁"))))),"") -> 🥾 | J16: =G16+N16-S16 -> 347.11606 | K16: =IFERROR(J16/(L16+N16),0) -> 0.078435609 | L16: =G16+F16+A16+B16 -> 4425.4907 | M16: =IF(R16=0,0,MAX(0,M15-G16+S16-N15)) -> 395308.09 | O16: =IF(AND(N16<>"",N16<R16),"V","") | P16: =IF(N15=0,"",(L15-L16)/N15) | Q16: =IF(N16=0,"",IF(N16>M16,"🚫",IF(INT(N16/G16<1),"👍",INT(N16/G16)&"x"))) | R16: =IF(M15=0,0,IF(OR(N15=0,O15="V"),R15-1,IF(OR(D$11="BRADESCO",D$11="BB"),R15-ROUNDDOWN(N15/(M15/R15),0)-1,ROUNDUP((M15-N15+S15-(M15/R15))/(L15-F16-A16-B16),0)+1))) -> 388 | S16: =M15*$T16 -> 672.61385 | T16: =IF(M15>0,T15,0) -> 0.0017 | AA16: =-(L16+N16) -> -4425.4907 | AH16: =ROUNDUP(E16/120,0) -> 1 | AI16: =ROUNDUP(E16/36,0) -> 1 | AJ16: =ROUNDUP(E16/12,0) -> 1 | AK16: =DAY(DATE(YEAR(C16),MONTH(C16)+1,1)-1) -> 31 | AR16: =IF(INT(AW16)>0,AR15,0) -> 25 | AS16: =IF(AW16>0.1,AS15,0) -> 75 | AT16: =DATE(YEAR(AT15),MONTH(AT15)+1,1) -> 46082 | AU16: =IFERROR(AX16/BD15,0) -> 0.0025773196 | AV16: =AV15+1 -> 2 | AW16: =IF(OR(BD15<1,BE15>BD15),0,(BD15-BE15)*IF(AU$11<>"BB",$E$7,(1+$D$7)^(BY15/365)-1)) -> 3305.7608 | AX16: =IF(BI16=0,0,IF(BD15<1,0,IF(AND(((BD15-BE15)/BI16)<AX15,BF15<>"V"),AX15, (BD15-BE15)/BI16))) -> 1019.7299 | AY16: =IF(OR(AX16=0,BC16<1),"",IF(AX16/BC16>90%,"🛩",IF(AX16/BC16>70%,"🏎",IF(AX16/BC16>50%,"🚙",IF(AX16/BC16>30%,"🛵",IF(AX16/BC16>15%,"🐢","⚓️")))))) -> 🐢 | AZ16: =IFERROR(IF((AX16+BE16-BJ16)/BC16<0,"🔙",IF((AX16+BE16-BJ16)/BC16<10%,"🥾",IF((AX16+BE16-BJ16)/BC16<20%,"🛴",IF((AX16+BE16-BJ16)/BC16<50%,"🚴‍♂️",IF((AX16+BE16-BJ16)/BC16<75%,"🚖","🚁"))))),"") -> 🥾 | BA16: =AX16+BE16-BJ16 -> 347.11606 | BB16: =IFERROR(BA16/(BC16+BE16),0) -> 0.078435609 | BC16: =AX16+AW16+AR16+AS16 -> 4425.4907 | BD16: =IF(BI16=0,0,MAX(0,BD15-AX16+BJ16-BE15)) -> 395308.09 | BF16: =IF(AND(BE16<>"",BE16<BI16),"V","") | BG16: =IF(BE15=0,"",(BC15-BC16)/BE15) | BH16: =IF(BE16=0,"",IF(BE16>BD16,"🚫",IF(INT(BE16/AX16<1),"👍",INT(BE16/AX16)&"x"))) | BI16: =IF(BD15=0,0,IF(OR(BE15=0,BF15="V"),BI15-1,IF(OR(AU$11="BRADESCO",AU$11="BB"),BI15-ROUNDDOWN(BE15/(BD15/BI15),0)-1,ROUNDUP((BD15-BE15+BJ15-(BD15/BI15))/(BC15-AW16-AR16-AS16),0)+1))) -> 388 | BJ16: =BD15*$BK15 -> 672.61385 | BK16: =IF(BD15>0,BK15,0) -> 0.0017
A17: =IF(INT(F17)>0,A16,0) -> 25 | B17: =IF(F17>0.1,B16,0) -> 75 | C17: =DATE(YEAR(C16),MONTH(C16)+1,1) -> 46113 | D17: =IFERROR(G17/M16,0) -> 0.0025839793 | E17: =E16+1 -> 3 | F17: =IF(OR(M16<1,N16>M16),0,(M16-N16)*IF(D$11<>"BB",$E$7,(1+$D$7)^(AK16/365)-1)) -> 3302.8606 | G17: =IF(R17=0,0,IF(M16<1,0,IF(AND(AND(((M16-N16)/R17)<G16,O16<>"V"),D$11<>"BRADESCO"),G16, (M16-N16)/R17))) -> 1021.4679 | H17: =IF(OR(G17=0,L17<1),"",IF(G17/L17>90%,"🛩",IF(G17/L17>70%,"🏎",IF(G17/L17>50%,"🚙",IF(G17/L17>30%,"🛵",IF(G17/L17>15%,"🐢","⚓️")))))) -> 🐢 | I17: =IFERROR(IF((G17+N17-S17)/L17<0,"🔙",IF((G17+N17-S17)/L17<10%,"🥾",IF((G17+N17-S17)/L17<20%,"🛴",IF((G17+N17-S17)/L17<50%,"🚴‍♂️",IF((G17+N17-S17)/L17<75%,"🚖","🚁"))))),"") -> 🥾 | J17: =G17+N17-S17 -> 349.44418 | K17: =IFERROR(J17/(L17+N17),0) -> 0.078982421 | L17: =G17+F17+A17+B17 -> 4424.3286 | M17: =IF(R17=0,0,MAX(0,M16-G17+S17-N16)) -> 394958.64 | O17: =IF(AND(N17<>"",N17<R17),"V","") | P17: =IF(N16=0,"",(L16-L17)/N16) | Q17: =IF(N17=0,"",IF(N17>M17,"🚫",IF(INT(N17/G17<1),"👍",INT(N17/G17)&"x"))) | R17: =IF(M16=0,0,IF(OR(N16=0,O16="V"),R16-1,IF(OR(D$11="BRADESCO",D$11="BB"),R16-ROUNDDOWN(N16/(M16/R16),0)-1,ROUNDUP((M16-N16+S16-(M16/R16))/(L16-F17-A17-B17),0)+1))) -> 387 | S17: =M16*$T17 -> 672.02375 | T17: =IF(M16>0,T16,0) -> 0.0017 | AA17: =-(L17+N17) -> -4424.3286 | AH17: =ROUNDUP(E17/120,0) -> 1 | AI17: =ROUNDUP(E17/36,0) -> 1 | AJ17: =ROUNDUP(E17/12,0) -> 1 | AK17: =DAY(DATE(YEAR(C17),MONTH(C17)+1,1)-1) -> 30 | AR17: =IF(INT(AW17)>0,AR16,0) -> 25 | AS17: =IF(AW17>0.1,AS16,0) -> 75 | AT17: =DATE(YEAR(AT16),MONTH(AT16)+1,1) -> 46113 | AU17: =IFERROR(AX17/BD16,0) -> 0.0025839793 | AV17: =AV16+1 -> 3 | AW17: =IF(OR(BD16<1,BE16>BD16),0,(BD16-BE16)*IF(AU$11<>"BB",$E$7,(1+$D$7)^(BY16/365)-1)) -> 3302.8606 | AX17: =IF(BI17=0,0,IF(BD16<1,0,IF(AND(AND(((BD16-BE16)/BI17)<AX16,BF16<>"V"),AU$11<>"BRADESCO"),AX16, (BD16-BE16)/BI17))) -> 1021.4679 | AY17: =IF(OR(AX17=0,BC17<1),"",IF(AX17/BC17>90%,"🛩",IF(AX17/BC17>70%,"🏎",IF(AX17/BC17>50%,"🚙",IF(AX17/BC17>30%,"🛵",IF(AX17/BC17>15%,"🐢","⚓️")))))) -> 🐢 | AZ17: =IFERROR(IF((AX17+BE17-BJ17)/BC17<0,"🔙",IF((AX17+BE17-BJ17)/BC17<10%,"🥾",IF((AX17+BE17-BJ17)/BC17<20%,"🛴",IF((AX17+BE17-BJ17)/BC17<50%,"🚴‍♂️",IF((AX17+BE17-BJ17)/BC17<75%,"🚖","🚁"))))),"") -> 🥾 | BA17: =AX17+BE17-BJ17 -> 349.44418 | BB17: =IFERROR(BA17/(BC17+BE17),0) -> 0.078982421 | BC17: =AX17+AW17+AR17+AS17 -> 4424.3286 | BD17: =IF(BI17=0,0,MAX(0,BD16-AX17+BJ17-BE16)) -> 394958.64 | BF17: =IF(AND(BE17<>"",BE17<BI17),"V","") | BG17: =IF(BE16=0,"",(BC16-BC17)/BE16) | BH17: =IF(BE17=0,"",IF(BE17>BD17,"🚫",IF(INT(BE17/AX17<1),"👍",INT(BE17/AX17)&"x"))) | BI17: =IF(BD16=0,0,IF(OR(BE16=0,BF16="V"),BI16-1,IF(OR(AU$11="BRADESCO",AU$11="BB"),BI16-ROUNDDOWN(BE16/(BD16/BI16),0)-1,ROUNDUP((BD16-BE16+BJ16-(BD16/BI16))/(BC16-AW17-AR17-AS17),0)+1))) -> 387 | BJ17: =BD16*$BK16 -> 672.02375 | BK17: =IF(BD16>0,BK16,0) -> 0.0017
A18: =IF(INT(F18)>0,A17,0) -> 25 | B18: =IF(F18>0.1,B17,0) -> 75 | C18: =DATE(YEAR(C17),MONTH(C17)+1,1) -> 46143 | D18: =IFERROR(G18/M17,0) -> 0.0025906736 | E18: =E17+1 -> 4 | F18: =IF(OR(M17<1,N17>M17),0,(M17-N17)*IF(D$11<>"BB",$E$7,(1+$D$7)^(AK17/365)-1)) -> 3299.941 | G18: =IF(R18=0,0,IF(M17<1,0,IF(AND(AND(((M17-N17)/R18)<G17,O17<>"V"),D$11<>"BRADESCO"),G17, (M17-N17)/R18))) -> 1023.2089 | H18: =IF(OR(G18=0,L18<1),"",IF(G18/L18>90%,"🛩",IF(G18/L18>70%,"🏎",IF(G18/L18>50%,"🚙",IF(G18/L18>30%,"🛵",IF(G18/L18>15%,"🐢","⚓️")))))) -> 🐢 | I18: =IFERROR(IF((G18+N18-S18)/L18<0,"🔙",IF((G18+N18-S18)/L18<10%,"🥾",IF((G18+N18-S18)/L18<20%,"🛴",IF((G18+N18-S18)/L18<50%,"🚴‍♂️",IF((G18+N18-S18)/L18<75%,"🚖","🚁"))))),"") -> 🥾 | J18: =G18+N18-S18 -> 351.77923 | K18: =IFERROR(J18/(L18+N18),0) -> 0.079531383 | L18: =G18+F18+A18+B18 -> 4423.1499 | M18: =IF(R18=0,0,MAX(0,M17-G18+S18-N17)) -> 394606.87 | O18: =IF(AND(N18<>"",N18<R18),"V","") | P18: =IF(N17=0,"",(L17-L18)/N17) | Q18: =IF(N18=0,"",IF(N18>M18,"🚫",IF(INT(N18/G18<1),"👍",INT(N18/G18)&"x"))) | R18: =IF(M17=0,0,IF(OR(N17=0,O17="V"),R17-1,IF(OR(D$11="BRADESCO",D$11="BB"),R17-ROUNDDOWN(N17/(M17/R17),0)-1,ROUNDUP((M17-N17+S17-(M17/R17))/(L17-F18-A18-B18),0)+1))) -> 386 | S18: =M17*$T18 -> 671.4297 | T18: =IF(M17>0,T17,0) -> 0.0017 | AA18: =-(L18+N18) -> -4423.1499 | AH18: =ROUNDUP(E18/120,0) -> 1 | AI18: =ROUNDUP(E18/36,0) -> 1 | AJ18: =ROUNDUP(E18/12,0) -> 1 | AK18: =DAY(DATE(YEAR(C18),MONTH(C18)+1,1)-1) -> 31 | AR18: =IF(INT(AW18)>0,AR17,0) -> 25 | AS18: =IF(AW18>0.1,AS17,0) -> 75 | AT18: =DATE(YEAR(AT17),MONTH(AT17)+1,1) -> 46143 | AU18: =IFERROR(AX18/BD17,0) -> 0.0025906736 | AV18: =AV17+1 -> 4 | AW18: =IF(OR(BD17<1,BE17>BD17),0,(BD17-BE17)*IF(AU$11<>"BB",$E$7,(1+$D$7)^(BY17/365)-1)) -> 3299.941 | AX18: =IF(BI18=0,0,IF(BD17<1,0,IF(AND(AND(((BD17-BE17)/BI18)<AX17,BF17<>"V"),AU$11<>"BRADESCO"),AX17, (BD17-BE17)/BI18))) -> 1023.2089 | AY18: =IF(OR(AX18=0,BC18<1),"",IF(AX18/BC18>90%,"🛩",IF(AX18/BC18>70%,"🏎",IF(AX18/BC18>50%,"🚙",IF(AX18/BC18>30%,"🛵",IF(AX18/BC18>15%,"🐢","⚓️")))))) -> 🐢 | AZ18: =IFERROR(IF((AX18+BE18-BJ18)/BC18<0,"🔙",IF((AX18+BE18-BJ18)/BC18<10%,"🥾",IF((AX18+BE18-BJ18)/BC18<20%,"🛴",IF((AX18+BE18-BJ18)/BC18<50%,"🚴‍♂️",IF((AX18+BE18-BJ18)/BC18<75%,"🚖","🚁"))))),"") -> 🥾 | BA18: =AX18+BE18-BJ18 -> 351.77923 | BB18: =IFERROR(BA18/(BC18+BE18),0) -> 0.079531383 | BC18: =AX18+AW18+AR18+AS18 -> 4423.1499 | BD18: =IF(BI18=0,0,MAX(0,BD17-AX18+BJ18-BE17)) -> 394606.87 | BF18: =IF(AND(BE18<>"",BE18<BI18),"V","") | BG18: =IF(BE17=0,"",(BC17-BC18)/BE17) | BH18: =IF(BE18=0,"",IF(BE18>BD18,"🚫",IF(INT(BE18/AX18<1),"👍",INT(BE18/AX18)&"x"))) | BI18: =IF(BD17=0,0,IF(OR(BE17=0,BF17="V"),BI17-1,IF(OR(AU$11="BRADESCO",AU$11="BB"),BI17-ROUNDDOWN(BE17/(BD17/BI17),0)-1,ROUNDUP((BD17-BE17+BJ17-(BD17/BI17))/(BC17-AW18-AR18-AS18),0)+1))) -> 386 | BJ18: =BD17*$BK17 -> 671.4297 | BK18: =IF(BD17>0,BK17,0) -> 0.0017
A19: =IF(INT(F19)>0,A18,0) -> 25 | B19: =IF(F19>0.1,B18,0) -> 75 | C19: =DATE(YEAR(C18),MONTH(C18)+1,1) -> 46174 | D19: =IFERROR(G19/M18,0) -> 0.0025974026 | E19: =E18+1 -> 5 | F19: =IF(OR(M18<1,N18>M18),0,(M18-N18)*IF(D$11<>"BB",$E$7,(1+$D$7)^(AK18/365)-1)) -> 3297.0018 | G19: =IF(R19=0,0,IF(M18<1,0,IF(AND(AND(((M18-N18)/R19)<G18,O18<>"V"),D$11<>"BRADESCO"),G18, (M18-N18)/R19))) -> 1024.9529 | H19: =IF(OR(G19=0,L19<1),"",IF(G19/L19>90%,"🛩",IF(G19/L19>70%,"🏎",IF(G19/L19>50%,"🚙",IF(G19/L19>30%,"🛵",IF(G19/L19>15%,"🐢","⚓️")))))) -> 🐢 | I19: =IFERROR(IF((G19+N19-S19)/L19<0,"🔙",IF((G19+N19-S19)/L19<10%,"🥾",IF((G19+N19-S19)/L19<20%,"🛴",IF((G19+N19-S19)/L19<50%,"🚴‍♂️",IF((G19+N19-S19)/L19<75%,"🚖","🚁"))))),"") -> 🥾 | J19: =G19+N19-S19 -> 354.12123 | K19: =IFERROR(J19/(L19+N19),0) -> 0.080082509 | L19: =G19+F19+A19+B19 -> 4421.9547 | M19: =IF(R19=0,0,MAX(0,M18-G19+S19-N18)) -> 394252.74 | O19: =IF(AND(N19<>"",N19<R19),"V","") | P19: =IF(N18=0,"",(L18-L19)/N18) | Q19: =IF(N19=0,"",IF(N19>M19,"🚫",IF(INT(N19/G19<1),"👍",INT(N19/G19)&"x"))) | R19: =IF(M18=0,0,IF(OR(N18=0,O18="V"),R18-1,IF(OR(D$11="BRADESCO",D$11="BB"),R18-ROUNDDOWN(N18/(M18/R18),0)-1,ROUNDUP((M18-N18+S18-(M18/R18))/(L18-F19-A19-B19),0)+1))) -> 385 | S19: =M18*$T19 -> 670.83167 | T19: =IF(M18>0,T18,0) -> 0.0017 | AA19: =-(L19+N19) -> -4421.9547 | AH19: =ROUNDUP(E19/120,0) -> 1 | AI19: =ROUNDUP(E19/36,0) -> 1 | AJ19: =ROUNDUP(E19/12,0) -> 1 | AK19: =DAY(DATE(YEAR(C19),MONTH(C19)+1,1)-1) -> 30 | AR19: =IF(INT(AW19)>0,AR18,0) -> 25 | AS19: =IF(AW19>0.1,AS18,0) -> 75 | AT19: =DATE(YEAR(AT18),MONTH(AT18)+1,1) -> 46174 | AU19: =IFERROR(AX19/BD18,0) -> 0.0025974026 | AV19: =AV18+1 -> 5 | AW19: =IF(OR(BD18<1,BE18>BD18),0,(BD18-BE18)*IF(AU$11<>"BB",$E$7,(1+$D$7)^(BY18/365)-1)) -> 3297.0018 | AX19: =IF(BI19=0,0,IF(BD18<1,0,IF(AND(AND(((BD18-BE18)/BI19)<AX18,BF18<>"V"),AU$11<>"BRADESCO"),AX18, (BD18-BE18)/BI19))) -> 1024.9529 | AY19: =IF(OR(AX19=0,BC19<1),"",IF(AX19/BC19>90%,"🛩",IF(AX19/BC19>70%,"🏎",IF(AX19/BC19>50%,"🚙",IF(AX19/BC19>30%,"🛵",IF(AX19/BC19>15%,"🐢","⚓️")))))) -> 🐢 | AZ19: =IFERROR(IF((AX19+BE19-BJ19)/BC19<0,"🔙",IF((AX19+BE19-BJ19)/BC19<10%,"🥾",IF((AX19+BE19-BJ19)/BC19<20%,"🛴",IF((AX19+BE19-BJ19)/BC19<50%,"🚴‍♂️",IF((AX19+BE19-BJ19)/BC19<75%,"🚖","🚁"))))),"") -> 🥾 | BA19: =AX19+BE19-BJ19 -> 354.12123 | BB19: =IFERROR(BA19/(BC19+BE19),0) -> 0.080082509 | BC19: =AX19+AW19+AR19+AS19 -> 4421.9547 | BD19: =IF(BI19=0,0,MAX(0,BD18-AX19+BJ19-BE18)) -> 394252.74 | BF19: =IF(AND(BE19<>"",BE19<BI19),"V","") | BG19: =IF(BE18=0,"",(BC18-BC19)/BE18) | BH19: =IF(BE19=0,"",IF(BE19>BD19,"🚫",IF(INT(BE19/AX19<1),"👍",INT(BE19/AX19)&"x"))) | BI19: =IF(BD18=0,0,IF(OR(BE18=0,BF18="V"),BI18-1,IF(OR(AU$11="BRADESCO",AU$11="BB"),BI18-ROUNDDOWN(BE18/(BD18/BI18),0)-1,ROUNDUP((BD18-BE18+BJ18-(BD18/BI18))/(BC18-AW19-AR19-AS19),0)+1))) -> 385 | BJ19: =BD18*$BK18 -> 670.83167 | BK19: =IF(BD18>0,BK18,0) -> 0.0017
A20: =IF(INT(F20)>0,A19,0) -> 25 | B20: =IF(F20>0.1,B19,0) -> 75 | C20: =DATE(YEAR(C19),MONTH(C19)+1,1) -> 46204 | D20: =IFERROR(G20/M19,0) -> 0.0026041667 | E20: =E19+1 -> 6 | F20: =IF(OR(M19<1,N19>M19),0,(M19-N19)*IF(D$11<>"BB",$E$7,(1+$D$7)^(AK19/365)-1)) -> 3294.0431 | G20: =IF(R20=0,0,IF(M19<1,0,IF(AND(AND(((M19-N19)/R20)<G19,O19<>"V"),D$11<>"BRADESCO"),G19, (M19-N19)/R20))) -> 1026.6999 | H20: =IF(OR(G20=0,L20<1),"",IF(G20/L20>90%,"🛩",IF(G20/L20>70%,"🏎",IF(G20/L20>50%,"🚙",IF(G20/L20>30%,"🛵",IF(G20/L20>15%,"🐢","⚓️")))))) -> 🐢 | I20: =IFERROR(IF((G20+N20-S20)/L20<0,"🔙",IF((G20+N20-S20)/L20<10%,"🥾",IF((G20+N20-S20)/L20<20%,"🛴",IF((G20+N20-S20)/L20<50%,"🚴‍♂️",IF((G20+N20-S20)/L20<75%,"🚖","🚁"))))),"") -> 🥾 | J20: =G20+N20-S20 -> 356.47019 | K20: =IFERROR(J20/(L20+N20),0) -> 0.080635811 | L20: =G20+F20+A20+B20 -> 4420.7429 | M20: =IF(R20=0,0,MAX(0,M19-G20+S20-N19)) -> 393896.27 | O20: =IF(AND(N20<>"",N20<R20),"V","") | P20: =IF(N19=0,"",(L19-L20)/N19) | Q20: =IF(N20=0,"",IF(N20>M20,"🚫",IF(INT(N20/G20<1),"👍",INT(N20/G20)&"x"))) | R20: =IF(M19=0,0,IF(OR(N19=0,O19="V"),R19-1,IF(OR(D$11="BRADESCO",D$11="BB"),R19-ROUNDDOWN(N19/(M19/R19),0)-1,ROUNDUP((M19-N19+S19-(M19/R19))/(L19-F20-A20-B20),0)+1))) -> 384 | S20: =M19*$T20 -> 670.22967 | T20: =IF(M19>0,T19,0) -> 0.0017 | AA20: =-(L20+N20) -> -4420.7429 | AH20: =ROUNDUP(E20/120,0) -> 1 | AI20: =ROUNDUP(E20/36,0) -> 1 | AJ20: =ROUNDUP(E20/12,0) -> 1 | AK20: =DAY(DATE(YEAR(C20),MONTH(C20)+1,1)-1) -> 31 | AR20: =IF(INT(AW20)>0,AR19,0) -> 25 | AS20: =IF(AW20>0.1,AS19,0) -> 75 | AT20: =DATE(YEAR(AT19),MONTH(AT19)+1,1) -> 46204 | AU20: =IFERROR(AX20/BD19,0) -> 0.0026041667 | AV20: =AV19+1 -> 6 | AW20: =IF(OR(BD19<1,BE19>BD19),0,(BD19-BE19)*IF(AU$11<>"BB",$E$7,(1+$D$7)^(BY19/365)-1)) -> 3294.0431 | AX20: =IF(BI20=0,0,IF(BD19<1,0,IF(AND(AND(((BD19-BE19)/BI20)<AX19,BF19<>"V"),AU$11<>"BRADESCO"),AX19, (BD19-BE19)/BI20))) -> 1026.6999 | AY20: =IF(OR(AX20=0,BC20<1),"",IF(AX20/BC20>90%,"🛩",IF(AX20/BC20>70%,"🏎",IF(AX20/BC20>50%,"🚙",IF(AX20/BC20>30%,"🛵",IF(AX20/BC20>15%,"🐢","⚓️")))))) -> 🐢 | AZ20: =IFERROR(IF((AX20+BE20-BJ20)/BC20<0,"🔙",IF((AX20+BE20-BJ20)/BC20<10%,"🥾",IF((AX20+BE20-BJ20)/BC20<20%,"🛴",IF((AX20+BE20-BJ20)/BC20<50%,"🚴‍♂️",IF((AX20+BE20-BJ20)/BC20<75%,"🚖","🚁"))))),"") -> 🥾 | BA20: =AX20+BE20-BJ20 -> 356.47019 | BB20: =IFERROR(BA20/(BC20+BE20),0) -> 0.080635811 | BC20: =AX20+AW20+AR20+AS20 -> 4420.7429 | BD20: =IF(BI20=0,0,MAX(0,BD19-AX20+BJ20-BE19)) -> 393896.27 | BF20: =IF(AND(BE20<>"",BE20<BI20),"V","") | BG20: =IF(BE19=0,"",(BC19-BC20)/BE19) | BH20: =IF(BE20=0,"",IF(BE20>BD20,"🚫",IF(INT(BE20/AX20<1),"👍",INT(BE20/AX20)&"x"))) | BI20: =IF(BD19=0,0,IF(OR(BE19=0,BF19="V"),BI19-1,IF(OR(AU$11="BRADESCO",AU$11="BB"),BI19-ROUNDDOWN(BE19/(BD19/BI19),0)-1,ROUNDUP((BD19-BE19+BJ19-(BD19/BI19))/(BC19-AW20-AR20-AS20),0)+1))) -> 384 | BJ20: =BD19*$BK19 -> 670.22967 | BK20: =IF(BD19>0,BK19,0) -> 0.0017
A21: =IF(INT(F21)>0,A20,0) -> 25 | B21: =IF(F21>0.1,B20,0) -> 75 | C21: =DATE(YEAR(C20),MONTH(C20)+1,1) -> 46235 | D21: =IFERROR(G21/M20,0) -> 0.0026109661 | E21: =E20+1 -> 7 | F21: =IF(OR(M20<1,N20>M20),0,(M20-N20)*IF(D$11<>"BB",$E$7,(1+$D$7)^(AK20/365)-1)) -> 3291.0647 | G21: =IF(R21=0,0,IF(M20<1,0,IF(AND(AND(((M20-N20)/R21)<G20,O20<>"V"),D$11<>"BRADESCO"),G20, (M20-N20)/R21))) -> 1028.4498 | H21: =IF(OR(G21=0,L21<1),"",IF(G21/L21>90%,"🛩",IF(G21/L21>70%,"🏎",IF(G21/L21>50%,"🚙",IF(G21/L21>30%,"🛵",IF(G21/L21>15%,"🐢","⚓️")))))) -> 🐢 | I21: =IFERROR(IF((G21+N21-S21)/L21<0,"🔙",IF((G21+N21-S21)/L21<10%,"🥾",IF((G21+N21-S21)/L21<20%,"🛴",IF((G21+N21-S21)/L21<50%,"🚴‍♂️",IF((G21+N21-S21)/L21<75%,"🚖","🚁"))))),"") -> 🥾 | J21: =G21+N21-S21 -> 358.82614 | K21: =IFERROR(J21/(L21+N21),0) -> 0.081191302 | L21: =G21+F21+A21+B21 -> 4419.5145 | M21: =IF(R21=0,0,MAX(0,M20-G21+S21-N20)) -> 393537.45 | O21: =IF(AND(N21<>"",N21<R21),"V","") | P21: =IF(N20=0,"",(L20-L21)/N20) | Q21: =IF(N21=0,"",IF(N21>M21,"🚫",IF(INT(N21/G21<1),"👍",INT(N21/G21)&"x"))) | R21: =IF(M20=0,0,IF(OR(N20=0,O20="V"),R20-1,IF(OR(D$11="BRADESCO",D$11="BB"),R20-ROUNDDOWN(N20/(M20/R20),0)-1,ROUNDUP((M20-N20+S20-(M20/R20))/(L20-F21-A21-B21),0)+1))) -> 383 | S21: =M20*$T21 -> 669.62367 | T21: =IF(M20>0,T20,0) -> 0.0017 | AA21: =-(L21+N21) -> -4419.5145 | AH21: =ROUNDUP(E21/120,0) -> 1 | AI21: =ROUNDUP(E21/36,0) -> 1 | AJ21: =ROUNDUP(E21/12,0) -> 1 | AK21: =DAY(DATE(YEAR(C21),MONTH(C21)+1,1)-1) -> 31 | AR21: =IF(INT(AW21)>0,AR20,0) -> 25 | AS21: =IF(AW21>0.1,AS20,0) -> 75 | AT21: =DATE(YEAR(AT20),MONTH(AT20)+1,1) -> 46235 | AU21: =IFERROR(AX21/BD20,0) -> 0.0026109661 | AV21: =AV20+1 -> 7 | AW21: =IF(OR(BD20<1,BE20>BD20),0,(BD20-BE20)*IF(AU$11<>"BB",$E$7,(1+$D$7)^(BY20/365)-1)) -> 3291.0647 | AX21: =IF(BI21=0,0,IF(BD20<1,0,IF(AND(AND(((BD20-BE20)/BI21)<AX20,BF20<>"V"),AU$11<>"BRADESCO"),AX20, (BD20-BE20)/BI21))) -> 1028.4498 | AY21: =IF(OR(AX21=0,BC21<1),"",IF(AX21/BC21>90%,"🛩",IF(AX21/BC21>70%,"🏎",IF(AX21/BC21>50%,"🚙",IF(AX21/BC21>30%,"🛵",IF(AX21/BC21>15%,"🐢","⚓️")))))) -> 🐢 | AZ21: =IFERROR(IF((AX21+BE21-BJ21)/BC21<0,"🔙",IF((AX21+BE21-BJ21)/BC21<10%,"🥾",IF((AX21+BE21-BJ21)/BC21<20%,"🛴",IF((AX21+BE21-BJ21)/BC21<50%,"🚴‍♂️",IF((AX21+BE21-BJ21)/BC21<75%,"🚖","🚁"))))),"") -> 🥾 | BA21: =AX21+BE21-BJ21 -> 358.82614 | BB21: =IFERROR(BA21/(BC21+BE21),0) -> 0.081191302 | BC21: =AX21+AW21+AR21+AS21 -> 4419.5145 | BD21: =IF(BI21=0,0,MAX(0,BD20-AX21+BJ21-BE20)) -> 393537.45 | BF21: =IF(AND(BE21<>"",BE21<BI21),"V","") | BG21: =IF(BE20=0,"",(BC20-BC21)/BE20) | BH21: =IF(BE21=0,"",IF(BE21>BD21,"🚫",IF(INT(BE21/AX21<1),"👍",INT(BE21/AX21)&"x"))) | BI21: =IF(BD20=0,0,IF(OR(BE20=0,BF20="V"),BI20-1,IF(OR(AU$11="BRADESCO",AU$11="BB"),BI20-ROUNDDOWN(BE20/(BD20/BI20),0)-1,ROUNDUP((BD20-BE20+BJ20-(BD20/BI20))/(BC20-AW21-AR21-AS21),0)+1))) -> 383 | BJ21: =BD20*$BK20 -> 669.62367 | BK21: =IF(BD20>0,BK20,0) -> 0.0017
A22: =IF(INT(F22)>0,A21,0) -> 25 | B22: =IF(F22>0.1,B21,0) -> 75 | C22: =DATE(YEAR(C21),MONTH(C21)+1,1) -> 46266 | D22: =IFERROR(G22/M21,0) -> 0.002617801 | E22: =E21+1 -> 8 | F22: =IF(OR(M21<1,N21>M21),0,(M21-N21)*IF(D$11<>"BB",$E$7,(1+$D$7)^(AK21/365)-1)) -> 3288.0666 | G22: =IF(R22=0,0,IF(M21<1,0,IF(AND(AND(((M21-N21)/R22)<G21,O21<>"V"),D$11<>"BRADESCO"),G21, (M21-N21)/R22))) -> 1030.2027 | H22: =IF(OR(G22=0,L22<1),"",IF(G22/L22>90%,"🛩",IF(G22/L22>70%,"🏎",IF(G22/L22>50%,"🚙",IF(G22/L22>30%,"🛵",IF(G22/L22>15%,"🐢","⚓️")))))) -> 🐢 | I22: =IFERROR(IF((G22+N22-S22)/L22<0,"🔙",IF((G22+N22-S22)/L22<10%,"🥾",IF((G22+N22-S22)/L22<20%,"🛴",IF((G22+N22-S22)/L22<50%,"🚴‍♂️",IF((G22+N22-S22)/L22<75%,"🚖","🚁"))))),"") -> 🥾 | J22: =G22+N22-S22 -> 361.18908 | K22: =IFERROR(J22/(L22+N22),0) -> 0.081748995 | L22: =G22+F22+A22+B22 -> 4418.2694 | M22: =IF(R22=0,0,MAX(0,M21-G22+S22-N21)) -> 393176.26 | O22: =IF(AND(N22<>"",N22<R22),"V","") | P22: =IF(N21=0,"",(L21-L22)/N21) | Q22: =IF(N22=0,"",IF(N22>M22,"🚫",IF(INT(N22/G22<1),"👍",INT(N22/G22)&"x"))) | R22: =IF(M21=0,0,IF(OR(N21=0,O21="V"),R21-1,IF(OR(D$11="BRADESCO",D$11="BB"),R21-ROUNDDOWN(N21/(M21/R21),0)-1,ROUNDUP((M21-N21+S21-(M21/R21))/(L21-F22-A22-B22),0)+1))) -> 382 | S22: =M21*$T22 -> 669.01366 | T22: =IF(M21>0,T21,0) -> 0.0017 | AA22: =-(L22+N22) -> -4418.2694 | AH22: =ROUNDUP(E22/120,0) -> 1 | AI22: =ROUNDUP(E22/36,0) -> 1 | AJ22: =ROUNDUP(E22/12,0) -> 1 | AK22: =DAY(DATE(YEAR(C22),MONTH(C22)+1,1)-1) -> 30 | AR22: =IF(INT(AW22)>0,AR21,0) -> 25 | AS22: =IF(AW22>0.1,AS21,0) -> 75 | AT22: =DATE(YEAR(AT21),MONTH(AT21)+1,1) -> 46266 | AU22: =IFERROR(AX22/BD21,0) -> 0.002617801 | AV22: =AV21+1 -> 8 | AW22: =IF(OR(BD21<1,BE21>BD21),0,(BD21-BE21)*IF(AU$11<>"BB",$E$7,(1+$D$7)^(BY21/365)-1)) -> 3288.0666 | AX22: =IF(BI22=0,0,IF(BD21<1,0,IF(AND(AND(((BD21-BE21)/BI22)<AX21,BF21<>"V"),AU$11<>"BRADESCO"),AX21, (BD21-BE21)/BI22))) -> 1030.2027 | AY22: =IF(OR(AX22=0,BC22<1),"",IF(AX22/BC22>90%,"🛩",IF(AX22/BC22>70%,"🏎",IF(AX22/BC22>50%,"🚙",IF(AX22/BC22>30%,"🛵",IF(AX22/BC22>15%,"🐢","⚓️")))))) -> 🐢 | AZ22: =IFERROR(IF((AX22+BE22-BJ22)/BC22<0,"🔙",IF((AX22+BE22-BJ22)/BC22<10%,"🥾",IF((AX22+BE22-BJ22)/BC22<20%,"🛴",IF((AX22+BE22-BJ22)/BC22<50%,"🚴‍♂️",IF((AX22+BE22-BJ22)/BC22<75%,"🚖","🚁"))))),"") -> 🥾 | BA22: =AX22+BE22-BJ22 -> 361.18908 | BB22: =IFERROR(BA22/(BC22+BE22),0) -> 0.081748995 | BC22: =AX22+AW22+AR22+AS22 -> 4418.2694 | BD22: =IF(BI22=0,0,MAX(0,BD21-AX22+BJ22-BE21)) -> 393176.26 | BF22: =IF(AND(BE22<>"",BE22<BI22),"V","") | BG22: =IF(BE21=0,"",(BC21-BC22)/BE21) | BH22: =IF(BE22=0,"",IF(BE22>BD22,"🚫",IF(INT(BE22/AX22<1),"👍",INT(BE22/AX22)&"x"))) | BI22: =IF(BD21=0,0,IF(OR(BE21=0,BF21="V"),BI21-1,IF(OR(AU$11="BRADESCO",AU$11="BB"),BI21-ROUNDDOWN(BE21/(BD21/BI21),0)-1,ROUNDUP((BD21-BE21+BJ21-(BD21/BI21))/(BC21-AW22-AR22-AS22),0)+1))) -> 382 | BJ22: =BD21*$BK21 -> 669.01366 | BK22: =IF(BD21>0,BK21,0) -> 0.0017
A23: =IF(INT(F23)>0,A22,0) -> 25 | B23: =IF(F23>0.1,B22,0) -> 75 | C23: =DATE(YEAR(C22),MONTH(C22)+1,1) -> 46296 | D23: =IFERROR(G23/M22,0) -> 0.0026246719 | E23: =E22+1 -> 9 | F23: =IF(OR(M22<1,N22>M22),0,(M22-N22)*IF(D$11<>"BB",$E$7,(1+$D$7)^(AK22/365)-1)) -> 3285.0489 | G23: =IF(R23=0,0,IF(M22<1,0,IF(AND(AND(((M22-N22)/R23)<G22,O22<>"V"),D$11<>"BRADESCO"),G22, (M22-N22)/R23))) -> 1031.9587 | H23: =IF(OR(G23=0,L23<1),"",IF(G23/L23>90%,"🛩",IF(G23/L23>70%,"🏎",IF(G23/L23>50%,"🚙",IF(G23/L23>30%,"🛵",IF(G23/L23>15%,"🐢","⚓️")))))) -> 🐢 | I23: =IFERROR(IF((G23+N23-S23)/L23<0,"🔙",IF((G23+N23-S23)/L23<10%,"🥾",IF((G23+N23-S23)/L23<20%,"🛴",IF((G23+N23-S23)/L23<50%,"🚴‍♂️",IF((G23+N23-S23)/L23<75%,"🚖","🚁"))))),"") -> 🥾 | J23: =G23+N23-S23 -> 363.55904 | K23: =IFERROR(J23/(L23+N23),0) -> 0.082308903 | L23: =G23+F23+A23+B23 -> 4417.0075 | M23: =IF(R23=0,0,MAX(0,M22-G23+S23-N22)) -> 392812.7 | O23: =IF(AND(N23<>"",N23<R23),"V","") | P23: =IF(N22=0,"",(L22-L23)/N22) | Q23: =IF(N23=0,"",IF(N23>M23,"🚫",IF(INT(N23/G23<1),"👍",INT(N23/G23)&"x"))) | R23: =IF(M22=0,0,IF(OR(N22=0,O22="V"),R22-1,IF(OR(D$11="BRADESCO",D$11="BB"),R22-ROUNDDOWN(N22/(M22/R22),0)-1,ROUNDUP((M22-N22+S22-(M22/R22))/(L22-F23-A23-B23),0)+1))) -> 381 | S23: =M22*$T23 -> 668.39964 | T23: =IF(M22>0,T22,0) -> 0.0017 | AA23: =-(L23+N23) -> -4417.0075 | AH23: =ROUNDUP(E23/120,0) -> 1 | AI23: =ROUNDUP(E23/36,0) -> 1 | AJ23: =ROUNDUP(E23/12,0) -> 1 | AK23: =DAY(DATE(YEAR(C23),MONTH(C23)+1,1)-1) -> 31 | AR23: =IF(INT(AW23)>0,AR22,0) -> 25 | AS23: =IF(AW23>0.1,AS22,0) -> 75 | AT23: =DATE(YEAR(AT22),MONTH(AT22)+1,1) -> 46296 | AU23: =IFERROR(AX23/BD22,0) -> 0.0026246719 | AV23: =AV22+1 -> 9 | AW23: =IF(OR(BD22<1,BE22>BD22),0,(BD22-BE22)*IF(AU$11<>"BB",$E$7,(1+$D$7)^(BY22/365)-1)) -> 3285.0489 | AX23: =IF(BI23=0,0,IF(BD22<1,0,IF(AND(AND(((BD22-BE22)/BI23)<AX22,BF22<>"V"),AU$11<>"BRADESCO"),AX22, (BD22-BE22)/BI23))) -> 1031.9587 | AY23: =IF(OR(AX23=0,BC23<1),"",IF(AX23/BC23>90%,"🛩",IF(AX23/BC23>70%,"🏎",IF(AX23/BC23>50%,"🚙",IF(AX23/BC23>30%,"🛵",IF(AX23/BC23>15%,"🐢","⚓️")))))) -> 🐢 | AZ23: =IFERROR(IF((AX23+BE23-BJ23)/BC23<0,"🔙",IF((AX23+BE23-BJ23)/BC23<10%,"🥾",IF((AX23+BE23-BJ23)/BC23<20%,"🛴",IF((AX23+BE23-BJ23)/BC23<50%,"🚴‍♂️",IF((AX23+BE23-BJ23)/BC23<75%,"🚖","🚁"))))),"") -> 🥾 | BA23: =AX23+BE23-BJ23 -> 363.55904 | BB23: =IFERROR(BA23/(BC23+BE23),0) -> 0.082308903 | BC23: =AX23+AW23+AR23+AS23 -> 4417.0075 | BD23: =IF(BI23=0,0,MAX(0,BD22-AX23+BJ23-BE22)) -> 392812.7 | BF23: =IF(AND(BE23<>"",BE23<BI23),"V","") | BG23: =IF(BE22=0,"",(BC22-BC23)/BE22) | BH23: =IF(BE23=0,"",IF(BE23>BD23,"🚫",IF(INT(BE23/AX23<1),"👍",INT(BE23/AX23)&"x"))) | BI23: =IF(BD22=0,0,IF(OR(BE22=0,BF22="V"),BI22-1,IF(OR(AU$11="BRADESCO",AU$11="BB"),BI22-ROUNDDOWN(BE22/(BD22/BI22),0)-1,ROUNDUP((BD22-BE22+BJ22-(BD22/BI22))/(BC22-AW23-AR23-AS23),0)+1))) -> 381 | BJ23: =BD22*$BK22 -> 668.39964 | BK23: =IF(BD22>0,BK22,0) -> 0.0017
A24: =IF(INT(F24)>0,A23,0) -> 25 | B24: =IF(F24>0.1,B23,0) -> 75 | C24: =DATE(YEAR(C23),MONTH(C23)+1,1) -> 46327 | D24: =IFERROR(G24/M23,0) -> 0.0026315789 | E24: =E23+1 -> 10 | F24: =IF(OR(M23<1,N23>M23),0,(M23-N23)*IF(D$11<>"BB",$E$7,(1+$D$7)^(AK23/365)-1)) -> 3282.0113 | G24: =IF(R24=0,0,IF(M23<1,0,IF(AND(AND(((M23-N23)/R24)<G23,O23<>"V"),D$11<>"BRADESCO"),G23, (M23-N23)/R24))) -> 1033.7176 | H24: =IF(OR(G24=0,L24<1),"",IF(G24/L24>90%,"🛩",IF(G24/L24>70%,"🏎",IF(G24/L24>50%,"🚙",IF(G24/L24>30%,"🛵",IF(G24/L24>15%,"🐢","⚓️")))))) -> 🐢 | I24: =IFERROR(IF((G24+N24-S24)/L24<0,"🔙",IF((G24+N24-S24)/L24<10%,"🥾",IF((G24+N24-S24)/L24<20%,"🛴",IF((G24+N24-S24)/L24<50%,"🚴‍♂️",IF((G24+N24-S24)/L24<75%,"🚖","🚁"))))),"") -> 🥾 | J24: =G24+N24-S24 -> 365.93604 | K24: =IFERROR(J24/(L24+N24),0) -> 0.082871039 | L24: =G24+F24+A24+B24 -> 4415.7289 | M24: =IF(R24=0,0,MAX(0,M23-G24+S24-N23)) -> 392446.76 | O24: =IF(AND(N24<>"",N24<R24),"V","") | P24: =IF(N23=0,"",(L23-L24)/N23) | Q24: =IF(N24=0,"",IF(N24>M24,"🚫",IF(INT(N24/G24<1),"👍",INT(N24/G24)&"x"))) | R24: =IF(M23=0,0,IF(OR(N23=0,O23="V"),R23-1,IF(OR(D$11="BRADESCO",D$11="BB"),R23-ROUNDDOWN(N23/(M23/R23),0)-1,ROUNDUP((M23-N23+S23-(M23/R23))/(L23-F24-A24-B24),0)+1))) -> 380 | S24: =M23*$T24 -> 667.78159 | T24: =IF(M23>0,T23,0) -> 0.0017 | AA24: =-(L24+N24) -> -4415.7289 | AH24: =ROUNDUP(E24/120,0) -> 1 | AI24: =ROUNDUP(E24/36,0) -> 1 | AJ24: =ROUNDUP(E24/12,0) -> 1 | AK24: =DAY(DATE(YEAR(C24),MONTH(C24)+1,1)-1) -> 30 | AR24: =IF(INT(AW24)>0,AR23,0) -> 25 | AS24: =IF(AW24>0.1,AS23,0) -> 75 | AT24: =DATE(YEAR(AT23),MONTH(AT23)+1,1) -> 46327 | AU24: =IFERROR(AX24/BD23,0) -> 0.0026315789 | AV24: =AV23+1 -> 10 | AW24: =IF(OR(BD23<1,BE23>BD23),0,(BD23-BE23)*IF(AU$11<>"BB",$E$7,(1+$D$7)^(BY23/365)-1)) -> 3282.0113 | AX24: =IF(BI24=0,0,IF(BD23<1,0,IF(AND(AND(((BD23-BE23)/BI24)<AX23,BF23<>"V"),AU$11<>"BRADESCO"),AX23, (BD23-BE23)/BI24))) -> 1033.7176 | AY24: =IF(OR(AX24=0,BC24<1),"",IF(AX24/BC24>90%,"🛩",IF(AX24/BC24>70%,"🏎",IF(AX24/BC24>50%,"🚙",IF(AX24/BC24>30%,"🛵",IF(AX24/BC24>15%,"🐢","⚓️")))))) -> 🐢 | AZ24: =IFERROR(IF((AX24+BE24-BJ24)/BC24<0,"🔙",IF((AX24+BE24-BJ24)/BC24<10%,"🥾",IF((AX24+BE24-BJ24)/BC24<20%,"🛴",IF((AX24+BE24-BJ24)/BC24<50%,"🚴‍♂️",IF((AX24+BE24-BJ24)/BC24<75%,"🚖","🚁"))))),"") -> 🥾 | BA24: =AX24+BE24-BJ24 -> 365.93604 | BB24: =IFERROR(BA24/(BC24+BE24),0) -> 0.082871039 | BC24: =AX24+AW24+AR24+AS24 -> 4415.7289 | BD24: =IF(BI24=0,0,MAX(0,BD23-AX24+BJ24-BE23)) -> 392446.76 | BF24: =IF(AND(BE24<>"",BE24<BI24),"V","") | BG24: =IF(BE23=0,"",(BC23-BC24)/BE23) | BH24: =IF(BE24=0,"",IF(BE24>BD24,"🚫",IF(INT(BE24/AX24<1),"👍",INT(BE24/AX24)&"x"))) | BI24: =IF(BD23=0,0,IF(OR(BE23=0,BF23="V"),BI23-1,IF(OR(AU$11="BRADESCO",AU$11="BB"),BI23-ROUNDDOWN(BE23/(BD23/BI23),0)-1,ROUNDUP((BD23-BE23+BJ23-(BD23/BI23))/(BC23-AW24-AR24-AS24),0)+1))) -> 380 | BJ24: =BD23*$BK23 -> 667.78159 | BK24: =IF(BD23>0,BK23,0) -> 0.0017
A25: =IF(INT(F25)>0,A24,0) -> 25 | B25: =IF(F25>0.1,B24,0) -> 75 | C25: =DATE(YEAR(C24),MONTH(C24)+1,1) -> 46357 | D25: =IFERROR(G25/M24,0) -> 0.0026385224 | E25: =E24+1 -> 11 | F25: =IF(OR(M24<1,N24>M24),0,(M24-N24)*IF(D$11<>"BB",$E$7,(1+$D$7)^(AK24/365)-1)) -> 3278.9538 | G25: =IF(R25=0,0,IF(M24<1,0,IF(AND(AND(((M24-N24)/R25)<G24,O24<>"V"),D$11<>"BRADESCO"),G24, (M24-N24)/R25))) -> 1035.4796 | H25: =IF(OR(G25=0,L25<1),"",IF(G25/L25>90%,"🛩",IF(G25/L25>70%,"🏎",IF(G25/L25>50%,"🚙",IF(G25/L25>30%,"🛵",IF(G25/L25>15%,"🐢","⚓️")))))) -> 🐢 | I25: =IFERROR(IF((G25+N25-S25)/L25<0,"🔙",IF((G25+N25-S25)/L25<10%,"🥾",IF((G25+N25-S25)/L25<20%,"🛴",IF((G25+N25-S25)/L25<50%,"🚴‍♂️",IF((G25+N25-S25)/L25<75%,"🚖","🚁"))))),"") -> 🥾 | J25: =G25+N25-S25 -> 368.32009 | K25: =IFERROR(J25/(L25+N25),0) -> 0.083435417 | L25: =G25+F25+A25+B25 -> 4414.4334 | M25: =IF(R25=0,0,MAX(0,M24-G25+S25-N24)) -> 392078.44 | O25: =IF(AND(N25<>"",N25<R25),"V","") | P25: =IF(N24=0,"",(L24-L25)/N24) | Q25: =IF(N25=0,"",IF(N25>M25,"🚫",IF(INT(N25/G25<1),"👍",INT(N25/G25)&"x"))) | R25: =IF(M24=0,0,IF(OR(N24=0,O24="V"),R24-1,IF(OR(D$11="BRADESCO",D$11="BB"),R24-ROUNDDOWN(N24/(M24/R24),0)-1,ROUNDUP((M24-N24+S24-(M24/R24))/(L24-F25-A25-B25),0)+1))) -> 379 | S25: =M24*$T25 -> 667.1595 | T25: =IF(M24>0,T24,0) -> 0.0017 | AA25: =-(L25+N25) -> -4414.4334 | AD25: ATENÇÃO: Esta planilha deve ser usada apenas para simulações | AH25: =ROUNDUP(E25/120,0) -> 1 | AI25: =ROUNDUP(E25/36,0) -> 1 | AJ25: =ROUNDUP(E25/12,0) -> 1 | AK25: =DAY(DATE(YEAR(C25),MONTH(C25)+1,1)-1) -> 31 | AR25: =IF(INT(AW25)>0,AR24,0) -> 25 | AS25: =IF(AW25>0.1,AS24,0) -> 75 | AT25: =DATE(YEAR(AT24),MONTH(AT24)+1,1) -> 46357 | AU25: =IFERROR(AX25/BD24,0) -> 0.0026385224 | AV25: =AV24+1 -> 11 | AW25: =IF(OR(BD24<1,BE24>BD24),0,(BD24-BE24)*IF(AU$11<>"BB",$E$7,(1+$D$7)^(BY24/365)-1)) -> 3278.9538 | AX25: =IF(BI25=0,0,IF(BD24<1,0,IF(AND(AND(((BD24-BE24)/BI25)<AX24,BF24<>"V"),AU$11<>"BRADESCO"),AX24, (BD24-BE24)/BI25))) -> 1035.4796 | AY25: =IF(OR(AX25=0,BC25<1),"",IF(AX25/BC25>90%,"🛩",IF(AX25/BC25>70%,"🏎",IF(AX25/BC25>50%,"🚙",IF(AX25/BC25>30%,"🛵",IF(AX25/BC25>15%,"🐢","⚓️")))))) -> 🐢 | AZ25: =IFERROR(IF((AX25+BE25-BJ25)/BC25<0,"🔙",IF((AX25+BE25-BJ25)/BC25<10%,"🥾",IF((AX25+BE25-BJ25)/BC25<20%,"🛴",IF((AX25+BE25-BJ25)/BC25<50%,"🚴‍♂️",IF((AX25+BE25-BJ25)/BC25<75%,"🚖","🚁"))))),"") -> 🥾 | BA25: =AX25+BE25-BJ25 -> 368.32009 | BB25: =IFERROR(BA25/(BC25+BE25),0) -> 0.083435417 | BC25: =AX25+AW25+AR25+AS25 -> 4414.4334 | BD25: =IF(BI25=0,0,MAX(0,BD24-AX25+BJ25-BE24)) -> 392078.44 | BF25: =IF(AND(BE25<>"",BE25<BI25),"V","") | BG25: =IF(BE24=0,"",(BC24-BC25)/BE24) | BH25: =IF(BE25=0,"",IF(BE25>BD25,"🚫",IF(INT(BE25/AX25<1),"👍",INT(BE25/AX25)&"x"))) | BI25: =IF(BD24=0,0,IF(OR(BE24=0,BF24="V"),BI24-1,IF(OR(AU$11="BRADESCO",AU$11="BB"),BI24-ROUNDDOWN(BE24/(BD24/BI24),0)-1,ROUNDUP((BD24-BE24+BJ24-(BD24/BI24))/(BC24-AW25-AR25-AS25),0)+1))) -> 379 | BJ25: =BD24*$BK24 -> 667.1595 | BK25: =IF(BD24>0,BK24,0) -> 0.0017
A26: =IF(INT(F26)>0,A25,0) -> 25 | B26: =IF(F26>0.1,B25,0) -> 75 | C26: =DATE(YEAR(C25),MONTH(C25)+1,1) -> 46388 | D26: =IFERROR(G26/M25,0) -> 0.0026455026 | E26: =E25+1 -> 12 | F26: =IF(OR(M25<1,N25>M25),0,(M25-N25)*IF(D$11<>"BB",$E$7,(1+$D$7)^(AK25/365)-1)) -> 3275.8764 | G26: =IF(R26=0,0,IF(M25<1,0,IF(AND(AND(((M25-N25)/R26)<G25,O25<>"V"),D$11<>"BRADESCO"),G25, (M25-N25)/R26))) -> 1037.2446 | H26: =IF(OR(G26=0,L26<1),"",IF(G26/L26>90%,"🛩",IF(G26/L26>70%,"🏎",IF(G26/L26>50%,"🚙",IF(G26/L26>30%,"🛵",IF(G26/L26>15%,"🐢","⚓️")))))) -> 🐢 | I26: =IFERROR(IF((G26+N26-S26)/L26<0,"🔙",IF((G26+N26-S26)/L26<10%,"🥾",IF((G26+N26-S26)/L26<20%,"🛴",IF((G26+N26-S26)/L26<50%,"🚴‍♂️",IF((G26+N26-S26)/L26<75%,"🚖","🚁"))))),"") -> 🥾 | J26: =G26+N26-S26 -> 370.71121 | K26: =IFERROR(J26/(L26+N26),0) -> 0.084002049 | L26: =G26+F26+A26+B26 -> 4413.121 | M26: =IF(R26=0,0,MAX(0,M25-G26+S26-N25)) -> 391707.73 | O26: =IF(AND(N26<>"",N26<R26),"V","") | P26: =IF(N25=0,"",(L25-L26)/N25) | Q26: =IF(N26=0,"",IF(N26>M26,"🚫",IF(INT(N26/G26<1),"👍",INT(N26/G26)&"x"))) | R26: =IF(M25=0,0,IF(OR(N25=0,O25="V"),R25-1,IF(OR(D$11="BRADESCO",D$11="BB"),R25-ROUNDDOWN(N25/(M25/R25),0)-1,ROUNDUP((M25-N25+S25-(M25/R25))/(L25-F26-A26-B26),0)+1))) -> 378 | S26: =M25*$T26 -> 666.53335 | T26: =IF(M25>0,T25,0) -> 0.0017 | AA26: =-(L26+N26) -> -4413.121 | AD26: e planejamentos futuros. | AH26: =ROUNDUP(E26/120,0) -> 1 | AI26: =ROUNDUP(E26/36,0) -> 1 | AJ26: =ROUNDUP(E26/12,0) -> 1 | AK26: =DAY(DATE(YEAR(C26),MONTH(C26)+1,1)-1) -> 31 | AR26: =IF(INT(AW26)>0,AR25,0) -> 25 | AS26: =IF(AW26>0.1,AS25,0) -> 75 | AT26: =DATE(YEAR(AT25),MONTH(AT25)+1,1) -> 46388 | AU26: =IFERROR(AX26/BD25,0) -> 0.0026455026 | AV26: =AV25+1 -> 12 | AW26: =IF(OR(BD25<1,BE25>BD25),0,(BD25-BE25)*IF(AU$11<>"BB",$E$7,(1+$D$7)^(BY25/365)-1)) -> 3275.8764 | AX26: =IF(BI26=0,0,IF(BD25<1,0,IF(AND(AND(((BD25-BE25)/BI26)<AX25,BF25<>"V"),AU$11<>"BRADESCO"),AX25, (BD25-BE25)/BI26))) -> 1037.2446 | AY26: =IF(OR(AX26=0,BC26<1),"",IF(AX26/BC26>90%,"🛩",IF(AX26/BC26>70%,"🏎",IF(AX26/BC26>50%,"🚙",IF(AX26/BC26>30%,"🛵",IF(AX26/BC26>15%,"🐢","⚓️")))))) -> 🐢 | AZ26: =IFERROR(IF((AX26+BE26-BJ26)/BC26<0,"🔙",IF((AX26+BE26-BJ26)/BC26<10%,"🥾",IF((AX26+BE26-BJ26)/BC26<20%,"🛴",IF((AX26+BE26-BJ26)/BC26<50%,"🚴‍♂️",IF((AX26+BE26-BJ26)/BC26<75%,"🚖","🚁"))))),"") -> 🥾 | BA26: =AX26+BE26-BJ26 -> 370.71121 | BB26: =IFERROR(BA26/(BC26+BE26),0) -> 0.084002049 | BC26: =AX26+AW26+AR26+AS26 -> 4413.121 | BD26: =IF(BI26=0,0,MAX(0,BD25-AX26+BJ26-BE25)) -> 391707.73 | BF26: =IF(AND(BE26<>"",BE26<BI26),"V","") | BG26: =IF(BE25=0,"",(BC25-BC26)/BE25) | BH26: =IF(BE26=0,"",IF(BE26>BD26,"🚫",IF(INT(BE26/AX26<1),"👍",INT(BE26/AX26)&"x"))) | BI26: =IF(BD25=0,0,IF(OR(BE25=0,BF25="V"),BI25-1,IF(OR(AU$11="BRADESCO",AU$11="BB"),BI25-ROUNDDOWN(BE25/(BD25/BI25),0)-1,ROUNDUP((BD25-BE25+BJ25-(BD25/BI25))/(BC25-AW26-AR26-AS26),0)+1))) -> 378 | BJ26: =BD25*$BK25 -> 666.53335 | BK26: =IF(BD25>0,BK25,0) -> 0.0017
A27: =IF(INT(F27)>0,A26,0) -> 25 | B27: =IF(F27>0.1,B26,0) -> 75 | C27: =DATE(YEAR(C26),MONTH(C26)+1,1) -> 46419 | D27: =IFERROR(G27/M26,0) -> 0.0026525199 | E27: =E26+1 -> 13 | F27: =IF(OR(M26<1,N26>M26),0,(M26-N26)*IF(D$11<>"BB",$E$7,(1+$D$7)^(AK26/365)-1)) -> 3272.7791 | G27: =IF(R27=0,0,IF(M26<1,0,IF(AND(AND(((M26-N26)/R27)<G26,O26<>"V"),D$11<>"BRADESCO"),G26, (M26-N26)/R27))) -> 1039.0126 | H27: =IF(OR(G27=0,L27<1),"",IF(G27/L27>90%,"🛩",IF(G27/L27>70%,"🏎",IF(G27/L27>50%,"🚙",IF(G27/L27>30%,"🛵",IF(G27/L27>15%,"🐢","⚓️")))))) -> 🐢 | I27: =IFERROR(IF((G27+N27-S27)/L27<0,"🔙",IF((G27+N27-S27)/L27<10%,"🥾",IF((G27+N27-S27)/L27<20%,"🛴",IF((G27+N27-S27)/L27<50%,"🚴‍♂️",IF((G27+N27-S27)/L27<75%,"🚖","🚁"))))),"") -> 🥾 | J27: =G27+N27-S27 -> 373.10941 | K27: =IFERROR(J27/(L27+N27),0) -> 0.084570949 | L27: =G27+F27+A27+B27 -> 4411.7916 | M27: =IF(R27=0,0,MAX(0,M26-G27+S27-N26)) -> 391334.62 | O27: =IF(AND(N27<>"",N27<R27),"V","") | P27: =IF(N26=0,"",(L26-L27)/N26) | Q27: =IF(N27=0,"",IF(N27>M27,"🚫",IF(INT(N27/G27<1),"👍",INT(N27/G27)&"x"))) | R27: =IF(M26=0,0,IF(OR(N26=0,O26="V"),R26-1,IF(OR(D$11="BRADESCO",D$11="BB"),R26-ROUNDDOWN(N26/(M26/R26),0)-1,ROUNDUP((M26-N26+S26-(M26/R26))/(L26-F27-A27-B27),0)+1))) -> 377 | S27: =M26*$T27 -> 665.90315 | T27: =IF(M26>0,T26,0) -> 0.0017 | AA27: =-(L27+N27) -> -4411.7916 | AD27: Confira sempre os valores no seu Documento Descritivo de Crédito. | AH27: =ROUNDUP(E27/120,0) -> 1 | AI27: =ROUNDUP(E27/36,0) -> 1 | AJ27: =ROUNDUP(E27/12,0) -> 2 | AK27: =DAY(DATE(YEAR(C27),MONTH(C27)+1,1)-1) -> 28 | AR27: =IF(INT(AW27)>0,AR26,0) -> 25 | AS27: =IF(AW27>0.1,AS26,0) -> 75 | AT27: =DATE(YEAR(AT26),MONTH(AT26)+1,1) -> 46419 | AU27: =IFERROR(AX27/BD26,0) -> 0.0026525199 | AV27: =AV26+1 -> 13 | AW27: =IF(OR(BD26<1,BE26>BD26),0,(BD26-BE26)*IF(AU$11<>"BB",$E$7,(1+$D$7)^(BY26/365)-1)) -> 3272.7791 | AX27: =IF(BI27=0,0,IF(BD26<1,0,IF(AND(AND(((BD26-BE26)/BI27)<AX26,BF26<>"V"),AU$11<>"BRADESCO"),AX26, (BD26-BE26)/BI27))) -> 1039.0126 | AY27: =IF(OR(AX27=0,BC27<1),"",IF(AX27/BC27>90%,"🛩",IF(AX27/BC27>70%,"🏎",IF(AX27/BC27>50%,"🚙",IF(AX27/BC27>30%,"🛵",IF(AX27/BC27>15%,"🐢","⚓️")))))) -> 🐢 | AZ27: =IFERROR(IF((AX27+BE27-BJ27)/BC27<0,"🔙",IF((AX27+BE27-BJ27)/BC27<10%,"🥾",IF((AX27+BE27-BJ27)/BC27<20%,"🛴",IF((AX27+BE27-BJ27)/BC27<50%,"🚴‍♂️",IF((AX27+BE27-BJ27)/BC27<75%,"🚖","🚁"))))),"") -> 🥾 | BA27: =AX27+BE27-BJ27 -> 373.10941 | BB27: =IFERROR(BA27/(BC27+BE27),0) -> 0.084570949 | BC27: =AX27+AW27+AR27+AS27 -> 4411.7916 | BD27: =IF(BI27=0,0,MAX(0,BD26-AX27+BJ27-BE26)) -> 391334.62 | BF27: =IF(AND(BE27<>"",BE27<BI27),"V","") | BG27: =IF(BE26=0,"",(BC26-BC27)/BE26) | BH27: =IF(BE27=0,"",IF(BE27>BD27,"🚫",IF(INT(BE27/AX27<1),"👍",INT(BE27/AX27)&"x"))) | BI27: =IF(BD26=0,0,IF(OR(BE26=0,BF26="V"),BI26-1,IF(OR(AU$11="BRADESCO",AU$11="BB"),BI26-ROUNDDOWN(BE26/(BD26/BI26),0)-1,ROUNDUP((BD26-BE26+BJ26-(BD26/BI26))/(BC26-AW27-AR27-AS27),0)+1))) -> 377 | BJ27: =BD26*$BK26 -> 665.90315 | BK27: =IF(BD26>0,BK26,0) -> 0.0017
A28: =IF(INT(F28)>0,A27,0) -> 25 | B28: =IF(F28>0.1,B27,0) -> 75 | C28: =DATE(YEAR(C27),MONTH(C27)+1,1) -> 46447 | D28: =IFERROR(G28/M27,0) -> 0.0026595745 | E28: =E27+1 -> 14 | F28: =IF(OR(M27<1,N27>M27),0,(M27-N27)*IF(D$11<>"BB",$E$7,(1+$D$7)^(AK27/365)-1)) -> 3269.6617 | G28: =IF(R28=0,0,IF(M27<1,0,IF(AND(AND(((M27-N27)/R28)<G27,O27<>"V"),D$11<>"BRADESCO"),G27, (M27-N27)/R28))) -> 1040.7836 | H28: =IF(OR(G28=0,L28<1),"",IF(G28/L28>90%,"🛩",IF(G28/L28>70%,"🏎",IF(G28/L28>50%,"🚙",IF(G28/L28>30%,"🛵",IF(G28/L28>15%,"🐢","⚓️")))))) -> 🐢 | I28: =IFERROR(IF((G28+N28-S28)/L28<0,"🔙",IF((G28+N28-S28)/L28<10%,"🥾",IF((G28+N28-S28)/L28<20%,"🛴",IF((G28+N28-S28)/L28<50%,"🚴‍♂️",IF((G28+N28-S28)/L28<75%,"🚖","🚁"))))),"") -> 🥾 | J28: =G28+N28-S28 -> 375.51471 | K28: =IFERROR(J28/(L28+N28),0) -> 0.085142132 | L28: =G28+F28+A28+B28 -> 4410.4453 | M28: =IF(R28=0,0,MAX(0,M27-G28+S28-N27)) -> 390959.11 | O28: =IF(AND(N28<>"",N28<R28),"V","") | P28: =IF(N27=0,"",(L27-L28)/N27) | Q28: =IF(N28=0,"",IF(N28>M28,"🚫",IF(INT(N28/G28<1),"👍",INT(N28/G28)&"x"))) | R28: =IF(M27=0,0,IF(OR(N27=0,O27="V"),R27-1,IF(OR(D$11="BRADESCO",D$11="BB"),R27-ROUNDDOWN(N27/(M27/R27),0)-1,ROUNDUP((M27-N27+S27-(M27/R27))/(L27-F28-A28-B28),0)+1))) -> 376 | S28: =M27*$T28 -> 665.26886 | T28: =IF(M27>0,T27,0) -> 0.0017 | AA28: =-(L28+N28) -> -4410.4453 | AD28: Para chegar nos valores mais próximos, adicione as | AH28: =ROUNDUP(E28/120,0) -> 1 | AI28: =ROUNDUP(E28/36,0) -> 1 | AJ28: =ROUNDUP(E28/12,0) -> 2 | AK28: =DAY(DATE(YEAR(C28),MONTH(C28)+1,1)-1) -> 31 | AR28: =IF(INT(AW28)>0,AR27,0) -> 25 | AS28: =IF(AW28>0.1,AS27,0) -> 75 | AT28: =DATE(YEAR(AT27),MONTH(AT27)+1,1) -> 46447 | AU28: =IFERROR(AX28/BD27,0) -> 0.0026595745 | AV28: =AV27+1 -> 14 | AW28: =IF(OR(BD27<1,BE27>BD27),0,(BD27-BE27)*IF(AU$11<>"BB",$E$7,(1+$D$7)^(BY27/365)-1)) -> 3269.6617 | AX28: =IF(BI28=0,0,IF(BD27<1,0,IF(AND(AND(((BD27-BE27)/BI28)<AX27,BF27<>"V"),AU$11<>"BRADESCO"),AX27, (BD27-BE27)/BI28))) -> 1040.7836 | AY28: =IF(OR(AX28=0,BC28<1),"",IF(AX28/BC28>90%,"🛩",IF(AX28/BC28>70%,"🏎",IF(AX28/BC28>50%,"🚙",IF(AX28/BC28>30%,"🛵",IF(AX28/BC28>15%,"🐢","⚓️")))))) -> 🐢 | AZ28: =IFERROR(IF((AX28+BE28-BJ28)/BC28<0,"🔙",IF((AX28+BE28-BJ28)/BC28<10%,"🥾",IF((AX28+BE28-BJ28)/BC28<20%,"🛴",IF((AX28+BE28-BJ28)/BC28<50%,"🚴‍♂️",IF((AX28+BE28-BJ28)/BC28<75%,"🚖","🚁"))))),"") -> 🥾 | BA28: =AX28+BE28-BJ28 -> 375.51471 | BB28: =IFERROR(BA28/(BC28+BE28),0) -> 0.085142132 | BC28: =AX28+AW28+AR28+AS28 -> 4410.4453 | BD28: =IF(BI28=0,0,MAX(0,BD27-AX28+BJ28-BE27)) -> 390959.11 | BF28: =IF(AND(BE28<>"",BE28<BI28),"V","") | BG28: =IF(BE27=0,"",(BC27-BC28)/BE27) | BH28: =IF(BE28=0,"",IF(BE28>BD28,"🚫",IF(INT(BE28/AX28<1),"👍",INT(BE28/AX28)&"x"))) | BI28: =IF(BD27=0,0,IF(OR(BE27=0,BF27="V"),BI27-1,IF(OR(AU$11="BRADESCO",AU$11="BB"),BI27-ROUNDDOWN(BE27/(BD27/BI27),0)-1,ROUNDUP((BD27-BE27+BJ27-(BD27/BI27))/(BC27-AW28-AR28-AS28),0)+1))) -> 376 | BJ28: =BD27*$BK27 -> 665.26886 | BK28: =IF(BD27>0,BK27,0) -> 0.0017
A29: =IF(INT(F29)>0,A28,0) -> 25 | B29: =IF(F29>0.1,B28,0) -> 75 | C29: =DATE(YEAR(C28),MONTH(C28)+1,1) -> 46478 | D29: =IFERROR(G29/M28,0) -> 0.0026666667 | E29: =E28+1 -> 15 | F29: =IF(OR(M28<1,N28>M28),0,(M28-N28)*IF(D$11<>"BB",$E$7,(1+$D$7)^(AK28/365)-1)) -> 3266.5242 | G29: =IF(R29=0,0,IF(M28<1,0,IF(AND(AND(((M28-N28)/R29)<G28,O28<>"V"),D$11<>"BRADESCO"),G28, (M28-N28)/R29))) -> 1042.5576 | H29: =IF(OR(G29=0,L29<1),"",IF(G29/L29>90%,"🛩",IF(G29/L29>70%,"🏎",IF(G29/L29>50%,"🚙",IF(G29/L29>30%,"🛵",IF(G29/L29>15%,"🐢","⚓️")))))) -> 🐢 | I29: =IFERROR(IF((G29+N29-S29)/L29<0,"🔙",IF((G29+N29-S29)/L29<10%,"🥾",IF((G29+N29-S29)/L29<20%,"🛴",IF((G29+N29-S29)/L29<50%,"🚴‍♂️",IF((G29+N29-S29)/L29<75%,"🚖","🚁"))))),"") -> 🥾 | J29: =G29+N29-S29 -> 377.92714 | K29: =IFERROR(J29/(L29+N29),0) -> 0.08571561 | L29: =G29+F29+A29+B29 -> 4409.0818 | M29: =IF(R29=0,0,MAX(0,M28-G29+S29-N28)) -> 390581.18 | O29: =IF(AND(N29<>"",N29<R29),"V","") | P29: =IF(N28=0,"",(L28-L29)/N28) | Q29: =IF(N29=0,"",IF(N29>M29,"🚫",IF(INT(N29/G29<1),"👍",INT(N29/G29)&"x"))) | R29: =IF(M28=0,0,IF(OR(N28=0,O28="V"),R28-1,IF(OR(D$11="BRADESCO",D$11="BB"),R28-ROUNDDOWN(N28/(M28/R28),0)-1,ROUNDUP((M28-N28+S28-(M28/R28))/(L28-F29-A29-B29),0)+1))) -> 375 | S29: =M28*$T29 -> 664.63048 | T29: =IF(M28>0,T28,0) -> 0.0017 | AA29: =-(L29+N29) -> -4409.0818 | AD29: correções monetárias e o seguro a cada mês. | AH29: =ROUNDUP(E29/120,0) -> 1 | AI29: =ROUNDUP(E29/36,0) -> 1 | AJ29: =ROUNDUP(E29/12,0) -> 2 | AK29: =DAY(DATE(YEAR(C29),MONTH(C29)+1,1)-1) -> 30 | AR29: =IF(INT(AW29)>0,AR28,0) -> 25 | AS29: =IF(AW29>0.1,AS28,0) -> 75 | AT29: =DATE(YEAR(AT28),MONTH(AT28)+1,1) -> 46478 | AU29: =IFERROR(AX29/BD28,0) -> 0.0026666667 | AV29: =AV28+1 -> 15 | AW29: =IF(OR(BD28<1,BE28>BD28),0,(BD28-BE28)*IF(AU$11<>"BB",$E$7,(1+$D$7)^(BY28/365)-1)) -> 3266.5242 | AX29: =IF(BI29=0,0,IF(BD28<1,0,IF(AND(AND(((BD28-BE28)/BI29)<AX28,BF28<>"V"),AU$11<>"BRADESCO"),AX28, (BD28-BE28)/BI29))) -> 1042.5576 | AY29: =IF(OR(AX29=0,BC29<1),"",IF(AX29/BC29>90%,"🛩",IF(AX29/BC29>70%,"🏎",IF(AX29/BC29>50%,"🚙",IF(AX29/BC29>30%,"🛵",IF(AX29/BC29>15%,"🐢","⚓️")))))) -> 🐢 | AZ29: =IFERROR(IF((AX29+BE29-BJ29)/BC29<0,"🔙",IF((AX29+BE29-BJ29)/BC29<10%,"🥾",IF((AX29+BE29-BJ29)/BC29<20%,"🛴",IF((AX29+BE29-BJ29)/BC29<50%,"🚴‍♂️",IF((AX29+BE29-BJ29)/BC29<75%,"🚖","🚁"))))),"") -> 🥾 | BA29: =AX29+BE29-BJ29 -> 377.92714 | BB29: =IFERROR(BA29/(BC29+BE29),0) -> 0.08571561 | BC29: =AX29+AW29+AR29+AS29 -> 4409.0818 | BD29: =IF(BI29=0,0,MAX(0,BD28-AX29+BJ29-BE28)) -> 390581.18 | BF29: =IF(AND(BE29<>"",BE29<BI29),"V","") | BG29: =IF(BE28=0,"",(BC28-BC29)/BE28) | BH29: =IF(BE29=0,"",IF(BE29>BD29,"🚫",IF(INT(BE29/AX29<1),"👍",INT(BE29/AX29)&"x"))) | BI29: =IF(BD28=0,0,IF(OR(BE28=0,BF28="V"),BI28-1,IF(OR(AU$11="BRADESCO",AU$11="BB"),BI28-ROUNDDOWN(BE28/(BD28/BI28),0)-1,ROUNDUP((BD28-BE28+BJ28-(BD28/BI28))/(BC28-AW29-AR29-AS29),0)+1))) -> 375 | BJ29: =BD28*$BK28 -> 664.63048 | BK29: =IF(BD28>0,BK28,0) -> 0.0017
A30: =IF(INT(F30)>0,A29,0) -> 25 | B30: =IF(F30>0.1,B29,0) -> 75 | C30: =DATE(YEAR(C29),MONTH(C29)+1,1) -> 46508 | D30: =IFERROR(G30/M29,0) -> 0.0026737968 | E30: =E29+1 -> 16 | F30: =IF(OR(M29<1,N29>M29),0,(M29-N29)*IF(D$11<>"BB",$E$7,(1+$D$7)^(AK29/365)-1)) -> 3263.3666 | G30: =IF(R30=0,0,IF(M29<1,0,IF(AND(AND(((M29-N29)/R30)<G29,O29<>"V"),D$11<>"BRADESCO"),G29, (M29-N29)/R30))) -> 1044.3347 | H30: =IF(OR(G30=0,L30<1),"",IF(G30/L30>90%,"🛩",IF(G30/L30>70%,"🏎",IF(G30/L30>50%,"🚙",IF(G30/L30>30%,"🛵",IF(G30/L30>15%,"🐢","⚓️")))))) -> 🐢 | I30: =IFERROR(IF((G30+N30-S30)/L30<0,"🔙",IF((G30+N30-S30)/L30<10%,"🥾",IF((G30+N30-S30)/L30<20%,"🛴",IF((G30+N30-S30)/L30<50%,"🚴‍♂️",IF((G30+N30-S30)/L30<75%,"🚖","🚁"))))),"") -> 🥾 | J30: =G30+N30-S30 -> 380.3467 | K30: =IFERROR(J30/(L30+N30),0) -> 0.086291397 | L30: =G30+F30+A30+B30 -> 4407.7013 | M30: =IF(R30=0,0,MAX(0,M29-G30+S30-N29)) -> 390200.83 | O30: =IF(AND(N30<>"",N30<R30),"V","") | P30: =IF(N29=0,"",(L29-L30)/N29) | Q30: =IF(N30=0,"",IF(N30>M30,"🚫",IF(INT(N30/G30<1),"👍",INT(N30/G30)&"x"))) | R30: =IF(M29=0,0,IF(OR(N29=0,O29="V"),R29-1,IF(OR(D$11="BRADESCO",D$11="BB"),R29-ROUNDDOWN(N29/(M29/R29),0)-1,ROUNDUP((M29-N29+S29-(M29/R29))/(L29-F30-A30-B30),0)+1))) -> 374 | S30: =M29*$T30 -> 663.98801 | T30: =IF(M29>0,T29,0) -> 0.0017 | AA30: =-(L30+N30) -> -4407.7013 | AD30: https://www.habitacaodigital.caixa.gov.br/ | AH30: =ROUNDUP(E30/120,0) -> 1 | AI30: =ROUNDUP(E30/36,0) -> 1 | AJ30: =ROUNDUP(E30/12,0) -> 2 | AK30: =DAY(DATE(YEAR(C30),MONTH(C30)+1,1)-1) -> 31 | AR30: =IF(INT(AW30)>0,AR29,0) -> 25 | AS30: =IF(AW30>0.1,AS29,0) -> 75 | AT30: =DATE(YEAR(AT29),MONTH(AT29)+1,1) -> 46508 | AU30: =IFERROR(AX30/BD29,0) -> 0.0026737968 | AV30: =AV29+1 -> 16 | AW30: =IF(OR(BD29<1,BE29>BD29),0,(BD29-BE29)*IF(AU$11<>"BB",$E$7,(1+$D$7)^(BY29/365)-1)) -> 3263.3666 | AX30: =IF(BI30=0,0,IF(BD29<1,0,IF(AND(AND(((BD29-BE29)/BI30)<AX29,BF29<>"V"),AU$11<>"BRADESCO"),AX29, (BD29-BE29)/BI30))) -> 1044.3347 | AY30: =IF(OR(AX30=0,BC30<1),"",IF(AX30/BC30>90%,"🛩",IF(AX30/BC30>70%,"🏎",IF(AX30/BC30>50%,"🚙",IF(AX30/BC30>30%,"🛵",IF(AX30/BC30>15%,"🐢","⚓️")))))) -> 🐢 | AZ30: =IFERROR(IF((AX30+BE30-BJ30)/BC30<0,"🔙",IF((AX30+BE30-BJ30)/BC30<10%,"🥾",IF((AX30+BE30-BJ30)/BC30<20%,"🛴",IF((AX30+BE30-BJ30)/BC30<50%,"🚴‍♂️",IF((AX30+BE30-BJ30)/BC30<75%,"🚖","🚁"))))),"") -> 🥾 | BA30: =AX30+BE30-BJ30 -> 380.3467 | BB30: =IFERROR(BA30/(BC30+BE30),0) -> 0.086291397 | BC30: =AX30+AW30+AR30+AS30 -> 4407.7013 | BD30: =IF(BI30=0,0,MAX(0,BD29-AX30+BJ30-BE29)) -> 390200.83 | BF30: =IF(AND(BE30<>"",BE30<BI30),"V","") | BG30: =IF(BE29=0,"",(BC29-BC30)/BE29) | BH30: =IF(BE30=0,"",IF(BE30>BD30,"🚫",IF(INT(BE30/AX30<1),"👍",INT(BE30/AX30)&"x"))) | BI30: =IF(BD29=0,0,IF(OR(BE29=0,BF29="V"),BI29-1,IF(OR(AU$11="BRADESCO",AU$11="BB"),BI29-ROUNDDOWN(BE29/(BD29/BI29),0)-1,ROUNDUP((BD29-BE29+BJ29-(BD29/BI29))/(BC29-AW30-AR30-AS30),0)+1))) -> 374 | BJ30: =BD29*$BK29 -> 663.98801 | BK30: =IF(BD29>0,BK29,0) -> 0.0017
A31: =IF(INT(F31)>0,A30,0) -> 25 | B31: =IF(F31>0.1,B30,0) -> 75 | C31: =DATE(YEAR(C30),MONTH(C30)+1,1) -> 46539 | D31: =IFERROR(G31/M30,0) -> 0.0026809651 | E31: =E30+1 -> 17 | F31: =IF(OR(M30<1,N30>M30),0,(M30-N30)*IF(D$11<>"BB",$E$7,(1+$D$7)^(AK30/365)-1)) -> 3260.1887 | G31: =IF(R31=0,0,IF(M30<1,0,IF(AND(AND(((M30-N30)/R31)<G30,O30<>"V"),D$11<>"BRADESCO"),G30, (M30-N30)/R31))) -> 1046.1148 | H31: =IF(OR(G31=0,L31<1),"",IF(G31/L31>90%,"🛩",IF(G31/L31>70%,"🏎",IF(G31/L31>50%,"🚙",IF(G31/L31>30%,"🛵",IF(G31/L31>15%,"🐢","⚓️")))))) -> 🐢 | I31: =IFERROR(IF((G31+N31-S31)/L31<0,"🔙",IF((G31+N31-S31)/L31<10%,"🥾",IF((G31+N31-S31)/L31<20%,"🛴",IF((G31+N31-S31)/L31<50%,"🚴‍♂️",IF((G31+N31-S31)/L31<75%,"🚖","🚁"))))),"") -> 🥾 | J31: =G31+N31-S31 -> 382.77342 | K31: =IFERROR(J31/(L31+N31),0) -> 0.086869507 | L31: =G31+F31+A31+B31 -> 4406.3036 | M31: =IF(R31=0,0,MAX(0,M30-G31+S31-N30)) -> 389818.06 | O31: =IF(AND(N31<>"",N31<R31),"V","") | P31: =IF(N30=0,"",(L30-L31)/N30) | Q31: =IF(N31=0,"",IF(N31>M31,"🚫",IF(INT(N31/G31<1),"👍",INT(N31/G31)&"x"))) | R31: =IF(M30=0,0,IF(OR(N30=0,O30="V"),R30-1,IF(OR(D$11="BRADESCO",D$11="BB"),R30-ROUNDDOWN(N30/(M30/R30),0)-1,ROUNDUP((M30-N30+S30-(M30/R30))/(L30-F31-A31-B31),0)+1))) -> 373 | S31: =M30*$T31 -> 663.34142 | T31: =IF(M30>0,T30,0) -> 0.0017 | AA31: =-(L31+N31) -> -4406.3036 | AD31: Documento Descritivo de Crédito | AH31: =ROUNDUP(E31/120,0) -> 1 | AI31: =ROUNDUP(E31/36,0) -> 1 | AJ31: =ROUNDUP(E31/12,0) -> 2 | AK31: =DAY(DATE(YEAR(C31),MONTH(C31)+1,1)-1) -> 30 | AR31: =IF(INT(AW31)>0,AR30,0) -> 25 | AS31: =IF(AW31>0.1,AS30,0) -> 75 | AT31: =DATE(YEAR(AT30),MONTH(AT30)+1,1) -> 46539 | AU31: =IFERROR(AX31/BD30,0) -> 0.0026809651 | AV31: =AV30+1 -> 17 | AW31: =IF(OR(BD30<1,BE30>BD30),0,(BD30-BE30)*IF(AU$11<>"BB",$E$7,(1+$D$7)^(BY30/365)-1)) -> 3260.1887 | AX31: =IF(BI31=0,0,IF(BD30<1,0,IF(AND(AND(((BD30-BE30)/BI31)<AX30,BF30<>"V"),AU$11<>"BRADESCO"),AX30, (BD30-BE30)/BI31))) -> 1046.1148 | AY31: =IF(OR(AX31=0,BC31<1),"",IF(AX31/BC31>90%,"🛩",IF(AX31/BC31>70%,"🏎",IF(AX31/BC31>50%,"🚙",IF(AX31/BC31>30%,"🛵",IF(AX31/BC31>15%,"🐢","⚓️")))))) -> 🐢 | AZ31: =IFERROR(IF((AX31+BE31-BJ31)/BC31<0,"🔙",IF((AX31+BE31-BJ31)/BC31<10%,"🥾",IF((AX31+BE31-BJ31)/BC31<20%,"🛴",IF((AX31+BE31-BJ31)/BC31<50%,"🚴‍♂️",IF((AX31+BE31-BJ31)/BC31<75%,"🚖","🚁"))))),"") -> 🥾 | BA31: =AX31+BE31-BJ31 -> 382.77342 | BB31: =IFERROR(BA31/(BC31+BE31),0) -> 0.086869507 | BC31: =AX31+AW31+AR31+AS31 -> 4406.3036 | BD31: =IF(BI31=0,0,MAX(0,BD30-AX31+BJ31-BE30)) -> 389818.06 | BF31: =IF(AND(BE31<>"",BE31<BI31),"V","") | BG31: =IF(BE30=0,"",(BC30-BC31)/BE30) | BH31: =IF(BE31=0,"",IF(BE31>BD31,"🚫",IF(INT(BE31/AX31<1),"👍",INT(BE31/AX31)&"x"))) | BI31: =IF(BD30=0,0,IF(OR(BE30=0,BF30="V"),BI30-1,IF(OR(AU$11="BRADESCO",AU$11="BB"),BI30-ROUNDDOWN(BE30/(BD30/BI30),0)-1,ROUNDUP((BD30-BE30+BJ30-(BD30/BI30))/(BC30-AW31-AR31-AS31),0)+1))) -> 373 | BJ31: =BD30*$BK30 -> 663.34142 | BK31: =IF(BD30>0,BK30,0) -> 0.0017
A32: =IF(INT(F32)>0,A31,0) -> 25 | B32: =IF(F32>0.1,B31,0) -> 75 | C32: =DATE(YEAR(C31),MONTH(C31)+1,1) -> 46569 | D32: =IFERROR(G32/M31,0) -> 0.002688172 | E32: =E31+1 -> 18 | F32: =IF(OR(M31<1,N31>M31),0,(M31-N31)*IF(D$11<>"BB",$E$7,(1+$D$7)^(AK31/365)-1)) -> 3256.9906 | G32: =IF(R32=0,0,IF(M31<1,0,IF(AND(AND(((M31-N31)/R32)<G31,O31<>"V"),D$11<>"BRADESCO"),G31, (M31-N31)/R32))) -> 1047.898 | H32: =IF(OR(G32=0,L32<1),"",IF(G32/L32>90%,"🛩",IF(G32/L32>70%,"🏎",IF(G32/L32>50%,"🚙",IF(G32/L32>30%,"🛵",IF(G32/L32>15%,"🐢","⚓️")))))) -> 🐢 | I32: =IFERROR(IF((G32+N32-S32)/L32<0,"🔙",IF((G32+N32-S32)/L32<10%,"🥾",IF((G32+N32-S32)/L32<20%,"🛴",IF((G32+N32-S32)/L32<50%,"🚴‍♂️",IF((G32+N32-S32)/L32<75%,"🚖","🚁"))))),"") -> 🥾 | J32: =G32+N32-S32 -> 385.20731 | K32: =IFERROR(J32/(L32+N32),0) -> 0.087449955 | L32: =G32+F32+A32+B32 -> 4404.8886 | M32: =IF(R32=0,0,MAX(0,M31-G32+S32-N31)) -> 389432.85 | O32: =IF(AND(N32<>"",N32<R32),"V","") | P32: =IF(N31=0,"",(L31-L32)/N31) | Q32: =IF(N32=0,"",IF(N32>M32,"🚫",IF(INT(N32/G32<1),"👍",INT(N32/G32)&"x"))) | R32: =IF(M31=0,0,IF(OR(N31=0,O31="V"),R31-1,IF(OR(D$11="BRADESCO",D$11="BB"),R31-ROUNDDOWN(N31/(M31/R31),0)-1,ROUNDUP((M31-N31+S31-(M31/R31))/(L31-F32-A32-B32),0)+1))) -> 372 | S32: =M31*$T32 -> 662.6907 | T32: =IF(M31>0,T31,0) -> 0.0017 | AA32: =-(L32+N32) -> -4404.8886 | AH32: =ROUNDUP(E32/120,0) -> 1 | AI32: =ROUNDUP(E32/36,0) -> 1 | AJ32: =ROUNDUP(E32/12,0) -> 2 | AK32: =DAY(DATE(YEAR(C32),MONTH(C32)+1,1)-1) -> 31 | AR32: =IF(INT(AW32)>0,AR31,0) -> 25 | AS32: =IF(AW32>0.1,AS31,0) -> 75 | AT32: =DATE(YEAR(AT31),MONTH(AT31)+1,1) -> 46569 | AU32: =IFERROR(AX32/BD31,0) -> 0.002688172 | AV32: =AV31+1 -> 18 | AW32: =IF(OR(BD31<1,BE31>BD31),0,(BD31-BE31)*IF(AU$11<>"BB",$E$7,(1+$D$7)^(BY31/365)-1)) -> 3256.9906 | AX32: =IF(BI32=0,0,IF(BD31<1,0,IF(AND(AND(((BD31-BE31)/BI32)<AX31,BF31<>"V"),AU$11<>"BRADESCO"),AX31, (BD31-BE31)/BI32))) -> 1047.898 | AY32: =IF(OR(AX32=0,BC32<1),"",IF(AX32/BC32>90%,"🛩",IF(AX32/BC32>70%,"🏎",IF(AX32/BC32>50%,"🚙",IF(AX32/BC32>30%,"🛵",IF(AX32/BC32>15%,"🐢","⚓️")))))) -> 🐢 | AZ32: =IFERROR(IF((AX32+BE32-BJ32)/BC32<0,"🔙",IF((AX32+BE32-BJ32)/BC32<10%,"🥾",IF((AX32+BE32-BJ32)/BC32<20%,"🛴",IF((AX32+BE32-BJ32)/BC32<50%,"🚴‍♂️",IF((AX32+BE32-BJ32)/BC32<75%,"🚖","🚁"))))),"") -> 🥾 | BA32: =AX32+BE32-BJ32 -> 385.20731 | BB32: =IFERROR(BA32/(BC32+BE32),0) -> 0.087449955 | BC32: =AX32+AW32+AR32+AS32 -> 4404.8886 | BD32: =IF(BI32=0,0,MAX(0,BD31-AX32+BJ32-BE31)) -> 389432.85 | BF32: =IF(AND(BE32<>"",BE32<BI32),"V","") | BG32: =IF(BE31=0,"",(BC31-BC32)/BE31) | BH32: =IF(BE32=0,"",IF(BE32>BD32,"🚫",IF(INT(BE32/AX32<1),"👍",INT(BE32/AX32)&"x"))) | BI32: =IF(BD31=0,0,IF(OR(BE31=0,BF31="V"),BI31-1,IF(OR(AU$11="BRADESCO",AU$11="BB"),BI31-ROUNDDOWN(BE31/(BD31/BI31),0)-1,ROUNDUP((BD31-BE31+BJ31-(BD31/BI31))/(BC31-AW32-AR32-AS32),0)+1))) -> 372 | BJ32: =BD31*$BK31 -> 662.6907 | BK32: =IF(BD31>0,BK31,0) -> 0.0017
A33: =IF(INT(F33)>0,A32,0) -> 25 | B33: =IF(F33>0.1,B32,0) -> 75 | C33: =DATE(YEAR(C32),MONTH(C32)+1,1) -> 46600 | D33: =IFERROR(G33/M32,0) -> 0.0026954178 | E33: =E32+1 -> 19 | F33: =IF(OR(M32<1,N32>M32),0,(M32-N32)*IF(D$11<>"BB",$E$7,(1+$D$7)^(AK32/365)-1)) -> 3253.7721 | G33: =IF(R33=0,0,IF(M32<1,0,IF(AND(AND(((M32-N32)/R33)<G32,O32<>"V"),D$11<>"BRADESCO"),G32, (M32-N32)/R33))) -> 1049.6842 | H33: =IF(OR(G33=0,L33<1),"",IF(G33/L33>90%,"🛩",IF(G33/L33>70%,"🏎",IF(G33/L33>50%,"🚙",IF(G33/L33>30%,"🛵",IF(G33/L33>15%,"🐢","⚓️")))))) -> 🐢 | I33: =IFERROR(IF((G33+N33-S33)/L33<0,"🔙",IF((G33+N33-S33)/L33<10%,"🥾",IF((G33+N33-S33)/L33<20%,"🛴",IF((G33+N33-S33)/L33<50%,"🚴‍♂️",IF((G33+N33-S33)/L33<75%,"🚖","🚁"))))),"") -> 🥾 | J33: =G33+N33-S33 -> 387.64839 | K33: =IFERROR(J33/(L33+N33),0) -> 0.088032754 | L33: =G33+F33+A33+B33 -> 4403.4564 | M33: =IF(R33=0,0,MAX(0,M32-G33+S33-N32)) -> 389045.21 | O33: =IF(AND(N33<>"",N33<R33),"V","") | P33: =IF(N32=0,"",(L32-L33)/N32) | Q33: =IF(N33=0,"",IF(N33>M33,"🚫",IF(INT(N33/G33<1),"👍",INT(N33/G33)&"x"))) | R33: =IF(M32=0,0,IF(OR(N32=0,O32="V"),R32-1,IF(OR(D$11="BRADESCO",D$11="BB"),R32-ROUNDDOWN(N32/(M32/R32),0)-1,ROUNDUP((M32-N32+S32-(M32/R32))/(L32-F33-A33-B33),0)+1))) -> 371 | S33: =M32*$T33 -> 662.03585 | T33: =IF(M32>0,T32,0) -> 0.0017 | AA33: =-(L33+N33) -> -4403.4564 | AD33: Autor: Alessandro Rodolpho Gonçalves da Silva | AH33: =ROUNDUP(E33/120,0) -> 1 | AI33: =ROUNDUP(E33/36,0) -> 1 | AJ33: =ROUNDUP(E33/12,0) -> 2 | AK33: =DAY(DATE(YEAR(C33),MONTH(C33)+1,1)-1) -> 31 | AR33: =IF(INT(AW33)>0,AR32,0) -> 25 | AS33: =IF(AW33>0.1,AS32,0) -> 75 | AT33: =DATE(YEAR(AT32),MONTH(AT32)+1,1) -> 46600 | AU33: =IFERROR(AX33/BD32,0) -> 0.0026954178 | AV33: =AV32+1 -> 19 | AW33: =IF(OR(BD32<1,BE32>BD32),0,(BD32-BE32)*IF(AU$11<>"BB",$E$7,(1+$D$7)^(BY32/365)-1)) -> 3253.7721 | AX33: =IF(BI33=0,0,IF(BD32<1,0,IF(AND(AND(((BD32-BE32)/BI33)<AX32,BF32<>"V"),AU$11<>"BRADESCO"),AX32, (BD32-BE32)/BI33))) -> 1049.6842 | AY33: =IF(OR(AX33=0,BC33<1),"",IF(AX33/BC33>90%,"🛩",IF(AX33/BC33>70%,"🏎",IF(AX33/BC33>50%,"🚙",IF(AX33/BC33>30%,"🛵",IF(AX33/BC33>15%,"🐢","⚓️")))))) -> 🐢 | AZ33: =IFERROR(IF((AX33+BE33-BJ33)/BC33<0,"🔙",IF((AX33+BE33-BJ33)/BC33<10%,"🥾",IF((AX33+BE33-BJ33)/BC33<20%,"🛴",IF((AX33+BE33-BJ33)/BC33<50%,"🚴‍♂️",IF((AX33+BE33-BJ33)/BC33<75%,"🚖","🚁"))))),"") -> 🥾 | BA33: =AX33+BE33-BJ33 -> 387.64839 | BB33: =IFERROR(BA33/(BC33+BE33),0) -> 0.088032754 | BC33: =AX33+AW33+AR33+AS33 -> 4403.4564 | BD33: =IF(BI33=0,0,MAX(0,BD32-AX33+BJ33-BE32)) -> 389045.21 | BF33: =IF(AND(BE33<>"",BE33<BI33),"V","") | BG33: =IF(BE32=0,"",(BC32-BC33)/BE32) | BH33: =IF(BE33=0,"",IF(BE33>BD33,"🚫",IF(INT(BE33/AX33<1),"👍",INT(BE33/AX33)&"x"))) | BI33: =IF(BD32=0,0,IF(OR(BE32=0,BF32="V"),BI32-1,IF(OR(AU$11="BRADESCO",AU$11="BB"),BI32-ROUNDDOWN(BE32/(BD32/BI32),0)-1,ROUNDUP((BD32-BE32+BJ32-(BD32/BI32))/(BC32-AW33-AR33-AS33),0)+1))) -> 371 | BJ33: =BD32*$BK32 -> 662.03585 | BK33: =IF(BD32>0,BK32,0) -> 0.0017
A34: =IF(INT(F34)>0,A33,0) -> 25 | B34: =IF(F34>0.1,B33,0) -> 75 | C34: =DATE(YEAR(C33),MONTH(C33)+1,1) -> 46631 | D34: =IFERROR(G34/M33,0) -> 0.0027027027 | E34: =E33+1 -> 20 | F34: =IF(OR(M33<1,N33>M33),0,(M33-N33)*IF(D$11<>"BB",$E$7,(1+$D$7)^(AK33/365)-1)) -> 3250.5333 | G34: =IF(R34=0,0,IF(M33<1,0,IF(AND(AND(((M33-N33)/R34)<G33,O33<>"V"),D$11<>"BRADESCO"),G33, (M33-N33)/R34))) -> 1051.4735 | H34: =IF(OR(G34=0,L34<1),"",IF(G34/L34>90%,"🛩",IF(G34/L34>70%,"🏎",IF(G34/L34>50%,"🚙",IF(G34/L34>30%,"🛵",IF(G34/L34>15%,"🐢","⚓️")))))) -> 🐢 | I34: =IFERROR(IF((G34+N34-S34)/L34<0,"🔙",IF((G34+N34-S34)/L34<10%,"🥾",IF((G34+N34-S34)/L34<20%,"🛴",IF((G34+N34-S34)/L34<50%,"🚴‍♂️",IF((G34+N34-S34)/L34<75%,"🚖","🚁"))))),"") -> 🥾 | J34: =G34+N34-S34 -> 390.09668 | K34: =IFERROR(J34/(L34+N34),0) -> 0.088617919 | L34: =G34+F34+A34+B34 -> 4402.0068 | M34: =IF(R34=0,0,MAX(0,M33-G34+S34-N33)) -> 388655.11 | O34: =IF(AND(N34<>"",N34<R34),"V","") | P34: =IF(N33=0,"",(L33-L34)/N33) | Q34: =IF(N34=0,"",IF(N34>M34,"🚫",IF(INT(N34/G34<1),"👍",INT(N34/G34)&"x"))) | R34: =IF(M33=0,0,IF(OR(N33=0,O33="V"),R33-1,IF(OR(D$11="BRADESCO",D$11="BB"),R33-ROUNDDOWN(N33/(M33/R33),0)-1,ROUNDUP((M33-N33+S33-(M33/R33))/(L33-F34-A34-B34),0)+1))) -> 370 | S34: =M33*$T34 -> 661.37685 | T34: =IF(M33>0,T33,0) -> 0.0017 | AA34: =-(L34+N34) -> -4402.0068 | AD34: instagram.com/amigodopairico | AH34: =ROUNDUP(E34/120,0) -> 1 | AI34: =ROUNDUP(E34/36,0) -> 1 | AJ34: =ROUNDUP(E34/12,0) -> 2 | AK34: =DAY(DATE(YEAR(C34),MONTH(C34)+1,1)-1) -> 30 | AR34: =IF(INT(AW34)>0,AR33,0) -> 25 | AS34: =IF(AW34>0.1,AS33,0) -> 75 | AT34: =DATE(YEAR(AT33),MONTH(AT33)+1,1) -> 46631 | AU34: =IFERROR(AX34/BD33,0) -> 0.0027027027 | AV34: =AV33+1 -> 20 | AW34: =IF(OR(BD33<1,BE33>BD33),0,(BD33-BE33)*IF(AU$11<>"BB",$E$7,(1+$D$7)^(BY33/365)-1)) -> 3250.5333 | AX34: =IF(BI34=0,0,IF(BD33<1,0,IF(AND(AND(((BD33-BE33)/BI34)<AX33,BF33<>"V"),AU$11<>"BRADESCO"),AX33, (BD33-BE33)/BI34))) -> 1051.4735 | AY34: =IF(OR(AX34=0,BC34<1),"",IF(AX34/BC34>90%,"🛩",IF(AX34/BC34>70%,"🏎",IF(AX34/BC34>50%,"🚙",IF(AX34/BC34>30%,"🛵",IF(AX34/BC34>15%,"🐢","⚓️")))))) -> 🐢 | AZ34: =IFERROR(IF((AX34+BE34-BJ34)/BC34<0,"🔙",IF((AX34+BE34-BJ34)/BC34<10%,"🥾",IF((AX34+BE34-BJ34)/BC34<20%,"🛴",IF((AX34+BE34-BJ34)/BC34<50%,"🚴‍♂️",IF((AX34+BE34-BJ34)/BC34<75%,"🚖","🚁"))))),"") -> 🥾 | BA34: =AX34+BE34-BJ34 -> 390.09668 | BB34: =IFERROR(BA34/(BC34+BE34),0) -> 0.088617919 | BC34: =AX34+AW34+AR34+AS34 -> 4402.0068 | BD34: =IF(BI34=0,0,MAX(0,BD33-AX34+BJ34-BE33)) -> 388655.11 | BF34: =IF(AND(BE34<>"",BE34<BI34),"V","") | BG34: =IF(BE33=0,"",(BC33-BC34)/BE33) | BH34: =IF(BE34=0,"",IF(BE34>BD34,"🚫",IF(INT(BE34/AX34<1),"👍",INT(BE34/AX34)&"x"))) | BI34: =IF(BD33=0,0,IF(OR(BE33=0,BF33="V"),BI33-1,IF(OR(AU$11="BRADESCO",AU$11="BB"),BI33-ROUNDDOWN(BE33/(BD33/BI33),0)-1,ROUNDUP((BD33-BE33+BJ33-(BD33/BI33))/(BC33-AW34-AR34-AS34),0)+1))) -> 370 | BJ34: =BD33*$BK33 -> 661.37685 | BK34: =IF(BD33>0,BK33,0) -> 0.0017
A35: =IF(INT(F35)>0,A34,0) -> 25 | B35: =IF(F35>0.1,B34,0) -> 75 | C35: =DATE(YEAR(C34),MONTH(C34)+1,1) -> 46661 | D35: =IFERROR(G35/M34,0) -> 0.0027100271 | E35: =E34+1 -> 21 | F35: =IF(OR(M34<1,N34>M34),0,(M34-N34)*IF(D$11<>"BB",$E$7,(1+$D$7)^(AK34/365)-1)) -> 3247.2739 | G35: =IF(R35=0,0,IF(M34<1,0,IF(AND(AND(((M34-N34)/R35)<G34,O34<>"V"),D$11<>"BRADESCO"),G34, (M34-N34)/R35))) -> 1053.2659 | H35: =IF(OR(G35=0,L35<1),"",IF(G35/L35>90%,"🛩",IF(G35/L35>70%,"🏎",IF(G35/L35>50%,"🚙",IF(G35/L35>30%,"🛵",IF(G35/L35>15%,"🐢","⚓️")))))) -> 🐢 | I35: =IFERROR(IF((G35+N35-S35)/L35<0,"🔙",IF((G35+N35-S35)/L35<10%,"🥾",IF((G35+N35-S35)/L35<20%,"🛴",IF((G35+N35-S35)/L35<50%,"🚴‍♂️",IF((G35+N35-S35)/L35<75%,"🚖","🚁"))))),"") -> 🥾 | J35: =G35+N35-S35 -> 392.55219 | K35: =IFERROR(J35/(L35+N35),0) -> 0.089205463 | L35: =G35+F35+A35+B35 -> 4400.5398 | M35: =IF(R35=0,0,MAX(0,M34-G35+S35-N34)) -> 388262.56 | O35: =IF(AND(N35<>"",N35<R35),"V","") | P35: =IF(N34=0,"",(L34-L35)/N34) | Q35: =IF(N35=0,"",IF(N35>M35,"🚫",IF(INT(N35/G35<1),"👍",INT(N35/G35)&"x"))) | R35: =IF(M34=0,0,IF(OR(N34=0,O34="V"),R34-1,IF(OR(D$11="BRADESCO",D$11="BB"),R34-ROUNDDOWN(N34/(M34/R34),0)-1,ROUNDUP((M34-N34+S34-(M34/R34))/(L34-F35-A35-B35),0)+1))) -> 369 | S35: =M34*$T35 -> 660.71369 | T35: =IF(M34>0,T34,0) -> 0.0017 | AA35: =-(L35+N35) -> -4400.5398 | AD35: alessandrogon.com.br / amigodopairico.com.br | AH35: =ROUNDUP(E35/120,0) -> 1 | AI35: =ROUNDUP(E35/36,0) -> 1 | AJ35: =ROUNDUP(E35/12,0) -> 2 | AK35: =DAY(DATE(YEAR(C35),MONTH(C35)+1,1)-1) -> 31 | AR35: =IF(INT(AW35)>0,AR34,0) -> 25 | AS35: =IF(AW35>0.1,AS34,0) -> 75 | AT35: =DATE(YEAR(AT34),MONTH(AT34)+1,1) -> 46661 | AU35: =IFERROR(AX35/BD34,0) -> 0.0027100271 | AV35: =AV34+1 -> 21 | AW35: =IF(OR(BD34<1,BE34>BD34),0,(BD34-BE34)*IF(AU$11<>"BB",$E$7,(1+$D$7)^(BY34/365)-1)) -> 3247.2739 | AX35: =IF(BI35=0,0,IF(BD34<1,0,IF(AND(AND(((BD34-BE34)/BI35)<AX34,BF34<>"V"),AU$11<>"BRADESCO"),AX34, (BD34-BE34)/BI35))) -> 1053.2659 | AY35: =IF(OR(AX35=0,BC35<1),"",IF(AX35/BC35>90%,"🛩",IF(AX35/BC35>70%,"🏎",IF(AX35/BC35>50%,"🚙",IF(AX35/BC35>30%,"🛵",IF(AX35/BC35>15%,"🐢","⚓️")))))) -> 🐢 | AZ35: =IFERROR(IF((AX35+BE35-BJ35)/BC35<0,"🔙",IF((AX35+BE35-BJ35)/BC35<10%,"🥾",IF((AX35+BE35-BJ35)/BC35<20%,"🛴",IF((AX35+BE35-BJ35)/BC35<50%,"🚴‍♂️",IF((AX35+BE35-BJ35)/BC35<75%,"🚖","🚁"))))),"") -> 🥾 | BA35: =AX35+BE35-BJ35 -> 392.55219 | BB35: =IFERROR(BA35/(BC35+BE35),0) -> 0.089205463 | BC35: =AX35+AW35+AR35+AS35 -> 4400.5398 | BD35: =IF(BI35=0,0,MAX(0,BD34-AX35+BJ35-BE34)) -> 388262.56 | BF35: =IF(AND(BE35<>"",BE35<BI35),"V","") | BG35: =IF(BE34=0,"",(BC34-BC35)/BE34) | BH35: =IF(BE35=0,"",IF(BE35>BD35,"🚫",IF(INT(BE35/AX35<1),"👍",INT(BE35/AX35)&"x"))) | BI35: =IF(BD34=0,0,IF(OR(BE34=0,BF34="V"),BI34-1,IF(OR(AU$11="BRADESCO",AU$11="BB"),BI34-ROUNDDOWN(BE34/(BD34/BI34),0)-1,ROUNDUP((BD34-BE34+BJ34-(BD34/BI34))/(BC34-AW35-AR35-AS35),0)+1))) -> 369 | BJ35: =BD34*$BK34 -> 660.71369 | BK35: =IF(BD34>0,BK34,0) -> 0.0017
A36: =IF(INT(F36)>0,A35,0) -> 25 | B36: =IF(F36>0.1,B35,0) -> 75 | C36: =DATE(YEAR(C35),MONTH(C35)+1,1) -> 46692 | D36: =IFERROR(G36/M35,0) -> 0.0027173913 | E36: =E35+1 -> 22 | F36: =IF(OR(M35<1,N35>M35),0,(M35-N35)*IF(D$11<>"BB",$E$7,(1+$D$7)^(AK35/365)-1)) -> 3243.9941 | G36: =IF(R36=0,0,IF(M35<1,0,IF(AND(AND(((M35-N35)/R36)<G35,O35<>"V"),D$11<>"BRADESCO"),G35, (M35-N35)/R36))) -> 1055.0613 | H36: =IF(OR(G36=0,L36<1),"",IF(G36/L36>90%,"🛩",IF(G36/L36>70%,"🏎",IF(G36/L36>50%,"🚙",IF(G36/L36>30%,"🛵",IF(G36/L36>15%,"🐢","⚓️")))))) -> 🐢 | I36: =IFERROR(IF((G36+N36-S36)/L36<0,"🔙",IF((G36+N36-S36)/L36<10%,"🥾",IF((G36+N36-S36)/L36<20%,"🛴",IF((G36+N36-S36)/L36<50%,"🚴‍♂️",IF((G36+N36-S36)/L36<75%,"🚖","🚁"))))),"") -> 🥾 | J36: =G36+N36-S36 -> 395.01495 | K36: =IFERROR(J36/(L36+N36),0) -> 0.089795402 | L36: =G36+F36+A36+B36 -> 4399.0554 | M36: =IF(R36=0,0,MAX(0,M35-G36+S36-N35)) -> 387867.54 | O36: =IF(AND(N36<>"",N36<R36),"V","") | P36: =IF(N35=0,"",(L35-L36)/N35) | Q36: =IF(N36=0,"",IF(N36>M36,"🚫",IF(INT(N36/G36<1),"👍",INT(N36/G36)&"x"))) | R36: =IF(M35=0,0,IF(OR(N35=0,O35="V"),R35-1,IF(OR(D$11="BRADESCO",D$11="BB"),R35-ROUNDDOWN(N35/(M35/R35),0)-1,ROUNDUP((M35-N35+S35-(M35/R35))/(L35-F36-A36-B36),0)+1))) -> 368 | S36: =M35*$T36 -> 660.04635 | T36: =IF(M35>0,T35,0) -> 0.0017 | AA36: =-(L36+N36) -> -4399.0554 | AH36: =ROUNDUP(E36/120,0) -> 1 | AI36: =ROUNDUP(E36/36,0) -> 1 | AJ36: =ROUNDUP(E36/12,0) -> 2 | AK36: =DAY(DATE(YEAR(C36),MONTH(C36)+1,1)-1) -> 30 | AR36: =IF(INT(AW36)>0,AR35,0) -> 25 | AS36: =IF(AW36>0.1,AS35,0) -> 75 | AT36: =DATE(YEAR(AT35),MONTH(AT35)+1,1) -> 46692 | AU36: =IFERROR(AX36/BD35,0) -> 0.0027173913 | AV36: =AV35+1 -> 22 | AW36: =IF(OR(BD35<1,BE35>BD35),0,(BD35-BE35)*IF(AU$11<>"BB",$E$7,(1+$D$7)^(BY35/365)-1)) -> 3243.9941 | AX36: =IF(BI36=0,0,IF(BD35<1,0,IF(AND(AND(((BD35-BE35)/BI36)<AX35,BF35<>"V"),AU$11<>"BRADESCO"),AX35, (BD35-BE35)/BI36))) -> 1055.0613 | AY36: =IF(OR(AX36=0,BC36<1),"",IF(AX36/BC36>90%,"🛩",IF(AX36/BC36>70%,"🏎",IF(AX36/BC36>50%,"🚙",IF(AX36/BC36>30%,"🛵",IF(AX36/BC36>15%,"🐢","⚓️")))))) -> 🐢 | AZ36: =IFERROR(IF((AX36+BE36-BJ36)/BC36<0,"🔙",IF((AX36+BE36-BJ36)/BC36<10%,"🥾",IF((AX36+BE36-BJ36)/BC36<20%,"🛴",IF((AX36+BE36-BJ36)/BC36<50%,"🚴‍♂️",IF((AX36+BE36-BJ36)/BC36<75%,"🚖","🚁"))))),"") -> 🥾 | BA36: =AX36+BE36-BJ36 -> 395.01495 | BB36: =IFERROR(BA36/(BC36+BE36),0) -> 0.089795402 | BC36: =AX36+AW36+AR36+AS36 -> 4399.0554 | BD36: =IF(BI36=0,0,MAX(0,BD35-AX36+BJ36-BE35)) -> 387867.54 | BF36: =IF(AND(BE36<>"",BE36<BI36),"V","") | BG36: =IF(BE35=0,"",(BC35-BC36)/BE35) | BH36: =IF(BE36=0,"",IF(BE36>BD36,"🚫",IF(INT(BE36/AX36<1),"👍",INT(BE36/AX36)&"x"))) | BI36: =IF(BD35=0,0,IF(OR(BE35=0,BF35="V"),BI35-1,IF(OR(AU$11="BRADESCO",AU$11="BB"),BI35-ROUNDDOWN(BE35/(BD35/BI35),0)-1,ROUNDUP((BD35-BE35+BJ35-(BD35/BI35))/(BC35-AW36-AR36-AS36),0)+1))) -> 368 | BJ36: =BD35*$BK35 -> 660.04635 | BK36: =IF(BD35>0,BK35,0) -> 0.0017
A37: =IF(INT(F37)>0,A36,0) -> 25 | B37: =IF(F37>0.1,B36,0) -> 75 | C37: =DATE(YEAR(C36),MONTH(C36)+1,1) -> 46722 | D37: =IFERROR(G37/M36,0) -> 0.0027247956 | E37: =E36+1 -> 23 | F37: =IF(OR(M36<1,N36>M36),0,(M36-N36)*IF(D$11<>"BB",$E$7,(1+$D$7)^(AK36/365)-1)) -> 3240.6937 | G37: =IF(R37=0,0,IF(M36<1,0,IF(AND(AND(((M36-N36)/R37)<G36,O36<>"V"),D$11<>"BRADESCO"),G36, (M36-N36)/R37))) -> 1056.8598 | H37: =IF(OR(G37=0,L37<1),"",IF(G37/L37>90%,"🛩",IF(G37/L37>70%,"🏎",IF(G37/L37>50%,"🚙",IF(G37/L37>30%,"🛵",IF(G37/L37>15%,"🐢","⚓️")))))) -> 🐢 | I37: =IFERROR(IF((G37+N37-S37)/L37<0,"🔙",IF((G37+N37-S37)/L37<10%,"🥾",IF((G37+N37-S37)/L37<20%,"🛴",IF((G37+N37-S37)/L37<50%,"🚴‍♂️",IF((G37+N37-S37)/L37<75%,"🚖","🚁"))))),"") -> 🥾 | J37: =G37+N37-S37 -> 397.48497 | K37: =IFERROR(J37/(L37+N37),0) -> 0.09038775 | L37: =G37+F37+A37+B37 -> 4397.5535 | M37: =IF(R37=0,0,MAX(0,M36-G37+S37-N36)) -> 387470.06 | O37: =IF(AND(N37<>"",N37<R37),"V","") | P37: =IF(N36=0,"",(L36-L37)/N36) | Q37: =IF(N37=0,"",IF(N37>M37,"🚫",IF(INT(N37/G37<1),"👍",INT(N37/G37)&"x"))) | R37: =IF(M36=0,0,IF(OR(N36=0,O36="V"),R36-1,IF(OR(D$11="BRADESCO",D$11="BB"),R36-ROUNDDOWN(N36/(M36/R36),0)-1,ROUNDUP((M36-N36+S36-(M36/R36))/(L36-F37-A37-B37),0)+1))) -> 367 | S37: =M36*$T37 -> 659.37482 | T37: =IF(M36>0,T36,0) -> 0.0017 | AA37: =-(L37+N37) -> -4397.5535 | AD37: O conteúdo e formato desta planilha encontram-se protegidos pelas | AH37: =ROUNDUP(E37/120,0) -> 1 | AI37: =ROUNDUP(E37/36,0) -> 1 | AJ37: =ROUNDUP(E37/12,0) -> 2 | AK37: =DAY(DATE(YEAR(C37),MONTH(C37)+1,1)-1) -> 31 | AR37: =IF(INT(AW37)>0,AR36,0) -> 25 | AS37: =IF(AW37>0.1,AS36,0) -> 75 | AT37: =DATE(YEAR(AT36),MONTH(AT36)+1,1) -> 46722 | AU37: =IFERROR(AX37/BD36,0) -> 0.0027247956 | AV37: =AV36+1 -> 23 | AW37: =IF(OR(BD36<1,BE36>BD36),0,(BD36-BE36)*IF(AU$11<>"BB",$E$7,(1+$D$7)^(BY36/365)-1)) -> 3240.6937 | AX37: =IF(BI37=0,0,IF(BD36<1,0,IF(AND(AND(((BD36-BE36)/BI37)<AX36,BF36<>"V"),AU$11<>"BRADESCO"),AX36, (BD36-BE36)/BI37))) -> 1056.8598 | AY37: =IF(OR(AX37=0,BC37<1),"",IF(AX37/BC37>90%,"🛩",IF(AX37/BC37>70%,"🏎",IF(AX37/BC37>50%,"🚙",IF(AX37/BC37>30%,"🛵",IF(AX37/BC37>15%,"🐢","⚓️")))))) -> 🐢 | AZ37: =IFERROR(IF((AX37+BE37-BJ37)/BC37<0,"🔙",IF((AX37+BE37-BJ37)/BC37<10%,"🥾",IF((AX37+BE37-BJ37)/BC37<20%,"🛴",IF((AX37+BE37-BJ37)/BC37<50%,"🚴‍♂️",IF((AX37+BE37-BJ37)/BC37<75%,"🚖","🚁"))))),"") -> 🥾 | BA37: =AX37+BE37-BJ37 -> 397.48497 | BB37: =IFERROR(BA37/(BC37+BE37),0) -> 0.09038775 | BC37: =AX37+AW37+AR37+AS37 -> 4397.5535 | BD37: =IF(BI37=0,0,MAX(0,BD36-AX37+BJ37-BE36)) -> 387470.06 | BF37: =IF(AND(BE37<>"",BE37<BI37),"V","") | BG37: =IF(BE36=0,"",(BC36-BC37)/BE36) | BH37: =IF(BE37=0,"",IF(BE37>BD37,"🚫",IF(INT(BE37/AX37<1),"👍",INT(BE37/AX37)&"x"))) | BI37: =IF(BD36=0,0,IF(OR(BE36=0,BF36="V"),BI36-1,IF(OR(AU$11="BRADESCO",AU$11="BB"),BI36-ROUNDDOWN(BE36/(BD36/BI36),0)-1,ROUNDUP((BD36-BE36+BJ36-(BD36/BI36))/(BC36-AW37-AR37-AS37),0)+1))) -> 367 | BJ37: =BD36*$BK36 -> 659.37482 | BK37: =IF(BD36>0,BK36,0) -> 0.0017
A38: =IF(INT(F38)>0,A37,0) -> 25 | B38: =IF(F38>0.1,B37,0) -> 75 | C38: =DATE(YEAR(C37),MONTH(C37)+1,1) -> 46753 | D38: =IFERROR(G38/M37,0) -> 0.0027322404 | E38: =E37+1 -> 24 | F38: =IF(OR(M37<1,N37>M37),0,(M37-N37)*IF(D$11<>"BB",$E$7,(1+$D$7)^(AK37/365)-1)) -> 3237.3726 | G38: =IF(R38=0,0,IF(M37<1,0,IF(AND(AND(((M37-N37)/R38)<G37,O37<>"V"),D$11<>"BRADESCO"),G37, (M37-N37)/R38))) -> 1058.6614 | H38: =IF(OR(G38=0,L38<1),"",IF(G38/L38>90%,"🛩",IF(G38/L38>70%,"🏎",IF(G38/L38>50%,"🚙",IF(G38/L38>30%,"🛵",IF(G38/L38>15%,"🐢","⚓️")))))) -> 🐢 | I38: =IFERROR(IF((G38+N38-S38)/L38<0,"🔙",IF((G38+N38-S38)/L38<10%,"🥾",IF((G38+N38-S38)/L38<20%,"🛴",IF((G38+N38-S38)/L38<50%,"🚴‍♂️",IF((G38+N38-S38)/L38<75%,"🚖","🚁"))))),"") -> 🥾 | J38: =G38+N38-S38 -> 399.96226 | K38: =IFERROR(J38/(L38+N38),0) -> 0.090982522 | L38: =G38+F38+A38+B38 -> 4396.034 | M38: =IF(R38=0,0,MAX(0,M37-G38+S38-N37)) -> 387070.09 | O38: =IF(AND(N38<>"",N38<R38),"V","") | P38: =IF(N37=0,"",(L37-L38)/N37) | Q38: =IF(N38=0,"",IF(N38>M38,"🚫",IF(INT(N38/G38<1),"👍",INT(N38/G38)&"x"))) | R38: =IF(M37=0,0,IF(OR(N37=0,O37="V"),R37-1,IF(OR(D$11="BRADESCO",D$11="BB"),R37-ROUNDDOWN(N37/(M37/R37),0)-1,ROUNDUP((M37-N37+S37-(M37/R37))/(L37-F38-A38-B38),0)+1))) -> 366 | S38: =M37*$T38 -> 658.6991 | T38: =IF(M37>0,T37,0) -> 0.0017 | AA38: =-(L38+N38) -> -4396.034 | AD38: leis brasileiras e internacionais sobre propriedade intelectual | AH38: =ROUNDUP(E38/120,0) -> 1 | AI38: =ROUNDUP(E38/36,0) -> 1 | AJ38: =ROUNDUP(E38/12,0) -> 2 | AK38: =DAY(DATE(YEAR(C38),MONTH(C38)+1,1)-1) -> 31 | AR38: =IF(INT(AW38)>0,AR37,0) -> 25 | AS38: =IF(AW38>0.1,AS37,0) -> 75 | AT38: =DATE(YEAR(AT37),MONTH(AT37)+1,1) -> 46753 | AU38: =IFERROR(AX38/BD37,0) -> 0.0027322404 | AV38: =AV37+1 -> 24 | AW38: =IF(OR(BD37<1,BE37>BD37),0,(BD37-BE37)*IF(AU$11<>"BB",$E$7,(1+$D$7)^(BY37/365)-1)) -> 3237.3726 | AX38: =IF(BI38=0,0,IF(BD37<1,0,IF(AND(AND(((BD37-BE37)/BI38)<AX37,BF37<>"V"),AU$11<>"BRADESCO"),AX37, (BD37-BE37)/BI38))) -> 1058.6614 | AY38: =IF(OR(AX38=0,BC38<1),"",IF(AX38/BC38>90%,"🛩",IF(AX38/BC38>70%,"🏎",IF(AX38/BC38>50%,"🚙",IF(AX38/BC38>30%,"🛵",IF(AX38/BC38>15%,"🐢","⚓️")))))) -> 🐢 | AZ38: =IFERROR(IF((AX38+BE38-BJ38)/BC38<0,"🔙",IF((AX38+BE38-BJ38)/BC38<10%,"🥾",IF((AX38+BE38-BJ38)/BC38<20%,"🛴",IF((AX38+BE38-BJ38)/BC38<50%,"🚴‍♂️",IF((AX38+BE38-BJ38)/BC38<75%,"🚖","🚁"))))),"") -> 🥾 | BA38: =AX38+BE38-BJ38 -> 399.96226 | BB38: =IFERROR(BA38/(BC38+BE38),0) -> 0.090982522 | BC38: =AX38+AW38+AR38+AS38 -> 4396.034 | BD38: =IF(BI38=0,0,MAX(0,BD37-AX38+BJ38-BE37)) -> 387070.09 | BF38: =IF(AND(BE38<>"",BE38<BI38),"V","") | BG38: =IF(BE37=0,"",(BC37-BC38)/BE37) | BH38: =IF(BE38=0,"",IF(BE38>BD38,"🚫",IF(INT(BE38/AX38<1),"👍",INT(BE38/AX38)&"x"))) | BI38: =IF(BD37=0,0,IF(OR(BE37=0,BF37="V"),BI37-1,IF(OR(AU$11="BRADESCO",AU$11="BB"),BI37-ROUNDDOWN(BE37/(BD37/BI37),0)-1,ROUNDUP((BD37-BE37+BJ37-(BD37/BI37))/(BC37-AW38-AR38-AS38),0)+1))) -> 366 | BJ38: =BD37*$BK37 -> 658.6991 | BK38: =IF(BD37>0,BK37,0) -> 0.0017
A39: =IF(INT(F39)>0,A38,0) -> 25 | B39: =IF(F39>0.1,B38,0) -> 75 | C39: =DATE(YEAR(C38),MONTH(C38)+1,1) -> 46784 | D39: =IFERROR(G39/M38,0) -> 0.002739726 | E39: =E38+1 -> 25 | F39: =IF(OR(M38<1,N38>M38),0,(M38-N38)*IF(D$11<>"BB",$E$7,(1+$D$7)^(AK38/365)-1)) -> 3234.0309 | G39: =IF(R39=0,0,IF(M38<1,0,IF(AND(AND(((M38-N38)/R39)<G38,O38<>"V"),D$11<>"BRADESCO"),G38, (M38-N38)/R39))) -> 1060.466 | H39: =IF(OR(G39=0,L39<1),"",IF(G39/L39>90%,"🛩",IF(G39/L39>70%,"🏎",IF(G39/L39>50%,"🚙",IF(G39/L39>30%,"🛵",IF(G39/L39>15%,"🐢","⚓️")))))) -> 🐢 | I39: =IFERROR(IF((G39+N39-S39)/L39<0,"🔙",IF((G39+N39-S39)/L39<10%,"🥾",IF((G39+N39-S39)/L39<20%,"🛴",IF((G39+N39-S39)/L39<50%,"🚴‍♂️",IF((G39+N39-S39)/L39<75%,"🚖","🚁"))))),"") -> 🥾 | J39: =G39+N39-S39 -> 402.44685 | K39: =IFERROR(J39/(L39+N39),0) -> 0.091579732 | L39: =G39+F39+A39+B39 -> 4394.4969 | M39: =IF(R39=0,0,MAX(0,M38-G39+S39-N38)) -> 386667.65 | O39: =IF(AND(N39<>"",N39<R39),"V","") | P39: =IF(N38=0,"",(L38-L39)/N38) | Q39: =IF(N39=0,"",IF(N39>M39,"🚫",IF(INT(N39/G39<1),"👍",INT(N39/G39)&"x"))) | R39: =IF(M38=0,0,IF(OR(N38=0,O38="V"),R38-1,IF(OR(D$11="BRADESCO",D$11="BB"),R38-ROUNDDOWN(N38/(M38/R38),0)-1,ROUNDUP((M38-N38+S38-(M38/R38))/(L38-F39-A39-B39),0)+1))) -> 365 | S39: =M38*$T39 -> 658.01916 | T39: =IF(M38>0,T38,0) -> 0.0017 | AA39: =-(L39+N39) -> -4394.4969 | AD39: e industrial. É expressamente proibida a reprodução, transferência, | AH39: =ROUNDUP(E39/120,0) -> 1 | AI39: =ROUNDUP(E39/36,0) -> 1 | AJ39: =ROUNDUP(E39/12,0) -> 3 | AK39: =DAY(DATE(YEAR(C39),MONTH(C39)+1,1)-1) -> 29 | AR39: =IF(INT(AW39)>0,AR38,0) -> 25 | AS39: =IF(AW39>0.1,AS38,0) -> 75 | AT39: =DATE(YEAR(AT38),MONTH(AT38)+1,1) -> 46784 | AU39: =IFERROR(AX39/BD38,0) -> 0.002739726 | AV39: =AV38+1 -> 25 | AW39: =IF(OR(BD38<1,BE38>BD38),0,(BD38-BE38)*IF(AU$11<>"BB",$E$7,(1+$D$7)^(BY38/365)-1)) -> 3234.0309 | AX39: =IF(BI39=0,0,IF(BD38<1,0,IF(AND(AND(((BD38-BE38)/BI39)<AX38,BF38<>"V"),AU$11<>"BRADESCO"),AX38, (BD38-BE38)/BI39))) -> 1060.466 | AY39: =IF(OR(AX39=0,BC39<1),"",IF(AX39/BC39>90%,"🛩",IF(AX39/BC39>70%,"🏎",IF(AX39/BC39>50%,"🚙",IF(AX39/BC39>30%,"🛵",IF(AX39/BC39>15%,"🐢","⚓️")))))) -> 🐢 | AZ39: =IFERROR(IF((AX39+BE39-BJ39)/BC39<0,"🔙",IF((AX39+BE39-BJ39)/BC39<10%,"🥾",IF((AX39+BE39-BJ39)/BC39<20%,"🛴",IF((AX39+BE39-BJ39)/BC39<50%,"🚴‍♂️",IF((AX39+BE39-BJ39)/BC39<75%,"🚖","🚁"))))),"") -> 🥾 | BA39: =AX39+BE39-BJ39 -> 402.44685 | BB39: =IFERROR(BA39/(BC39+BE39),0) -> 0.091579732 | BC39: =AX39+AW39+AR39+AS39 -> 4394.4969 | BD39: =IF(BI39=0,0,MAX(0,BD38-AX39+BJ39-BE38)) -> 386667.65 | BF39: =IF(AND(BE39<>"",BE39<BI39),"V","") | BG39: =IF(BE38=0,"",(BC38-BC39)/BE38) | BH39: =IF(BE39=0,"",IF(BE39>BD39,"🚫",IF(INT(BE39/AX39<1),"👍",INT(BE39/AX39)&"x"))) | BI39: =IF(BD38=0,0,IF(OR(BE38=0,BF38="V"),BI38-1,IF(OR(AU$11="BRADESCO",AU$11="BB"),BI38-ROUNDDOWN(BE38/(BD38/BI38),0)-1,ROUNDUP((BD38-BE38+BJ38-(BD38/BI38))/(BC38-AW39-AR39-AS39),0)+1))) -> 365 | BJ39: =BD38*$BK38 -> 658.01916 | BK39: =IF(BD38>0,BK38,0) -> 0.0017
A40: =IF(INT(F40)>0,A39,0) -> 25 | B40: =IF(F40>0.1,B39,0) -> 75 | C40: =DATE(YEAR(C39),MONTH(C39)+1,1) -> 46813 | D40: =IFERROR(G40/M39,0) -> 0.0027472527 | E40: =E39+1 -> 26 | F40: =IF(OR(M39<1,N39>M39),0,(M39-N39)*IF(D$11<>"BB",$E$7,(1+$D$7)^(AK39/365)-1)) -> 3230.6684 | G40: =IF(R40=0,0,IF(M39<1,0,IF(AND(AND(((M39-N39)/R40)<G39,O39<>"V"),D$11<>"BRADESCO"),G39, (M39-N39)/R40))) -> 1062.2738 | H40: =IF(OR(G40=0,L40<1),"",IF(G40/L40>90%,"🛩",IF(G40/L40>70%,"🏎",IF(G40/L40>50%,"🚙",IF(G40/L40>30%,"🛵",IF(G40/L40>15%,"🐢","⚓️")))))) -> 🐢 | I40: =IFERROR(IF((G40+N40-S40)/L40<0,"🔙",IF((G40+N40-S40)/L40<10%,"🥾",IF((G40+N40-S40)/L40<20%,"🛴",IF((G40+N40-S40)/L40<50%,"🚴‍♂️",IF((G40+N40-S40)/L40<75%,"🚖","🚁"))))),"") -> 🥾 | J40: =G40+N40-S40 -> 404.93876 | K40: =IFERROR(J40/(L40+N40),0) -> 0.092179396 | L40: =G40+F40+A40+B40 -> 4392.9422 | M40: =IF(R40=0,0,MAX(0,M39-G40+S40-N39)) -> 386262.71 | O40: =IF(AND(N40<>"",N40<R40),"V","") | P40: =IF(N39=0,"",(L39-L40)/N39) | Q40: =IF(N40=0,"",IF(N40>M40,"🚫",IF(INT(N40/G40<1),"👍",INT(N40/G40)&"x"))) | R40: =IF(M39=0,0,IF(OR(N39=0,O39="V"),R39-1,IF(OR(D$11="BRADESCO",D$11="BB"),R39-ROUNDDOWN(N39/(M39/R39),0)-1,ROUNDUP((M39-N39+S39-(M39/R39))/(L39-F40-A40-B40),0)+1))) -> 364 | S40: =M39*$T40 -> 657.335 | T40: =IF(M39>0,T39,0) -> 0.0017 | AA40: =-(L40+N40) -> -4392.9422 | AD40: negociação ou distribuição do conteúdo, total ou parcial, desta | AH40: =ROUNDUP(E40/120,0) -> 1 | AI40: =ROUNDUP(E40/36,0) -> 1 | AJ40: =ROUNDUP(E40/12,0) -> 3 | AK40: =DAY(DATE(YEAR(C40),MONTH(C40)+1,1)-1) -> 31 | AR40: =IF(INT(AW40)>0,AR39,0) -> 25 | AS40: =IF(AW40>0.1,AS39,0) -> 75 | AT40: =DATE(YEAR(AT39),MONTH(AT39)+1,1) -> 46813 | AU40: =IFERROR(AX40/BD39,0) -> 0.0027472527 | AV40: =AV39+1 -> 26 | AW40: =IF(OR(BD39<1,BE39>BD39),0,(BD39-BE39)*IF(AU$11<>"BB",$E$7,(1+$D$7)^(BY39/365)-1)) -> 3230.6684 | AX40: =IF(BI40=0,0,IF(BD39<1,0,IF(AND(AND(((BD39-BE39)/BI40)<AX39,BF39<>"V"),AU$11<>"BRADESCO"),AX39, (BD39-BE39)/BI40))) -> 1062.2738 | AY40: =IF(OR(AX40=0,BC40<1),"",IF(AX40/BC40>90%,"🛩",IF(AX40/BC40>70%,"🏎",IF(AX40/BC40>50%,"🚙",IF(AX40/BC40>30%,"🛵",IF(AX40/BC40>15%,"🐢","⚓️")))))) -> 🐢 | AZ40: =IFERROR(IF((AX40+BE40-BJ40)/BC40<0,"🔙",IF((AX40+BE40-BJ40)/BC40<10%,"🥾",IF((AX40+BE40-BJ40)/BC40<20%,"🛴",IF((AX40+BE40-BJ40)/BC40<50%,"🚴‍♂️",IF((AX40+BE40-BJ40)/BC40<75%,"🚖","🚁"))))),"") -> 🥾 | BA40: =AX40+BE40-BJ40 -> 404.93876 | BB40: =IFERROR(BA40/(BC40+BE40),0) -> 0.092179396 | BC40: =AX40+AW40+AR40+AS40 -> 4392.9422 | BD40: =IF(BI40=0,0,MAX(0,BD39-AX40+BJ40-BE39)) -> 386262.71 | BF40: =IF(AND(BE40<>"",BE40<BI40),"V","") | BG40: =IF(BE39=0,"",(BC39-BC40)/BE39) | BH40: =IF(BE40=0,"",IF(BE40>BD40,"🚫",IF(INT(BE40/AX40<1),"👍",INT(BE40/AX40)&"x"))) | BI40: =IF(BD39=0,0,IF(OR(BE39=0,BF39="V"),BI39-1,IF(OR(AU$11="BRADESCO",AU$11="BB"),BI39-ROUNDDOWN(BE39/(BD39/BI39),0)-1,ROUNDUP((BD39-BE39+BJ39-(BD39/BI39))/(BC39-AW40-AR40-AS40),0)+1))) -> 364 | BJ40: =BD39*$BK39 -> 657.335 | BK40: =IF(BD39>0,BK39,0) -> 0.0017
A41: =IF(INT(F41)>0,A40,0) -> 25 | B41: =IF(F41>0.1,B40,0) -> 75 | C41: =DATE(YEAR(C40),MONTH(C40)+1,1) -> 46844 | D41: =IFERROR(G41/M40,0) -> 0.0027548209 | E41: =E40+1 -> 27 | F41: =IF(OR(M40<1,N40>M40),0,(M40-N40)*IF(D$11<>"BB",$E$7,(1+$D$7)^(AK40/365)-1)) -> 3227.2851 | G41: =IF(R41=0,0,IF(M40<1,0,IF(AND(AND(((M40-N40)/R41)<G40,O40<>"V"),D$11<>"BRADESCO"),G40, (M40-N40)/R41))) -> 1064.0846 | H41: =IF(OR(G41=0,L41<1),"",IF(G41/L41>90%,"🛩",IF(G41/L41>70%,"🏎",IF(G41/L41>50%,"🚙",IF(G41/L41>30%,"🛵",IF(G41/L41>15%,"🐢","⚓️")))))) -> 🐢 | I41: =IFERROR(IF((G41+N41-S41)/L41<0,"🔙",IF((G41+N41-S41)/L41<10%,"🥾",IF((G41+N41-S41)/L41<20%,"🛴",IF((G41+N41-S41)/L41<50%,"🚴‍♂️",IF((G41+N41-S41)/L41<75%,"🚖","🚁"))))),"") -> 🥾 | J41: =G41+N41-S41 -> 407.43799 | K41: =IFERROR(J41/(L41+N41),0) -> 0.092781529 | L41: =G41+F41+A41+B41 -> 4391.3697 | M41: =IF(R41=0,0,MAX(0,M40-G41+S41-N40)) -> 385855.27 | O41: =IF(AND(N41<>"",N41<R41),"V","") | P41: =IF(N40=0,"",(L40-L41)/N40) | Q41: =IF(N41=0,"",IF(N41>M41,"🚫",IF(INT(N41/G41<1),"👍",INT(N41/G41)&"x"))) | R41: =IF(M40=0,0,IF(OR(N40=0,O40="V"),R40-1,IF(OR(D$11="BRADESCO",D$11="BB"),R40-ROUNDDOWN(N40/(M40/R40),0)-1,ROUNDUP((M40-N40+S40-(M40/R40))/(L40-F41-A41-B41),0)+1))) -> 363 | S41: =M40*$T41 -> 656.64661 | T41: =IF(M40>0,T40,0) -> 0.0017 | AA41: =-(L41+N41) -> -4391.3697 | AD41: planilha sem o consentimento expresso e por escrito do proprietário, | AH41: =ROUNDUP(E41/120,0) -> 1 | AI41: =ROUNDUP(E41/36,0) -> 1 | AJ41: =ROUNDUP(E41/12,0) -> 3 | AK41: =DAY(DATE(YEAR(C41),MONTH(C41)+1,1)-1) -> 30 | AR41: =IF(INT(AW41)>0,AR40,0) -> 25 | AS41: =IF(AW41>0.1,AS40,0) -> 75 | AT41: =DATE(YEAR(AT40),MONTH(AT40)+1,1) -> 46844 | AU41: =IFERROR(AX41/BD40,0) -> 0.0027548209 | AV41: =AV40+1 -> 27 | AW41: =IF(OR(BD40<1,BE40>BD40),0,(BD40-BE40)*IF(AU$11<>"BB",$E$7,(1+$D$7)^(BY40/365)-1)) -> 3227.2851 | AX41: =IF(BI41=0,0,IF(BD40<1,0,IF(AND(AND(((BD40-BE40)/BI41)<AX40,BF40<>"V"),AU$11<>"BRADESCO"),AX40, (BD40-BE40)/BI41))) -> 1064.0846 | AY41: =IF(OR(AX41=0,BC41<1),"",IF(AX41/BC41>90%,"🛩",IF(AX41/BC41>70%,"🏎",IF(AX41/BC41>50%,"🚙",IF(AX41/BC41>30%,"🛵",IF(AX41/BC41>15%,"🐢","⚓️")))))) -> 🐢 | AZ41: =IFERROR(IF((AX41+BE41-BJ41)/BC41<0,"🔙",IF((AX41+BE41-BJ41)/BC41<10%,"🥾",IF((AX41+BE41-BJ41)/BC41<20%,"🛴",IF((AX41+BE41-BJ41)/BC41<50%,"🚴‍♂️",IF((AX41+BE41-BJ41)/BC41<75%,"🚖","🚁"))))),"") -> 🥾 | BA41: =AX41+BE41-BJ41 -> 407.43799 | BB41: =IFERROR(BA41/(BC41+BE41),0) -> 0.092781529 | BC41: =AX41+AW41+AR41+AS41 -> 4391.3697 | BD41: =IF(BI41=0,0,MAX(0,BD40-AX41+BJ41-BE40)) -> 385855.27 | BF41: =IF(AND(BE41<>"",BE41<BI41),"V","") | BG41: =IF(BE40=0,"",(BC40-BC41)/BE40) | BH41: =IF(BE41=0,"",IF(BE41>BD41,"🚫",IF(INT(BE41/AX41<1),"👍",INT(BE41/AX41)&"x"))) | BI41: =IF(BD40=0,0,IF(OR(BE40=0,BF40="V"),BI40-1,IF(OR(AU$11="BRADESCO",AU$11="BB"),BI40-ROUNDDOWN(BE40/(BD40/BI40),0)-1,ROUNDUP((BD40-BE40+BJ40-(BD40/BI40))/(BC40-AW41-AR41-AS41),0)+1))) -> 363 | BJ41: =BD40*$BK40 -> 656.64661 | BK41: =IF(BD40>0,BK40,0) -> 0.0017
A42: =IF(INT(F42)>0,A41,0) -> 25 | B42: =IF(F42>0.1,B41,0) -> 75 | C42: =DATE(YEAR(C41),MONTH(C41)+1,1) -> 46874 | D42: =IFERROR(G42/M41,0) -> 0.0027624309 | E42: =E41+1 -> 28 | F42: =IF(OR(M41<1,N41>M41),0,(M41-N41)*IF(D$11<>"BB",$E$7,(1+$D$7)^(AK41/365)-1)) -> 3223.8809 | G42: =IF(R42=0,0,IF(M41<1,0,IF(AND(AND(((M41-N41)/R42)<G41,O41<>"V"),D$11<>"BRADESCO"),G41, (M41-N41)/R42))) -> 1065.8985 | H42: =IF(OR(G42=0,L42<1),"",IF(G42/L42>90%,"🛩",IF(G42/L42>70%,"🏎",IF(G42/L42>50%,"🚙",IF(G42/L42>30%,"🛵",IF(G42/L42>15%,"🐢","⚓️")))))) -> 🐢 | I42: =IFERROR(IF((G42+N42-S42)/L42<0,"🔙",IF((G42+N42-S42)/L42<10%,"🥾",IF((G42+N42-S42)/L42<20%,"🛴",IF((G42+N42-S42)/L42<50%,"🚴‍♂️",IF((G42+N42-S42)/L42<75%,"🚖","🚁"))))),"") -> 🥾 | J42: =G42+N42-S42 -> 409.94458 | K42: =IFERROR(J42/(L42+N42),0) -> 0.093386146 | L42: =G42+F42+A42+B42 -> 4389.7794 | M42: =IF(R42=0,0,MAX(0,M41-G42+S42-N41)) -> 385445.33 | O42: =IF(AND(N42<>"",N42<R42),"V","") | P42: =IF(N41=0,"",(L41-L42)/N41) | Q42: =IF(N42=0,"",IF(N42>M42,"🚫",IF(INT(N42/G42<1),"👍",INT(N42/G42)&"x"))) | R42: =IF(M41=0,0,IF(OR(N41=0,O41="V"),R41-1,IF(OR(D$11="BRADESCO",D$11="BB"),R41-ROUNDDOWN(N41/(M41/R41),0)-1,ROUNDUP((M41-N41+S41-(M41/R41))/(L41-F42-A42-B42),0)+1))) -> 362 | S42: =M41*$T42 -> 655.95396 | T42: =IF(M41>0,T41,0) -> 0.0017 | AA42: =-(L42+N42) -> -4389.7794 | AD42: sujeitando-se o infrator às penalidades cíveis e criminais cabíveis. | AH42: =ROUNDUP(E42/120,0) -> 1 | AI42: =ROUNDUP(E42/36,0) -> 1 | AJ42: =ROUNDUP(E42/12,0) -> 3 | AK42: =DAY(DATE(YEAR(C42),MONTH(C42)+1,1)-1) -> 31 | AR42: =IF(INT(AW42)>0,AR41,0) -> 25 | AS42: =IF(AW42>0.1,AS41,0) -> 75 | AT42: =DATE(YEAR(AT41),MONTH(AT41)+1,1) -> 46874 | AU42: =IFERROR(AX42/BD41,0) -> 0.0027624309 | AV42: =AV41+1 -> 28 | AW42: =IF(OR(BD41<1,BE41>BD41),0,(BD41-BE41)*IF(AU$11<>"BB",$E$7,(1+$D$7)^(BY41/365)-1)) -> 3223.8809 | AX42: =IF(BI42=0,0,IF(BD41<1,0,IF(AND(AND(((BD41-BE41)/BI42)<AX41,BF41<>"V"),AU$11<>"BRADESCO"),AX41, (BD41-BE41)/BI42))) -> 1065.8985 | AY42: =IF(OR(AX42=0,BC42<1),"",IF(AX42/BC42>90%,"🛩",IF(AX42/BC42>70%,"🏎",IF(AX42/BC42>50%,"🚙",IF(AX42/BC42>30%,"🛵",IF(AX42/BC42>15%,"🐢","⚓️")))))) -> 🐢 | AZ42: =IFERROR(IF((AX42+BE42-BJ42)/BC42<0,"🔙",IF((AX42+BE42-BJ42)/BC42<10%,"🥾",IF((AX42+BE42-BJ42)/BC42<20%,"🛴",IF((AX42+BE42-BJ42)/BC42<50%,"🚴‍♂️",IF((AX42+BE42-BJ42)/BC42<75%,"🚖","🚁"))))),"") -> 🥾 | BA42: =AX42+BE42-BJ42 -> 409.94458 | BB42: =IFERROR(BA42/(BC42+BE42),0) -> 0.093386146 | BC42: =AX42+AW42+AR42+AS42 -> 4389.7794 | BD42: =IF(BI42=0,0,MAX(0,BD41-AX42+BJ42-BE41)) -> 385445.33 | BF42: =IF(AND(BE42<>"",BE42<BI42),"V","") | BG42: =IF(BE41=0,"",(BC41-BC42)/BE41) | BH42: =IF(BE42=0,"",IF(BE42>BD42,"🚫",IF(INT(BE42/AX42<1),"👍",INT(BE42/AX42)&"x"))) | BI42: =IF(BD41=0,0,IF(OR(BE41=0,BF41="V"),BI41-1,IF(OR(AU$11="BRADESCO",AU$11="BB"),BI41-ROUNDDOWN(BE41/(BD41/BI41),0)-1,ROUNDUP((BD41-BE41+BJ41-(BD41/BI41))/(BC41-AW42-AR42-AS42),0)+1))) -> 362 | BJ42: =BD41*$BK41 -> 655.95396 | BK42: =IF(BD41>0,BK41,0) -> 0.0017
A43: =IF(INT(F43)>0,A42,0) -> 25 | B43: =IF(F43>0.1,B42,0) -> 75 | C43: =DATE(YEAR(C42),MONTH(C42)+1,1) -> 46905 | D43: =IFERROR(G43/M42,0) -> 0.0027700831 | E43: =E42+1 -> 29 | F43: =IF(OR(M42<1,N42>M42),0,(M42-N42)*IF(D$11<>"BB",$E$7,(1+$D$7)^(AK42/365)-1)) -> 3220.4557 | G43: =IF(R43=0,0,IF(M42<1,0,IF(AND(AND(((M42-N42)/R43)<G42,O42<>"V"),D$11<>"BRADESCO"),G42, (M42-N42)/R43))) -> 1067.7156 | H43: =IF(OR(G43=0,L43<1),"",IF(G43/L43>90%,"🛩",IF(G43/L43>70%,"🏎",IF(G43/L43>50%,"🚙",IF(G43/L43>30%,"🛵",IF(G43/L43>15%,"🐢","⚓️")))))) -> 🐢 | I43: =IFERROR(IF((G43+N43-S43)/L43<0,"🔙",IF((G43+N43-S43)/L43<10%,"🥾",IF((G43+N43-S43)/L43<20%,"🛴",IF((G43+N43-S43)/L43<50%,"🚴‍♂️",IF((G43+N43-S43)/L43<75%,"🚖","🚁"))))),"") -> 🥾 | J43: =G43+N43-S43 -> 412.45853 | K43: =IFERROR(J43/(L43+N43),0) -> 0.093993261 | L43: =G43+F43+A43+B43 -> 4388.1713 | M43: =IF(R43=0,0,MAX(0,M42-G43+S43-N42)) -> 385032.87 | O43: =IF(AND(N43<>"",N43<R43),"V","") | P43: =IF(N42=0,"",(L42-L43)/N42) | Q43: =IF(N43=0,"",IF(N43>M43,"🚫",IF(INT(N43/G43<1),"👍",INT(N43/G43)&"x"))) | R43: =IF(M42=0,0,IF(OR(N42=0,O42="V"),R42-1,IF(OR(D$11="BRADESCO",D$11="BB"),R42-ROUNDDOWN(N42/(M42/R42),0)-1,ROUNDUP((M42-N42+S42-(M42/R42))/(L42-F43-A43-B43),0)+1))) -> 361 | S43: =M42*$T43 -> 655.25705 | T43: =IF(M42>0,T42,0) -> 0.0017 | AA43: =-(L43+N43) -> -4388.1713 | AH43: =ROUNDUP(E43/120,0) -> 1 | AI43: =ROUNDUP(E43/36,0) -> 1 | AJ43: =ROUNDUP(E43/12,0) -> 3 | AK43: =DAY(DATE(YEAR(C43),MONTH(C43)+1,1)-1) -> 30 | AR43: =IF(INT(AW43)>0,AR42,0) -> 25 | AS43: =IF(AW43>0.1,AS42,0) -> 75 | AT43: =DATE(YEAR(AT42),MONTH(AT42)+1,1) -> 46905 | AU43: =IFERROR(AX43/BD42,0) -> 0.0027700831 | AV43: =AV42+1 -> 29 | AW43: =IF(OR(BD42<1,BE42>BD42),0,(BD42-BE42)*IF(AU$11<>"BB",$E$7,(1+$D$7)^(BY42/365)-1)) -> 3220.4557 | AX43: =IF(BI43=0,0,IF(BD42<1,0,IF(AND(AND(((BD42-BE42)/BI43)<AX42,BF42<>"V"),AU$11<>"BRADESCO"),AX42, (BD42-BE42)/BI43))) -> 1067.7156 | AY43: =IF(OR(AX43=0,BC43<1),"",IF(AX43/BC43>90%,"🛩",IF(AX43/BC43>70%,"🏎",IF(AX43/BC43>50%,"🚙",IF(AX43/BC43>30%,"🛵",IF(AX43/BC43>15%,"🐢","⚓️")))))) -> 🐢 | AZ43: =IFERROR(IF((AX43+BE43-BJ43)/BC43<0,"🔙",IF((AX43+BE43-BJ43)/BC43<10%,"🥾",IF((AX43+BE43-BJ43)/BC43<20%,"🛴",IF((AX43+BE43-BJ43)/BC43<50%,"🚴‍♂️",IF((AX43+BE43-BJ43)/BC43<75%,"🚖","🚁"))))),"") -> 🥾 | BA43: =AX43+BE43-BJ43 -> 412.45853 | BB43: =IFERROR(BA43/(BC43+BE43),0) -> 0.093993261 | BC43: =AX43+AW43+AR43+AS43 -> 4388.1713 | BD43: =IF(BI43=0,0,MAX(0,BD42-AX43+BJ43-BE42)) -> 385032.87 | BF43: =IF(AND(BE43<>"",BE43<BI43),"V","") | BG43: =IF(BE42=0,"",(BC42-BC43)/BE42) | BH43: =IF(BE43=0,"",IF(BE43>BD43,"🚫",IF(INT(BE43/AX43<1),"👍",INT(BE43/AX43)&"x"))) | BI43: =IF(BD42=0,0,IF(OR(BE42=0,BF42="V"),BI42-1,IF(OR(AU$11="BRADESCO",AU$11="BB"),BI42-ROUNDDOWN(BE42/(BD42/BI42),0)-1,ROUNDUP((BD42-BE42+BJ42-(BD42/BI42))/(BC42-AW43-AR43-AS43),0)+1))) -> 361 | BJ43: =BD42*$BK42 -> 655.25705 | BK43: =IF(BD42>0,BK42,0) -> 0.0017
A44: =IF(INT(F44)>0,A43,0) -> 25 | B44: =IF(F44>0.1,B43,0) -> 75 | C44: =DATE(YEAR(C43),MONTH(C43)+1,1) -> 46935 | D44: =IFERROR(G44/M43,0) -> 0.0027777778 | E44: =E43+1 -> 30 | F44: =IF(OR(M43<1,N43>M43),0,(M43-N43)*IF(D$11<>"BB",$E$7,(1+$D$7)^(AK43/365)-1)) -> 3217.0096 | G44: =IF(R44=0,0,IF(M43<1,0,IF(AND(AND(((M43-N43)/R44)<G43,O43<>"V"),D$11<>"BRADESCO"),G43, (M43-N43)/R44))) -> 1069.5357 | H44: =IF(OR(G44=0,L44<1),"",IF(G44/L44>90%,"🛩",IF(G44/L44>70%,"🏎",IF(G44/L44>50%,"🚙",IF(G44/L44>30%,"🛵",IF(G44/L44>15%,"🐢","⚓️")))))) -> 🐢 | I44: =IFERROR(IF((G44+N44-S44)/L44<0,"🔙",IF((G44+N44-S44)/L44<10%,"🥾",IF((G44+N44-S44)/L44<20%,"🛴",IF((G44+N44-S44)/L44<50%,"🚴‍♂️",IF((G44+N44-S44)/L44<75%,"🚖","🚁"))))),"") -> 🥾 | J44: =G44+N44-S44 -> 414.97987 | K44: =IFERROR(J44/(L44+N44),0) -> 0.094602891 | L44: =G44+F44+A44+B44 -> 4386.5453 | M44: =IF(R44=0,0,MAX(0,M43-G44+S44-N43)) -> 384617.89 | O44: =IF(AND(N44<>"",N44<R44),"V","") | P44: =IF(N43=0,"",(L43-L44)/N43) | Q44: =IF(N44=0,"",IF(N44>M44,"🚫",IF(INT(N44/G44<1),"👍",INT(N44/G44)&"x"))) | R44: =IF(M43=0,0,IF(OR(N43=0,O43="V"),R43-1,IF(OR(D$11="BRADESCO",D$11="BB"),R43-ROUNDDOWN(N43/(M43/R43),0)-1,ROUNDUP((M43-N43+S43-(M43/R43))/(L43-F44-A44-B44),0)+1))) -> 360 | S44: =M43*$T44 -> 654.55588 | T44: =IF(M43>0,T43,0) -> 0.0017 | AA44: =-(L44+N44) -> -4386.5453 | AH44: =ROUNDUP(E44/120,0) -> 1 | AI44: =ROUNDUP(E44/36,0) -> 1 | AJ44: =ROUNDUP(E44/12,0) -> 3 | AK44: =DAY(DATE(YEAR(C44),MONTH(C44)+1,1)-1) -> 31 | AR44: =IF(INT(AW44)>0,AR43,0) -> 25 | AS44: =IF(AW44>0.1,AS43,0) -> 75 | AT44: =DATE(YEAR(AT43),MONTH(AT43)+1,1) -> 46935 | AU44: =IFERROR(AX44/BD43,0) -> 0.0027777778 | AV44: =AV43+1 -> 30 | AW44: =IF(OR(BD43<1,BE43>BD43),0,(BD43-BE43)*IF(AU$11<>"BB",$E$7,(1+$D$7)^(BY43/365)-1)) -> 3217.0096 | AX44: =IF(BI44=0,0,IF(BD43<1,0,IF(AND(AND(((BD43-BE43)/BI44)<AX43,BF43<>"V"),AU$11<>"BRADESCO"),AX43, (BD43-BE43)/BI44))) -> 1069.5357 | AY44: =IF(OR(AX44=0,BC44<1),"",IF(AX44/BC44>90%,"🛩",IF(AX44/BC44>70%,"🏎",IF(AX44/BC44>50%,"🚙",IF(AX44/BC44>30%,"🛵",IF(AX44/BC44>15%,"🐢","⚓️")))))) -> 🐢 | AZ44: =IFERROR(IF((AX44+BE44-BJ44)/BC44<0,"🔙",IF((AX44+BE44-BJ44)/BC44<10%,"🥾",IF((AX44+BE44-BJ44)/BC44<20%,"🛴",IF((AX44+BE44-BJ44)/BC44<50%,"🚴‍♂️",IF((AX44+BE44-BJ44)/BC44<75%,"🚖","🚁"))))),"") -> 🥾 | BA44: =AX44+BE44-BJ44 -> 414.97987 | BB44: =IFERROR(BA44/(BC44+BE44),0) -> 0.094602891 | BC44: =AX44+AW44+AR44+AS44 -> 4386.5453 | BD44: =IF(BI44=0,0,MAX(0,BD43-AX44+BJ44-BE43)) -> 384617.89 | BF44: =IF(AND(BE44<>"",BE44<BI44),"V","") | BG44: =IF(BE43=0,"",(BC43-BC44)/BE43) | BH44: =IF(BE44=0,"",IF(BE44>BD44,"🚫",IF(INT(BE44/AX44<1),"👍",INT(BE44/AX44)&"x"))) | BI44: =IF(BD43=0,0,IF(OR(BE43=0,BF43="V"),BI43-1,IF(OR(AU$11="BRADESCO",AU$11="BB"),BI43-ROUNDDOWN(BE43/(BD43/BI43),0)-1,ROUNDUP((BD43-BE43+BJ43-(BD43/BI43))/(BC43-AW44-AR44-AS44),0)+1))) -> 360 | BJ44: =BD43*$BK43 -> 654.55588 | BK44: =IF(BD43>0,BK43,0) -> 0.0017
A45: =IF(INT(F45)>0,A44,0) -> 25 | B45: =IF(F45>0.1,B44,0) -> 75 | C45: =DATE(YEAR(C44),MONTH(C44)+1,1) -> 46966 | D45: =IFERROR(G45/M44,0) -> 0.0027855153 | E45: =E44+1 -> 31 | F45: =IF(OR(M44<1,N44>M44),0,(M44-N44)*IF(D$11<>"BB",$E$7,(1+$D$7)^(AK44/365)-1)) -> 3213.5423 | G45: =IF(R45=0,0,IF(M44<1,0,IF(AND(AND(((M44-N44)/R45)<G44,O44<>"V"),D$11<>"BRADESCO"),G44, (M44-N44)/R45))) -> 1071.359 | H45: =IF(OR(G45=0,L45<1),"",IF(G45/L45>90%,"🛩",IF(G45/L45>70%,"🏎",IF(G45/L45>50%,"🚙",IF(G45/L45>30%,"🛵",IF(G45/L45>15%,"🐢","⚓️")))))) -> 🐢 | I45: =IFERROR(IF((G45+N45-S45)/L45<0,"🔙",IF((G45+N45-S45)/L45<10%,"🥾",IF((G45+N45-S45)/L45<20%,"🛴",IF((G45+N45-S45)/L45<50%,"🚴‍♂️",IF((G45+N45-S45)/L45<75%,"🚖","🚁"))))),"") -> 🥾 | J45: =G45+N45-S45 -> 417.50861 | K45: =IFERROR(J45/(L45+N45),0) -> 0.095215052 | L45: =G45+F45+A45+B45 -> 4384.9014 | M45: =IF(R45=0,0,MAX(0,M44-G45+S45-N44)) -> 384200.38 | O45: =IF(AND(N45<>"",N45<R45),"V","") | P45: =IF(N44=0,"",(L44-L45)/N44) | Q45: =IF(N45=0,"",IF(N45>M45,"🚫",IF(INT(N45/G45<1),"👍",INT(N45/G45)&"x"))) | R45: =IF(M44=0,0,IF(OR(N44=0,O44="V"),R44-1,IF(OR(D$11="BRADESCO",D$11="BB"),R44-ROUNDDOWN(N44/(M44/R44),0)-1,ROUNDUP((M44-N44+S44-(M44/R44))/(L44-F45-A45-B45),0)+1))) -> 359 | S45: =M44*$T45 -> 653.85041 | T45: =IF(M44>0,T44,0) -> 0.0017 | AA45: =-(L45+N45) -> -4384.9014 | AH45: =ROUNDUP(E45/120,0) -> 1 | AI45: =ROUNDUP(E45/36,0) -> 1 | AJ45: =ROUNDUP(E45/12,0) -> 3 | AK45: =DAY(DATE(YEAR(C45),MONTH(C45)+1,1)-1) -> 31 | AR45: =IF(INT(AW45)>0,AR44,0) -> 25 | AS45: =IF(AW45>0.1,AS44,0) -> 75 | AT45: =DATE(YEAR(AT44),MONTH(AT44)+1,1) -> 46966 | AU45: =IFERROR(AX45/BD44,0) -> 0.0027855153 | AV45: =AV44+1 -> 31 | AW45: =IF(OR(BD44<1,BE44>BD44),0,(BD44-BE44)*IF(AU$11<>"BB",$E$7,(1+$D$7)^(BY44/365)-1)) -> 3213.5423 | AX45: =IF(BI45=0,0,IF(BD44<1,0,IF(AND(AND(((BD44-BE44)/BI45)<AX44,BF44<>"V"),AU$11<>"BRADESCO"),AX44, (BD44-BE44)/BI45))) -> 1071.359 | AY45: =IF(OR(AX45=0,BC45<1),"",IF(AX45/BC45>90%,"🛩",IF(AX45/BC45>70%,"🏎",IF(AX45/BC45>50%,"🚙",IF(AX45/BC45>30%,"🛵",IF(AX45/BC45>15%,"🐢","⚓️")))))) -> 🐢 | AZ45: =IFERROR(IF((AX45+BE45-BJ45)/BC45<0,"🔙",IF((AX45+BE45-BJ45)/BC45<10%,"🥾",IF((AX45+BE45-BJ45)/BC45<20%,"🛴",IF((AX45+BE45-BJ45)/BC45<50%,"🚴‍♂️",IF((AX45+BE45-BJ45)/BC45<75%,"🚖","🚁"))))),"") -> 🥾 | BA45: =AX45+BE45-BJ45 -> 417.50861 | BB45: =IFERROR(BA45/(BC45+BE45),0) -> 0.095215052 | BC45: =AX45+AW45+AR45+AS45 -> 4384.9014 | BD45: =IF(BI45=0,0,MAX(0,BD44-AX45+BJ45-BE44)) -> 384200.38 | BF45: =IF(AND(BE45<>"",BE45<BI45),"V","") | BG45: =IF(BE44=0,"",(BC44-BC45)/BE44) | BH45: =IF(BE45=0,"",IF(BE45>BD45,"🚫",IF(INT(BE45/AX45<1),"👍",INT(BE45/AX45)&"x"))) | BI45: =IF(BD44=0,0,IF(OR(BE44=0,BF44="V"),BI44-1,IF(OR(AU$11="BRADESCO",AU$11="BB"),BI44-ROUNDDOWN(BE44/(BD44/BI44),0)-1,ROUNDUP((BD44-BE44+BJ44-(BD44/BI44))/(BC44-AW45-AR45-AS45),0)+1))) -> 359 | BJ45: =BD44*$BK44 -> 653.85041 | BK45: =IF(BD44>0,BK44,0) -> 0.0017
A46: =IF(INT(F46)>0,A45,0) -> 25 | B46: =IF(F46>0.1,B45,0) -> 75 | C46: =DATE(YEAR(C45),MONTH(C45)+1,1) -> 46997 | D46: =IFERROR(G46/M45,0) -> 0.0027932961 | E46: =E45+1 -> 32 | F46: =IF(OR(M45<1,N45>M45),0,(M45-N45)*IF(D$11<>"BB",$E$7,(1+$D$7)^(AK45/365)-1)) -> 3210.054 | G46: =IF(R46=0,0,IF(M45<1,0,IF(AND(AND(((M45-N45)/R46)<G45,O45<>"V"),D$11<>"BRADESCO"),G45, (M45-N45)/R46))) -> 1073.1854 | H46: =IF(OR(G46=0,L46<1),"",IF(G46/L46>90%,"🛩",IF(G46/L46>70%,"🏎",IF(G46/L46>50%,"🚙",IF(G46/L46>30%,"🛵",IF(G46/L46>15%,"🐢","⚓️")))))) -> 🐢 | I46: =IFERROR(IF((G46+N46-S46)/L46<0,"🔙",IF((G46+N46-S46)/L46<10%,"🥾",IF((G46+N46-S46)/L46<20%,"🛴",IF((G46+N46-S46)/L46<50%,"🚴‍♂️",IF((G46+N46-S46)/L46<75%,"🚖","🚁"))))),"") -> 🥾 | J46: =G46+N46-S46 -> 420.04477 | K46: =IFERROR(J46/(L46+N46),0) -> 0.095829758 | L46: =G46+F46+A46+B46 -> 4383.2394 | M46: =IF(R46=0,0,MAX(0,M45-G46+S46-N45)) -> 383780.33 | O46: =IF(AND(N46<>"",N46<R46),"V","") | P46: =IF(N45=0,"",(L45-L46)/N45) | Q46: =IF(N46=0,"",IF(N46>M46,"🚫",IF(INT(N46/G46<1),"👍",INT(N46/G46)&"x"))) | R46: =IF(M45=0,0,IF(OR(N45=0,O45="V"),R45-1,IF(OR(D$11="BRADESCO",D$11="BB"),R45-ROUNDDOWN(N45/(M45/R45),0)-1,ROUNDUP((M45-N45+S45-(M45/R45))/(L45-F46-A46-B46),0)+1))) -> 358 | S46: =M45*$T46 -> 653.14064 | T46: =IF(M45>0,T45,0) -> 0.0017 | AA46: =-(L46+N46) -> -4383.2394 | AH46: =ROUNDUP(E46/120,0) -> 1 | AI46: =ROUNDUP(E46/36,0) -> 1 | AJ46: =ROUNDUP(E46/12,0) -> 3 | AK46: =DAY(DATE(YEAR(C46),MONTH(C46)+1,1)-1) -> 30 | AR46: =IF(INT(AW46)>0,AR45,0) -> 25 | AS46: =IF(AW46>0.1,AS45,0) -> 75 | AT46: =DATE(YEAR(AT45),MONTH(AT45)+1,1) -> 46997 | AU46: =IFERROR(AX46/BD45,0) -> 0.0027932961 | AV46: =AV45+1 -> 32 | AW46: =IF(OR(BD45<1,BE45>BD45),0,(BD45-BE45)*IF(AU$11<>"BB",$E$7,(1+$D$7)^(BY45/365)-1)) -> 3210.054 | AX46: =IF(BI46=0,0,IF(BD45<1,0,IF(AND(AND(((BD45-BE45)/BI46)<AX45,BF45<>"V"),AU$11<>"BRADESCO"),AX45, (BD45-BE45)/BI46))) -> 1073.1854 | AY46: =IF(OR(AX46=0,BC46<1),"",IF(AX46/BC46>90%,"🛩",IF(AX46/BC46>70%,"🏎",IF(AX46/BC46>50%,"🚙",IF(AX46/BC46>30%,"🛵",IF(AX46/BC46>15%,"🐢","⚓️")))))) -> 🐢 | AZ46: =IFERROR(IF((AX46+BE46-BJ46)/BC46<0,"🔙",IF((AX46+BE46-BJ46)/BC46<10%,"🥾",IF((AX46+BE46-BJ46)/BC46<20%,"🛴",IF((AX46+BE46-BJ46)/BC46<50%,"🚴‍♂️",IF((AX46+BE46-BJ46)/BC46<75%,"🚖","🚁"))))),"") -> 🥾 | BA46: =AX46+BE46-BJ46 -> 420.04477 | BB46: =IFERROR(BA46/(BC46+BE46),0) -> 0.095829758 | BC46: =AX46+AW46+AR46+AS46 -> 4383.2394 | BD46: =IF(BI46=0,0,MAX(0,BD45-AX46+BJ46-BE45)) -> 383780.33 | BF46: =IF(AND(BE46<>"",BE46<BI46),"V","") | BG46: =IF(BE45=0,"",(BC45-BC46)/BE45) | BH46: =IF(BE46=0,"",IF(BE46>BD46,"🚫",IF(INT(BE46/AX46<1),"👍",INT(BE46/AX46)&"x"))) | BI46: =IF(BD45=0,0,IF(OR(BE45=0,BF45="V"),BI45-1,IF(OR(AU$11="BRADESCO",AU$11="BB"),BI45-ROUNDDOWN(BE45/(BD45/BI45),0)-1,ROUNDUP((BD45-BE45+BJ45-(BD45/BI45))/(BC45-AW46-AR46-AS46),0)+1))) -> 358 | BJ46: =BD45*$BK45 -> 653.14064 | BK46: =IF(BD45>0,BK45,0) -> 0.0017
A47: =IF(INT(F47)>0,A46,0) -> 25 | B47: =IF(F47>0.1,B46,0) -> 75 | C47: =DATE(YEAR(C46),MONTH(C46)+1,1) -> 47027 | D47: =IFERROR(G47/M46,0) -> 0.0028011204 | E47: =E46+1 -> 33 | F47: =IF(OR(M46<1,N46>M46),0,(M46-N46)*IF(D$11<>"BB",$E$7,(1+$D$7)^(AK46/365)-1)) -> 3206.5444 | G47: =IF(R47=0,0,IF(M46<1,0,IF(AND(AND(((M46-N46)/R47)<G46,O46<>"V"),D$11<>"BRADESCO"),G46, (M46-N46)/R47))) -> 1075.0149 | H47: =IF(OR(G47=0,L47<1),"",IF(G47/L47>90%,"🛩",IF(G47/L47>70%,"🏎",IF(G47/L47>50%,"🚙",IF(G47/L47>30%,"🛵",IF(G47/L47>15%,"🐢","⚓️")))))) -> 🐢 | I47: =IFERROR(IF((G47+N47-S47)/L47<0,"🔙",IF((G47+N47-S47)/L47<10%,"🥾",IF((G47+N47-S47)/L47<20%,"🛴",IF((G47+N47-S47)/L47<50%,"🚴‍♂️",IF((G47+N47-S47)/L47<75%,"🚖","🚁"))))),"") -> 🥾 | J47: =G47+N47-S47 -> 422.58837 | K47: =IFERROR(J47/(L47+N47),0) -> 0.096447026 | L47: =G47+F47+A47+B47 -> 4381.5594 | M47: =IF(R47=0,0,MAX(0,M46-G47+S47-N46)) -> 383357.75 | O47: =IF(AND(N47<>"",N47<R47),"V","") | P47: =IF(N46=0,"",(L46-L47)/N46) | Q47: =IF(N47=0,"",IF(N47>M47,"🚫",IF(INT(N47/G47<1),"👍",INT(N47/G47)&"x"))) | R47: =IF(M46=0,0,IF(OR(N46=0,O46="V"),R46-1,IF(OR(D$11="BRADESCO",D$11="BB"),R46-ROUNDDOWN(N46/(M46/R46),0)-1,ROUNDUP((M46-N46+S46-(M46/R46))/(L46-F47-A47-B47),0)+1))) -> 357 | S47: =M46*$T47 -> 652.42657 | T47: =IF(M46>0,T46,0) -> 0.0017 | AA47: =-(L47+N47) -> -4381.5594 | AH47: =ROUNDUP(E47/120,0) -> 1 | AI47: =ROUNDUP(E47/36,0) -> 1 | AJ47: =ROUNDUP(E47/12,0) -> 3 | AK47: =DAY(DATE(YEAR(C47),MONTH(C47)+1,1)-1) -> 31 | AR47: =IF(INT(AW47)>0,AR46,0) -> 25 | AS47: =IF(AW47>0.1,AS46,0) -> 75 | AT47: =DATE(YEAR(AT46),MONTH(AT46)+1,1) -> 47027 | AU47: =IFERROR(AX47/BD46,0) -> 0.0028011204 | AV47: =AV46+1 -> 33 | AW47: =IF(OR(BD46<1,BE46>BD46),0,(BD46-BE46)*IF(AU$11<>"BB",$E$7,(1+$D$7)^(BY46/365)-1)) -> 3206.5444 | AX47: =IF(BI47=0,0,IF(BD46<1,0,IF(AND(AND(((BD46-BE46)/BI47)<AX46,BF46<>"V"),AU$11<>"BRADESCO"),AX46, (BD46-BE46)/BI47))) -> 1075.0149 | AY47: =IF(OR(AX47=0,BC47<1),"",IF(AX47/BC47>90%,"🛩",IF(AX47/BC47>70%,"🏎",IF(AX47/BC47>50%,"🚙",IF(AX47/BC47>30%,"🛵",IF(AX47/BC47>15%,"🐢","⚓️")))))) -> 🐢 | AZ47: =IFERROR(IF((AX47+BE47-BJ47)/BC47<0,"🔙",IF((AX47+BE47-BJ47)/BC47<10%,"🥾",IF((AX47+BE47-BJ47)/BC47<20%,"🛴",IF((AX47+BE47-BJ47)/BC47<50%,"🚴‍♂️",IF((AX47+BE47-BJ47)/BC47<75%,"🚖","🚁"))))),"") -> 🥾 | BA47: =AX47+BE47-BJ47 -> 422.58837 | BB47: =IFERROR(BA47/(BC47+BE47),0) -> 0.096447026 | BC47: =AX47+AW47+AR47+AS47 -> 4381.5594 | BD47: =IF(BI47=0,0,MAX(0,BD46-AX47+BJ47-BE46)) -> 383357.75 | BF47: =IF(AND(BE47<>"",BE47<BI47),"V","") | BG47: =IF(BE46=0,"",(BC46-BC47)/BE46) | BH47: =IF(BE47=0,"",IF(BE47>BD47,"🚫",IF(INT(BE47/AX47<1),"👍",INT(BE47/AX47)&"x"))) | BI47: =IF(BD46=0,0,IF(OR(BE46=0,BF46="V"),BI46-1,IF(OR(AU$11="BRADESCO",AU$11="BB"),BI46-ROUNDDOWN(BE46/(BD46/BI46),0)-1,ROUNDUP((BD46-BE46+BJ46-(BD46/BI46))/(BC46-AW47-AR47-AS47),0)+1))) -> 357 | BJ47: =BD46*$BK46 -> 652.42657 | BK47: =IF(BD46>0,BK46,0) -> 0.0017
A48: =IF(INT(F48)>0,A47,0) -> 25 | B48: =IF(F48>0.1,B47,0) -> 75 | C48: =DATE(YEAR(C47),MONTH(C47)+1,1) -> 47058 | D48: =IFERROR(G48/M47,0) -> 0.0028089888 | E48: =E47+1 -> 34 | F48: =IF(OR(M47<1,N47>M47),0,(M47-N47)*IF(D$11<>"BB",$E$7,(1+$D$7)^(AK47/365)-1)) -> 3203.0137 | G48: =IF(R48=0,0,IF(M47<1,0,IF(AND(AND(((M47-N47)/R48)<G47,O47<>"V"),D$11<>"BRADESCO"),G47, (M47-N47)/R48))) -> 1076.8476 | H48: =IF(OR(G48=0,L48<1),"",IF(G48/L48>90%,"🛩",IF(G48/L48>70%,"🏎",IF(G48/L48>50%,"🚙",IF(G48/L48>30%,"🛵",IF(G48/L48>15%,"🐢","⚓️")))))) -> 🐢 | I48: =IFERROR(IF((G48+N48-S48)/L48<0,"🔙",IF((G48+N48-S48)/L48<10%,"🥾",IF((G48+N48-S48)/L48<20%,"🛴",IF((G48+N48-S48)/L48<50%,"🚴‍♂️",IF((G48+N48-S48)/L48<75%,"🚖","🚁"))))),"") -> 🥾 | J48: =G48+N48-S48 -> 425.13943 | K48: =IFERROR(J48/(L48+N48),0) -> 0.097066872 | L48: =G48+F48+A48+B48 -> 4379.8613 | M48: =IF(R48=0,0,MAX(0,M47-G48+S48-N47)) -> 382932.61 | O48: =IF(AND(N48<>"",N48<R48),"V","") | P48: =IF(N47=0,"",(L47-L48)/N47) | Q48: =IF(N48=0,"",IF(N48>M48,"🚫",IF(INT(N48/G48<1),"👍",INT(N48/G48)&"x"))) | R48: =IF(M47=0,0,IF(OR(N47=0,O47="V"),R47-1,IF(OR(D$11="BRADESCO",D$11="BB"),R47-ROUNDDOWN(N47/(M47/R47),0)-1,ROUNDUP((M47-N47+S47-(M47/R47))/(L47-F48-A48-B48),0)+1))) -> 356 | S48: =M47*$T48 -> 651.70817 | T48: =IF(M47>0,T47,0) -> 0.0017 | AA48: =-(L48+N48) -> -4379.8613 | AH48: =ROUNDUP(E48/120,0) -> 1 | AI48: =ROUNDUP(E48/36,0) -> 1 | AJ48: =ROUNDUP(E48/12,0) -> 3 | AK48: =DAY(DATE(YEAR(C48),MONTH(C48)+1,1)-1) -> 30 | AR48: =IF(INT(AW48)>0,AR47,0) -> 25 | AS48: =IF(AW48>0.1,AS47,0) -> 75 | AT48: =DATE(YEAR(AT47),MONTH(AT47)+1,1) -> 47058 | AU48: =IFERROR(AX48/BD47,0) -> 0.0028089888 | AV48: =AV47+1 -> 34 | AW48: =IF(OR(BD47<1,BE47>BD47),0,(BD47-BE47)*IF(AU$11<>"BB",$E$7,(1+$D$7)^(BY47/365)-1)) -> 3203.0137 | AX48: =IF(BI48=0,0,IF(BD47<1,0,IF(AND(AND(((BD47-BE47)/BI48)<AX47,BF47<>"V"),AU$11<>"BRADESCO"),AX47, (BD47-BE47)/BI48))) -> 1076.8476 | AY48: =IF(OR(AX48=0,BC48<1),"",IF(AX48/BC48>90%,"🛩",IF(AX48/BC48>70%,"🏎",IF(AX48/BC48>50%,"🚙",IF(AX48/BC48>30%,"🛵",IF(AX48/BC48>15%,"🐢","⚓️")))))) -> 🐢 | AZ48: =IFERROR(IF((AX48+BE48-BJ48)/BC48<0,"🔙",IF((AX48+BE48-BJ48)/BC48<10%,"🥾",IF((AX48+BE48-BJ48)/BC48<20%,"🛴",IF((AX48+BE48-BJ48)/BC48<50%,"🚴‍♂️",IF((AX48+BE48-BJ48)/BC48<75%,"🚖","🚁"))))),"") -> 🥾 | BA48: =AX48+BE48-BJ48 -> 425.13943 | BB48: =IFERROR(BA48/(BC48+BE48),0) -> 0.097066872 | BC48: =AX48+AW48+AR48+AS48 -> 4379.8613 | BD48: =IF(BI48=0,0,MAX(0,BD47-AX48+BJ48-BE47)) -> 382932.61 | BF48: =IF(AND(BE48<>"",BE48<BI48),"V","") | BG48: =IF(BE47=0,"",(BC47-BC48)/BE47) | BH48: =IF(BE48=0,"",IF(BE48>BD48,"🚫",IF(INT(BE48/AX48<1),"👍",INT(BE48/AX48)&"x"))) | BI48: =IF(BD47=0,0,IF(OR(BE47=0,BF47="V"),BI47-1,IF(OR(AU$11="BRADESCO",AU$11="BB"),BI47-ROUNDDOWN(BE47/(BD47/BI47),0)-1,ROUNDUP((BD47-BE47+BJ47-(BD47/BI47))/(BC47-AW48-AR48-AS48),0)+1))) -> 356 | BJ48: =BD47*$BK47 -> 651.70817 | BK48: =IF(BD47>0,BK47,0) -> 0.0017
A49: =IF(INT(F49)>0,A48,0) -> 25 | B49: =IF(F49>0.1,B48,0) -> 75 | C49: =DATE(YEAR(C48),MONTH(C48)+1,1) -> 47088 | D49: =IFERROR(G49/M48,0) -> 0.0028169014 | E49: =E48+1 -> 35 | F49: =IF(OR(M48<1,N48>M48),0,(M48-N48)*IF(D$11<>"BB",$E$7,(1+$D$7)^(AK48/365)-1)) -> 3199.4615 | G49: =IF(R49=0,0,IF(M48<1,0,IF(AND(AND(((M48-N48)/R49)<G48,O48<>"V"),D$11<>"BRADESCO"),G48, (M48-N48)/R49))) -> 1078.6834 | H49: =IF(OR(G49=0,L49<1),"",IF(G49/L49>90%,"🛩",IF(G49/L49>70%,"🏎",IF(G49/L49>50%,"🚙",IF(G49/L49>30%,"🛵",IF(G49/L49>15%,"🐢","⚓️")))))) -> 🐢 | I49: =IFERROR(IF((G49+N49-S49)/L49<0,"🔙",IF((G49+N49-S49)/L49<10%,"🥾",IF((G49+N49-S49)/L49<20%,"🛴",IF((G49+N49-S49)/L49<50%,"🚴‍♂️",IF((G49+N49-S49)/L49<75%,"🚖","🚁"))))),"") -> 🥾 | J49: =G49+N49-S49 -> 427.69797 | K49: =IFERROR(J49/(L49+N49),0) -> 0.097689312 | L49: =G49+F49+A49+B49 -> 4378.1449 | M49: =IF(R49=0,0,MAX(0,M48-G49+S49-N48)) -> 382504.91 | O49: =IF(AND(N49<>"",N49<R49),"V","") | P49: =IF(N48=0,"",(L48-L49)/N48) | Q49: =IF(N49=0,"",IF(N49>M49,"🚫",IF(INT(N49/G49<1),"👍",INT(N49/G49)&"x"))) | R49: =IF(M48=0,0,IF(OR(N48=0,O48="V"),R48-1,IF(OR(D$11="BRADESCO",D$11="BB"),R48-ROUNDDOWN(N48/(M48/R48),0)-1,ROUNDUP((M48-N48+S48-(M48/R48))/(L48-F49-A49-B49),0)+1))) -> 355 | S49: =M48*$T49 -> 650.98543 | T49: =IF(M48>0,T48,0) -> 0.0017 | AA49: =-(L49+N49) -> -4378.1449 | AH49: =ROUNDUP(E49/120,0) -> 1 | AI49: =ROUNDUP(E49/36,0) -> 1 | AJ49: =ROUNDUP(E49/12,0) -> 3 | AK49: =DAY(DATE(YEAR(C49),MONTH(C49)+1,1)-1) -> 31 | AR49: =IF(INT(AW49)>0,AR48,0) -> 25 | AS49: =IF(AW49>0.1,AS48,0) -> 75 | AT49: =DATE(YEAR(AT48),MONTH(AT48)+1,1) -> 47088 | AU49: =IFERROR(AX49/BD48,0) -> 0.0028169014 | AV49: =AV48+1 -> 35 | AW49: =IF(OR(BD48<1,BE48>BD48),0,(BD48-BE48)*IF(AU$11<>"BB",$E$7,(1+$D$7)^(BY48/365)-1)) -> 3199.4615 | AX49: =IF(BI49=0,0,IF(BD48<1,0,IF(AND(AND(((BD48-BE48)/BI49)<AX48,BF48<>"V"),AU$11<>"BRADESCO"),AX48, (BD48-BE48)/BI49))) -> 1078.6834 | AY49: =IF(OR(AX49=0,BC49<1),"",IF(AX49/BC49>90%,"🛩",IF(AX49/BC49>70%,"🏎",IF(AX49/BC49>50%,"🚙",IF(AX49/BC49>30%,"🛵",IF(AX49/BC49>15%,"🐢","⚓️")))))) -> 🐢 | AZ49: =IFERROR(IF((AX49+BE49-BJ49)/BC49<0,"🔙",IF((AX49+BE49-BJ49)/BC49<10%,"🥾",IF((AX49+BE49-BJ49)/BC49<20%,"🛴",IF((AX49+BE49-BJ49)/BC49<50%,"🚴‍♂️",IF((AX49+BE49-BJ49)/BC49<75%,"🚖","🚁"))))),"") -> 🥾 | BA49: =AX49+BE49-BJ49 -> 427.69797 | BB49: =IFERROR(BA49/(BC49+BE49),0) -> 0.097689312 | BC49: =AX49+AW49+AR49+AS49 -> 4378.1449 | BD49: =IF(BI49=0,0,MAX(0,BD48-AX49+BJ49-BE48)) -> 382504.91 | BF49: =IF(AND(BE49<>"",BE49<BI49),"V","") | BG49: =IF(BE48=0,"",(BC48-BC49)/BE48) | BH49: =IF(BE49=0,"",IF(BE49>BD49,"🚫",IF(INT(BE49/AX49<1),"👍",INT(BE49/AX49)&"x"))) | BI49: =IF(BD48=0,0,IF(OR(BE48=0,BF48="V"),BI48-1,IF(OR(AU$11="BRADESCO",AU$11="BB"),BI48-ROUNDDOWN(BE48/(BD48/BI48),0)-1,ROUNDUP((BD48-BE48+BJ48-(BD48/BI48))/(BC48-AW49-AR49-AS49),0)+1))) -> 355 | BJ49: =BD48*$BK48 -> 650.98543 | BK49: =IF(BD48>0,BK48,0) -> 0.0017
A50: =IF(INT(F50)>0,A49,0) -> 25 | B50: =IF(F50>0.1,B49,0) -> 75 | C50: =DATE(YEAR(C49),MONTH(C49)+1,1) -> 47119 | D50: =IFERROR(G50/M49,0) -> 0.0028248588 | E50: =E49+1 -> 36 | F50: =IF(OR(M49<1,N49>M49),0,(M49-N49)*IF(D$11<>"BB",$E$7,(1+$D$7)^(AK49/365)-1)) -> 3195.8881 | G50: =IF(R50=0,0,IF(M49<1,0,IF(AND(AND(((M49-N49)/R50)<G49,O49<>"V"),D$11<>"BRADESCO"),G49, (M49-N49)/R50))) -> 1080.5223 | H50: =IF(OR(G50=0,L50<1),"",IF(G50/L50>90%,"🛩",IF(G50/L50>70%,"🏎",IF(G50/L50>50%,"🚙",IF(G50/L50>30%,"🛵",IF(G50/L50>15%,"🐢","⚓️")))))) -> 🐢 | I50: =IFERROR(IF((G50+N50-S50)/L50<0,"🔙",IF((G50+N50-S50)/L50<10%,"🥾",IF((G50+N50-S50)/L50<20%,"🛴",IF((G50+N50-S50)/L50<50%,"🚴‍♂️",IF((G50+N50-S50)/L50<75%,"🚖","🚁"))))),"") -> 🥾 | J50: =G50+N50-S50 -> 430.264 | K50: =IFERROR(J50/(L50+N50),0) -> 0.098314362 | L50: =G50+F50+A50+B50 -> 4376.4104 | M50: =IF(R50=0,0,MAX(0,M49-G50+S50-N49)) -> 382074.64 | O50: =IF(AND(N50<>"",N50<R50),"V","") | P50: =IF(N49=0,"",(L49-L50)/N49) | Q50: =IF(N50=0,"",IF(N50>M50,"🚫",IF(INT(N50/G50<1),"👍",INT(N50/G50)&"x"))) | R50: =IF(M49=0,0,IF(OR(N49=0,O49="V"),R49-1,IF(OR(D$11="BRADESCO",D$11="BB"),R49-ROUNDDOWN(N49/(M49/R49),0)-1,ROUNDUP((M49-N49+S49-(M49/R49))/(L49-F50-A50-B50),0)+1))) -> 354 | S50: =M49*$T50 -> 650.25834 | T50: =IF(M49>0,T49,0) -> 0.0017 | AA50: =-(L50+N50) -> -4376.4104 | AH50: =ROUNDUP(E50/120,0) -> 1 | AI50: =ROUNDUP(E50/36,0) -> 1 | AJ50: =ROUNDUP(E50/12,0) -> 3 | AK50: =DAY(DATE(YEAR(C50),MONTH(C50)+1,1)-1) -> 31 | AR50: =IF(INT(AW50)>0,AR49,0) -> 25 | AS50: =IF(AW50>0.1,AS49,0) -> 75 | AT50: =DATE(YEAR(AT49),MONTH(AT49)+1,1) -> 47119 | AU50: =IFERROR(AX50/BD49,0) -> 0.0028248588 | AV50: =AV49+1 -> 36 | AW50: =IF(OR(BD49<1,BE49>BD49),0,(BD49-BE49)*IF(AU$11<>"BB",$E$7,(1+$D$7)^(BY49/365)-1)) -> 3195.8881 | AX50: =IF(BI50=0,0,IF(BD49<1,0,IF(AND(AND(((BD49-BE49)/BI50)<AX49,BF49<>"V"),AU$11<>"BRADESCO"),AX49, (BD49-BE49)/BI50))) -> 1080.5223 | AY50: =IF(OR(AX50=0,BC50<1),"",IF(AX50/BC50>90%,"🛩",IF(AX50/BC50>70%,"🏎",IF(AX50/BC50>50%,"🚙",IF(AX50/BC50>30%,"🛵",IF(AX50/BC50>15%,"🐢","⚓️")))))) -> 🐢 | AZ50: =IFERROR(IF((AX50+BE50-BJ50)/BC50<0,"🔙",IF((AX50+BE50-BJ50)/BC50<10%,"🥾",IF((AX50+BE50-BJ50)/BC50<20%,"🛴",IF((AX50+BE50-BJ50)/BC50<50%,"🚴‍♂️",IF((AX50+BE50-BJ50)/BC50<75%,"🚖","🚁"))))),"") -> 🥾 | BA50: =AX50+BE50-BJ50 -> 430.264 | BB50: =IFERROR(BA50/(BC50+BE50),0) -> 0.098314362 | BC50: =AX50+AW50+AR50+AS50 -> 4376.4104 | BD50: =IF(BI50=0,0,MAX(0,BD49-AX50+BJ50-BE49)) -> 382074.64 | BF50: =IF(AND(BE50<>"",BE50<BI50),"V","") | BG50: =IF(BE49=0,"",(BC49-BC50)/BE49) | BH50: =IF(BE50=0,"",IF(BE50>BD50,"🚫",IF(INT(BE50/AX50<1),"👍",INT(BE50/AX50)&"x"))) | BI50: =IF(BD49=0,0,IF(OR(BE49=0,BF49="V"),BI49-1,IF(OR(AU$11="BRADESCO",AU$11="BB"),BI49-ROUNDDOWN(BE49/(BD49/BI49),0)-1,ROUNDUP((BD49-BE49+BJ49-(BD49/BI49))/(BC49-AW50-AR50-AS50),0)+1))) -> 354 | BJ50: =BD49*$BK49 -> 650.25834 | BK50: =IF(BD49>0,BK49,0) -> 0.0017
A51: =IF(INT(F51)>0,A50,0) -> 25 | B51: =IF(F51>0.1,B50,0) -> 75 | C51: =DATE(YEAR(C50),MONTH(C50)+1,1) -> 47150 | D51: =IFERROR(G51/M50,0) -> 0.0028328612 | E51: =E50+1 -> 37 | F51: =IF(OR(M50<1,N50>M50),0,(M50-N50)*IF(D$11<>"BB",$E$7,(1+$D$7)^(AK50/365)-1)) -> 3192.2931 | G51: =IF(R51=0,0,IF(M50<1,0,IF(AND(AND(((M50-N50)/R51)<G50,O50<>"V"),D$11<>"BRADESCO"),G50, (M50-N50)/R51))) -> 1082.3644 | H51: =IF(OR(G51=0,L51<1),"",IF(G51/L51>90%,"🛩",IF(G51/L51>70%,"🏎",IF(G51/L51>50%,"🚙",IF(G51/L51>30%,"🛵",IF(G51/L51>15%,"🐢","⚓️")))))) -> 🐢 | I51: =IFERROR(IF((G51+N51-S51)/L51<0,"🔙",IF((G51+N51-S51)/L51<10%,"🥾",IF((G51+N51-S51)/L51<20%,"🛴",IF((G51+N51-S51)/L51<50%,"🚴‍♂️",IF((G51+N51-S51)/L51<75%,"🚖","🚁"))))),"") -> 🥾 | J51: =G51+N51-S51 -> 432.83754 | K51: =IFERROR(J51/(L51+N51),0) -> 0.098942038 | L51: =G51+F51+A51+B51 -> 4374.6576 | M51: =IF(R51=0,0,MAX(0,M50-G51+S51-N50)) -> 381641.81 | P51: =IF(N50=0,"",(L50-L51)/N50) | Q51: =IF(N51=0,"",IF(N51>M51,"🚫",IF(INT(N51/G51<1),"👍",INT(N51/G51)&"x"))) | R51: =IF(M50=0,0,IF(OR(N50=0,O50="V"),R50-1,IF(OR(D$11="BRADESCO",D$11="BB"),R50-ROUNDDOWN(N50/(M50/R50),0)-1,ROUNDUP((M50-N50+S50-(M50/R50))/(L50-F51-A51-B51),0)+1))) -> 353 | S51: =M50*$T51 -> 649.5269 | T51: =IF(M50>0,T50,0) -> 0.0017 | AA51: =-(L51+N51) -> -4374.6576 | AH51: =ROUNDUP(E51/120,0) -> 1 | AI51: =ROUNDUP(E51/36,0) -> 2 | AJ51: =ROUNDUP(E51/12,0) -> 4 | AK51: =DAY(DATE(YEAR(C51),MONTH(C51)+1,1)-1) -> 28 | AR51: =IF(INT(AW51)>0,AR50,0) -> 25 | AS51: =IF(AW51>0.1,AS50,0) -> 75 | AT51: =DATE(YEAR(AT50),MONTH(AT50)+1,1) -> 47150 | AU51: =IFERROR(AX51/BD50,0) -> 0.0028328612 | AV51: =AV50+1 -> 37 | AW51: =IF(OR(BD50<1,BE50>BD50),0,(BD50-BE50)*IF(AU$11<>"BB",$E$7,(1+$D$7)^(BY50/365)-1)) -> 3192.2931 | AX51: =IF(BI51=0,0,IF(BD50<1,0,IF(AND(AND(((BD50-BE50)/BI51)<AX50,BF50<>"V"),AU$11<>"BRADESCO"),AX50, (BD50-BE50)/BI51))) -> 1082.3644 | AY51: =IF(OR(AX51=0,BC51<1),"",IF(AX51/BC51>90%,"🛩",IF(AX51/BC51>70%,"🏎",IF(AX51/BC51>50%,"🚙",IF(AX51/BC51>30%,"🛵",IF(AX51/BC51>15%,"🐢","⚓️")))))) -> 🐢 | AZ51: =IFERROR(IF((AX51+BE51-BJ51)/BC51<0,"🔙",IF((AX51+BE51-BJ51)/BC51<10%,"🥾",IF((AX51+BE51-BJ51)/BC51<20%,"🛴",IF((AX51+BE51-BJ51)/BC51<50%,"🚴‍♂️",IF((AX51+BE51-BJ51)/BC51<75%,"🚖","🚁"))))),"") -> 🥾 | BA51: =AX51+BE51-BJ51 -> 432.83754 | BB51: =IFERROR(BA51/(BC51+BE51),0) -> 0.098942038 | BC51: =AX51+AW51+AR51+AS51 -> 4374.6576 | BD51: =IF(BI51=0,0,MAX(0,BD50-AX51+BJ51-BE50)) -> 381641.81 | BG51: =IF(BE50=0,"",(BC50-BC51)/BE50) | BH51: =IF(BE51=0,"",IF(BE51>BD51,"🚫",IF(INT(BE51/AX51<1),"👍",INT(BE51/AX51)&"x"))) | BI51: =IF(BD50=0,0,IF(OR(BE50=0,BF50="V"),BI50-1,IF(OR(AU$11="BRADESCO",AU$11="BB"),BI50-ROUNDDOWN(BE50/(BD50/BI50),0)-1,ROUNDUP((BD50-BE50+BJ50-(BD50/BI50))/(BC50-AW51-AR51-AS51),0)+1))) -> 353 | BJ51: =BD50*$BK50 -> 649.5269 | BK51: =IF(BD50>0,BK50,0) -> 0.0017
A52: =IF(INT(F52)>0,A51,0) -> 25 | B52: =IF(F52>0.1,B51,0) -> 75 | C52: =DATE(YEAR(C51),MONTH(C51)+1,1) -> 47178 | D52: =IFERROR(G52/M51,0) -> 0.0028409091 | E52: =E51+1 -> 38 | F52: =IF(OR(M51<1,N51>M51),0,(M51-N51)*IF(D$11<>"BB",$E$7,(1+$D$7)^(AK51/365)-1)) -> 3188.6767 | G52: =IF(R52=0,0,IF(M51<1,0,IF(AND(AND(((M51-N51)/R52)<G51,O51<>"V"),D$11<>"BRADESCO"),G51, (M51-N51)/R52))) -> 1084.2097 | H52: =IF(OR(G52=0,L52<1),"",IF(G52/L52>90%,"🛩",IF(G52/L52>70%,"🏎",IF(G52/L52>50%,"🚙",IF(G52/L52>30%,"🛵",IF(G52/L52>15%,"🐢","⚓️")))))) -> 🐢 | I52: =IFERROR(IF((G52+N52-S52)/L52<0,"🔙",IF((G52+N52-S52)/L52<10%,"🥾",IF((G52+N52-S52)/L52<20%,"🛴",IF((G52+N52-S52)/L52<50%,"🚴‍♂️",IF((G52+N52-S52)/L52<75%,"🚖","🚁"))))),"") -> 🥾 | J52: =G52+N52-S52 -> 435.41861 | K52: =IFERROR(J52/(L52+N52),0) -> 0.099572357 | L52: =G52+F52+A52+B52 -> 4372.8864 | M52: =IF(R52=0,0,MAX(0,M51-G52+S52-N51)) -> 381206.39 | O52: =IF(AND(N52<>"",N52<R52),"V","") | P52: =IF(N51=0,"",(L51-L52)/N51) | Q52: =IF(N52=0,"",IF(N52>M52,"🚫",IF(INT(N52/G52<1),"👍",INT(N52/G52)&"x"))) | R52: =IF(M51=0,0,IF(OR(N51=0,O51="V"),R51-1,IF(OR(D$11="BRADESCO",D$11="BB"),R51-ROUNDDOWN(N51/(M51/R51),0)-1,ROUNDUP((M51-N51+S51-(M51/R51))/(L51-F52-A52-B52),0)+1))) -> 352 | S52: =M51*$T52 -> 648.79107 | T52: =IF(M51>0,T51,0) -> 0.0017 | AA52: =-(L52+N52) -> -4372.8864 | AH52: =ROUNDUP(E52/120,0) -> 1 | AI52: =ROUNDUP(E52/36,0) -> 2 | AJ52: =ROUNDUP(E52/12,0) -> 4 | AK52: =DAY(DATE(YEAR(C52),MONTH(C52)+1,1)-1) -> 31 | AR52: =IF(INT(AW52)>0,AR51,0) -> 25 | AS52: =IF(AW52>0.1,AS51,0) -> 75 | AT52: =DATE(YEAR(AT51),MONTH(AT51)+1,1) -> 47178 | AU52: =IFERROR(AX52/BD51,0) -> 0.0028409091 | AV52: =AV51+1 -> 38 | AW52: =IF(OR(BD51<1,BE51>BD51),0,(BD51-BE51)*IF(AU$11<>"BB",$E$7,(1+$D$7)^(BY51/365)-1)) -> 3188.6767 | AX52: =IF(BI52=0,0,IF(BD51<1,0,IF(AND(AND(((BD51-BE51)/BI52)<AX51,BF51<>"V"),AU$11<>"BRADESCO"),AX51, (BD51-BE51)/BI52))) -> 1084.2097 | AY52: =IF(OR(AX52=0,BC52<1),"",IF(AX52/BC52>90%,"🛩",IF(AX52/BC52>70%,"🏎",IF(AX52/BC52>50%,"🚙",IF(AX52/BC52>30%,"🛵",IF(AX52/BC52>15%,"🐢","⚓️")))))) -> 🐢 | AZ52: =IFERROR(IF((AX52+BE52-BJ52)/BC52<0,"🔙",IF((AX52+BE52-BJ52)/BC52<10%,"🥾",IF((AX52+BE52-BJ52)/BC52<20%,"🛴",IF((AX52+BE52-BJ52)/BC52<50%,"🚴‍♂️",IF((AX52+BE52-BJ52)/BC52<75%,"🚖","🚁"))))),"") -> 🥾 | BA52: =AX52+BE52-BJ52 -> 435.41861 | BB52: =IFERROR(BA52/(BC52+BE52),0) -> 0.099572357 | BC52: =AX52+AW52+AR52+AS52 -> 4372.8864 | BD52: =IF(BI52=0,0,MAX(0,BD51-AX52+BJ52-BE51)) -> 381206.39 | BF52: =IF(AND(BE52<>"",BE52<BI52),"V","") | BG52: =IF(BE51=0,"",(BC51-BC52)/BE51) | BH52: =IF(BE52=0,"",IF(BE52>BD52,"🚫",IF(INT(BE52/AX52<1),"👍",INT(BE52/AX52)&"x"))) | BI52: =IF(BD51=0,0,IF(OR(BE51=0,BF51="V"),BI51-1,IF(OR(AU$11="BRADESCO",AU$11="BB"),BI51-ROUNDDOWN(BE51/(BD51/BI51),0)-1,ROUNDUP((BD51-BE51+BJ51-(BD51/BI51))/(BC51-AW52-AR52-AS52),0)+1))) -> 352 | BJ52: =BD51*$BK51 -> 648.79107 | BK52: =IF(BD51>0,BK51,0) -> 0.0017
A53: =IF(INT(F53)>0,A52,0) -> 25 | B53: =IF(F53>0.1,B52,0) -> 75 | C53: =DATE(YEAR(C52),MONTH(C52)+1,1) -> 47209 | D53: =IFERROR(G53/M52,0) -> 0.0028490028 | E53: =E52+1 -> 39 | F53: =IF(OR(M52<1,N52>M52),0,(M52-N52)*IF(D$11<>"BB",$E$7,(1+$D$7)^(AK52/365)-1)) -> 3185.0387 | G53: =IF(R53=0,0,IF(M52<1,0,IF(AND(AND(((M52-N52)/R53)<G52,O52<>"V"),D$11<>"BRADESCO"),G52, (M52-N52)/R53))) -> 1086.0581 | H53: =IF(OR(G53=0,L53<1),"",IF(G53/L53>90%,"🛩",IF(G53/L53>70%,"🏎",IF(G53/L53>50%,"🚙",IF(G53/L53>30%,"🛵",IF(G53/L53>15%,"🐢","⚓️")))))) -> 🐢 | I53: =IFERROR(IF((G53+N53-S53)/L53<0,"🔙",IF((G53+N53-S53)/L53<10%,"🥾",IF((G53+N53-S53)/L53<20%,"🛴",IF((G53+N53-S53)/L53<50%,"🚴‍♂️",IF((G53+N53-S53)/L53<75%,"🚖","🚁"))))),"") -> 🛴 | J53: =G53+N53-S53 -> 438.00723 | K53: =IFERROR(J53/(L53+N53),0) -> 0.10020534 | L53: =G53+F53+A53+B53 -> 4371.0968 | M53: =IF(R53=0,0,MAX(0,M52-G53+S53-N52)) -> 380768.38 | O53: =IF(AND(N53<>"",N53<R53),"V","") | P53: =IF(N52=0,"",(L52-L53)/N52) | Q53: =IF(N53=0,"",IF(N53>M53,"🚫",IF(INT(N53/G53<1),"👍",INT(N53/G53)&"x"))) | R53: =IF(M52=0,0,IF(OR(N52=0,O52="V"),R52-1,IF(OR(D$11="BRADESCO",D$11="BB"),R52-ROUNDDOWN(N52/(M52/R52),0)-1,ROUNDUP((M52-N52+S52-(M52/R52))/(L52-F53-A53-B53),0)+1))) -> 351 | S53: =M52*$T53 -> 648.05086 | T53: =IF(M52>0,T52,0) -> 0.0017 | AA53: =-(L53+N53) -> -4371.0968 | AH53: =ROUNDUP(E53/120,0) -> 1 | AI53: =ROUNDUP(E53/36,0) -> 2 | AJ53: =ROUNDUP(E53/12,0) -> 4 | AK53: =DAY(DATE(YEAR(C53),MONTH(C53)+1,1)-1) -> 30 | AR53: =IF(INT(AW53)>0,AR52,0) -> 25 | AS53: =IF(AW53>0.1,AS52,0) -> 75 | AT53: =DATE(YEAR(AT52),MONTH(AT52)+1,1) -> 47209 | AU53: =IFERROR(AX53/BD52,0) -> 0.0028490028 | AV53: =AV52+1 -> 39 | AW53: =IF(OR(BD52<1,BE52>BD52),0,(BD52-BE52)*IF(AU$11<>"BB",$E$7,(1+$D$7)^(BY52/365)-1)) -> 3185.0387 | AX53: =IF(BI53=0,0,IF(BD52<1,0,IF(AND(AND(((BD52-BE52)/BI53)<AX52,BF52<>"V"),AU$11<>"BRADESCO"),AX52, (BD52-BE52)/BI53))) -> 1086.0581 | AY53: =IF(OR(AX53=0,BC53<1),"",IF(AX53/BC53>90%,"🛩",IF(AX53/BC53>70%,"🏎",IF(AX53/BC53>50%,"🚙",IF(AX53/BC53>30%,"🛵",IF(AX53/BC53>15%,"🐢","⚓️")))))) -> 🐢 | AZ53: =IFERROR(IF((AX53+BE53-BJ53)/BC53<0,"🔙",IF((AX53+BE53-BJ53)/BC53<10%,"🥾",IF((AX53+BE53-BJ53)/BC53<20%,"🛴",IF((AX53+BE53-BJ53)/BC53<50%,"🚴‍♂️",IF((AX53+BE53-BJ53)/BC53<75%,"🚖","🚁"))))),"") -> 🛴 | BA53: =AX53+BE53-BJ53 -> 438.00723 | BB53: =IFERROR(BA53/(BC53+BE53),0) -> 0.10020534 | BC53: =AX53+AW53+AR53+AS53 -> 4371.0968 | BD53: =IF(BI53=0,0,MAX(0,BD52-AX53+BJ53-BE52)) -> 380768.38 | BF53: =IF(AND(BE53<>"",BE53<BI53),"V","") | BG53: =IF(BE52=0,"",(BC52-BC53)/BE52) | BH53: =IF(BE53=0,"",IF(BE53>BD53,"🚫",IF(INT(BE53/AX53<1),"👍",INT(BE53/AX53)&"x"))) | BI53: =IF(BD52=0,0,IF(OR(BE52=0,BF52="V"),BI52-1,IF(OR(AU$11="BRADESCO",AU$11="BB"),BI52-ROUNDDOWN(BE52/(BD52/BI52),0)-1,ROUNDUP((BD52-BE52+BJ52-(BD52/BI52))/(BC52-AW53-AR53-AS53),0)+1))) -> 351 | BJ53: =BD52*$BK52 -> 648.05086 | BK53: =IF(BD52>0,BK52,0) -> 0.0017
A54: =IF(INT(F54)>0,A53,0) -> 25 | B54: =IF(F54>0.1,B53,0) -> 75 | C54: =DATE(YEAR(C53),MONTH(C53)+1,1) -> 47239 | D54: =IFERROR(G54/M53,0) -> 0.0028571429 | E54: =E53+1 -> 40 | F54: =IF(OR(M53<1,N53>M53),0,(M53-N53)*IF(D$11<>"BB",$E$7,(1+$D$7)^(AK53/365)-1)) -> 3181.3791 | G54: =IF(R54=0,0,IF(M53<1,0,IF(AND(AND(((M53-N53)/R54)<G53,O53<>"V"),D$11<>"BRADESCO"),G53, (M53-N53)/R54))) -> 1087.9097 | H54: =IF(OR(G54=0,L54<1),"",IF(G54/L54>90%,"🛩",IF(G54/L54>70%,"🏎",IF(G54/L54>50%,"🚙",IF(G54/L54>30%,"🛵",IF(G54/L54>15%,"🐢","⚓️")))))) -> 🐢 | I54: =IFERROR(IF((G54+N54-S54)/L54<0,"🔙",IF((G54+N54-S54)/L54<10%,"🥾",IF((G54+N54-S54)/L54<20%,"🛴",IF((G54+N54-S54)/L54<50%,"🚴‍♂️",IF((G54+N54-S54)/L54<75%,"🚖","🚁"))))),"") -> 🛴 | J54: =G54+N54-S54 -> 440.60341 | K54: =IFERROR(J54/(L54+N54),0) -> 0.10084099 | L54: =G54+F54+A54+B54 -> 4369.2888 | M54: =IF(R54=0,0,MAX(0,M53-G54+S54-N53)) -> 380327.78 | O54: =IF(AND(N54<>"",N54<R54),"V","") | P54: =IF(N53=0,"",(L53-L54)/N53) | Q54: =IF(N54=0,"",IF(N54>M54,"🚫",IF(INT(N54/G54<1),"👍",INT(N54/G54)&"x"))) | R54: =IF(M53=0,0,IF(OR(N53=0,O53="V"),R53-1,IF(OR(D$11="BRADESCO",D$11="BB"),R53-ROUNDDOWN(N53/(M53/R53),0)-1,ROUNDUP((M53-N53+S53-(M53/R53))/(L53-F54-A54-B54),0)+1))) -> 350 | S54: =M53*$T54 -> 647.30625 | T54: =IF(M53>0,T53,0) -> 0.0017 | AA54: =-(L54+N54) -> -4369.2888 | AH54: =ROUNDUP(E54/120,0) -> 1 | AI54: =ROUNDUP(E54/36,0) -> 2 | AJ54: =ROUNDUP(E54/12,0) -> 4 | AK54: =DAY(DATE(YEAR(C54),MONTH(C54)+1,1)-1) -> 31 | AR54: =IF(INT(AW54)>0,AR53,0) -> 25 | AS54: =IF(AW54>0.1,AS53,0) -> 75 | AT54: =DATE(YEAR(AT53),MONTH(AT53)+1,1) -> 47239 | AU54: =IFERROR(AX54/BD53,0) -> 0.0028571429 | AV54: =AV53+1 -> 40 | AW54: =IF(OR(BD53<1,BE53>BD53),0,(BD53-BE53)*IF(AU$11<>"BB",$E$7,(1+$D$7)^(BY53/365)-1)) -> 3181.3791 | AX54: =IF(BI54=0,0,IF(BD53<1,0,IF(AND(AND(((BD53-BE53)/BI54)<AX53,BF53<>"V"),AU$11<>"BRADESCO"),AX53, (BD53-BE53)/BI54))) -> 1087.9097 | AY54: =IF(OR(AX54=0,BC54<1),"",IF(AX54/BC54>90%,"🛩",IF(AX54/BC54>70%,"🏎",IF(AX54/BC54>50%,"🚙",IF(AX54/BC54>30%,"🛵",IF(AX54/BC54>15%,"🐢","⚓️")))))) -> 🐢 | AZ54: =IFERROR(IF((AX54+BE54-BJ54)/BC54<0,"🔙",IF((AX54+BE54-BJ54)/BC54<10%,"🥾",IF((AX54+BE54-BJ54)/BC54<20%,"🛴",IF((AX54+BE54-BJ54)/BC54<50%,"🚴‍♂️",IF((AX54+BE54-BJ54)/BC54<75%,"🚖","🚁"))))),"") -> 🛴 | BA54: =AX54+BE54-BJ54 -> 440.60341 | BB54: =IFERROR(BA54/(BC54+BE54),0) -> 0.10084099 | BC54: =AX54+AW54+AR54+AS54 -> 4369.2888 | BD54: =IF(BI54=0,0,MAX(0,BD53-AX54+BJ54-BE53)) -> 380327.78 | BF54: =IF(AND(BE54<>"",BE54<BI54),"V","") | BG54: =IF(BE53=0,"",(BC53-BC54)/BE53) | BH54: =IF(BE54=0,"",IF(BE54>BD54,"🚫",IF(INT(BE54/AX54<1),"👍",INT(BE54/AX54)&"x"))) | BI54: =IF(BD53=0,0,IF(OR(BE53=0,BF53="V"),BI53-1,IF(OR(AU$11="BRADESCO",AU$11="BB"),BI53-ROUNDDOWN(BE53/(BD53/BI53),0)-1,ROUNDUP((BD53-BE53+BJ53-(BD53/BI53))/(BC53-AW54-AR54-AS54),0)+1))) -> 350 | BJ54: =BD53*$BK53 -> 647.30625 | BK54: =IF(BD53>0,BK53,0) -> 0.0017
A55: =IF(INT(F55)>0,A54,0) -> 25 | B55: =IF(F55>0.1,B54,0) -> 75 | C55: =DATE(YEAR(C54),MONTH(C54)+1,1) -> 47270 | D55: =IFERROR(G55/M54,0) -> 0.0028653295 | E55: =E54+1 -> 41 | F55: =IF(OR(M54<1,N54>M54),0,(M54-N54)*IF(D$11<>"BB",$E$7,(1+$D$7)^(AK54/365)-1)) -> 3177.6978 | G55: =IF(R55=0,0,IF(M54<1,0,IF(AND(AND(((M54-N54)/R55)<G54,O54<>"V"),D$11<>"BRADESCO"),G54, (M54-N54)/R55))) -> 1089.7644 | H55: =IF(OR(G55=0,L55<1),"",IF(G55/L55>90%,"🛩",IF(G55/L55>70%,"🏎",IF(G55/L55>50%,"🚙",IF(G55/L55>30%,"🛵",IF(G55/L55>15%,"🐢","⚓️")))))) -> 🐢 | I55: =IFERROR(IF((G55+N55-S55)/L55<0,"🔙",IF((G55+N55-S55)/L55<10%,"🥾",IF((G55+N55-S55)/L55<20%,"🛴",IF((G55+N55-S55)/L55<50%,"🚴‍♂️",IF((G55+N55-S55)/L55<75%,"🚖","🚁"))))),"") -> 🛴 | J55: =G55+N55-S55 -> 443.20718 | K55: =IFERROR(J55/(L55+N55),0) -> 0.10147934 | L55: =G55+F55+A55+B55 -> 4367.4622 | M55: =IF(R55=0,0,MAX(0,M54-G55+S55-N54)) -> 379884.57 | O55: =IF(AND(N55<>"",N55<R55),"V","") | P55: =IF(N54=0,"",(L54-L55)/N54) | Q55: =IF(N55=0,"",IF(N55>M55,"🚫",IF(INT(N55/G55<1),"👍",INT(N55/G55)&"x"))) | R55: =IF(M54=0,0,IF(OR(N54=0,O54="V"),R54-1,IF(OR(D$11="BRADESCO",D$11="BB"),R54-ROUNDDOWN(N54/(M54/R54),0)-1,ROUNDUP((M54-N54+S54-(M54/R54))/(L54-F55-A55-B55),0)+1))) -> 349 | S55: =M54*$T55 -> 646.55722 | T55: =IF(M54>0,T54,0) -> 0.0017 | AA55: =-(L55+N55) -> -4367.4622 | AH55: =ROUNDUP(E55/120,0) -> 1 | AI55: =ROUNDUP(E55/36,0) -> 2 | AJ55: =ROUNDUP(E55/12,0) -> 4 | AK55: =DAY(DATE(YEAR(C55),MONTH(C55)+1,1)-1) -> 30 | AR55: =IF(INT(AW55)>0,AR54,0) -> 25 | AS55: =IF(AW55>0.1,AS54,0) -> 75 | AT55: =DATE(YEAR(AT54),MONTH(AT54)+1,1) -> 47270 | AU55: =IFERROR(AX55/BD54,0) -> 0.0028653295 | AV55: =AV54+1 -> 41 | AW55: =IF(OR(BD54<1,BE54>BD54),0,(BD54-BE54)*IF(AU$11<>"BB",$E$7,(1+$D$7)^(BY54/365)-1)) -> 3177.6978 | AX55: =IF(BI55=0,0,IF(BD54<1,0,IF(AND(AND(((BD54-BE54)/BI55)<AX54,BF54<>"V"),AU$11<>"BRADESCO"),AX54, (BD54-BE54)/BI55))) -> 1089.7644 | AY55: =IF(OR(AX55=0,BC55<1),"",IF(AX55/BC55>90%,"🛩",IF(AX55/BC55>70%,"🏎",IF(AX55/BC55>50%,"🚙",IF(AX55/BC55>30%,"🛵",IF(AX55/BC55>15%,"🐢","⚓️")))))) -> 🐢 | AZ55: =IFERROR(IF((AX55+BE55-BJ55)/BC55<0,"🔙",IF((AX55+BE55-BJ55)/BC55<10%,"🥾",IF((AX55+BE55-BJ55)/BC55<20%,"🛴",IF((AX55+BE55-BJ55)/BC55<50%,"🚴‍♂️",IF((AX55+BE55-BJ55)/BC55<75%,"🚖","🚁"))))),"") -> 🛴 | BA55: =AX55+BE55-BJ55 -> 443.20718 | BB55: =IFERROR(BA55/(BC55+BE55),0) -> 0.10147934 | BC55: =AX55+AW55+AR55+AS55 -> 4367.4622 | BD55: =IF(BI55=0,0,MAX(0,BD54-AX55+BJ55-BE54)) -> 379884.57 | BF55: =IF(AND(BE55<>"",BE55<BI55),"V","") | BG55: =IF(BE54=0,"",(BC54-BC55)/BE54) | BH55: =IF(BE55=0,"",IF(BE55>BD55,"🚫",IF(INT(BE55/AX55<1),"👍",INT(BE55/AX55)&"x"))) | BI55: =IF(BD54=0,0,IF(OR(BE54=0,BF54="V"),BI54-1,IF(OR(AU$11="BRADESCO",AU$11="BB"),BI54-ROUNDDOWN(BE54/(BD54/BI54),0)-1,ROUNDUP((BD54-BE54+BJ54-(BD54/BI54))/(BC54-AW55-AR55-AS55),0)+1))) -> 349 | BJ55: =BD54*$BK54 -> 646.55722 | BK55: =IF(BD54>0,BK54,0) -> 0.0017
A56: =IF(INT(F56)>0,A55,0) -> 25 | B56: =IF(F56>0.1,B55,0) -> 75 | C56: =DATE(YEAR(C55),MONTH(C55)+1,1) -> 47300 | D56: =IFERROR(G56/M55,0) -> 0.0028735632 | E56: =E55+1 -> 42 | F56: =IF(OR(M55<1,N55>M55),0,(M55-N55)*IF(D$11<>"BB",$E$7,(1+$D$7)^(AK55/365)-1)) -> 3173.9947 | G56: =IF(R56=0,0,IF(M55<1,0,IF(AND(AND(((M55-N55)/R56)<G55,O55<>"V"),D$11<>"BRADESCO"),G55, (M55-N55)/R56))) -> 1091.6223 | H56: =IF(OR(G56=0,L56<1),"",IF(G56/L56>90%,"🛩",IF(G56/L56>70%,"🏎",IF(G56/L56>50%,"🚙",IF(G56/L56>30%,"🛵",IF(G56/L56>15%,"🐢","⚓️")))))) -> 🐢 | I56: =IFERROR(IF((G56+N56-S56)/L56<0,"🔙",IF((G56+N56-S56)/L56<10%,"🥾",IF((G56+N56-S56)/L56<20%,"🛴",IF((G56+N56-S56)/L56<50%,"🚴‍♂️",IF((G56+N56-S56)/L56<75%,"🚖","🚁"))))),"") -> 🛴 | J56: =G56+N56-S56 -> 445.81856 | K56: =IFERROR(J56/(L56+N56),0) -> 0.1021204 | L56: =G56+F56+A56+B56 -> 4365.6171 | M56: =IF(R56=0,0,MAX(0,M55-G56+S56-N55)) -> 379438.75 | O56: =IF(AND(N56<>"",N56<R56),"V","") | P56: =IF(N55=0,"",(L55-L56)/N55) | Q56: =IF(N56=0,"",IF(N56>M56,"🚫",IF(INT(N56/G56<1),"👍",INT(N56/G56)&"x"))) | R56: =IF(M55=0,0,IF(OR(N55=0,O55="V"),R55-1,IF(OR(D$11="BRADESCO",D$11="BB"),R55-ROUNDDOWN(N55/(M55/R55),0)-1,ROUNDUP((M55-N55+S55-(M55/R55))/(L55-F56-A56-B56),0)+1))) -> 348 | S56: =M55*$T56 -> 645.80377 | T56: =IF(M55>0,T55,0) -> 0.0017 | AA56: =-(L56+N56) -> -4365.6171 | AH56: =ROUNDUP(E56/120,0) -> 1 | AI56: =ROUNDUP(E56/36,0) -> 2 | AJ56: =ROUNDUP(E56/12,0) -> 4 | AK56: =DAY(DATE(YEAR(C56),MONTH(C56)+1,1)-1) -> 31 | AR56: =IF(INT(AW56)>0,AR55,0) -> 25 | AS56: =IF(AW56>0.1,AS55,0) -> 75 | AT56: =DATE(YEAR(AT55),MONTH(AT55)+1,1) -> 47300 | AU56: =IFERROR(AX56/BD55,0) -> 0.0028735632 | AV56: =AV55+1 -> 42 | AW56: =IF(OR(BD55<1,BE55>BD55),0,(BD55-BE55)*IF(AU$11<>"BB",$E$7,(1+$D$7)^(BY55/365)-1)) -> 3173.9947 | AX56: =IF(BI56=0,0,IF(BD55<1,0,IF(AND(AND(((BD55-BE55)/BI56)<AX55,BF55<>"V"),AU$11<>"BRADESCO"),AX55, (BD55-BE55)/BI56))) -> 1091.6223 | AY56: =IF(OR(AX56=0,BC56<1),"",IF(AX56/BC56>90%,"🛩",IF(AX56/BC56>70%,"🏎",IF(AX56/BC56>50%,"🚙",IF(AX56/BC56>30%,"🛵",IF(AX56/BC56>15%,"🐢","⚓️")))))) -> 🐢 | AZ56: =IFERROR(IF((AX56+BE56-BJ56)/BC56<0,"🔙",IF((AX56+BE56-BJ56)/BC56<10%,"🥾",IF((AX56+BE56-BJ56)/BC56<20%,"🛴",IF((AX56+BE56-BJ56)/BC56<50%,"🚴‍♂️",IF((AX56+BE56-BJ56)/BC56<75%,"🚖","🚁"))))),"") -> 🛴 | BA56: =AX56+BE56-BJ56 -> 445.81856 | BB56: =IFERROR(BA56/(BC56+BE56),0) -> 0.1021204 | BC56: =AX56+AW56+AR56+AS56 -> 4365.6171 | BD56: =IF(BI56=0,0,MAX(0,BD55-AX56+BJ56-BE55)) -> 379438.75 | BF56: =IF(AND(BE56<>"",BE56<BI56),"V","") | BG56: =IF(BE55=0,"",(BC55-BC56)/BE55) | BH56: =IF(BE56=0,"",IF(BE56>BD56,"🚫",IF(INT(BE56/AX56<1),"👍",INT(BE56/AX56)&"x"))) | BI56: =IF(BD55=0,0,IF(OR(BE55=0,BF55="V"),BI55-1,IF(OR(AU$11="BRADESCO",AU$11="BB"),BI55-ROUNDDOWN(BE55/(BD55/BI55),0)-1,ROUNDUP((BD55-BE55+BJ55-(BD55/BI55))/(BC55-AW56-AR56-AS56),0)+1))) -> 348 | BJ56: =BD55*$BK55 -> 645.80377 | BK56: =IF(BD55>0,BK55,0) -> 0.0017
A57: =IF(INT(F57)>0,A56,0) -> 25 | B57: =IF(F57>0.1,B56,0) -> 75 | C57: =DATE(YEAR(C56),MONTH(C56)+1,1) -> 47331 | D57: =IFERROR(G57/M56,0) -> 0.0028818444 | E57: =E56+1 -> 43 | F57: =IF(OR(M56<1,N56>M56),0,(M56-N56)*IF(D$11<>"BB",$E$7,(1+$D$7)^(AK56/365)-1)) -> 3170.2698 | G57: =IF(R57=0,0,IF(M56<1,0,IF(AND(AND(((M56-N56)/R57)<G56,O56<>"V"),D$11<>"BRADESCO"),G56, (M56-N56)/R57))) -> 1093.4834 | H57: =IF(OR(G57=0,L57<1),"",IF(G57/L57>90%,"🛩",IF(G57/L57>70%,"🏎",IF(G57/L57>50%,"🚙",IF(G57/L57>30%,"🛵",IF(G57/L57>15%,"🐢","⚓️")))))) -> 🐢 | I57: =IFERROR(IF((G57+N57-S57)/L57<0,"🔙",IF((G57+N57-S57)/L57<10%,"🥾",IF((G57+N57-S57)/L57<20%,"🛴",IF((G57+N57-S57)/L57<50%,"🚴‍♂️",IF((G57+N57-S57)/L57<75%,"🚖","🚁"))))),"") -> 🛴 | J57: =G57+N57-S57 -> 448.43756 | K57: =IFERROR(J57/(L57+N57),0) -> 0.10276419 | L57: =G57+F57+A57+B57 -> 4363.7533 | M57: =IF(R57=0,0,MAX(0,M56-G57+S57-N56)) -> 378990.31 | O57: =IF(AND(N57<>"",N57<R57),"V","") | P57: =IF(N56=0,"",(L56-L57)/N56) | Q57: =IF(N57=0,"",IF(N57>M57,"🚫",IF(INT(N57/G57<1),"👍",INT(N57/G57)&"x"))) | R57: =IF(M56=0,0,IF(OR(N56=0,O56="V"),R56-1,IF(OR(D$11="BRADESCO",D$11="BB"),R56-ROUNDDOWN(N56/(M56/R56),0)-1,ROUNDUP((M56-N56+S56-(M56/R56))/(L56-F57-A57-B57),0)+1))) -> 347 | S57: =M56*$T57 -> 645.04588 | T57: =IF(M56>0,T56,0) -> 0.0017 | AA57: =-(L57+N57) -> -4363.7533 | AH57: =ROUNDUP(E57/120,0) -> 1 | AI57: =ROUNDUP(E57/36,0) -> 2 | AJ57: =ROUNDUP(E57/12,0) -> 4 | AK57: =DAY(DATE(YEAR(C57),MONTH(C57)+1,1)-1) -> 31 | AR57: =IF(INT(AW57)>0,AR56,0) -> 25 | AS57: =IF(AW57>0.1,AS56,0) -> 75 | AT57: =DATE(YEAR(AT56),MONTH(AT56)+1,1) -> 47331 | AU57: =IFERROR(AX57/BD56,0) -> 0.0028818444 | AV57: =AV56+1 -> 43 | AW57: =IF(OR(BD56<1,BE56>BD56),0,(BD56-BE56)*IF(AU$11<>"BB",$E$7,(1+$D$7)^(BY56/365)-1)) -> 3170.2698 | AX57: =IF(BI57=0,0,IF(BD56<1,0,IF(AND(AND(((BD56-BE56)/BI57)<AX56,BF56<>"V"),AU$11<>"BRADESCO"),AX56, (BD56-BE56)/BI57))) -> 1093.4834 | AY57: =IF(OR(AX57=0,BC57<1),"",IF(AX57/BC57>90%,"🛩",IF(AX57/BC57>70%,"🏎",IF(AX57/BC57>50%,"🚙",IF(AX57/BC57>30%,"🛵",IF(AX57/BC57>15%,"🐢","⚓️")))))) -> 🐢 | AZ57: =IFERROR(IF((AX57+BE57-BJ57)/BC57<0,"🔙",IF((AX57+BE57-BJ57)/BC57<10%,"🥾",IF((AX57+BE57-BJ57)/BC57<20%,"🛴",IF((AX57+BE57-BJ57)/BC57<50%,"🚴‍♂️",IF((AX57+BE57-BJ57)/BC57<75%,"🚖","🚁"))))),"") -> 🛴 | BA57: =AX57+BE57-BJ57 -> 448.43756 | BB57: =IFERROR(BA57/(BC57+BE57),0) -> 0.10276419 | BC57: =AX57+AW57+AR57+AS57 -> 4363.7533 | BD57: =IF(BI57=0,0,MAX(0,BD56-AX57+BJ57-BE56)) -> 378990.31 | BF57: =IF(AND(BE57<>"",BE57<BI57),"V","") | BG57: =IF(BE56=0,"",(BC56-BC57)/BE56) | BH57: =IF(BE57=0,"",IF(BE57>BD57,"🚫",IF(INT(BE57/AX57<1),"👍",INT(BE57/AX57)&"x"))) | BI57: =IF(BD56=0,0,IF(OR(BE56=0,BF56="V"),BI56-1,IF(OR(AU$11="BRADESCO",AU$11="BB"),BI56-ROUNDDOWN(BE56/(BD56/BI56),0)-1,ROUNDUP((BD56-BE56+BJ56-(BD56/BI56))/(BC56-AW57-AR57-AS57),0)+1))) -> 347 | BJ57: =BD56*$BK56 -> 645.04588 | BK57: =IF(BD56>0,BK56,0) -> 0.0017
A58: =IF(INT(F58)>0,A57,0) -> 25 | B58: =IF(F58>0.1,B57,0) -> 75 | C58: =DATE(YEAR(C57),MONTH(C57)+1,1) -> 47362 | D58: =IFERROR(G58/M57,0) -> 0.0028901734 | E58: =E57+1 -> 44 | F58: =IF(OR(M57<1,N57>M57),0,(M57-N57)*IF(D$11<>"BB",$E$7,(1+$D$7)^(AK57/365)-1)) -> 3166.5231 | G58: =IF(R58=0,0,IF(M57<1,0,IF(AND(AND(((M57-N57)/R58)<G57,O57<>"V"),D$11<>"BRADESCO"),G57, (M57-N57)/R58))) -> 1095.3477 | H58: =IF(OR(G58=0,L58<1),"",IF(G58/L58>90%,"🛩",IF(G58/L58>70%,"🏎",IF(G58/L58>50%,"🚙",IF(G58/L58>30%,"🛵",IF(G58/L58>15%,"🐢","⚓️")))))) -> 🐢 | I58: =IFERROR(IF((G58+N58-S58)/L58<0,"🔙",IF((G58+N58-S58)/L58<10%,"🥾",IF((G58+N58-S58)/L58<20%,"🛴",IF((G58+N58-S58)/L58<50%,"🚴‍♂️",IF((G58+N58-S58)/L58<75%,"🚖","🚁"))))),"") -> 🛴 | J58: =G58+N58-S58 -> 451.0642 | K58: =IFERROR(J58/(L58+N58),0) -> 0.10341072 | L58: =G58+F58+A58+B58 -> 4361.8708 | M58: =IF(R58=0,0,MAX(0,M57-G58+S58-N57)) -> 378539.25 | O58: =IF(AND(N58<>"",N58<R58),"V","") | P58: =IF(N57=0,"",(L57-L58)/N57) | Q58: =IF(N58=0,"",IF(N58>M58,"🚫",IF(INT(N58/G58<1),"👍",INT(N58/G58)&"x"))) | R58: =IF(M57=0,0,IF(OR(N57=0,O57="V"),R57-1,IF(OR(D$11="BRADESCO",D$11="BB"),R57-ROUNDDOWN(N57/(M57/R57),0)-1,ROUNDUP((M57-N57+S57-(M57/R57))/(L57-F58-A58-B58),0)+1))) -> 346 | S58: =M57*$T58 -> 644.28354 | T58: =IF(M57>0,T57,0) -> 0.0017 | AA58: =-(L58+N58) -> -4361.8708 | AH58: =ROUNDUP(E58/120,0) -> 1 | AI58: =ROUNDUP(E58/36,0) -> 2 | AJ58: =ROUNDUP(E58/12,0) -> 4 | AK58: =DAY(DATE(YEAR(C58),MONTH(C58)+1,1)-1) -> 30 | AR58: =IF(INT(AW58)>0,AR57,0) -> 25 | AS58: =IF(AW58>0.1,AS57,0) -> 75 | AT58: =DATE(YEAR(AT57),MONTH(AT57)+1,1) -> 47362 | AU58: =IFERROR(AX58/BD57,0) -> 0.0028901734 | AV58: =AV57+1 -> 44 | AW58: =IF(OR(BD57<1,BE57>BD57),0,(BD57-BE57)*IF(AU$11<>"BB",$E$7,(1+$D$7)^(BY57/365)-1)) -> 3166.5231 | AX58: =IF(BI58=0,0,IF(BD57<1,0,IF(AND(AND(((BD57-BE57)/BI58)<AX57,BF57<>"V"),AU$11<>"BRADESCO"),AX57, (BD57-BE57)/BI58))) -> 1095.3477 | AY58: =IF(OR(AX58=0,BC58<1),"",IF(AX58/BC58>90%,"🛩",IF(AX58/BC58>70%,"🏎",IF(AX58/BC58>50%,"🚙",IF(AX58/BC58>30%,"🛵",IF(AX58/BC58>15%,"🐢","⚓️")))))) -> 🐢 | AZ58: =IFERROR(IF((AX58+BE58-BJ58)/BC58<0,"🔙",IF((AX58+BE58-BJ58)/BC58<10%,"🥾",IF((AX58+BE58-BJ58)/BC58<20%,"🛴",IF((AX58+BE58-BJ58)/BC58<50%,"🚴‍♂️",IF((AX58+BE58-BJ58)/BC58<75%,"🚖","🚁"))))),"") -> 🛴 | BA58: =AX58+BE58-BJ58 -> 451.0642 | BB58: =IFERROR(BA58/(BC58+BE58),0) -> 0.10341072 | BC58: =AX58+AW58+AR58+AS58 -> 4361.8708 | BD58: =IF(BI58=0,0,MAX(0,BD57-AX58+BJ58-BE57)) -> 378539.25 | BF58: =IF(AND(BE58<>"",BE58<BI58),"V","") | BG58: =IF(BE57=0,"",(BC57-BC58)/BE57) | BH58: =IF(BE58=0,"",IF(BE58>BD58,"🚫",IF(INT(BE58/AX58<1),"👍",INT(BE58/AX58)&"x"))) | BI58: =IF(BD57=0,0,IF(OR(BE57=0,BF57="V"),BI57-1,IF(OR(AU$11="BRADESCO",AU$11="BB"),BI57-ROUNDDOWN(BE57/(BD57/BI57),0)-1,ROUNDUP((BD57-BE57+BJ57-(BD57/BI57))/(BC57-AW58-AR58-AS58),0)+1))) -> 346 | BJ58: =BD57*$BK57 -> 644.28354 | BK58: =IF(BD57>0,BK57,0) -> 0.0017
A59: =IF(INT(F59)>0,A58,0) -> 25 | B59: =IF(F59>0.1,B58,0) -> 75 | C59: =DATE(YEAR(C58),MONTH(C58)+1,1) -> 47392 | D59: =IFERROR(G59/M58,0) -> 0.0028985507 | E59: =E58+1 -> 45 | F59: =IF(OR(M58<1,N58>M58),0,(M58-N58)*IF(D$11<>"BB",$E$7,(1+$D$7)^(AK58/365)-1)) -> 3162.7544 | G59: =IF(R59=0,0,IF(M58<1,0,IF(AND(AND(((M58-N58)/R59)<G58,O58<>"V"),D$11<>"BRADESCO"),G58, (M58-N58)/R59))) -> 1097.2152 | H59: =IF(OR(G59=0,L59<1),"",IF(G59/L59>90%,"🛩",IF(G59/L59>70%,"🏎",IF(G59/L59>50%,"🚙",IF(G59/L59>30%,"🛵",IF(G59/L59>15%,"🐢","⚓️")))))) -> 🐢 | I59: =IFERROR(IF((G59+N59-S59)/L59<0,"🔙",IF((G59+N59-S59)/L59<10%,"🥾",IF((G59+N59-S59)/L59<20%,"🛴",IF((G59+N59-S59)/L59<50%,"🚴‍♂️",IF((G59+N59-S59)/L59<75%,"🚖","🚁"))))),"") -> 🛴 | J59: =G59+N59-S59 -> 453.69849 | K59: =IFERROR(J59/(L59+N59),0) -> 0.10406001 | L59: =G59+F59+A59+B59 -> 4359.9696 | M59: =IF(R59=0,0,MAX(0,M58-G59+S59-N58)) -> 378085.55 | O59: =IF(AND(N59<>"",N59<R59),"V","") | P59: =IF(N58=0,"",(L58-L59)/N58) | Q59: =IF(N59=0,"",IF(N59>M59,"🚫",IF(INT(N59/G59<1),"👍",INT(N59/G59)&"x"))) | R59: =IF(M58=0,0,IF(OR(N58=0,O58="V"),R58-1,IF(OR(D$11="BRADESCO",D$11="BB"),R58-ROUNDDOWN(N58/(M58/R58),0)-1,ROUNDUP((M58-N58+S58-(M58/R58))/(L58-F59-A59-B59),0)+1))) -> 345 | S59: =M58*$T59 -> 643.51673 | T59: =IF(M58>0,T58,0) -> 0.0017 | AA59: =-(L59+N59) -> -4359.9696 | AH59: =ROUNDUP(E59/120,0) -> 1 | AI59: =ROUNDUP(E59/36,0) -> 2 | AJ59: =ROUNDUP(E59/12,0) -> 4 | AK59: =DAY(DATE(YEAR(C59),MONTH(C59)+1,1)-1) -> 31 | AR59: =IF(INT(AW59)>0,AR58,0) -> 25 | AS59: =IF(AW59>0.1,AS58,0) -> 75 | AT59: =DATE(YEAR(AT58),MONTH(AT58)+1,1) -> 47392 | AU59: =IFERROR(AX59/BD58,0) -> 0.0028985507 | AV59: =AV58+1 -> 45 | AW59: =IF(OR(BD58<1,BE58>BD58),0,(BD58-BE58)*IF(AU$11<>"BB",$E$7,(1+$D$7)^(BY58/365)-1)) -> 3162.7544 | AX59: =IF(BI59=0,0,IF(BD58<1,0,IF(AND(AND(((BD58-BE58)/BI59)<AX58,BF58<>"V"),AU$11<>"BRADESCO"),AX58, (BD58-BE58)/BI59))) -> 1097.2152 | AY59: =IF(OR(AX59=0,BC59<1),"",IF(AX59/BC59>90%,"🛩",IF(AX59/BC59>70%,"🏎",IF(AX59/BC59>50%,"🚙",IF(AX59/BC59>30%,"🛵",IF(AX59/BC59>15%,"🐢","⚓️")))))) -> 🐢 | AZ59: =IFERROR(IF((AX59+BE59-BJ59)/BC59<0,"🔙",IF((AX59+BE59-BJ59)/BC59<10%,"🥾",IF((AX59+BE59-BJ59)/BC59<20%,"🛴",IF((AX59+BE59-BJ59)/BC59<50%,"🚴‍♂️",IF((AX59+BE59-BJ59)/BC59<75%,"🚖","🚁"))))),"") -> 🛴 | BA59: =AX59+BE59-BJ59 -> 453.69849 | BB59: =IFERROR(BA59/(BC59+BE59),0) -> 0.10406001 | BC59: =AX59+AW59+AR59+AS59 -> 4359.9696 | BD59: =IF(BI59=0,0,MAX(0,BD58-AX59+BJ59-BE58)) -> 378085.55 | BF59: =IF(AND(BE59<>"",BE59<BI59),"V","") | BG59: =IF(BE58=0,"",(BC58-BC59)/BE58) | BH59: =IF(BE59=0,"",IF(BE59>BD59,"🚫",IF(INT(BE59/AX59<1),"👍",INT(BE59/AX59)&"x"))) | BI59: =IF(BD58=0,0,IF(OR(BE58=0,BF58="V"),BI58-1,IF(OR(AU$11="BRADESCO",AU$11="BB"),BI58-ROUNDDOWN(BE58/(BD58/BI58),0)-1,ROUNDUP((BD58-BE58+BJ58-(BD58/BI58))/(BC58-AW59-AR59-AS59),0)+1))) -> 345 | BJ59: =BD58*$BK58 -> 643.51673 | BK59: =IF(BD58>0,BK58,0) -> 0.0017
A60: =IF(INT(F60)>0,A59,0) -> 25 | B60: =IF(F60>0.1,B59,0) -> 75 | C60: =DATE(YEAR(C59),MONTH(C59)+1,1) -> 47423 | D60: =IFERROR(G60/M59,0) -> 0.0029069767 | E60: =E59+1 -> 46 | F60: =IF(OR(M59<1,N59>M59),0,(M59-N59)*IF(D$11<>"BB",$E$7,(1+$D$7)^(AK59/365)-1)) -> 3158.9636 | G60: =IF(R60=0,0,IF(M59<1,0,IF(AND(AND(((M59-N59)/R60)<G59,O59<>"V"),D$11<>"BRADESCO"),G59, (M59-N59)/R60))) -> 1099.0859 | H60: =IF(OR(G60=0,L60<1),"",IF(G60/L60>90%,"🛩",IF(G60/L60>70%,"🏎",IF(G60/L60>50%,"🚙",IF(G60/L60>30%,"🛵",IF(G60/L60>15%,"🐢","⚓️")))))) -> 🐢 | I60: =IFERROR(IF((G60+N60-S60)/L60<0,"🔙",IF((G60+N60-S60)/L60<10%,"🥾",IF((G60+N60-S60)/L60<20%,"🛴",IF((G60+N60-S60)/L60<50%,"🚴‍♂️",IF((G60+N60-S60)/L60<75%,"🚖","🚁"))))),"") -> 🛴 | J60: =G60+N60-S60 -> 456.34047 | K60: =IFERROR(J60/(L60+N60),0) -> 0.10471209 | L60: =G60+F60+A60+B60 -> 4358.0496 | M60: =IF(R60=0,0,MAX(0,M59-G60+S60-N59)) -> 377629.21 | O60: =IF(AND(N60<>"",N60<R60),"V","") | P60: =IF(N59=0,"",(L59-L60)/N59) | Q60: =IF(N60=0,"",IF(N60>M60,"🚫",IF(INT(N60/G60<1),"👍",INT(N60/G60)&"x"))) | R60: =IF(M59=0,0,IF(OR(N59=0,O59="V"),R59-1,IF(OR(D$11="BRADESCO",D$11="BB"),R59-ROUNDDOWN(N59/(M59/R59),0)-1,ROUNDUP((M59-N59+S59-(M59/R59))/(L59-F60-A60-B60),0)+1))) -> 344 | S60: =M59*$T60 -> 642.74544 | T60: =IF(M59>0,T59,0) -> 0.0017 | AA60: =-(L60+N60) -> -4358.0496 | AH60: =ROUNDUP(E60/120,0) -> 1 | AI60: =ROUNDUP(E60/36,0) -> 2 | AJ60: =ROUNDUP(E60/12,0) -> 4 | AK60: =DAY(DATE(YEAR(C60),MONTH(C60)+1,1)-1) -> 30 | AR60: =IF(INT(AW60)>0,AR59,0) -> 25 | AS60: =IF(AW60>0.1,AS59,0) -> 75 | AT60: =DATE(YEAR(AT59),MONTH(AT59)+1,1) -> 47423 | AU60: =IFERROR(AX60/BD59,0) -> 0.0029069767 | AV60: =AV59+1 -> 46 | AW60: =IF(OR(BD59<1,BE59>BD59),0,(BD59-BE59)*IF(AU$11<>"BB",$E$7,(1+$D$7)^(BY59/365)-1)) -> 3158.9636 | AX60: =IF(BI60=0,0,IF(BD59<1,0,IF(AND(AND(((BD59-BE59)/BI60)<AX59,BF59<>"V"),AU$11<>"BRADESCO"),AX59, (BD59-BE59)/BI60))) -> 1099.0859 | AY60: =IF(OR(AX60=0,BC60<1),"",IF(AX60/BC60>90%,"🛩",IF(AX60/BC60>70%,"🏎",IF(AX60/BC60>50%,"🚙",IF(AX60/BC60>30%,"🛵",IF(AX60/BC60>15%,"🐢","⚓️")))))) -> 🐢 | AZ60: =IFERROR(IF((AX60+BE60-BJ60)/BC60<0,"🔙",IF((AX60+BE60-BJ60)/BC60<10%,"🥾",IF((AX60+BE60-BJ60)/BC60<20%,"🛴",IF((AX60+BE60-BJ60)/BC60<50%,"🚴‍♂️",IF((AX60+BE60-BJ60)/BC60<75%,"🚖","🚁"))))),"") -> 🛴 | BA60: =AX60+BE60-BJ60 -> 456.34047 | BB60: =IFERROR(BA60/(BC60+BE60),0) -> 0.10471209 | BC60: =AX60+AW60+AR60+AS60 -> 4358.0496 | BD60: =IF(BI60=0,0,MAX(0,BD59-AX60+BJ60-BE59)) -> 377629.21 | BF60: =IF(AND(BE60<>"",BE60<BI60),"V","") | BG60: =IF(BE59=0,"",(BC59-BC60)/BE59) | BH60: =IF(BE60=0,"",IF(BE60>BD60,"🚫",IF(INT(BE60/AX60<1),"👍",INT(BE60/AX60)&"x"))) | BI60: =IF(BD59=0,0,IF(OR(BE59=0,BF59="V"),BI59-1,IF(OR(AU$11="BRADESCO",AU$11="BB"),BI59-ROUNDDOWN(BE59/(BD59/BI59),0)-1,ROUNDUP((BD59-BE59+BJ59-(BD59/BI59))/(BC59-AW60-AR60-AS60),0)+1))) -> 344 | BJ60: =BD59*$BK59 -> 642.74544 | BK60: =IF(BD59>0,BK59,0) -> 0.0017
A61: =IF(INT(F61)>0,A60,0) -> 25 | B61: =IF(F61>0.1,B60,0) -> 75 | C61: =DATE(YEAR(C60),MONTH(C60)+1,1) -> 47453 | D61: =IFERROR(G61/M60,0) -> 0.0029154519 | E61: =E60+1 -> 47 | F61: =IF(OR(M60<1,N60>M60),0,(M60-N60)*IF(D$11<>"BB",$E$7,(1+$D$7)^(AK60/365)-1)) -> 3155.1509 | G61: =IF(R61=0,0,IF(M60<1,0,IF(AND(AND(((M60-N60)/R61)<G60,O60<>"V"),D$11<>"BRADESCO"),G60, (M60-N60)/R61))) -> 1100.9598 | H61: =IF(OR(G61=0,L61<1),"",IF(G61/L61>90%,"🛩",IF(G61/L61>70%,"🏎",IF(G61/L61>50%,"🚙",IF(G61/L61>30%,"🛵",IF(G61/L61>15%,"🐢","⚓️")))))) -> 🐢 | I61: =IFERROR(IF((G61+N61-S61)/L61<0,"🔙",IF((G61+N61-S61)/L61<10%,"🥾",IF((G61+N61-S61)/L61<20%,"🛴",IF((G61+N61-S61)/L61<50%,"🚴‍♂️",IF((G61+N61-S61)/L61<75%,"🚖","🚁"))))),"") -> 🛴 | J61: =G61+N61-S61 -> 458.99014 | K61: =IFERROR(J61/(L61+N61),0) -> 0.10536696 | L61: =G61+F61+A61+B61 -> 4356.1107 | M61: =IF(R61=0,0,MAX(0,M60-G61+S61-N60)) -> 377170.22 | O61: =IF(AND(N61<>"",N61<R61),"V","") | P61: =IF(N60=0,"",(L60-L61)/N60) | Q61: =IF(N61=0,"",IF(N61>M61,"🚫",IF(INT(N61/G61<1),"👍",INT(N61/G61)&"x"))) | R61: =IF(M60=0,0,IF(OR(N60=0,O60="V"),R60-1,IF(OR(D$11="BRADESCO",D$11="BB"),R60-ROUNDDOWN(N60/(M60/R60),0)-1,ROUNDUP((M60-N60+S60-(M60/R60))/(L60-F61-A61-B61),0)+1))) -> 343 | S61: =M60*$T61 -> 641.96966 | T61: =IF(M60>0,T60,0) -> 0.0017 | AA61: =-(L61+N61) -> -4356.1107 | AH61: =ROUNDUP(E61/120,0) -> 1 | AI61: =ROUNDUP(E61/36,0) -> 2 | AJ61: =ROUNDUP(E61/12,0) -> 4 | AK61: =DAY(DATE(YEAR(C61),MONTH(C61)+1,1)-1) -> 31 | AR61: =IF(INT(AW61)>0,AR60,0) -> 25 | AS61: =IF(AW61>0.1,AS60,0) -> 75 | AT61: =DATE(YEAR(AT60),MONTH(AT60)+1,1) -> 47453 | AU61: =IFERROR(AX61/BD60,0) -> 0.0029154519 | AV61: =AV60+1 -> 47 | AW61: =IF(OR(BD60<1,BE60>BD60),0,(BD60-BE60)*IF(AU$11<>"BB",$E$7,(1+$D$7)^(BY60/365)-1)) -> 3155.1509 | AX61: =IF(BI61=0,0,IF(BD60<1,0,IF(AND(AND(((BD60-BE60)/BI61)<AX60,BF60<>"V"),AU$11<>"BRADESCO"),AX60, (BD60-BE60)/BI61))) -> 1100.9598 | AY61: =IF(OR(AX61=0,BC61<1),"",IF(AX61/BC61>90%,"🛩",IF(AX61/BC61>70%,"🏎",IF(AX61/BC61>50%,"🚙",IF(AX61/BC61>30%,"🛵",IF(AX61/BC61>15%,"🐢","⚓️")))))) -> 🐢 | AZ61: =IFERROR(IF((AX61+BE61-BJ61)/BC61<0,"🔙",IF((AX61+BE61-BJ61)/BC61<10%,"🥾",IF((AX61+BE61-BJ61)/BC61<20%,"🛴",IF((AX61+BE61-BJ61)/BC61<50%,"🚴‍♂️",IF((AX61+BE61-BJ61)/BC61<75%,"🚖","🚁"))))),"") -> 🛴 | BA61: =AX61+BE61-BJ61 -> 458.99014 | BB61: =IFERROR(BA61/(BC61+BE61),0) -> 0.10536696 | BC61: =AX61+AW61+AR61+AS61 -> 4356.1107 | BD61: =IF(BI61=0,0,MAX(0,BD60-AX61+BJ61-BE60)) -> 377170.22 | BF61: =IF(AND(BE61<>"",BE61<BI61),"V","") | BG61: =IF(BE60=0,"",(BC60-BC61)/BE60) | BH61: =IF(BE61=0,"",IF(BE61>BD61,"🚫",IF(INT(BE61/AX61<1),"👍",INT(BE61/AX61)&"x"))) | BI61: =IF(BD60=0,0,IF(OR(BE60=0,BF60="V"),BI60-1,IF(OR(AU$11="BRADESCO",AU$11="BB"),BI60-ROUNDDOWN(BE60/(BD60/BI60),0)-1,ROUNDUP((BD60-BE60+BJ60-(BD60/BI60))/(BC60-AW61-AR61-AS61),0)+1))) -> 343 | BJ61: =BD60*$BK60 -> 641.96966 | BK61: =IF(BD60>0,BK60,0) -> 0.0017
A62: =IF(INT(F62)>0,A61,0) -> 25 | B62: =IF(F62>0.1,B61,0) -> 75 | C62: =DATE(YEAR(C61),MONTH(C61)+1,1) -> 47484 | D62: =IFERROR(G62/M61,0) -> 0.0029239766 | E62: =E61+1 -> 48 | F62: =IF(OR(M61<1,N61>M61),0,(M61-N61)*IF(D$11<>"BB",$E$7,(1+$D$7)^(AK61/365)-1)) -> 3151.3159 | G62: =IF(R62=0,0,IF(M61<1,0,IF(AND(AND(((M61-N61)/R62)<G61,O61<>"V"),D$11<>"BRADESCO"),G61, (M61-N61)/R62))) -> 1102.8369 | H62: =IF(OR(G62=0,L62<1),"",IF(G62/L62>90%,"🛩",IF(G62/L62>70%,"🏎",IF(G62/L62>50%,"🚙",IF(G62/L62>30%,"🛵",IF(G62/L62>15%,"🐢","⚓️")))))) -> 🐢 | I62: =IFERROR(IF((G62+N62-S62)/L62<0,"🔙",IF((G62+N62-S62)/L62<10%,"🥾",IF((G62+N62-S62)/L62<20%,"🛴",IF((G62+N62-S62)/L62<50%,"🚴‍♂️",IF((G62+N62-S62)/L62<75%,"🚖","🚁"))))),"") -> 🛴 | J62: =G62+N62-S62 -> 461.64753 | K62: =IFERROR(J62/(L62+N62),0) -> 0.10602465 | L62: =G62+F62+A62+B62 -> 4354.1528 | M62: =IF(R62=0,0,MAX(0,M61-G62+S62-N61)) -> 376708.57 | O62: =IF(AND(N62<>"",N62<R62),"V","") | P62: =IF(N61=0,"",(L61-L62)/N61) | Q62: =IF(N62=0,"",IF(N62>M62,"🚫",IF(INT(N62/G62<1),"👍",INT(N62/G62)&"x"))) | R62: =IF(M61=0,0,IF(OR(N61=0,O61="V"),R61-1,IF(OR(D$11="BRADESCO",D$11="BB"),R61-ROUNDDOWN(N61/(M61/R61),0)-1,ROUNDUP((M61-N61+S61-(M61/R61))/(L61-F62-A62-B62),0)+1))) -> 342 | S62: =M61*$T62 -> 641.18938 | T62: =IF(M61>0,T61,0) -> 0.0017 | AA62: =-(L62+N62) -> -4354.1528 | AH62: =ROUNDUP(E62/120,0) -> 1 | AI62: =ROUNDUP(E62/36,0) -> 2 | AJ62: =ROUNDUP(E62/12,0) -> 4 | AK62: =DAY(DATE(YEAR(C62),MONTH(C62)+1,1)-1) -> 31 | AR62: =IF(INT(AW62)>0,AR61,0) -> 25 | AS62: =IF(AW62>0.1,AS61,0) -> 75 | AT62: =DATE(YEAR(AT61),MONTH(AT61)+1,1) -> 47484 | AU62: =IFERROR(AX62/BD61,0) -> 0.0029239766 | AV62: =AV61+1 -> 48 | AW62: =IF(OR(BD61<1,BE61>BD61),0,(BD61-BE61)*IF(AU$11<>"BB",$E$7,(1+$D$7)^(BY61/365)-1)) -> 3151.3159 | AX62: =IF(BI62=0,0,IF(BD61<1,0,IF(AND(AND(((BD61-BE61)/BI62)<AX61,BF61<>"V"),AU$11<>"BRADESCO"),AX61, (BD61-BE61)/BI62))) -> 1102.8369 | AY62: =IF(OR(AX62=0,BC62<1),"",IF(AX62/BC62>90%,"🛩",IF(AX62/BC62>70%,"🏎",IF(AX62/BC62>50%,"🚙",IF(AX62/BC62>30%,"🛵",IF(AX62/BC62>15%,"🐢","⚓️")))))) -> 🐢 | AZ62: =IFERROR(IF((AX62+BE62-BJ62)/BC62<0,"🔙",IF((AX62+BE62-BJ62)/BC62<10%,"🥾",IF((AX62+BE62-BJ62)/BC62<20%,"🛴",IF((AX62+BE62-BJ62)/BC62<50%,"🚴‍♂️",IF((AX62+BE62-BJ62)/BC62<75%,"🚖","🚁"))))),"") -> 🛴 | BA62: =AX62+BE62-BJ62 -> 461.64753 | BB62: =IFERROR(BA62/(BC62+BE62),0) -> 0.10602465 | BC62: =AX62+AW62+AR62+AS62 -> 4354.1528 | BD62: =IF(BI62=0,0,MAX(0,BD61-AX62+BJ62-BE61)) -> 376708.57 | BF62: =IF(AND(BE62<>"",BE62<BI62),"V","") | BG62: =IF(BE61=0,"",(BC61-BC62)/BE61) | BH62: =IF(BE62=0,"",IF(BE62>BD62,"🚫",IF(INT(BE62/AX62<1),"👍",INT(BE62/AX62)&"x"))) | BI62: =IF(BD61=0,0,IF(OR(BE61=0,BF61="V"),BI61-1,IF(OR(AU$11="BRADESCO",AU$11="BB"),BI61-ROUNDDOWN(BE61/(BD61/BI61),0)-1,ROUNDUP((BD61-BE61+BJ61-(BD61/BI61))/(BC61-AW62-AR62-AS62),0)+1))) -> 342 | BJ62: =BD61*$BK61 -> 641.18938 | BK62: =IF(BD61>0,BK61,0) -> 0.0017
A63: =IF(INT(F63)>0,A62,0) -> 25 | B63: =IF(F63>0.1,B62,0) -> 75 | C63: =DATE(YEAR(C62),MONTH(C62)+1,1) -> 47515 | D63: =IFERROR(G63/M62,0) -> 0.0029325513 | E63: =E62+1 -> 49 | F63: =IF(OR(M62<1,N62>M62),0,(M62-N62)*IF(D$11<>"BB",$E$7,(1+$D$7)^(AK62/365)-1)) -> 3147.4588 | G63: =IF(R63=0,0,IF(M62<1,0,IF(AND(AND(((M62-N62)/R63)<G62,O62<>"V"),D$11<>"BRADESCO"),G62, (M62-N62)/R63))) -> 1104.7172 | H63: =IF(OR(G63=0,L63<1),"",IF(G63/L63>90%,"🛩",IF(G63/L63>70%,"🏎",IF(G63/L63>50%,"🚙",IF(G63/L63>30%,"🛵",IF(G63/L63>15%,"🐢","⚓️")))))) -> 🐢 | I63: =IFERROR(IF((G63+N63-S63)/L63<0,"🔙",IF((G63+N63-S63)/L63<10%,"🥾",IF((G63+N63-S63)/L63<20%,"🛴",IF((G63+N63-S63)/L63<50%,"🚴‍♂️",IF((G63+N63-S63)/L63<75%,"🚖","🚁"))))),"") -> 🛴 | J63: =G63+N63-S63 -> 464.31265 | K63: =IFERROR(J63/(L63+N63),0) -> 0.10668517 | L63: =G63+F63+A63+B63 -> 4352.176 | M63: =IF(R63=0,0,MAX(0,M62-G63+S63-N62)) -> 376244.26 | O63: =IF(AND(N63<>"",N63<R63),"V","") | P63: =IF(N62=0,"",(L62-L63)/N62) | Q63: =IF(N63=0,"",IF(N63>M63,"🚫",IF(INT(N63/G63<1),"👍",INT(N63/G63)&"x"))) | R63: =IF(M62=0,0,IF(OR(N62=0,O62="V"),R62-1,IF(OR(D$11="BRADESCO",D$11="BB"),R62-ROUNDDOWN(N62/(M62/R62),0)-1,ROUNDUP((M62-N62+S62-(M62/R62))/(L62-F63-A63-B63),0)+1))) -> 341 | S63: =M62*$T63 -> 640.40458 | T63: =IF(M62>0,T62,0) -> 0.0017 | AA63: =-(L63+N63) -> -4352.176 | AH63: =ROUNDUP(E63/120,0) -> 1 | AI63: =ROUNDUP(E63/36,0) -> 2 | AJ63: =ROUNDUP(E63/12,0) -> 5 | AK63: =DAY(DATE(YEAR(C63),MONTH(C63)+1,1)-1) -> 28 | AR63: =IF(INT(AW63)>0,AR62,0) -> 25 | AS63: =IF(AW63>0.1,AS62,0) -> 75 | AT63: =DATE(YEAR(AT62),MONTH(AT62)+1,1) -> 47515 | AU63: =IFERROR(AX63/BD62,0) -> 0.0029325513 | AV63: =AV62+1 -> 49 | AW63: =IF(OR(BD62<1,BE62>BD62),0,(BD62-BE62)*IF(AU$11<>"BB",$E$7,(1+$D$7)^(BY62/365)-1)) -> 3147.4588 | AX63: =IF(BI63=0,0,IF(BD62<1,0,IF(AND(AND(((BD62-BE62)/BI63)<AX62,BF62<>"V"),AU$11<>"BRADESCO"),AX62, (BD62-BE62)/BI63))) -> 1104.7172 | AY63: =IF(OR(AX63=0,BC63<1),"",IF(AX63/BC63>90%,"🛩",IF(AX63/BC63>70%,"🏎",IF(AX63/BC63>50%,"🚙",IF(AX63/BC63>30%,"🛵",IF(AX63/BC63>15%,"🐢","⚓️")))))) -> 🐢 | AZ63: =IFERROR(IF((AX63+BE63-BJ63)/BC63<0,"🔙",IF((AX63+BE63-BJ63)/BC63<10%,"🥾",IF((AX63+BE63-BJ63)/BC63<20%,"🛴",IF((AX63+BE63-BJ63)/BC63<50%,"🚴‍♂️",IF((AX63+BE63-BJ63)/BC63<75%,"🚖","🚁"))))),"") -> 🛴 | BA63: =AX63+BE63-BJ63 -> 464.31265 | BB63: =IFERROR(BA63/(BC63+BE63),0) -> 0.10668517 | BC63: =AX63+AW63+AR63+AS63 -> 4352.176 | BD63: =IF(BI63=0,0,MAX(0,BD62-AX63+BJ63-BE62)) -> 376244.26 | BF63: =IF(AND(BE63<>"",BE63<BI63),"V","") | BG63: =IF(BE62=0,"",(BC62-BC63)/BE62) | BH63: =IF(BE63=0,"",IF(BE63>BD63,"🚫",IF(INT(BE63/AX63<1),"👍",INT(BE63/AX63)&"x"))) | BI63: =IF(BD62=0,0,IF(OR(BE62=0,BF62="V"),BI62-1,IF(OR(AU$11="BRADESCO",AU$11="BB"),BI62-ROUNDDOWN(BE62/(BD62/BI62),0)-1,ROUNDUP((BD62-BE62+BJ62-(BD62/BI62))/(BC62-AW63-AR63-AS63),0)+1))) -> 341 | BJ63: =BD62*$BK62 -> 640.40458 | BK63: =IF(BD62>0,BK62,0) -> 0.0017
... A74: =IF(INT(F74)>0,A73,0) -> 25 | B74: =IF(F74>0.1,B73,0) -> 75 | C74: =DATE(YEAR(C73),MONTH(C73)+1,1) -> 47849 | D74: =IFERROR(G74/M73,0) -> 0.003030303 | E74: =E73+1 -> 60 | F74: =IF(OR(M73<1,N73>M73),0,(M73-N73)*IF(D$11<>"BB",$E$7,(1+$D$7)^(AK73/365)-1)) -> 3103.5463 | G74: =IF(R74=0,0,IF(M73<1,0,IF(AND(AND(((M73-N73)/R74)<G73,O73<>"V"),D$11<>"BRADESCO"),G73, (M73-N73)/R74))) -> 1125.6147 | H74: =IF(OR(G74=0,L74<1),"",IF(G74/L74>90%,"🛩",IF(G74/L74>70%,"🏎",IF(G74/L74>50%,"🚙",IF(G74/L74>30%,"🛵",IF(G74/L74>15%,"🐢","⚓️")))))) -> 🐢 | I74: =IFERROR(IF((G74+N74-S74)/L74<0,"🔙",IF((G74+N74-S74)/L74<10%,"🥾",IF((G74+N74-S74)/L74<20%,"🛴",IF((G74+N74-S74)/L74<50%,"🚴‍♂️",IF((G74+N74-S74)/L74<75%,"🚖","🚁"))))),"") -> 🛴 | J74: =G74+N74-S74 -> 494.14484 | K74: =IFERROR(J74/(L74+N74),0) -> 0.11414333 | L74: =G74+F74+A74+B74 -> 4329.161 | M74: =IF(R74=0,0,MAX(0,M73-G74+S74-N73)) -> 370958.69 | O74: =IF(AND(N74<>"",N74<R74),"V","") | P74: =IF(N73=0,"",(L73-L74)/N73) | Q74: =IF(N74=0,"",IF(N74>M74,"🚫",IF(INT(N74/G74<1),"👍",INT(N74/G74)&"x"))) | R74: =IF(M73=0,0,IF(OR(N73=0,O73="V"),R73-1,IF(OR(D$11="BRADESCO",D$11="BB"),R73-ROUNDDOWN(N73/(M73/R73),0)-1,ROUNDUP((M73-N73+S73-(M73/R73))/(L73-F74-A74-B74),0)+1))) -> 330 | S74: =M73*$T74 -> 631.46982 | T74: =IF(M73>0,T73,0) -> 0.0017 | AA74: =-(L74+N74) -> -4329.161 | AH74: =ROUNDUP(E74/120,0) -> 1 | AI74: =ROUNDUP(E74/36,0) -> 2 | AJ74: =ROUNDUP(E74/12,0) -> 5 | AK74: =DAY(DATE(YEAR(C74),MONTH(C74)+1,1)-1) -> 31 | AR74: =IF(INT(AW74)>0,AR73,0) -> 25 | AS74: =IF(AW74>0.1,AS73,0) -> 75 | AT74: =DATE(YEAR(AT73),MONTH(AT73)+1,1) -> 47849 | AU74: =IFERROR(AX74/BD73,0) -> 0.003030303 | AV74: =AV73+1 -> 60 | AW74: =IF(OR(BD73<1,BE73>BD73),0,(BD73-BE73)*IF(AU$11<>"BB",$E$7,(1+$D$7)^(BY73/365)-1)) -> 3103.5463 | AX74: =IF(BI74=0,0,IF(BD73<1,0,IF(AND(AND(((BD73-BE73)/BI74)<AX73,BF73<>"V"),AU$11<>"BRADESCO"),AX73, (BD73-BE73)/BI74))) -> 1125.6147 | AY74: =IF(OR(AX74=0,BC74<1),"",IF(AX74/BC74>90%,"🛩",IF(AX74/BC74>70%,"🏎",IF(AX74/BC74>50%,"🚙",IF(AX74/BC74>30%,"🛵",IF(AX74/BC74>15%,"🐢","⚓️")))))) -> 🐢 | AZ74: =IFERROR(IF((AX74+BE74-BJ74)/BC74<0,"🔙",IF((AX74+BE74-BJ74)/BC74<10%,"🥾",IF((AX74+BE74-BJ74)/BC74<20%,"🛴",IF((AX74+BE74-BJ74)/BC74<50%,"🚴‍♂️",IF((AX74+BE74-BJ74)/BC74<75%,"🚖","🚁"))))),"") -> 🛴 | BA74: =AX74+BE74-BJ74 -> 494.14484 | BB74: =IFERROR(BA74/(BC74+BE74),0) -> 0.11414333 | BC74: =AX74+AW74+AR74+AS74 -> 4329.161 | BD74: =IF(BI74=0,0,MAX(0,BD73-AX74+BJ74-BE73)) -> 370958.69 | BF74: =IF(AND(BE74<>"",BE74<BI74),"V","") | BG74: =IF(BE73=0,"",(BC73-BC74)/BE73) | BH74: =IF(BE74=0,"",IF(BE74>BD74,"🚫",IF(INT(BE74/AX74<1),"👍",INT(BE74/AX74)&"x"))) | BI74: =IF(BD73=0,0,IF(OR(BE73=0,BF73="V"),BI73-1,IF(OR(AU$11="BRADESCO",AU$11="BB"),BI73-ROUNDDOWN(BE73/(BD73/BI73),0)-1,ROUNDUP((BD73-BE73+BJ73-(BD73/BI73))/(BC73-AW74-AR74-AS74),0)+1))) -> 330 | BJ74: =BD73*$BK73 -> 631.46982 | BK74: =IF(BD73>0,BK73,0) -> 0.0017
A75: =IF(INT(F75)>0,A74,0) -> 25 | B75: =IF(F75>0.1,B74,0) -> 75 | C75: =DATE(YEAR(C74),MONTH(C74)+1,1) -> 47880 | D75: =IFERROR(G75/M74,0) -> 0.0030395137 | E75: =E74+1 -> 61 | F75: =IF(OR(M74<1,N74>M74),0,(M74-N74)*IF(D$11<>"BB",$E$7,(1+$D$7)^(AK74/365)-1)) -> 3099.4176 | G75: =IF(R75=0,0,IF(M74<1,0,IF(AND(AND(((M74-N74)/R75)<G74,O74<>"V"),D$11<>"BRADESCO"),G74, (M74-N74)/R75))) -> 1127.534 | H75: =IF(OR(G75=0,L75<1),"",IF(G75/L75>90%,"🛩",IF(G75/L75>70%,"🏎",IF(G75/L75>50%,"🚙",IF(G75/L75>30%,"🛵",IF(G75/L75>15%,"🐢","⚓️")))))) -> 🐢 | I75: =IFERROR(IF((G75+N75-S75)/L75<0,"🔙",IF((G75+N75-S75)/L75<10%,"🥾",IF((G75+N75-S75)/L75<20%,"🛴",IF((G75+N75-S75)/L75<50%,"🚴‍♂️",IF((G75+N75-S75)/L75<75%,"🚖","🚁"))))),"") -> 🛴 | J75: =G75+N75-S75 -> 496.90424 | K75: =IFERROR(J75/(L75+N75),0) -> 0.11483933 | L75: =G75+F75+A75+B75 -> 4326.9517 | M75: =IF(R75=0,0,MAX(0,M74-G75+S75-N74)) -> 370461.79 | P75: =IF(N74=0,"",(L74-L75)/N74) | Q75: =IF(N75=0,"",IF(N75>M75,"🚫",IF(INT(N75/G75<1),"👍",INT(N75/G75)&"x"))) | R75: =IF(M74=0,0,IF(OR(N74=0,O74="V"),R74-1,IF(OR(D$11="BRADESCO",D$11="BB"),R74-ROUNDDOWN(N74/(M74/R74),0)-1,ROUNDUP((M74-N74+S74-(M74/R74))/(L74-F75-A75-B75),0)+1))) -> 329 | S75: =M74*$T75 -> 630.62978 | T75: =IF(M74>0,T74,0) -> 0.0017 | AA75: =-(L75+N75) -> -4326.9517 | AH75: =ROUNDUP(E75/120,0) -> 1 | AI75: =ROUNDUP(E75/36,0) -> 2 | AJ75: =ROUNDUP(E75/12,0) -> 6 | AK75: =DAY(DATE(YEAR(C75),MONTH(C75)+1,1)-1) -> 28 | AR75: =IF(INT(AW75)>0,AR74,0) -> 25 | AS75: =IF(AW75>0.1,AS74,0) -> 75 | AT75: =DATE(YEAR(AT74),MONTH(AT74)+1,1) -> 47880 | AU75: =IFERROR(AX75/BD74,0) -> 0.0030395137 | AV75: =AV74+1 -> 61 | AW75: =IF(OR(BD74<1,BE74>BD74),0,(BD74-BE74)*IF(AU$11<>"BB",$E$7,(1+$D$7)^(BY74/365)-1)) -> 3099.4176 | AX75: =IF(BI75=0,0,IF(BD74<1,0,IF(AND(AND(((BD74-BE74)/BI75)<AX74,BF74<>"V"),AU$11<>"BRADESCO"),AX74, (BD74-BE74)/BI75))) -> 1127.534 | AY75: =IF(OR(AX75=0,BC75<1),"",IF(AX75/BC75>90%,"🛩",IF(AX75/BC75>70%,"🏎",IF(AX75/BC75>50%,"🚙",IF(AX75/BC75>30%,"🛵",IF(AX75/BC75>15%,"🐢","⚓️")))))) -> 🐢 | AZ75: =IFERROR(IF((AX75+BE75-BJ75)/BC75<0,"🔙",IF((AX75+BE75-BJ75)/BC75<10%,"🥾",IF((AX75+BE75-BJ75)/BC75<20%,"🛴",IF((AX75+BE75-BJ75)/BC75<50%,"🚴‍♂️",IF((AX75+BE75-BJ75)/BC75<75%,"🚖","🚁"))))),"") -> 🛴 | BA75: =AX75+BE75-BJ75 -> 496.90424 | BB75: =IFERROR(BA75/(BC75+BE75),0) -> 0.11483933 | BC75: =AX75+AW75+AR75+AS75 -> 4326.9517 | BD75: =IF(BI75=0,0,MAX(0,BD74-AX75+BJ75-BE74)) -> 370461.79 | BG75: =IF(BE74=0,"",(BC74-BC75)/BE74) | BH75: =IF(BE75=0,"",IF(BE75>BD75,"🚫",IF(INT(BE75/AX75<1),"👍",INT(BE75/AX75)&"x"))) | BI75: =IF(BD74=0,0,IF(OR(BE74=0,BF74="V"),BI74-1,IF(OR(AU$11="BRADESCO",AU$11="BB"),BI74-ROUNDDOWN(BE74/(BD74/BI74),0)-1,ROUNDUP((BD74-BE74+BJ74-(BD74/BI74))/(BC74-AW75-AR75-AS75),0)+1))) -> 329 | BJ75: =BD74*$BK74 -> 630.62978 | BK75: =IF(BD74>0,BK74,0) -> 0.0017
A76: =IF(INT(F76)>0,A75,0) -> 25 | B76: =IF(F76>0.1,B75,0) -> 75 | C76: =DATE(YEAR(C75),MONTH(C75)+1,1) -> 47908 | D76: =IFERROR(G76/M75,0) -> 0.0030487805 | E76: =E75+1 -> 62 | F76: =IF(OR(M75<1,N75>M75),0,(M75-N75)*IF(D$11<>"BB",$E$7,(1+$D$7)^(AK75/365)-1)) -> 3095.2659 | G76: =IF(R76=0,0,IF(M75<1,0,IF(AND(AND(((M75-N75)/R76)<G75,O75<>"V"),D$11<>"BRADESCO"),G75, (M75-N75)/R76))) -> 1129.4567 | H76: =IF(OR(G76=0,L76<1),"",IF(G76/L76>90%,"🛩",IF(G76/L76>70%,"🏎",IF(G76/L76>50%,"🚙",IF(G76/L76>30%,"🛵",IF(G76/L76>15%,"🐢","⚓️")))))) -> 🐢 | I76: =IFERROR(IF((G76+N76-S76)/L76<0,"🔙",IF((G76+N76-S76)/L76<10%,"🥾",IF((G76+N76-S76)/L76<20%,"🛴",IF((G76+N76-S76)/L76<50%,"🚴‍♂️",IF((G76+N76-S76)/L76<75%,"🚖","🚁"))))),"") -> 🛴 | J76: =G76+N76-S76 -> 499.67163 | K76: =IFERROR(J76/(L76+N76),0) -> 0.11553842 | L76: =G76+F76+A76+B76 -> 4324.7226 | M76: =IF(R76=0,0,MAX(0,M75-G76+S76-N75)) -> 369962.12 | O76: =IF(AND(N76<>"",N76<R76),"V","") | P76: =IF(N75=0,"",(L75-L76)/N75) | Q76: =IF(N76=0,"",IF(N76>M76,"🚫",IF(INT(N76/G76<1),"👍",INT(N76/G76)&"x"))) | R76: =IF(M75=0,0,IF(OR(N75=0,O75="V"),R75-1,IF(OR(D$11="BRADESCO",D$11="BB"),R75-ROUNDDOWN(N75/(M75/R75),0)-1,ROUNDUP((M75-N75+S75-(M75/R75))/(L75-F76-A76-B76),0)+1))) -> 328 | S76: =M75*$T76 -> 629.78504 | T76: =IF(M75>0,T75,0) -> 0.0017 | AA76: =-(L76+N76) -> -4324.7226 | AH76: =ROUNDUP(E76/120,0) -> 1 | AI76: =ROUNDUP(E76/36,0) -> 2 | AJ76: =ROUNDUP(E76/12,0) -> 6 | AK76: =DAY(DATE(YEAR(C76),MONTH(C76)+1,1)-1) -> 31 | AR76: =IF(INT(AW76)>0,AR75,0) -> 25 | AS76: =IF(AW76>0.1,AS75,0) -> 75 | AT76: =DATE(YEAR(AT75),MONTH(AT75)+1,1) -> 47908 | AU76: =IFERROR(AX76/BD75,0) -> 0.0030487805 | AV76: =AV75+1 -> 62 | AW76: =IF(OR(BD75<1,BE75>BD75),0,(BD75-BE75)*IF(AU$11<>"BB",$E$7,(1+$D$7)^(BY75/365)-1)) -> 3095.2659 | AX76: =IF(BI76=0,0,IF(BD75<1,0,IF(AND(AND(((BD75-BE75)/BI76)<AX75,BF75<>"V"),AU$11<>"BRADESCO"),AX75, (BD75-BE75)/BI76))) -> 1129.4567 | AY76: =IF(OR(AX76=0,BC76<1),"",IF(AX76/BC76>90%,"🛩",IF(AX76/BC76>70%,"🏎",IF(AX76/BC76>50%,"🚙",IF(AX76/BC76>30%,"🛵",IF(AX76/BC76>15%,"🐢","⚓️")))))) -> 🐢 | AZ76: =IFERROR(IF((AX76+BE76-BJ76)/BC76<0,"🔙",IF((AX76+BE76-BJ76)/BC76<10%,"🥾",IF((AX76+BE76-BJ76)/BC76<20%,"🛴",IF((AX76+BE76-BJ76)/BC76<50%,"🚴‍♂️",IF((AX76+BE76-BJ76)/BC76<75%,"🚖","🚁"))))),"") -> 🛴 | BA76: =AX76+BE76-BJ76 -> 499.67163 | BB76: =IFERROR(BA76/(BC76+BE76),0) -> 0.11553842 | BC76: =AX76+AW76+AR76+AS76 -> 4324.7226 | BD76: =IF(BI76=0,0,MAX(0,BD75-AX76+BJ76-BE75)) -> 369962.12 | BF76: =IF(AND(BE76<>"",BE76<BI76),"V","") | BG76: =IF(BE75=0,"",(BC75-BC76)/BE75) | BH76: =IF(BE76=0,"",IF(BE76>BD76,"🚫",IF(INT(BE76/AX76<1),"👍",INT(BE76/AX76)&"x"))) | BI76: =IF(BD75=0,0,IF(OR(BE75=0,BF75="V"),BI75-1,IF(OR(AU$11="BRADESCO",AU$11="BB"),BI75-ROUNDDOWN(BE75/(BD75/BI75),0)-1,ROUNDUP((BD75-BE75+BJ75-(BD75/BI75))/(BC75-AW76-AR76-AS76),0)+1))) -> 328 | BJ76: =BD75*$BK75 -> 629.78504 | BK76: =IF(BD75>0,BK75,0) -> 0.0017
A77: =IF(INT(F77)>0,A76,0) -> 25 | B77: =IF(F77>0.1,B76,0) -> 75 | C77: =DATE(YEAR(C76),MONTH(C76)+1,1) -> 47939 | D77: =IFERROR(G77/M76,0) -> 0.003058104 | E77: =E76+1 -> 63 | F77: =IF(OR(M76<1,N76>M76),0,(M76-N76)*IF(D$11<>"BB",$E$7,(1+$D$7)^(AK76/365)-1)) -> 3091.0911 | G77: =IF(R77=0,0,IF(M76<1,0,IF(AND(AND(((M76-N76)/R77)<G76,O76<>"V"),D$11<>"BRADESCO"),G76, (M76-N76)/R77))) -> 1131.3826 | H77: =IF(OR(G77=0,L77<1),"",IF(G77/L77>90%,"🛩",IF(G77/L77>70%,"🏎",IF(G77/L77>50%,"🚙",IF(G77/L77>30%,"🛵",IF(G77/L77>15%,"🐢","⚓️")))))) -> 🐢 | I77: =IFERROR(IF((G77+N77-S77)/L77<0,"🔙",IF((G77+N77-S77)/L77<10%,"🥾",IF((G77+N77-S77)/L77<20%,"🛴",IF((G77+N77-S77)/L77<50%,"🚴‍♂️",IF((G77+N77-S77)/L77<75%,"🚖","🚁"))))),"") -> 🛴 | J77: =G77+N77-S77 -> 502.44702 | K77: =IFERROR(J77/(L77+N77),0) -> 0.11624062 | L77: =G77+F77+A77+B77 -> 4322.4737 | M77: =IF(R77=0,0,MAX(0,M76-G77+S77-N76)) -> 369459.67 | O77: =IF(AND(N77<>"",N77<R77),"V","") | P77: =IF(N76=0,"",(L76-L77)/N76) | Q77: =IF(N77=0,"",IF(N77>M77,"🚫",IF(INT(N77/G77<1),"👍",INT(N77/G77)&"x"))) | R77: =IF(M76=0,0,IF(OR(N76=0,O76="V"),R76-1,IF(OR(D$11="BRADESCO",D$11="BB"),R76-ROUNDDOWN(N76/(M76/R76),0)-1,ROUNDUP((M76-N76+S76-(M76/R76))/(L76-F77-A77-B77),0)+1))) -> 327 | S77: =M76*$T77 -> 628.9356 | T77: =IF(M76>0,T76,0) -> 0.0017 | AA77: =-(L77+N77) -> -4322.4737 | AH77: =ROUNDUP(E77/120,0) -> 1 | AI77: =ROUNDUP(E77/36,0) -> 2 | AJ77: =ROUNDUP(E77/12,0) -> 6 | AK77: =DAY(DATE(YEAR(C77),MONTH(C77)+1,1)-1) -> 30 | AR77: =IF(INT(AW77)>0,AR76,0) -> 25 | AS77: =IF(AW77>0.1,AS76,0) -> 75 | AT77: =DATE(YEAR(AT76),MONTH(AT76)+1,1) -> 47939 | AU77: =IFERROR(AX77/BD76,0) -> 0.003058104 | AV77: =AV76+1 -> 63 | AW77: =IF(OR(BD76<1,BE76>BD76),0,(BD76-BE76)*IF(AU$11<>"BB",$E$7,(1+$D$7)^(BY76/365)-1)) -> 3091.0911 | AX77: =IF(BI77=0,0,IF(BD76<1,0,IF(AND(AND(((BD76-BE76)/BI77)<AX76,BF76<>"V"),AU$11<>"BRADESCO"),AX76, (BD76-BE76)/BI77))) -> 1131.3826 | AY77: =IF(OR(AX77=0,BC77<1),"",IF(AX77/BC77>90%,"🛩",IF(AX77/BC77>70%,"🏎",IF(AX77/BC77>50%,"🚙",IF(AX77/BC77>30%,"🛵",IF(AX77/BC77>15%,"🐢","⚓️")))))) -> 🐢 | AZ77: =IFERROR(IF((AX77+BE77-BJ77)/BC77<0,"🔙",IF((AX77+BE77-BJ77)/BC77<10%,"🥾",IF((AX77+BE77-BJ77)/BC77<20%,"🛴",IF((AX77+BE77-BJ77)/BC77<50%,"🚴‍♂️",IF((AX77+BE77-BJ77)/BC77<75%,"🚖","🚁"))))),"") -> 🛴 | BA77: =AX77+BE77-BJ77 -> 502.44702 | BB77: =IFERROR(BA77/(BC77+BE77),0) -> 0.11624062 | BC77: =AX77+AW77+AR77+AS77 -> 4322.4737 | BD77: =IF(BI77=0,0,MAX(0,BD76-AX77+BJ77-BE76)) -> 369459.67 | BF77: =IF(AND(BE77<>"",BE77<BI77),"V","") | BG77: =IF(BE76=0,"",(BC76-BC77)/BE76) | BH77: =IF(BE77=0,"",IF(BE77>BD77,"🚫",IF(INT(BE77/AX77<1),"👍",INT(BE77/AX77)&"x"))) | BI77: =IF(BD76=0,0,IF(OR(BE76=0,BF76="V"),BI76-1,IF(OR(AU$11="BRADESCO",AU$11="BB"),BI76-ROUNDDOWN(BE76/(BD76/BI76),0)-1,ROUNDUP((BD76-BE76+BJ76-(BD76/BI76))/(BC76-AW77-AR77-AS77),0)+1))) -> 327 | BJ77: =BD76*$BK76 -> 628.9356 | BK77: =IF(BD76>0,BK76,0) -> 0.0017
A78: =IF(INT(F78)>0,A77,0) -> 25 | B78: =IF(F78>0.1,B77,0) -> 75 | C78: =DATE(YEAR(C77),MONTH(C77)+1,1) -> 47969 | D78: =IFERROR(G78/M77,0) -> 0.0030674847 | E78: =E77+1 -> 64 | F78: =IF(OR(M77<1,N77>M77),0,(M77-N77)*IF(D$11<>"BB",$E$7,(1+$D$7)^(AK77/365)-1)) -> 3086.8931 | G78: =IF(R78=0,0,IF(M77<1,0,IF(AND(AND(((M77-N77)/R78)<G77,O77<>"V"),D$11<>"BRADESCO"),G77, (M77-N77)/R78))) -> 1133.3119 | H78: =IF(OR(G78=0,L78<1),"",IF(G78/L78>90%,"🛩",IF(G78/L78>70%,"🏎",IF(G78/L78>50%,"🚙",IF(G78/L78>30%,"🛵",IF(G78/L78>15%,"🐢","⚓️")))))) -> 🐢 | I78: =IFERROR(IF((G78+N78-S78)/L78<0,"🔙",IF((G78+N78-S78)/L78<10%,"🥾",IF((G78+N78-S78)/L78<20%,"🛴",IF((G78+N78-S78)/L78<50%,"🚴‍♂️",IF((G78+N78-S78)/L78<75%,"🚖","🚁"))))),"") -> 🛴 | J78: =G78+N78-S78 -> 505.23043 | K78: =IFERROR(J78/(L78+N78),0) -> 0.11694594 | L78: =G78+F78+A78+B78 -> 4320.2049 | M78: =IF(R78=0,0,MAX(0,M77-G78+S78-N77)) -> 368954.44 | O78: =IF(AND(N78<>"",N78<R78),"V","") | P78: =IF(N77=0,"",(L77-L78)/N77) | Q78: =IF(N78=0,"",IF(N78>M78,"🚫",IF(INT(N78/G78<1),"👍",INT(N78/G78)&"x"))) | R78: =IF(M77=0,0,IF(OR(N77=0,O77="V"),R77-1,IF(OR(D$11="BRADESCO",D$11="BB"),R77-ROUNDDOWN(N77/(M77/R77),0)-1,ROUNDUP((M77-N77+S77-(M77/R77))/(L77-F78-A78-B78),0)+1))) -> 326 | S78: =M77*$T78 -> 628.08144 | T78: =IF(M77>0,T77,0) -> 0.0017 | AA78: =-(L78+N78) -> -4320.2049 | AH78: =ROUNDUP(E78/120,0) -> 1 | AI78: =ROUNDUP(E78/36,0) -> 2 | AJ78: =ROUNDUP(E78/12,0) -> 6 | AK78: =DAY(DATE(YEAR(C78),MONTH(C78)+1,1)-1) -> 31 | AR78: =IF(INT(AW78)>0,AR77,0) -> 25 | AS78: =IF(AW78>0.1,AS77,0) -> 75 | AT78: =DATE(YEAR(AT77),MONTH(AT77)+1,1) -> 47969 | AU78: =IFERROR(AX78/BD77,0) -> 0.0030674847 | AV78: =AV77+1 -> 64 | AW78: =IF(OR(BD77<1,BE77>BD77),0,(BD77-BE77)*IF(AU$11<>"BB",$E$7,(1+$D$7)^(BY77/365)-1)) -> 3086.8931 | AX78: =IF(BI78=0,0,IF(BD77<1,0,IF(AND(AND(((BD77-BE77)/BI78)<AX77,BF77<>"V"),AU$11<>"BRADESCO"),AX77, (BD77-BE77)/BI78))) -> 1133.3119 | AY78: =IF(OR(AX78=0,BC78<1),"",IF(AX78/BC78>90%,"🛩",IF(AX78/BC78>70%,"🏎",IF(AX78/BC78>50%,"🚙",IF(AX78/BC78>30%,"🛵",IF(AX78/BC78>15%,"🐢","⚓️")))))) -> 🐢 | AZ78: =IFERROR(IF((AX78+BE78-BJ78)/BC78<0,"🔙",IF((AX78+BE78-BJ78)/BC78<10%,"🥾",IF((AX78+BE78-BJ78)/BC78<20%,"🛴",IF((AX78+BE78-BJ78)/BC78<50%,"🚴‍♂️",IF((AX78+BE78-BJ78)/BC78<75%,"🚖","🚁"))))),"") -> 🛴 | BA78: =AX78+BE78-BJ78 -> 505.23043 | BB78: =IFERROR(BA78/(BC78+BE78),0) -> 0.11694594 | BC78: =AX78+AW78+AR78+AS78 -> 4320.2049 | BD78: =IF(BI78=0,0,MAX(0,BD77-AX78+BJ78-BE77)) -> 368954.44 | BF78: =IF(AND(BE78<>"",BE78<BI78),"V","") | BG78: =IF(BE77=0,"",(BC77-BC78)/BE77) | BH78: =IF(BE78=0,"",IF(BE78>BD78,"🚫",IF(INT(BE78/AX78<1),"👍",INT(BE78/AX78)&"x"))) | BI78: =IF(BD77=0,0,IF(OR(BE77=0,BF77="V"),BI77-1,IF(OR(AU$11="BRADESCO",AU$11="BB"),BI77-ROUNDDOWN(BE77/(BD77/BI77),0)-1,ROUNDUP((BD77-BE77+BJ77-(BD77/BI77))/(BC77-AW78-AR78-AS78),0)+1))) -> 326 | BJ78: =BD77*$BK77 -> 628.08144 | BK78: =IF(BD77>0,BK77,0) -> 0.0017
A79: =IF(INT(F79)>0,A78,0) -> 25 | B79: =IF(F79>0.1,B78,0) -> 75 | C79: =DATE(YEAR(C78),MONTH(C78)+1,1) -> 48000 | D79: =IFERROR(G79/M78,0) -> 0.0030769231 | E79: =E78+1 -> 65 | F79: =IF(OR(M78<1,N78>M78),0,(M78-N78)*IF(D$11<>"BB",$E$7,(1+$D$7)^(AK78/365)-1)) -> 3082.6718 | G79: =IF(R79=0,0,IF(M78<1,0,IF(AND(AND(((M78-N78)/R79)<G78,O78<>"V"),D$11<>"BRADESCO"),G78, (M78-N78)/R79))) -> 1135.2444 | H79: =IF(OR(G79=0,L79<1),"",IF(G79/L79>90%,"🛩",IF(G79/L79>70%,"🏎",IF(G79/L79>50%,"🚙",IF(G79/L79>30%,"🛵",IF(G79/L79>15%,"🐢","⚓️")))))) -> 🐢 | I79: =IFERROR(IF((G79+N79-S79)/L79<0,"🔙",IF((G79+N79-S79)/L79<10%,"🥾",IF((G79+N79-S79)/L79<20%,"🛴",IF((G79+N79-S79)/L79<50%,"🚴‍♂️",IF((G79+N79-S79)/L79<75%,"🚖","🚁"))))),"") -> 🛴 | J79: =G79+N79-S79 -> 508.02188 | K79: =IFERROR(J79/(L79+N79),0) -> 0.11765441 | L79: =G79+F79+A79+B79 -> 4317.9162 | M79: =IF(R79=0,0,MAX(0,M78-G79+S79-N78)) -> 368446.42 | O79: =IF(AND(N79<>"",N79<R79),"V","") | P79: =IF(N78=0,"",(L78-L79)/N78) | Q79: =IF(N79=0,"",IF(N79>M79,"🚫",IF(INT(N79/G79<1),"👍",INT(N79/G79)&"x"))) | R79: =IF(M78=0,0,IF(OR(N78=0,O78="V"),R78-1,IF(OR(D$11="BRADESCO",D$11="BB"),R78-ROUNDDOWN(N78/(M78/R78),0)-1,ROUNDUP((M78-N78+S78-(M78/R78))/(L78-F79-A79-B79),0)+1))) -> 325 | S79: =M78*$T79 -> 627.22255 | T79: =IF(M78>0,T78,0) -> 0.0017 | AA79: =-(L79+N79) -> -4317.9162 | AH79: =ROUNDUP(E79/120,0) -> 1 | AI79: =ROUNDUP(E79/36,0) -> 2 | AJ79: =ROUNDUP(E79/12,0) -> 6 | AK79: =DAY(DATE(YEAR(C79),MONTH(C79)+1,1)-1) -> 30 | AR79: =IF(INT(AW79)>0,AR78,0) -> 25 | AS79: =IF(AW79>0.1,AS78,0) -> 75 | AT79: =DATE(YEAR(AT78),MONTH(AT78)+1,1) -> 48000 | AU79: =IFERROR(AX79/BD78,0) -> 0.0030769231 | AV79: =AV78+1 -> 65 | AW79: =IF(OR(BD78<1,BE78>BD78),0,(BD78-BE78)*IF(AU$11<>"BB",$E$7,(1+$D$7)^(BY78/365)-1)) -> 3082.6718 | AX79: =IF(BI79=0,0,IF(BD78<1,0,IF(AND(AND(((BD78-BE78)/BI79)<AX78,BF78<>"V"),AU$11<>"BRADESCO"),AX78, (BD78-BE78)/BI79))) -> 1135.2444 | AY79: =IF(OR(AX79=0,BC79<1),"",IF(AX79/BC79>90%,"🛩",IF(AX79/BC79>70%,"🏎",IF(AX79/BC79>50%,"🚙",IF(AX79/BC79>30%,"🛵",IF(AX79/BC79>15%,"🐢","⚓️")))))) -> 🐢 | AZ79: =IFERROR(IF((AX79+BE79-BJ79)/BC79<0,"🔙",IF((AX79+BE79-BJ79)/BC79<10%,"🥾",IF((AX79+BE79-BJ79)/BC79<20%,"🛴",IF((AX79+BE79-BJ79)/BC79<50%,"🚴‍♂️",IF((AX79+BE79-BJ79)/BC79<75%,"🚖","🚁"))))),"") -> 🛴 | BA79: =AX79+BE79-BJ79 -> 508.02188 | BB79: =IFERROR(BA79/(BC79+BE79),0) -> 0.11765441 | BC79: =AX79+AW79+AR79+AS79 -> 4317.9162 | BD79: =IF(BI79=0,0,MAX(0,BD78-AX79+BJ79-BE78)) -> 368446.42 | BF79: =IF(AND(BE79<>"",BE79<BI79),"V","") | BG79: =IF(BE78=0,"",(BC78-BC79)/BE78) | BH79: =IF(BE79=0,"",IF(BE79>BD79,"🚫",IF(INT(BE79/AX79<1),"👍",INT(BE79/AX79)&"x"))) | BI79: =IF(BD78=0,0,IF(OR(BE78=0,BF78="V"),BI78-1,IF(OR(AU$11="BRADESCO",AU$11="BB"),BI78-ROUNDDOWN(BE78/(BD78/BI78),0)-1,ROUNDUP((BD78-BE78+BJ78-(BD78/BI78))/(BC78-AW79-AR79-AS79),0)+1))) -> 325 | BJ79: =BD78*$BK78 -> 627.22255 | BK79: =IF(BD78>0,BK78,0) -> 0.0017
A80: =IF(INT(F80)>0,A79,0) -> 25 | B80: =IF(F80>0.1,B79,0) -> 75 | C80: =DATE(YEAR(C79),MONTH(C79)+1,1) -> 48030 | D80: =IFERROR(G80/M79,0) -> 0.0030864198 | E80: =E79+1 -> 66 | F80: =IF(OR(M79<1,N79>M79),0,(M79-N79)*IF(D$11<>"BB",$E$7,(1+$D$7)^(AK79/365)-1)) -> 3078.4272 | G80: =IF(R80=0,0,IF(M79<1,0,IF(AND(AND(((M79-N79)/R80)<G79,O79<>"V"),D$11<>"BRADESCO"),G79, (M79-N79)/R80))) -> 1137.1803 | H80: =IF(OR(G80=0,L80<1),"",IF(G80/L80>90%,"🛩",IF(G80/L80>70%,"🏎",IF(G80/L80>50%,"🚙",IF(G80/L80>30%,"🛵",IF(G80/L80>15%,"🐢","⚓️")))))) -> 🐢 | I80: =IFERROR(IF((G80+N80-S80)/L80<0,"🔙",IF((G80+N80-S80)/L80<10%,"🥾",IF((G80+N80-S80)/L80<20%,"🛴",IF((G80+N80-S80)/L80<50%,"🚴‍♂️",IF((G80+N80-S80)/L80<75%,"🚖","🚁"))))),"") -> 🛴 | J80: =G80+N80-S80 -> 510.82139 | K80: =IFERROR(J80/(L80+N80),0) -> 0.11836605 | L80: =G80+F80+A80+B80 -> 4315.6075 | M80: =IF(R80=0,0,MAX(0,M79-G80+S80-N79)) -> 367935.6 | O80: =IF(AND(N80<>"",N80<R80),"V","") | P80: =IF(N79=0,"",(L79-L80)/N79) | Q80: =IF(N80=0,"",IF(N80>M80,"🚫",IF(INT(N80/G80<1),"👍",INT(N80/G80)&"x"))) | R80: =IF(M79=0,0,IF(OR(N79=0,O79="V"),R79-1,IF(OR(D$11="BRADESCO",D$11="BB"),R79-ROUNDDOWN(N79/(M79/R79),0)-1,ROUNDUP((M79-N79+S79-(M79/R79))/(L79-F80-A80-B80),0)+1))) -> 324 | S80: =M79*$T80 -> 626.35891 | T80: =IF(M79>0,T79,0) -> 0.0017 | AA80: =-(L80+N80) -> -4315.6075 | AH80: =ROUNDUP(E80/120,0) -> 1 | AI80: =ROUNDUP(E80/36,0) -> 2 | AJ80: =ROUNDUP(E80/12,0) -> 6 | AK80: =DAY(DATE(YEAR(C80),MONTH(C80)+1,1)-1) -> 31 | AR80: =IF(INT(AW80)>0,AR79,0) -> 25 | AS80: =IF(AW80>0.1,AS79,0) -> 75 | AT80: =DATE(YEAR(AT79),MONTH(AT79)+1,1) -> 48030 | AU80: =IFERROR(AX80/BD79,0) -> 0.0030864198 | AV80: =AV79+1 -> 66 | AW80: =IF(OR(BD79<1,BE79>BD79),0,(BD79-BE79)*IF(AU$11<>"BB",$E$7,(1+$D$7)^(BY79/365)-1)) -> 3078.4272 | AX80: =IF(BI80=0,0,IF(BD79<1,0,IF(AND(AND(((BD79-BE79)/BI80)<AX79,BF79<>"V"),AU$11<>"BRADESCO"),AX79, (BD79-BE79)/BI80))) -> 1137.1803 | AY80: =IF(OR(AX80=0,BC80<1),"",IF(AX80/BC80>90%,"🛩",IF(AX80/BC80>70%,"🏎",IF(AX80/BC80>50%,"🚙",IF(AX80/BC80>30%,"🛵",IF(AX80/BC80>15%,"🐢","⚓️")))))) -> 🐢 | AZ80: =IFERROR(IF((AX80+BE80-BJ80)/BC80<0,"🔙",IF((AX80+BE80-BJ80)/BC80<10%,"🥾",IF((AX80+BE80-BJ80)/BC80<20%,"🛴",IF((AX80+BE80-BJ80)/BC80<50%,"🚴‍♂️",IF((AX80+BE80-BJ80)/BC80<75%,"🚖","🚁"))))),"") -> 🛴 | BA80: =AX80+BE80-BJ80 -> 510.82139 | BB80: =IFERROR(BA80/(BC80+BE80),0) -> 0.11836605 | BC80: =AX80+AW80+AR80+AS80 -> 4315.6075 | BD80: =IF(BI80=0,0,MAX(0,BD79-AX80+BJ80-BE79)) -> 367935.6 | BF80: =IF(AND(BE80<>"",BE80<BI80),"V","") | BG80: =IF(BE79=0,"",(BC79-BC80)/BE79) | BH80: =IF(BE80=0,"",IF(BE80>BD80,"🚫",IF(INT(BE80/AX80<1),"👍",INT(BE80/AX80)&"x"))) | BI80: =IF(BD79=0,0,IF(OR(BE79=0,BF79="V"),BI79-1,IF(OR(AU$11="BRADESCO",AU$11="BB"),BI79-ROUNDDOWN(BE79/(BD79/BI79),0)-1,ROUNDUP((BD79-BE79+BJ79-(BD79/BI79))/(BC79-AW80-AR80-AS80),0)+1))) -> 324 | BJ80: =BD79*$BK79 -> 626.35891 | BK80: =IF(BD79>0,BK79,0) -> 0.0017
A81: =IF(INT(F81)>0,A80,0) -> 25 | B81: =IF(F81>0.1,B80,0) -> 75 | C81: =DATE(YEAR(C80),MONTH(C80)+1,1) -> 48061 | D81: =IFERROR(G81/M80,0) -> 0.0030959752 | E81: =E80+1 -> 67 | F81: =IF(OR(M80<1,N80>M80),0,(M80-N80)*IF(D$11<>"BB",$E$7,(1+$D$7)^(AK80/365)-1)) -> 3074.1592 | G81: =IF(R81=0,0,IF(M80<1,0,IF(AND(AND(((M80-N80)/R81)<G80,O80<>"V"),D$11<>"BRADESCO"),G80, (M80-N80)/R81))) -> 1139.1195 | H81: =IF(OR(G81=0,L81<1),"",IF(G81/L81>90%,"🛩",IF(G81/L81>70%,"🏎",IF(G81/L81>50%,"🚙",IF(G81/L81>30%,"🛵",IF(G81/L81>15%,"🐢","⚓️")))))) -> 🐢 | I81: =IFERROR(IF((G81+N81-S81)/L81<0,"🔙",IF((G81+N81-S81)/L81<10%,"🥾",IF((G81+N81-S81)/L81<20%,"🛴",IF((G81+N81-S81)/L81<50%,"🚴‍♂️",IF((G81+N81-S81)/L81<75%,"🚖","🚁"))))),"") -> 🛴 | J81: =G81+N81-S81 -> 513.62898 | K81: =IFERROR(J81/(L81+N81),0) -> 0.11908087 | L81: =G81+F81+A81+B81 -> 4313.2787 | M81: =IF(R81=0,0,MAX(0,M80-G81+S81-N80)) -> 367421.97 | O81: =IF(AND(N81<>"",N81<R81),"V","") | P81: =IF(N80=0,"",(L80-L81)/N80) | Q81: =IF(N81=0,"",IF(N81>M81,"🚫",IF(INT(N81/G81<1),"👍",INT(N81/G81)&"x"))) | R81: =IF(M80=0,0,IF(OR(N80=0,O80="V"),R80-1,IF(OR(D$11="BRADESCO",D$11="BB"),R80-ROUNDDOWN(N80/(M80/R80),0)-1,ROUNDUP((M80-N80+S80-(M80/R80))/(L80-F81-A81-B81),0)+1))) -> 323 | S81: =M80*$T81 -> 625.49051 | T81: =IF(M80>0,T80,0) -> 0.0017 | AA81: =-(L81+N81) -> -4313.2787 | AH81: =ROUNDUP(E81/120,0) -> 1 | AI81: =ROUNDUP(E81/36,0) -> 2 | AJ81: =ROUNDUP(E81/12,0) -> 6 | AK81: =DAY(DATE(YEAR(C81),MONTH(C81)+1,1)-1) -> 31 | AR81: =IF(INT(AW81)>0,AR80,0) -> 25 | AS81: =IF(AW81>0.1,AS80,0) -> 75 | AT81: =DATE(YEAR(AT80),MONTH(AT80)+1,1) -> 48061 | AU81: =IFERROR(AX81/BD80,0) -> 0.0030959752 | AV81: =AV80+1 -> 67 | AW81: =IF(OR(BD80<1,BE80>BD80),0,(BD80-BE80)*IF(AU$11<>"BB",$E$7,(1+$D$7)^(BY80/365)-1)) -> 3074.1592 | AX81: =IF(BI81=0,0,IF(BD80<1,0,IF(AND(AND(((BD80-BE80)/BI81)<AX80,BF80<>"V"),AU$11<>"BRADESCO"),AX80, (BD80-BE80)/BI81))) -> 1139.1195 | AY81: =IF(OR(AX81=0,BC81<1),"",IF(AX81/BC81>90%,"🛩",IF(AX81/BC81>70%,"🏎",IF(AX81/BC81>50%,"🚙",IF(AX81/BC81>30%,"🛵",IF(AX81/BC81>15%,"🐢","⚓️")))))) -> 🐢 | AZ81: =IFERROR(IF((AX81+BE81-BJ81)/BC81<0,"🔙",IF((AX81+BE81-BJ81)/BC81<10%,"🥾",IF((AX81+BE81-BJ81)/BC81<20%,"🛴",IF((AX81+BE81-BJ81)/BC81<50%,"🚴‍♂️",IF((AX81+BE81-BJ81)/BC81<75%,"🚖","🚁"))))),"") -> 🛴 | BA81: =AX81+BE81-BJ81 -> 513.62898 | BB81: =IFERROR(BA81/(BC81+BE81),0) -> 0.11908087 | BC81: =AX81+AW81+AR81+AS81 -> 4313.2787 | BD81: =IF(BI81=0,0,MAX(0,BD80-AX81+BJ81-BE80)) -> 367421.97 | BF81: =IF(AND(BE81<>"",BE81<BI81),"V","") | BG81: =IF(BE80=0,"",(BC80-BC81)/BE80) | BH81: =IF(BE81=0,"",IF(BE81>BD81,"🚫",IF(INT(BE81/AX81<1),"👍",INT(BE81/AX81)&"x"))) | BI81: =IF(BD80=0,0,IF(OR(BE80=0,BF80="V"),BI80-1,IF(OR(AU$11="BRADESCO",AU$11="BB"),BI80-ROUNDDOWN(BE80/(BD80/BI80),0)-1,ROUNDUP((BD80-BE80+BJ80-(BD80/BI80))/(BC80-AW81-AR81-AS81),0)+1))) -> 323 | BJ81: =BD80*$BK80 -> 625.49051 | BK81: =IF(BD80>0,BK80,0) -> 0.0017
A82: =IF(INT(F82)>0,A81,0) -> 25 | B82: =IF(F82>0.1,B81,0) -> 75 | C82: =DATE(YEAR(C81),MONTH(C81)+1,1) -> 48092 | D82: =IFERROR(G82/M81,0) -> 0.0031055901 | E82: =E81+1 -> 68 | F82: =IF(OR(M81<1,N81>M81),0,(M81-N81)*IF(D$11<>"BB",$E$7,(1+$D$7)^(AK81/365)-1)) -> 3069.8677 | G82: =IF(R82=0,0,IF(M81<1,0,IF(AND(AND(((M81-N81)/R82)<G81,O81<>"V"),D$11<>"BRADESCO"),G81, (M81-N81)/R82))) -> 1141.062 | H82: =IF(OR(G82=0,L82<1),"",IF(G82/L82>90%,"🛩",IF(G82/L82>70%,"🏎",IF(G82/L82>50%,"🚙",IF(G82/L82>30%,"🛵",IF(G82/L82>15%,"🐢","⚓️")))))) -> 🐢 | I82: =IFERROR(IF((G82+N82-S82)/L82<0,"🔙",IF((G82+N82-S82)/L82<10%,"🥾",IF((G82+N82-S82)/L82<20%,"🛴",IF((G82+N82-S82)/L82<50%,"🚴‍♂️",IF((G82+N82-S82)/L82<75%,"🚖","🚁"))))),"") -> 🛴 | J82: =G82+N82-S82 -> 516.44467 | K82: =IFERROR(J82/(L82+N82),0) -> 0.11979891 | L82: =G82+F82+A82+B82 -> 4310.9298 | M82: =IF(R82=0,0,MAX(0,M81-G82+S82-N81)) -> 366905.52 | O82: =IF(AND(N82<>"",N82<R82),"V","") | P82: =IF(N81=0,"",(L81-L82)/N81) | Q82: =IF(N82=0,"",IF(N82>M82,"🚫",IF(INT(N82/G82<1),"👍",INT(N82/G82)&"x"))) | R82: =IF(M81=0,0,IF(OR(N81=0,O81="V"),R81-1,IF(OR(D$11="BRADESCO",D$11="BB"),R81-ROUNDDOWN(N81/(M81/R81),0)-1,ROUNDUP((M81-N81+S81-(M81/R81))/(L81-F82-A82-B82),0)+1))) -> 322 | S82: =M81*$T82 -> 624.61735 | T82: =IF(M81>0,T81,0) -> 0.0017 | AA82: =-(L82+N82) -> -4310.9298 | AH82: =ROUNDUP(E82/120,0) -> 1 | AI82: =ROUNDUP(E82/36,0) -> 2 | AJ82: =ROUNDUP(E82/12,0) -> 6 | AK82: =DAY(DATE(YEAR(C82),MONTH(C82)+1,1)-1) -> 30 | AR82: =IF(INT(AW82)>0,AR81,0) -> 25 | AS82: =IF(AW82>0.1,AS81,0) -> 75 | AT82: =DATE(YEAR(AT81),MONTH(AT81)+1,1) -> 48092 | AU82: =IFERROR(AX82/BD81,0) -> 0.0031055901 | AV82: =AV81+1 -> 68 | AW82: =IF(OR(BD81<1,BE81>BD81),0,(BD81-BE81)*IF(AU$11<>"BB",$E$7,(1+$D$7)^(BY81/365)-1)) -> 3069.8677 | AX82: =IF(BI82=0,0,IF(BD81<1,0,IF(AND(AND(((BD81-BE81)/BI82)<AX81,BF81<>"V"),AU$11<>"BRADESCO"),AX81, (BD81-BE81)/BI82))) -> 1141.062 | AY82: =IF(OR(AX82=0,BC82<1),"",IF(AX82/BC82>90%,"🛩",IF(AX82/BC82>70%,"🏎",IF(AX82/BC82>50%,"🚙",IF(AX82/BC82>30%,"🛵",IF(AX82/BC82>15%,"🐢","⚓️")))))) -> 🐢 | AZ82: =IFERROR(IF((AX82+BE82-BJ82)/BC82<0,"🔙",IF((AX82+BE82-BJ82)/BC82<10%,"🥾",IF((AX82+BE82-BJ82)/BC82<20%,"🛴",IF((AX82+BE82-BJ82)/BC82<50%,"🚴‍♂️",IF((AX82+BE82-BJ82)/BC82<75%,"🚖","🚁"))))),"") -> 🛴 | BA82: =AX82+BE82-BJ82 -> 516.44467 | BB82: =IFERROR(BA82/(BC82+BE82),0) -> 0.11979891 | BC82: =AX82+AW82+AR82+AS82 -> 4310.9298 | BD82: =IF(BI82=0,0,MAX(0,BD81-AX82+BJ82-BE81)) -> 366905.52 | BF82: =IF(AND(BE82<>"",BE82<BI82),"V","") | BG82: =IF(BE81=0,"",(BC81-BC82)/BE81) | BH82: =IF(BE82=0,"",IF(BE82>BD82,"🚫",IF(INT(BE82/AX82<1),"👍",INT(BE82/AX82)&"x"))) | BI82: =IF(BD81=0,0,IF(OR(BE81=0,BF81="V"),BI81-1,IF(OR(AU$11="BRADESCO",AU$11="BB"),BI81-ROUNDDOWN(BE81/(BD81/BI81),0)-1,ROUNDUP((BD81-BE81+BJ81-(BD81/BI81))/(BC81-AW82-AR82-AS82),0)+1))) -> 322 | BJ82: =BD81*$BK81 -> 624.61735 | BK82: =IF(BD81>0,BK81,0) -> 0.0017
A83: =IF(INT(F83)>0,A82,0) -> 25 | B83: =IF(F83>0.1,B82,0) -> 75 | C83: =DATE(YEAR(C82),MONTH(C82)+1,1) -> 48122 | D83: =IFERROR(G83/M82,0) -> 0.0031152648 | E83: =E82+1 -> 69 | F83: =IF(OR(M82<1,N82>M82),0,(M82-N82)*IF(D$11<>"BB",$E$7,(1+$D$7)^(AK82/365)-1)) -> 3065.5528 | G83: =IF(R83=0,0,IF(M82<1,0,IF(AND(AND(((M82-N82)/R83)<G82,O82<>"V"),D$11<>"BRADESCO"),G82, (M82-N82)/R83))) -> 1143.0079 | H83: =IF(OR(G83=0,L83<1),"",IF(G83/L83>90%,"🛩",IF(G83/L83>70%,"🏎",IF(G83/L83>50%,"🚙",IF(G83/L83>30%,"🛵",IF(G83/L83>15%,"🐢","⚓️")))))) -> 🐢 | I83: =IFERROR(IF((G83+N83-S83)/L83<0,"🔙",IF((G83+N83-S83)/L83<10%,"🥾",IF((G83+N83-S83)/L83<20%,"🛴",IF((G83+N83-S83)/L83<50%,"🚴‍♂️",IF((G83+N83-S83)/L83<75%,"🚖","🚁"))))),"") -> 🛴 | J83: =G83+N83-S83 -> 519.26847 | K83: =IFERROR(J83/(L83+N83),0) -> 0.12052017 | L83: =G83+F83+A83+B83 -> 4308.5606 | M83: =IF(R83=0,0,MAX(0,M82-G83+S83-N82)) -> 366386.25 | O83: =IF(AND(N83<>"",N83<R83),"V","") | P83: =IF(N82=0,"",(L82-L83)/N82) | Q83: =IF(N83=0,"",IF(N83>M83,"🚫",IF(INT(N83/G83<1),"👍",INT(N83/G83)&"x"))) | R83: =IF(M82=0,0,IF(OR(N82=0,O82="V"),R82-1,IF(OR(D$11="BRADESCO",D$11="BB"),R82-ROUNDDOWN(N82/(M82/R82),0)-1,ROUNDUP((M82-N82+S82-(M82/R82))/(L82-F83-A83-B83),0)+1))) -> 321 | S83: =M82*$T83 -> 623.73939 | T83: =IF(M82>0,T82,0) -> 0.0017 | AA83: =-(L83+N83) -> -4308.5606 | AH83: =ROUNDUP(E83/120,0) -> 1 | AI83: =ROUNDUP(E83/36,0) -> 2 | AJ83: =ROUNDUP(E83/12,0) -> 6 | AK83: =DAY(DATE(YEAR(C83),MONTH(C83)+1,1)-1) -> 31 | AR83: =IF(INT(AW83)>0,AR82,0) -> 25 | AS83: =IF(AW83>0.1,AS82,0) -> 75 | AT83: =DATE(YEAR(AT82),MONTH(AT82)+1,1) -> 48122 | AU83: =IFERROR(AX83/BD82,0) -> 0.0031152648 | AV83: =AV82+1 -> 69 | AW83: =IF(OR(BD82<1,BE82>BD82),0,(BD82-BE82)*IF(AU$11<>"BB",$E$7,(1+$D$7)^(BY82/365)-1)) -> 3065.5528 | AX83: =IF(BI83=0,0,IF(BD82<1,0,IF(AND(AND(((BD82-BE82)/BI83)<AX82,BF82<>"V"),AU$11<>"BRADESCO"),AX82, (BD82-BE82)/BI83))) -> 1143.0079 | AY83: =IF(OR(AX83=0,BC83<1),"",IF(AX83/BC83>90%,"🛩",IF(AX83/BC83>70%,"🏎",IF(AX83/BC83>50%,"🚙",IF(AX83/BC83>30%,"🛵",IF(AX83/BC83>15%,"🐢","⚓️")))))) -> 🐢 | AZ83: =IFERROR(IF((AX83+BE83-BJ83)/BC83<0,"🔙",IF((AX83+BE83-BJ83)/BC83<10%,"🥾",IF((AX83+BE83-BJ83)/BC83<20%,"🛴",IF((AX83+BE83-BJ83)/BC83<50%,"🚴‍♂️",IF((AX83+BE83-BJ83)/BC83<75%,"🚖","🚁"))))),"") -> 🛴 | BA83: =AX83+BE83-BJ83 -> 519.26847 | BB83: =IFERROR(BA83/(BC83+BE83),0) -> 0.12052017 | BC83: =AX83+AW83+AR83+AS83 -> 4308.5606 | BD83: =IF(BI83=0,0,MAX(0,BD82-AX83+BJ83-BE82)) -> 366386.25 | BF83: =IF(AND(BE83<>"",BE83<BI83),"V","") | BG83: =IF(BE82=0,"",(BC82-BC83)/BE82) | BH83: =IF(BE83=0,"",IF(BE83>BD83,"🚫",IF(INT(BE83/AX83<1),"👍",INT(BE83/AX83)&"x"))) | BI83: =IF(BD82=0,0,IF(OR(BE82=0,BF82="V"),BI82-1,IF(OR(AU$11="BRADESCO",AU$11="BB"),BI82-ROUNDDOWN(BE82/(BD82/BI82),0)-1,ROUNDUP((BD82-BE82+BJ82-(BD82/BI82))/(BC82-AW83-AR83-AS83),0)+1))) -> 321 | BJ83: =BD82*$BK82 -> 623.73939 | BK83: =IF(BD82>0,BK82,0) -> 0.0017
A84: =IF(INT(F84)>0,A83,0) -> 25 | B84: =IF(F84>0.1,B83,0) -> 75 | C84: =DATE(YEAR(C83),MONTH(C83)+1,1) -> 48153 | D84: =IFERROR(G84/M83,0) -> 0.003125 | E84: =E83+1 -> 70 | F84: =IF(OR(M83<1,N83>M83),0,(M83-N83)*IF(D$11<>"BB",$E$7,(1+$D$7)^(AK83/365)-1)) -> 3061.2142 | G84: =IF(R84=0,0,IF(M83<1,0,IF(AND(AND(((M83-N83)/R84)<G83,O83<>"V"),D$11<>"BRADESCO"),G83, (M83-N83)/R84))) -> 1144.957 | H84: =IF(OR(G84=0,L84<1),"",IF(G84/L84>90%,"🛩",IF(G84/L84>70%,"🏎",IF(G84/L84>50%,"🚙",IF(G84/L84>30%,"🛵",IF(G84/L84>15%,"🐢","⚓️")))))) -> 🐢 | I84: =IFERROR(IF((G84+N84-S84)/L84<0,"🔙",IF((G84+N84-S84)/L84<10%,"🥾",IF((G84+N84-S84)/L84<20%,"🛴",IF((G84+N84-S84)/L84<50%,"🚴‍♂️",IF((G84+N84-S84)/L84<75%,"🚖","🚁"))))),"") -> 🛴 | J84: =G84+N84-S84 -> 522.10041 | K84: =IFERROR(J84/(L84+N84),0) -> 0.12124469 | L84: =G84+F84+A84+B84 -> 4306.1712 | M84: =IF(R84=0,0,MAX(0,M83-G84+S84-N83)) -> 365864.15 | O84: =IF(AND(N84<>"",N84<R84),"V","") | P84: =IF(N83=0,"",(L83-L84)/N83) | Q84: =IF(N84=0,"",IF(N84>M84,"🚫",IF(INT(N84/G84<1),"👍",INT(N84/G84)&"x"))) | R84: =IF(M83=0,0,IF(OR(N83=0,O83="V"),R83-1,IF(OR(D$11="BRADESCO",D$11="BB"),R83-ROUNDDOWN(N83/(M83/R83),0)-1,ROUNDUP((M83-N83+S83-(M83/R83))/(L83-F84-A84-B84),0)+1))) -> 320 | S84: =M83*$T84 -> 622.85663 | T84: =IF(M83>0,T83,0) -> 0.0017 | AA84: =-(L84+N84) -> -4306.1712 | AH84: =ROUNDUP(E84/120,0) -> 1 | AI84: =ROUNDUP(E84/36,0) -> 2 | AJ84: =ROUNDUP(E84/12,0) -> 6 | AK84: =DAY(DATE(YEAR(C84),MONTH(C84)+1,1)-1) -> 30 | AR84: =IF(INT(AW84)>0,AR83,0) -> 25 | AS84: =IF(AW84>0.1,AS83,0) -> 75 | AT84: =DATE(YEAR(AT83),MONTH(AT83)+1,1) -> 48153 | AU84: =IFERROR(AX84/BD83,0) -> 0.003125 | AV84: =AV83+1 -> 70 | AW84: =IF(OR(BD83<1,BE83>BD83),0,(BD83-BE83)*IF(AU$11<>"BB",$E$7,(1+$D$7)^(BY83/365)-1)) -> 3061.2142 | AX84: =IF(BI84=0,0,IF(BD83<1,0,IF(AND(AND(((BD83-BE83)/BI84)<AX83,BF83<>"V"),AU$11<>"BRADESCO"),AX83, (BD83-BE83)/BI84))) -> 1144.957 | AY84: =IF(OR(AX84=0,BC84<1),"",IF(AX84/BC84>90%,"🛩",IF(AX84/BC84>70%,"🏎",IF(AX84/BC84>50%,"🚙",IF(AX84/BC84>30%,"🛵",IF(AX84/BC84>15%,"🐢","⚓️")))))) -> 🐢 | AZ84: =IFERROR(IF((AX84+BE84-BJ84)/BC84<0,"🔙",IF((AX84+BE84-BJ84)/BC84<10%,"🥾",IF((AX84+BE84-BJ84)/BC84<20%,"🛴",IF((AX84+BE84-BJ84)/BC84<50%,"🚴‍♂️",IF((AX84+BE84-BJ84)/BC84<75%,"🚖","🚁"))))),"") -> 🛴 | BA84: =AX84+BE84-BJ84 -> 522.10041 | BB84: =IFERROR(BA84/(BC84+BE84),0) -> 0.12124469 | BC84: =AX84+AW84+AR84+AS84 -> 4306.1712 | BD84: =IF(BI84=0,0,MAX(0,BD83-AX84+BJ84-BE83)) -> 365864.15 | BF84: =IF(AND(BE84<>"",BE84<BI84),"V","") | BG84: =IF(BE83=0,"",(BC83-BC84)/BE83) | BH84: =IF(BE84=0,"",IF(BE84>BD84,"🚫",IF(INT(BE84/AX84<1),"👍",INT(BE84/AX84)&"x"))) | BI84: =IF(BD83=0,0,IF(OR(BE83=0,BF83="V"),BI83-1,IF(OR(AU$11="BRADESCO",AU$11="BB"),BI83-ROUNDDOWN(BE83/(BD83/BI83),0)-1,ROUNDUP((BD83-BE83+BJ83-(BD83/BI83))/(BC83-AW84-AR84-AS84),0)+1))) -> 320 | BJ84: =BD83*$BK83 -> 622.85663 | BK84: =IF(BD83>0,BK83,0) -> 0.0017
A85: =IF(INT(F85)>0,A84,0) -> 25 | B85: =IF(F85>0.1,B84,0) -> 75 | C85: =DATE(YEAR(C84),MONTH(C84)+1,1) -> 48183 | D85: =IFERROR(G85/M84,0) -> 0.0031347962 | E85: =E84+1 -> 71 | F85: =IF(OR(M84<1,N84>M84),0,(M84-N84)*IF(D$11<>"BB",$E$7,(1+$D$7)^(AK84/365)-1)) -> 3056.852 | G85: =IF(R85=0,0,IF(M84<1,0,IF(AND(AND(((M84-N84)/R85)<G84,O84<>"V"),D$11<>"BRADESCO"),G84, (M84-N84)/R85))) -> 1146.9096 | H85: =IF(OR(G85=0,L85<1),"",IF(G85/L85>90%,"🛩",IF(G85/L85>70%,"🏎",IF(G85/L85>50%,"🚙",IF(G85/L85>30%,"🛵",IF(G85/L85>15%,"🐢","⚓️")))))) -> 🐢 | I85: =IFERROR(IF((G85+N85-S85)/L85<0,"🔙",IF((G85+N85-S85)/L85<10%,"🥾",IF((G85+N85-S85)/L85<20%,"🛴",IF((G85+N85-S85)/L85<50%,"🚴‍♂️",IF((G85+N85-S85)/L85<75%,"🚖","🚁"))))),"") -> 🛴 | J85: =G85+N85-S85 -> 524.94051 | K85: =IFERROR(J85/(L85+N85),0) -> 0.12197249 | L85: =G85+F85+A85+B85 -> 4303.7615 | M85: =IF(R85=0,0,MAX(0,M84-G85+S85-N84)) -> 365339.21 | O85: =IF(AND(N85<>"",N85<R85),"V","") | P85: =IF(N84=0,"",(L84-L85)/N84) | Q85: =IF(N85=0,"",IF(N85>M85,"🚫",IF(INT(N85/G85<1),"👍",INT(N85/G85)&"x"))) | R85: =IF(M84=0,0,IF(OR(N84=0,O84="V"),R84-1,IF(OR(D$11="BRADESCO",D$11="BB"),R84-ROUNDDOWN(N84/(M84/R84),0)-1,ROUNDUP((M84-N84+S84-(M84/R84))/(L84-F85-A85-B85),0)+1))) -> 319 | S85: =M84*$T85 -> 621.96906 | T85: =IF(M84>0,T84,0) -> 0.0017 | AA85: =-(L85+N85) -> -4303.7615 | AH85: =ROUNDUP(E85/120,0) -> 1 | AI85: =ROUNDUP(E85/36,0) -> 2 | AJ85: =ROUNDUP(E85/12,0) -> 6 | AK85: =DAY(DATE(YEAR(C85),MONTH(C85)+1,1)-1) -> 31 | AR85: =IF(INT(AW85)>0,AR84,0) -> 25 | AS85: =IF(AW85>0.1,AS84,0) -> 75 | AT85: =DATE(YEAR(AT84),MONTH(AT84)+1,1) -> 48183 | AU85: =IFERROR(AX85/BD84,0) -> 0.0031347962 | AV85: =AV84+1 -> 71 | AW85: =IF(OR(BD84<1,BE84>BD84),0,(BD84-BE84)*IF(AU$11<>"BB",$E$7,(1+$D$7)^(BY84/365)-1)) -> 3056.852 | AX85: =IF(BI85=0,0,IF(BD84<1,0,IF(AND(AND(((BD84-BE84)/BI85)<AX84,BF84<>"V"),AU$11<>"BRADESCO"),AX84, (BD84-BE84)/BI85))) -> 1146.9096 | AY85: =IF(OR(AX85=0,BC85<1),"",IF(AX85/BC85>90%,"🛩",IF(AX85/BC85>70%,"🏎",IF(AX85/BC85>50%,"🚙",IF(AX85/BC85>30%,"🛵",IF(AX85/BC85>15%,"🐢","⚓️")))))) -> 🐢 | AZ85: =IFERROR(IF((AX85+BE85-BJ85)/BC85<0,"🔙",IF((AX85+BE85-BJ85)/BC85<10%,"🥾",IF((AX85+BE85-BJ85)/BC85<20%,"🛴",IF((AX85+BE85-BJ85)/BC85<50%,"🚴‍♂️",IF((AX85+BE85-BJ85)/BC85<75%,"🚖","🚁"))))),"") -> 🛴 | BA85: =AX85+BE85-BJ85 -> 524.94051 | BB85: =IFERROR(BA85/(BC85+BE85),0) -> 0.12197249 | BC85: =AX85+AW85+AR85+AS85 -> 4303.7615 | BD85: =IF(BI85=0,0,MAX(0,BD84-AX85+BJ85-BE84)) -> 365339.21 | BF85: =IF(AND(BE85<>"",BE85<BI85),"V","") | BG85: =IF(BE84=0,"",(BC84-BC85)/BE84) | BH85: =IF(BE85=0,"",IF(BE85>BD85,"🚫",IF(INT(BE85/AX85<1),"👍",INT(BE85/AX85)&"x"))) | BI85: =IF(BD84=0,0,IF(OR(BE84=0,BF84="V"),BI84-1,IF(OR(AU$11="BRADESCO",AU$11="BB"),BI84-ROUNDDOWN(BE84/(BD84/BI84),0)-1,ROUNDUP((BD84-BE84+BJ84-(BD84/BI84))/(BC84-AW85-AR85-AS85),0)+1))) -> 319 | BJ85: =BD84*$BK84 -> 621.96906 | BK85: =IF(BD84>0,BK84,0) -> 0.0017
A86: =IF(INT(F86)>0,A85,0) -> 25 | B86: =IF(F86>0.1,B85,0) -> 75 | C86: =DATE(YEAR(C85),MONTH(C85)+1,1) -> 48214 | D86: =IFERROR(G86/M85,0) -> 0.0031446541 | E86: =E85+1 -> 72 | F86: =IF(OR(M85<1,N85>M85),0,(M85-N85)*IF(D$11<>"BB",$E$7,(1+$D$7)^(AK85/365)-1)) -> 3052.466 | G86: =IF(R86=0,0,IF(M85<1,0,IF(AND(AND(((M85-N85)/R86)<G85,O85<>"V"),D$11<>"BRADESCO"),G85, (M85-N85)/R86))) -> 1148.8655 | H86: =IF(OR(G86=0,L86<1),"",IF(G86/L86>90%,"🛩",IF(G86/L86>70%,"🏎",IF(G86/L86>50%,"🚙",IF(G86/L86>30%,"🛵",IF(G86/L86>15%,"🐢","⚓️")))))) -> 🐢 | I86: =IFERROR(IF((G86+N86-S86)/L86<0,"🔙",IF((G86+N86-S86)/L86<10%,"🥾",IF((G86+N86-S86)/L86<20%,"🛴",IF((G86+N86-S86)/L86<50%,"🚴‍♂️",IF((G86+N86-S86)/L86<75%,"🚖","🚁"))))),"") -> 🛴 | J86: =G86+N86-S86 -> 527.78879 | K86: =IFERROR(J86/(L86+N86),0) -> 0.12270358 | L86: =G86+F86+A86+B86 -> 4301.3315 | M86: =IF(R86=0,0,MAX(0,M85-G86+S86-N85)) -> 364811.42 | O86: =IF(AND(N86<>"",N86<R86),"V","") | P86: =IF(N85=0,"",(L85-L86)/N85) | Q86: =IF(N86=0,"",IF(N86>M86,"🚫",IF(INT(N86/G86<1),"👍",INT(N86/G86)&"x"))) | R86: =IF(M85=0,0,IF(OR(N85=0,O85="V"),R85-1,IF(OR(D$11="BRADESCO",D$11="BB"),R85-ROUNDDOWN(N85/(M85/R85),0)-1,ROUNDUP((M85-N85+S85-(M85/R85))/(L85-F86-A86-B86),0)+1))) -> 318 | S86: =M85*$T86 -> 621.07666 | T86: =IF(M85>0,T85,0) -> 0.0017 | AA86: =-(L86+N86) -> -4301.3315 | AH86: =ROUNDUP(E86/120,0) -> 1 | AI86: =ROUNDUP(E86/36,0) -> 2 | AJ86: =ROUNDUP(E86/12,0) -> 6 | AK86: =DAY(DATE(YEAR(C86),MONTH(C86)+1,1)-1) -> 31 | AR86: =IF(INT(AW86)>0,AR85,0) -> 25 | AS86: =IF(AW86>0.1,AS85,0) -> 75 | AT86: =DATE(YEAR(AT85),MONTH(AT85)+1,1) -> 48214 | AU86: =IFERROR(AX86/BD85,0) -> 0.0031446541 | AV86: =AV85+1 -> 72 | AW86: =IF(OR(BD85<1,BE85>BD85),0,(BD85-BE85)*IF(AU$11<>"BB",$E$7,(1+$D$7)^(BY85/365)-1)) -> 3052.466 | AX86: =IF(BI86=0,0,IF(BD85<1,0,IF(AND(AND(((BD85-BE85)/BI86)<AX85,BF85<>"V"),AU$11<>"BRADESCO"),AX85, (BD85-BE85)/BI86))) -> 1148.8655 | AY86: =IF(OR(AX86=0,BC86<1),"",IF(AX86/BC86>90%,"🛩",IF(AX86/BC86>70%,"🏎",IF(AX86/BC86>50%,"🚙",IF(AX86/BC86>30%,"🛵",IF(AX86/BC86>15%,"🐢","⚓️")))))) -> 🐢 | AZ86: =IFERROR(IF((AX86+BE86-BJ86)/BC86<0,"🔙",IF((AX86+BE86-BJ86)/BC86<10%,"🥾",IF((AX86+BE86-BJ86)/BC86<20%,"🛴",IF((AX86+BE86-BJ86)/BC86<50%,"🚴‍♂️",IF((AX86+BE86-BJ86)/BC86<75%,"🚖","🚁"))))),"") -> 🛴 | BA86: =AX86+BE86-BJ86 -> 527.78879 | BB86: =IFERROR(BA86/(BC86+BE86),0) -> 0.12270358 | BC86: =AX86+AW86+AR86+AS86 -> 4301.3315 | BD86: =IF(BI86=0,0,MAX(0,BD85-AX86+BJ86-BE85)) -> 364811.42 | BF86: =IF(AND(BE86<>"",BE86<BI86),"V","") | BG86: =IF(BE85=0,"",(BC85-BC86)/BE85) | BH86: =IF(BE86=0,"",IF(BE86>BD86,"🚫",IF(INT(BE86/AX86<1),"👍",INT(BE86/AX86)&"x"))) | BI86: =IF(BD85=0,0,IF(OR(BE85=0,BF85="V"),BI85-1,IF(OR(AU$11="BRADESCO",AU$11="BB"),BI85-ROUNDDOWN(BE85/(BD85/BI85),0)-1,ROUNDUP((BD85-BE85+BJ85-(BD85/BI85))/(BC85-AW86-AR86-AS86),0)+1))) -> 318 | BJ86: =BD85*$BK85 -> 621.07666 | BK86: =IF(BD85>0,BK85,0) -> 0.0017
A87: =IF(INT(F87)>0,A86,0) -> 25 | B87: =IF(F87>0.1,B86,0) -> 75 | C87: =DATE(YEAR(C86),MONTH(C86)+1,1) -> 48245 | D87: =IFERROR(G87/M86,0) -> 0.0031545741 | E87: =E86+1 -> 73 | F87: =IF(OR(M86<1,N86>M86),0,(M86-N86)*IF(D$11<>"BB",$E$7,(1+$D$7)^(AK86/365)-1)) -> 3048.0562 | G87: =IF(R87=0,0,IF(M86<1,0,IF(AND(AND(((M86-N86)/R87)<G86,O86<>"V"),D$11<>"BRADESCO"),G86, (M86-N86)/R87))) -> 1150.8247 | H87: =IF(OR(G87=0,L87<1),"",IF(G87/L87>90%,"🛩",IF(G87/L87>70%,"🏎",IF(G87/L87>50%,"🚙",IF(G87/L87>30%,"🛵",IF(G87/L87>15%,"🐢","⚓️")))))) -> 🐢 | I87: =IFERROR(IF((G87+N87-S87)/L87<0,"🔙",IF((G87+N87-S87)/L87<10%,"🥾",IF((G87+N87-S87)/L87<20%,"🛴",IF((G87+N87-S87)/L87<50%,"🚴‍♂️",IF((G87+N87-S87)/L87<75%,"🚖","🚁"))))),"") -> 🛴 | J87: =G87+N87-S87 -> 530.64526 | K87: =IFERROR(J87/(L87+N87),0) -> 0.123438 | L87: =G87+F87+A87+B87 -> 4298.8809 | M87: =IF(R87=0,0,MAX(0,M86-G87+S87-N86)) -> 364280.78 | O87: =IF(AND(N87<>"",N87<R87),"V","") | P87: =IF(N86=0,"",(L86-L87)/N86) | Q87: =IF(N87=0,"",IF(N87>M87,"🚫",IF(INT(N87/G87<1),"👍",INT(N87/G87)&"x"))) | R87: =IF(M86=0,0,IF(OR(N86=0,O86="V"),R86-1,IF(OR(D$11="BRADESCO",D$11="BB"),R86-ROUNDDOWN(N86/(M86/R86),0)-1,ROUNDUP((M86-N86+S86-(M86/R86))/(L86-F87-A87-B87),0)+1))) -> 317 | S87: =M86*$T87 -> 620.17942 | T87: =IF(M86>0,T86,0) -> 0.0017 | AA87: =-(L87+N87) -> -4298.8809 | AH87: =ROUNDUP(E87/120,0) -> 1 | AI87: =ROUNDUP(E87/36,0) -> 3 | AJ87: =ROUNDUP(E87/12,0) -> 7 | AK87: =DAY(DATE(YEAR(C87),MONTH(C87)+1,1)-1) -> 29 | AR87: =IF(INT(AW87)>0,AR86,0) -> 25 | AS87: =IF(AW87>0.1,AS86,0) -> 75 | AT87: =DATE(YEAR(AT86),MONTH(AT86)+1,1) -> 48245 | AU87: =IFERROR(AX87/BD86,0) -> 0.0031545741 | AV87: =AV86+1 -> 73 | AW87: =IF(OR(BD86<1,BE86>BD86),0,(BD86-BE86)*IF(AU$11<>"BB",$E$7,(1+$D$7)^(BY86/365)-1)) -> 3048.0562 | AX87: =IF(BI87=0,0,IF(BD86<1,0,IF(AND(AND(((BD86-BE86)/BI87)<AX86,BF86<>"V"),AU$11<>"BRADESCO"),AX86, (BD86-BE86)/BI87))) -> 1150.8247 | AY87: =IF(OR(AX87=0,BC87<1),"",IF(AX87/BC87>90%,"🛩",IF(AX87/BC87>70%,"🏎",IF(AX87/BC87>50%,"🚙",IF(AX87/BC87>30%,"🛵",IF(AX87/BC87>15%,"🐢","⚓️")))))) -> 🐢 | AZ87: =IFERROR(IF((AX87+BE87-BJ87)/BC87<0,"🔙",IF((AX87+BE87-BJ87)/BC87<10%,"🥾",IF((AX87+BE87-BJ87)/BC87<20%,"🛴",IF((AX87+BE87-BJ87)/BC87<50%,"🚴‍♂️",IF((AX87+BE87-BJ87)/BC87<75%,"🚖","🚁"))))),"") -> 🛴 | BA87: =AX87+BE87-BJ87 -> 530.64526 | BB87: =IFERROR(BA87/(BC87+BE87),0) -> 0.123438 | BC87: =AX87+AW87+AR87+AS87 -> 4298.8809 | BD87: =IF(BI87=0,0,MAX(0,BD86-AX87+BJ87-BE86)) -> 364280.78 | BF87: =IF(AND(BE87<>"",BE87<BI87),"V","") | BG87: =IF(BE86=0,"",(BC86-BC87)/BE86) | BH87: =IF(BE87=0,"",IF(BE87>BD87,"🚫",IF(INT(BE87/AX87<1),"👍",INT(BE87/AX87)&"x"))) | BI87: =IF(BD86=0,0,IF(OR(BE86=0,BF86="V"),BI86-1,IF(OR(AU$11="BRADESCO",AU$11="BB"),BI86-ROUNDDOWN(BE86/(BD86/BI86),0)-1,ROUNDUP((BD86-BE86+BJ86-(BD86/BI86))/(BC86-AW87-AR87-AS87),0)+1))) -> 317 | BJ87: =BD86*$BK86 -> 620.17942 | BK87: =IF(BD86>0,BK86,0) -> 0.0017
... A128: =IF(INT(F128)>0,A127,0) -> 25 | B128: =IF(F128>0.1,B127,0) -> 75 | C128: =DATE(YEAR(C127),MONTH(C127)+1,1) -> 49491 | D128: =IFERROR(G128/M127,0) -> 0.0036231884 | E128: =E127+1 -> 114 | F128: =IF(OR(M127<1,N127>M127),0,(M127-N127)*IF(D$11<>"BB",$E$7,(1+$D$7)^(AK127/365)-1)) -> 2845.9003 | G128: =IF(R128=0,0,IF(M127<1,0,IF(AND(AND(((M127-N127)/R128)<G127,O127<>"V"),D$11<>"BRADESCO"),G127, (M127-N127)/R128))) -> 1234.1162 | H128: =IF(OR(G128=0,L128<1),"",IF(G128/L128>90%,"🛩",IF(G128/L128>70%,"🏎",IF(G128/L128>50%,"🚙",IF(G128/L128>30%,"🛵",IF(G128/L128>15%,"🐢","⚓️")))))) -> 🐢 | I128: =IFERROR(IF((G128+N128-S128)/L128<0,"🔙",IF((G128+N128-S128)/L128<10%,"🥾",IF((G128+N128-S128)/L128<20%,"🛴",IF((G128+N128-S128)/L128<50%,"🚴‍♂️",IF((G128+N128-S128)/L128<75%,"🚖","🚁"))))),"") -> 🛴 | J128: =G128+N128-S128 -> 655.06887 | K128: =IFERROR(J128/(L128+N128),0) -> 0.15671442 | L128: =G128+F128+A128+B128 -> 4180.0164 | M128: =IF(R128=0,0,MAX(0,M127-G128+S128-N127)) -> 339961 | O128: =IF(AND(N128<>"",N128<R128),"V","") | P128: =IF(N127=0,"",(L127-L128)/N127) | Q128: =IF(N128=0,"",IF(N128>M128,"🚫",IF(INT(N128/G128<1),"👍",INT(N128/G128)&"x"))) | R128: =IF(M127=0,0,IF(OR(N127=0,O127="V"),R127-1,IF(OR(D$11="BRADESCO",D$11="BB"),R127-ROUNDDOWN(N127/(M127/R127),0)-1,ROUNDUP((M127-N127+S127-(M127/R127))/(L127-F128-A128-B128),0)+1))) -> 276 | S128: =M127*$T128 -> 579.04731 | T128: =IF(M127>0,T127,0) -> 0.0017 | AA128: =-(L128+N128) -> -4180.0164 | AH128: =ROUNDUP(E128/120,0) -> 1 | AI128: =ROUNDUP(E128/36,0) -> 4 | AJ128: =ROUNDUP(E128/12,0) -> 10 | AK128: =DAY(DATE(YEAR(C128),MONTH(C128)+1,1)-1) -> 31 | AR128: =IF(INT(AW128)>0,AR127,0) -> 25 | AS128: =IF(AW128>0.1,AS127,0) -> 75 | AT128: =DATE(YEAR(AT127),MONTH(AT127)+1,1) -> 49491 | AU128: =IFERROR(AX128/BD127,0) -> 0.0036231884 | AV128: =AV127+1 -> 114 | AW128: =IF(OR(BD127<1,BE127>BD127),0,(BD127-BE127)*IF(AU$11<>"BB",$E$7,(1+$D$7)^(BY127/365)-1)) -> 2845.9003 | AX128: =IF(BI128=0,0,IF(BD127<1,0,IF(AND(AND(((BD127-BE127)/BI128)<AX127,BF127<>"V"),AU$11<>"BRADESCO"),AX127, (BD127-BE127)/BI128))) -> 1234.1162 | AY128: =IF(OR(AX128=0,BC128<1),"",IF(AX128/BC128>90%,"🛩",IF(AX128/BC128>70%,"🏎",IF(AX128/BC128>50%,"🚙",IF(AX128/BC128>30%,"🛵",IF(AX128/BC128>15%,"🐢","⚓️")))))) -> 🐢 | AZ128: =IFERROR(IF((AX128+BE128-BJ128)/BC128<0,"🔙",IF((AX128+BE128-BJ128)/BC128<10%,"🥾",IF((AX128+BE128-BJ128)/BC128<20%,"🛴",IF((AX128+BE128-BJ128)/BC128<50%,"🚴‍♂️",IF((AX128+BE128-BJ128)/BC128<75%,"🚖","🚁"))))),"") -> 🛴 | BA128: =AX128+BE128-BJ128 -> 655.06887 | BB128: =IFERROR(BA128/(BC128+BE128),0) -> 0.15671442 | BC128: =AX128+AW128+AR128+AS128 -> 4180.0164 | BD128: =IF(BI128=0,0,MAX(0,BD127-AX128+BJ128-BE127)) -> 339961 | BF128: =IF(AND(BE128<>"",BE128<BI128),"V","") | BG128: =IF(BE127=0,"",(BC127-BC128)/BE127) | BH128: =IF(BE128=0,"",IF(BE128>BD128,"🚫",IF(INT(BE128/AX128<1),"👍",INT(BE128/AX128)&"x"))) | BI128: =IF(BD127=0,0,IF(OR(BE127=0,BF127="V"),BI127-1,IF(OR(AU$11="BRADESCO",AU$11="BB"),BI127-ROUNDDOWN(BE127/(BD127/BI127),0)-1,ROUNDUP((BD127-BE127+BJ127-(BD127/BI127))/(BC127-AW128-AR128-AS128),0)+1))) -> 276 | BJ128: =BD127*$BK127 -> 579.04731 | BK128: =IF(BD127>0,BK127,0) -> 0.0017
A129: =IF(INT(F129)>0,A128,0) -> 25 | B129: =IF(F129>0.1,B128,0) -> 75 | C129: =DATE(YEAR(C128),MONTH(C128)+1,1) -> 49522 | D129: =IFERROR(G129/M128,0) -> 0.0036363636 | E129: =E128+1 -> 115 | F129: =IF(OR(M128<1,N128>M128),0,(M128-N128)*IF(D$11<>"BB",$E$7,(1+$D$7)^(AK128/365)-1)) -> 2840.4271 | G129: =IF(R129=0,0,IF(M128<1,0,IF(AND(AND(((M128-N128)/R129)<G128,O128<>"V"),D$11<>"BRADESCO"),G128, (M128-N128)/R129))) -> 1236.2218 | H129: =IF(OR(G129=0,L129<1),"",IF(G129/L129>90%,"🛩",IF(G129/L129>70%,"🏎",IF(G129/L129>50%,"🚙",IF(G129/L129>30%,"🛵",IF(G129/L129>15%,"🐢","⚓️")))))) -> 🐢 | I129: =IFERROR(IF((G129+N129-S129)/L129<0,"🔙",IF((G129+N129-S129)/L129<10%,"🥾",IF((G129+N129-S129)/L129<20%,"🛴",IF((G129+N129-S129)/L129<50%,"🚴‍♂️",IF((G129+N129-S129)/L129<75%,"🚖","🚁"))))),"") -> 🛴 | J129: =G129+N129-S129 -> 658.28811 | K129: =IFERROR(J129/(L129+N129),0) -> 0.15761155 | L129: =G129+F129+A129+B129 -> 4176.6489 | M129: =IF(R129=0,0,MAX(0,M128-G129+S129-N128)) -> 339302.71 | P129: =IF(N128=0,"",(L128-L129)/N128) | Q129: =IF(N129=0,"",IF(N129>M129,"🚫",IF(INT(N129/G129<1),"👍",INT(N129/G129)&"x"))) | R129: =IF(M128=0,0,IF(OR(N128=0,O128="V"),R128-1,IF(OR(D$11="BRADESCO",D$11="BB"),R128-ROUNDDOWN(N128/(M128/R128),0)-1,ROUNDUP((M128-N128+S128-(M128/R128))/(L128-F129-A129-B129),0)+1))) -> 275 | S129: =M128*$T129 -> 577.9337 | T129: =IF(M128>0,T128,0) -> 0.0017 | AA129: =-(L129+N129) -> -4176.6489 | AH129: =ROUNDUP(E129/120,0) -> 1 | AI129: =ROUNDUP(E129/36,0) -> 4 | AJ129: =ROUNDUP(E129/12,0) -> 10 | AK129: =DAY(DATE(YEAR(C129),MONTH(C129)+1,1)-1) -> 31 | AR129: =IF(INT(AW129)>0,AR128,0) -> 25 | AS129: =IF(AW129>0.1,AS128,0) -> 75 | AT129: =DATE(YEAR(AT128),MONTH(AT128)+1,1) -> 49522 | AU129: =IFERROR(AX129/BD128,0) -> 0.0036363636 | AV129: =AV128+1 -> 115 | AW129: =IF(OR(BD128<1,BE128>BD128),0,(BD128-BE128)*IF(AU$11<>"BB",$E$7,(1+$D$7)^(BY128/365)-1)) -> 2840.4271 | AX129: =IF(BI129=0,0,IF(BD128<1,0,IF(AND(AND(((BD128-BE128)/BI129)<AX128,BF128<>"V"),AU$11<>"BRADESCO"),AX128, (BD128-BE128)/BI129))) -> 1236.2218 | AY129: =IF(OR(AX129=0,BC129<1),"",IF(AX129/BC129>90%,"🛩",IF(AX129/BC129>70%,"🏎",IF(AX129/BC129>50%,"🚙",IF(AX129/BC129>30%,"🛵",IF(AX129/BC129>15%,"🐢","⚓️")))))) -> 🐢 | AZ129: =IFERROR(IF((AX129+BE129-BJ129)/BC129<0,"🔙",IF((AX129+BE129-BJ129)/BC129<10%,"🥾",IF((AX129+BE129-BJ129)/BC129<20%,"🛴",IF((AX129+BE129-BJ129)/BC129<50%,"🚴‍♂️",IF((AX129+BE129-BJ129)/BC129<75%,"🚖","🚁"))))),"") -> 🛴 | BA129: =AX129+BE129-BJ129 -> 658.28811 | BB129: =IFERROR(BA129/(BC129+BE129),0) -> 0.15761155 | BC129: =AX129+AW129+AR129+AS129 -> 4176.6489 | BD129: =IF(BI129=0,0,MAX(0,BD128-AX129+BJ129-BE128)) -> 339302.71 | BG129: =IF(BE128=0,"",(BC128-BC129)/BE128) | BH129: =IF(BE129=0,"",IF(BE129>BD129,"🚫",IF(INT(BE129/AX129<1),"👍",INT(BE129/AX129)&"x"))) | BI129: =IF(BD128=0,0,IF(OR(BE128=0,BF128="V"),BI128-1,IF(OR(AU$11="BRADESCO",AU$11="BB"),BI128-ROUNDDOWN(BE128/(BD128/BI128),0)-1,ROUNDUP((BD128-BE128+BJ128-(BD128/BI128))/(BC128-AW129-AR129-AS129),0)+1))) -> 275 | BJ129: =BD128*$BK128 -> 577.9337 | BK129: =IF(BD128>0,BK128,0) -> 0.0017
A130: =IF(INT(F130)>0,A129,0) -> 25 | B130: =IF(F130>0.1,B129,0) -> 75 | C130: =DATE(YEAR(C129),MONTH(C129)+1,1) -> 49553 | D130: =IFERROR(G130/M129,0) -> 0.003649635 | E130: =E129+1 -> 116 | F130: =IF(OR(M129<1,N129>M129),0,(M129-N129)*IF(D$11<>"BB",$E$7,(1+$D$7)^(AK129/365)-1)) -> 2834.927 | G130: =IF(R130=0,0,IF(M129<1,0,IF(AND(AND(((M129-N129)/R130)<G129,O129<>"V"),D$11<>"BRADESCO"),G129, (M129-N129)/R130))) -> 1238.3311 | H130: =IF(OR(G130=0,L130<1),"",IF(G130/L130>90%,"🛩",IF(G130/L130>70%,"🏎",IF(G130/L130>50%,"🚙",IF(G130/L130>30%,"🛵",IF(G130/L130>15%,"🐢","⚓️")))))) -> 🐢 | I130: =IFERROR(IF((G130+N130-S130)/L130<0,"🔙",IF((G130+N130-S130)/L130<10%,"🥾",IF((G130+N130-S130)/L130<20%,"🛴",IF((G130+N130-S130)/L130<50%,"🚴‍♂️",IF((G130+N130-S130)/L130<75%,"🚖","🚁"))))),"") -> 🛴 | J130: =G130+N130-S130 -> 661.51645 | K130: =IFERROR(J130/(L130+N130),0) -> 0.15851319 | L130: =G130+F130+A130+B130 -> 4173.258 | M130: =IF(R130=0,0,MAX(0,M129-G130+S130-N129)) -> 338641.19 | O130: =IF(AND(N130<>"",N130<R130),"V","") | P130: =IF(N129=0,"",(L129-L130)/N129) | Q130: =IF(N130=0,"",IF(N130>M130,"🚫",IF(INT(N130/G130<1),"👍",INT(N130/G130)&"x"))) | R130: =IF(M129=0,0,IF(OR(N129=0,O129="V"),R129-1,IF(OR(D$11="BRADESCO",D$11="BB"),R129-ROUNDDOWN(N129/(M129/R129),0)-1,ROUNDUP((M129-N129+S129-(M129/R129))/(L129-F130-A130-B130),0)+1))) -> 274 | S130: =M129*$T130 -> 576.81461 | T130: =IF(M129>0,T129,0) -> 0.0017 | AA130: =-(L130+N130) -> -4173.258 | AH130: =ROUNDUP(E130/120,0) -> 1 | AI130: =ROUNDUP(E130/36,0) -> 4 | AJ130: =ROUNDUP(E130/12,0) -> 10 | AK130: =DAY(DATE(YEAR(C130),MONTH(C130)+1,1)-1) -> 30 | AR130: =IF(INT(AW130)>0,AR129,0) -> 25 | AS130: =IF(AW130>0.1,AS129,0) -> 75 | AT130: =DATE(YEAR(AT129),MONTH(AT129)+1,1) -> 49553 | AU130: =IFERROR(AX130/BD129,0) -> 0.003649635 | AV130: =AV129+1 -> 116 | AW130: =IF(OR(BD129<1,BE129>BD129),0,(BD129-BE129)*IF(AU$11<>"BB",$E$7,(1+$D$7)^(BY129/365)-1)) -> 2834.927 | AX130: =IF(BI130=0,0,IF(BD129<1,0,IF(AND(AND(((BD129-BE129)/BI130)<AX129,BF129<>"V"),AU$11<>"BRADESCO"),AX129, (BD129-BE129)/BI130))) -> 1238.3311 | AY130: =IF(OR(AX130=0,BC130<1),"",IF(AX130/BC130>90%,"🛩",IF(AX130/BC130>70%,"🏎",IF(AX130/BC130>50%,"🚙",IF(AX130/BC130>30%,"🛵",IF(AX130/BC130>15%,"🐢","⚓️")))))) -> 🐢 | AZ130: =IFERROR(IF((AX130+BE130-BJ130)/BC130<0,"🔙",IF((AX130+BE130-BJ130)/BC130<10%,"🥾",IF((AX130+BE130-BJ130)/BC130<20%,"🛴",IF((AX130+BE130-BJ130)/BC130<50%,"🚴‍♂️",IF((AX130+BE130-BJ130)/BC130<75%,"🚖","🚁"))))),"") -> 🛴 | BA130: =AX130+BE130-BJ130 -> 661.51645 | BB130: =IFERROR(BA130/(BC130+BE130),0) -> 0.15851319 | BC130: =AX130+AW130+AR130+AS130 -> 4173.258 | BD130: =IF(BI130=0,0,MAX(0,BD129-AX130+BJ130-BE129)) -> 338641.19 | BF130: =IF(AND(BE130<>"",BE130<BI130),"V","") | BG130: =IF(BE129=0,"",(BC129-BC130)/BE129) | BH130: =IF(BE130=0,"",IF(BE130>BD130,"🚫",IF(INT(BE130/AX130<1),"👍",INT(BE130/AX130)&"x"))) | BI130: =IF(BD129=0,0,IF(OR(BE129=0,BF129="V"),BI129-1,IF(OR(AU$11="BRADESCO",AU$11="BB"),BI129-ROUNDDOWN(BE129/(BD129/BI129),0)-1,ROUNDUP((BD129-BE129+BJ129-(BD129/BI129))/(BC129-AW130-AR130-AS130),0)+1))) -> 274 | BJ130: =BD129*$BK129 -> 576.81461 | BK130: =IF(BD129>0,BK129,0) -> 0.0017
A131: =IF(INT(F131)>0,A130,0) -> 25 | B131: =IF(F131>0.1,B130,0) -> 75 | C131: =DATE(YEAR(C130),MONTH(C130)+1,1) -> 49583 | D131: =IFERROR(G131/M130,0) -> 0.0036630037 | E131: =E130+1 -> 117 | F131: =IF(OR(M130<1,N130>M130),0,(M130-N130)*IF(D$11<>"BB",$E$7,(1+$D$7)^(AK130/365)-1)) -> 2829.3999 | G131: =IF(R131=0,0,IF(M130<1,0,IF(AND(AND(((M130-N130)/R131)<G130,O130<>"V"),D$11<>"BRADESCO"),G130, (M130-N130)/R131))) -> 1240.4439 | H131: =IF(OR(G131=0,L131<1),"",IF(G131/L131>90%,"🛩",IF(G131/L131>70%,"🏎",IF(G131/L131>50%,"🚙",IF(G131/L131>30%,"🛵",IF(G131/L131>15%,"🐢","⚓️")))))) -> 🐢 | I131: =IFERROR(IF((G131+N131-S131)/L131<0,"🔙",IF((G131+N131-S131)/L131<10%,"🥾",IF((G131+N131-S131)/L131<20%,"🛴",IF((G131+N131-S131)/L131<50%,"🚴‍♂️",IF((G131+N131-S131)/L131<75%,"🚖","🚁"))))),"") -> 🛴 | J131: =G131+N131-S131 -> 664.7539 | K131: =IFERROR(J131/(L131+N131),0) -> 0.15941938 | L131: =G131+F131+A131+B131 -> 4169.8438 | M131: =IF(R131=0,0,MAX(0,M130-G131+S131-N130)) -> 337976.44 | O131: =IF(AND(N131<>"",N131<R131),"V","") | P131: =IF(N130=0,"",(L130-L131)/N130) | Q131: =IF(N131=0,"",IF(N131>M131,"🚫",IF(INT(N131/G131<1),"👍",INT(N131/G131)&"x"))) | R131: =IF(M130=0,0,IF(OR(N130=0,O130="V"),R130-1,IF(OR(D$11="BRADESCO",D$11="BB"),R130-ROUNDDOWN(N130/(M130/R130),0)-1,ROUNDUP((M130-N130+S130-(M130/R130))/(L130-F131-A131-B131),0)+1))) -> 273 | S131: =M130*$T131 -> 575.69003 | T131: =IF(M130>0,T130,0) -> 0.0017 | AA131: =-(L131+N131) -> -4169.8438 | AH131: =ROUNDUP(E131/120,0) -> 1 | AI131: =ROUNDUP(E131/36,0) -> 4 | AJ131: =ROUNDUP(E131/12,0) -> 10 | AK131: =DAY(DATE(YEAR(C131),MONTH(C131)+1,1)-1) -> 31 | AR131: =IF(INT(AW131)>0,AR130,0) -> 25 | AS131: =IF(AW131>0.1,AS130,0) -> 75 | AT131: =DATE(YEAR(AT130),MONTH(AT130)+1,1) -> 49583 | AU131: =IFERROR(AX131/BD130,0) -> 0.0036630037 | AV131: =AV130+1 -> 117 | AW131: =IF(OR(BD130<1,BE130>BD130),0,(BD130-BE130)*IF(AU$11<>"BB",$E$7,(1+$D$7)^(BY130/365)-1)) -> 2829.3999 | AX131: =IF(BI131=0,0,IF(BD130<1,0,IF(AND(AND(((BD130-BE130)/BI131)<AX130,BF130<>"V"),AU$11<>"BRADESCO"),AX130, (BD130-BE130)/BI131))) -> 1240.4439 | AY131: =IF(OR(AX131=0,BC131<1),"",IF(AX131/BC131>90%,"🛩",IF(AX131/BC131>70%,"🏎",IF(AX131/BC131>50%,"🚙",IF(AX131/BC131>30%,"🛵",IF(AX131/BC131>15%,"🐢","⚓️")))))) -> 🐢 | AZ131: =IFERROR(IF((AX131+BE131-BJ131)/BC131<0,"🔙",IF((AX131+BE131-BJ131)/BC131<10%,"🥾",IF((AX131+BE131-BJ131)/BC131<20%,"🛴",IF((AX131+BE131-BJ131)/BC131<50%,"🚴‍♂️",IF((AX131+BE131-BJ131)/BC131<75%,"🚖","🚁"))))),"") -> 🛴 | BA131: =AX131+BE131-BJ131 -> 664.7539 | BB131: =IFERROR(BA131/(BC131+BE131),0) -> 0.15941938 | BC131: =AX131+AW131+AR131+AS131 -> 4169.8438 | BD131: =IF(BI131=0,0,MAX(0,BD130-AX131+BJ131-BE130)) -> 337976.44 | BF131: =IF(AND(BE131<>"",BE131<BI131),"V","") | BG131: =IF(BE130=0,"",(BC130-BC131)/BE130) | BH131: =IF(BE131=0,"",IF(BE131>BD131,"🚫",IF(INT(BE131/AX131<1),"👍",INT(BE131/AX131)&"x"))) | BI131: =IF(BD130=0,0,IF(OR(BE130=0,BF130="V"),BI130-1,IF(OR(AU$11="BRADESCO",AU$11="BB"),BI130-ROUNDDOWN(BE130/(BD130/BI130),0)-1,ROUNDUP((BD130-BE130+BJ130-(BD130/BI130))/(BC130-AW131-AR131-AS131),0)+1))) -> 273 | BJ131: =BD130*$BK130 -> 575.69003 | BK131: =IF(BD130>0,BK130,0) -> 0.0017
